Workbook

Sheet 00_Cover
B3: TEAM FALCONS
B4: Unified Talent Pricing OS · v1.3
B5: One operating system for Players, Creators & Mixed campaigns.
B6: Updated: 18 April 2026 · Currency: SAR · 1 USD = 3.75 SAR · Confidential — internal use only
B7: Updated: 18 April 2026 · Currency: SAR · VAT: 15% · Owner: Team Falcons Commercial
B8: =COUNTA('20_Player_Rate_Card'!C6:C500)+COUNTA('30_Creator_Rate_Card'!C6:C100) -> 206 | D8: =COUNTA('20_Player_Rate_Card'!C6:C500) -> 189 | F8: =COUNTA('30_Creator_Rate_Card'!C6:C100) -> 17 | H8: =COUNTIF('20_Player_Rate_Card'!I6:I500,"Tier 1")&"/"&COUNTIF('20_Player_Rate_Card'!I6:I500,"Tier 2")&"/"&COUNTIF('20_Player_Rate_Card'!I6:I500,"Tier 3") -> 25/106/58
B9: Total Talent | D9: Players | F9: Creators | H9: T1 / T2 / T3 (Players)
B12: NAVIGATION
B13: GOVERNANCE
B14: 01_Settings | C14: Global config · VAT · USD · approvers · bank · Shikenso
B15: 02_Lookups | C15: Canonical dropdown values used across the workbook
B16: 03_Benchmarks | C16: Market benchmarks — Tier 1 / MENA / platform CPMs
B18: DATA BACKBONE
B19: 10_Social_Tracker | C19: Normalized handles + followers (source of truth for social data)
B20: 11_Confidence | C20: Verification rules & measurement confidence tiering
B22: PLAYER LANE
B23: 20_Player_Rate_Card | C23: 189 active entries · platform rates · floor · confidence
B25: CREATOR LANE
B26: 30_Creator_Rate_Card | C26: 17 creators · ceiling rates · opening factor
B28: PRICING ENGINE
B29: 40_Adjustment_Matrix | C29: 9-axis commercial decision system + live price calculator
B30: 41_Add_On_Rights | C30: Rights packages & add-ons (separate from organic)
B32: QUOTATION
B33: 42_Preview | C33: Quick scenario preview calculator — live multipliers
B34: 51_Quote_Preview | C34: Client-facing KFC-style quote — template for Apps Script output
B35: 52_Quote_Log | C35: All generated quotes · audit trail
B36: 53_Inquiry_Log | C36: Inbound pipeline · approval flags
B38: METHODOLOGY & DOCS
B39: 90_Methodology | C39: Rewritten commercial methodology
B40: 91_Roadmap | C40: Phased evolution plan (V1 → Shikenso → rolling)
B41: 95_Guide_EN | C41: English user guide
B42: 96_Guide_AR | C42: دليل المستخدم بالعربي
B43: 97_Changelog | C43: Version log
B44: 99_Script_Map | C44: Named ranges & addresses for future Apps Script
B46: LEGEND — CELL CONVENTIONS
B47: Blue text / yellow fill | C47: User input cell — safe to edit
B48: Black text | C48: Formula — do not overwrite
B49: Green text | C49: Cross-sheet link
B50: Red text | C50: External / placeholder
B52: Team Falcons — Unified Talent Pricing OS v1.1 · Confidential
B53: Team Falcons — Unified Talent Pricing OS v1.3 · Confidential

Sheet 01_Settings
B2: 01 — SETTINGS & GOVERNANCE
B3: Single source of truth for global parameters. Anything here is read by every other tab.
B5: WORKBOOK
B6: Key | C6: Value | D6: Notes
B7: Workbook Version | C7: v1.0 | D7: Schema version — bump on breaking changes
B8: Last Updated | C8: 18 April 2026 | D8: Human-readable revision date
B9: Schema Stable Until | C9: v2.0 | D9: Apps Script may bind to addresses until this version
B11: CURRENCY & TAX
B12: Key | C12: Value | D12: Notes
B13: Primary Currency | C13: SAR | D13: All rate cards and quotes in SAR
B14: USD Rate (SAR per USD) | C14: 3.75 | D14: Used for USD preview columns
B15: VAT Rate | C15: 0.15 | D15: Saudi VAT 15%
B17: COMMERCIAL DEFAULTS
B18: Key | C18: Value | D18: Notes
B19: Default Management Fee | C19: 0.1 | D19: Applied to quote subtotal unless overridden
B20: Default Opening Factor | C20: 0.75 | D20: Creator opening offer = Ceiling × Opening Factor
B21: Default Rush Uplift | C21: 0.25 | D21: Rush <72h — aligned to industry standard
B22: Default Markup on Player Cost | C22: 0.75 | D22: Legacy; override per talent on rate card
B24: APPROVAL & COMPLIANCE
B25: Key | C25: Value | D25: Notes
B26: Legal Approver Email | C26: legal@teamfalcons.gg | D26: Quotes > trigger threshold require legal
B27: Finance Approver Email | C27: finance@teamfalcons.gg | D27: Finance co-sign on all invoiced quotes
B28: High-Value Approval Threshold (SAR) | C28: 150000 | D28: Quotes above this trigger legal approval
B29: Exclusivity Approval Required? | C29: Yes | D29: Any exclusivity add-on requires legal sign-off
B30: Approval Secret | C30: falcons2026 | D30: Apps Script approval token (placeholder)
B32: FUTURE AUTOMATION PLACEHOLDERS
B33: Key | C33: Value | D33: Notes
B34: output_folder_id | D34: Google Drive folder for generated PDFs
B35: Shikenso API Key | D35: Enterprise analytics — integrated in roadmap Phase 2
B36: Shikenso Base URL | C36: https://api.shikenso.com/v1 | D36: Default endpoint
B37: client_email | D37: Optional default recipient
B39: BANKING (INVOICE)
B40: Key | C40: Value | D40: Notes
B41: Bank Name | C41: Al Rajhi Bank | D41: Invoice banking details
B42: Account Name | C42: Team Falcons
B43: IBAN | D43: To fill — banking
B44: Swift / BIC
B47: Team Falcons · Unified Talent Pricing OS v1.2 · Confidential

Sheet 02_Lookups
B2: 02 — CANONICAL LOOKUPS
B3: Every dropdown value and multiplier in the workbook resolves here. Change a number here = change the whole engine.
B5: TIERS
B6: Label | C6: Tier | D6: Description / Notes
B7: Tier S — Superstar | C7: Global anchor · 1M+ on any platform
B8: Tier 1 — Star | C8: Core pro or creator · 250K–1M
B9: Tier 2 — Core | C9: Active pros / mid-tier creators · 50K–250K
B10: Tier 3 — Rising | C10: Emerging talent · 10K–50K
B11: Tier 4 — Entry/Staff | C11: Support roles · <10K
B13: ENGAGEMENT
B14: Label | C14: Multiplier | D14: Description / Notes
B15: < 2% — Below | C15: 0.7
B16: 2–4% — Average | C16: 0.9
B17: 4–6% — Baseline | C17: 1
B18: 6–8% — Good | C18: 1.2
B19: 8–10% — Excellent | C19: 1.4
B20: > 10% — Premium | C20: 1.6
B22: AUDIENCE QUALITY / FIT
B23: Label | C23: Multiplier | D23: Description / Notes
B24: Generic / Broad | C24: 0.85
B25: Gaming-adjacent | C25: 1
B26: Core Gaming | C26: 1.2
B27: Esports-focused | C27: 1.4
B28: MENA / Saudi focus | C28: 1.3
B29: Global Esports Elite | C29: 1.5
B30: Sports / Football / Active | C30: 1.1
B31: Youth Entertainment / Variety | C31: 1.05
B33: CAMPAIGN OBJECTIVE
B34: Label | C34: ObjWeight | D34: Description / Notes
B35: Awareness | C35: 0.2
B36: Conversion | C36: 0.4
B37: Trust (Pro Authority) | C37: 0.7
B39: AUTHORITY / STATUS
B40: Label | C40: AuthMult | D40: Description / Notes
B41: Normal | C41: 1
B42: Proven / Established | C42: 1.15
B43: Elite Contender | C43: 1.3
B44: Global Star / Major Winner | C44: 1.5
B46: LANGUAGE
B47: Label | C47: Multiplier | D47: Description / Notes
B48: English | C48: 1
B49: Arabic | C49: 1.05
B50: Dialect Arabic | C50: 1.05
B51: Bilingual | C51: 1.15
B53: SEASONALITY / TIMING
B54: Label | C54: Multiplier | D54: Description / Notes
B55: Off-season | C55: 0.8
B56: Regular season | C56: 1
B57: Regional Major | C57: 1.25
B58: Global Major / Worlds | C58: 1.4
B59: Game launch | C59: 1.3
B60: Holiday season (Q4) | C60: 1.2
B61: Ramadan (MENA) | C61: 1.35
B62: EWC / Mega Peak | C62: 1.5
B64: CONTENT TYPE
B65: Label | C65: Multiplier | D65: Description / Notes
B66: Integrated (Player-led) | C66: 1
B67: Dedicated (Brand-led) | C67: 1.3
B69: MEASUREMENT CONFIDENCE
B70: Label | C70: Allowed Cap | D70: Description / Notes
B71: exact — verified API | C71: 1
B72: rounded — manual verified | C72: 1
B73: estimated — partial data | C73: 0.9
B74: pending — no data | C74: 0.75
B76: AUTHORITY FLOOR (FloorShare)
B77: Label | C77: Value | D77: Description / Notes
B78: Not used | C78: 0
B79: Partial floor | C79: 0.4
B80: Standard floor | C80: 0.5
B81: Strong floor | C81: 0.7
B82: Hard floor | C82: 0.8
B84: TALENT TYPE (Quote Builder)
B85: Label | C85: — | D85: Description / Notes
B86: Player
B87: Creator
B88: Mixed
B90: INQUIRY STAGE
B91: Label | C91: — | D91: Description / Notes
B92: Lead
B93: Qualified
B94: Proposal Sent
B95: Negotiation
B96: Contract
B97: Delivered
B98: Closed
B100: INQUIRY STATUS
B101: Label | C101: — | D101: Description / Notes
B102: In Progress
B103: Won
B104: Lost
B105: On Hold
B107: BUNDLE DISCOUNT
B108: Label | C108: Discount | D108: Description / Notes
B109: None | C109: 0
B110: 2 lines | C110: 0.03
B111: 3–4 lines | C111: 0.05
B112: 5+ lines | C112: 0.08
B115: Team Falcons · Unified Talent Pricing OS v1.2 · Confidential
E200: TALENT UNION (helper — do not edit) | F200: PLATFORM UNION (helper — do not edit)
E201: ='20_Player_Rate_Card'!$C$6 -> Bijw | F201: IG Reel
...

Sheet 03_Benchmarks
B2: 03 — MARKET BENCHMARKS & COMPETITIVE INTELLIGENCE
B3: Industry rate benchmarks and competitive positioning for Team Falcons talent monetisation.
B5: SECTION 1 — GLOBAL TIER 1 ESPORTS ORG BENCHMARKS
B6: Organisation | C6: Region | D6: Tier | E6: Avg Followers | F6: Avg Base Fee / Post (USD) | G6: Avg Stream Deal (USD) | H6: Avg Annual Sponsorship (USD) | I6: Exclusivity Premium | J6: Engagement Benchmark | K6: Source / Notes
B7: T1 Esports | C7: Global | D7: Tier 1 | E7: 2M–8M | F7: $8k–$25k | G7: $20k–$80k | H7: $500K–$2M | I7: +50-100% | J7: 4-7% ER | K7: Newzoo 2025; public disclosures
B8: FaZe Clan | C8: Global | D8: Tier 1 | E8: 3M–15M | F8: $10k–$40k | G8: $30k–$120k | H8: $1M–$5M | I8: +40-75% | J8: 3-6% ER | K8: Newzoo 2025; SEC filings
B9: NaVi | C9: EMEA | D9: Tier 1 | E9: 1M–5M | F9: $5k–$20k | G9: $15k–$60k | H9: $300K–$1.5M | I9: +35-60% | J9: 4-8% ER | K9: Shikenso Esports Sponsorship 2025
B10: Fnatic | C10: EMEA | D10: Tier 1 | E10: 500K–3M | F10: $4k–$15k | G10: $10k–$45k | H10: $200K–$800K | I10: +30-50% | J10: 5-9% ER | K10: Influencity 2026
B11: Cloud9 | C11: NA | D11: Tier 1 | E11: 1M–6M | F11: $6k–$22k | G11: $18k–$70k | H11: $400K–$1.8M | I11: +30-50% | J11: 3-6% ER | K11: Nielsen Esports 2025
B12: 100 Thieves | C12: NA | D12: Tier 1 | E12: 500K–4M | F12: $5k–$18k | G12: $15k–$55k | H12: $350K–$1.2M | I12: +40-70% | J12: 5-10% ER | K12: Porter Wills 2025
B14: SECTION 2 — MENA ESPORTS ORG BENCHMARKS
B15: Organisation | C15: Region | D15: Tier | E15: Avg Followers | F15: Avg Base Fee / Post (SAR) | G15: Avg Stream Deal (SAR) | H15: Avg Annual Sponsorship (SAR) | I15: Exclusivity Premium | J15: Engagement Benchmark | K15: Source / Notes
B16: Team Falcons | C16: KSA/MENA | D16: Tier 1 | E16: 200K–2M | F16: SAR 8k–60k | G16: SAR 20k–120k | H16: SAR 500K–2M | I16: +35-60% | J16: 5-12% ER | K16: Internal Falcons data 2025
B17: Nasr Esports | C17: KSA/MENA | D17: Tier 1 | E17: 100K–800K | F17: SAR 5k–30k | G17: SAR 12k–60k | H17: SAR 200K–800K | I17: +30-50% | J17: 4-9% ER | K17: Shikenso MENA 2025
B18: Twisted Minds | C18: KSA | D18: Tier 2 | E18: 80K–500K | F18: SAR 4k–20k | G18: SAR 10k–45k | H18: SAR 150K–500K | I18: +25-45% | J18: 6-11% ER | K18: Internal market intel 2025
B19: Galaxy Racer | C19: UAE/MENA | D19: Tier 2 | E19: 100K–1M | F19: SAR 4.5k–22k | G19: SAR 11k–50k | H19: SAR 180K–600K | I19: +25-40% | J19: 4-9% ER | K19: Newzoo MENA 2025
B20: Team Vitality | C20: MENA | D20: Tier 1 | E20: 200K–1.5M | F20: SAR 6k–35k | G20: SAR 15k–70k | H20: SAR 250K–900K | I20: +30-50% | J20: 4-8% ER | K20: Shikenso 2025
B22: SECTION 3 — PLATFORM RATE BENCHMARKS (Industry Standard CPM / CPE)
B23: Platform | C23: Content Type | D23: Nano 1-10K | E23: Micro 10-100K | F23: Mid 100K-1M | G23: Macro 1-5M | H23: Mega 5M+ | I23: Min ER | J23: Avg CPM | K23: Notes
B24: Instagram | C24: Reel (60s) | D24: $200–1k | E24: $1k–5k | F24: $5k–15k | G24: $15k–50k | H24: $50k+ | I24: 3% | J24: $8–15 | K24: Reels outperform static 3:1 for brand recall
B25: Instagram | C25: Static | D25: $150–800 | E25: $800–4k | F25: $4k–12k | G25: $12k–40k | H25: $40k+ | I25: 2% | J25: $5–10 | K25: Declining vs Reels
B26: TikTok | C26: Branded video | D26: $300–1.5k | E26: $1.5k–6k | F26: $6k–20k | G26: $20k–60k | H26: $60k+ | I26: 5% | J26: $10–20 | K26: MENA: 20–40% premium vs IG
B27: YouTube | C27: Integration (30s) | D27: $500–2k | E27: $2k–8k | F27: $8k–25k | G27: $25k–80k | H27: $80k+ | I27: 1% | J27: $15–30 | K27: Highest brand recall 72%
B28: YouTube | C28: Short (<60s) | D28: $200–1k | E28: $1k–4k | F28: $4k–12k | G28: $12k–35k | H28: $35k+ | I28: 3% | J28: $8–18 | K28: Growing rapidly in MENA
B29: Twitch | C29: Stream integration (2h) | D29: $1k–4k | E29: $4k–15k | F29: $15k–40k | G29: $40k–100k | H29: $100k+ | I29: 500 CCU | J29: $5–15 | K29: CCU-based not followers
B30: X / Twitter | C30: Sponsored post | D30: $100–500 | E30: $500–2k | F30: $2k–6k | G30: $6k–20k | H30: $20k+ | I30: 1% | J30: $3–8 | K30: Declining post-rebrand
B32: Sources: Newzoo 2025, Nielsen Esports 2025, Shikenso MENA 2025, Influencity 2026, Porter Wills Esports Marketing Guide 2025, StreamElements 2025, Internal Falcons data 2025.
B35: Team Falcons · Unified Talent Pricing OS v1.2 · Confidential

Sheet 10_Social_Tracker
B2: 10 — SOCIAL TRACKER (source of truth for handles & followers)
B3: One row per (talent × platform). Drives rate card follower columns via lookups. Leave Current Count blank if unverified — the engine will tag 'pending' automatically.
B4: Source Row | C4: Game | D4: Team | E4: Nickname | F4: Full Name | G4: Role | H4: Platform | I4: Handle | J4: Normalized URL | K4: Metric | L4: Current Count | M4: Retrieved On | N4: Source Method | O4: Confidence | P4: Notes
B5: 4 | C5: Apex Legends | D5: Apex Legends | E5: Gild | F5: Zachary Dennis | G5: Player | H5: X | I5: Gildersons_ | J5: https://x.com/Gildersons_ | K5: Followers | N5: manual | O5: =IF(ISBLANK(L5),"pending","estimated") -> pending
B6: 4 | C6: Apex Legends | D6: Apex Legends | E6: Gild | F6: Zachary Dennis | G6: Player | H6: Twitch | I6: Gild | J6: https://www.twitch.tv/Gild | K6: Followers | N6: manual | O6: =IF(ISBLANK(L6),"pending","estimated") -> pending
B7: 5 | C7: Apex Legends | D7: Apex Legends | E7: ImperialHal | F7: Phillip Dosen | G7: Player | H7: X | I7: ImperialHal | J7: https://x.com/ImperialHal | K7: Followers | N7: manual | O7: =IF(ISBLANK(L7),"pending","estimated") -> pending
B8: 5 | C8: Apex Legends | D8: Apex Legends | E8: ImperialHal | F8: Phillip Dosen | G8: Player | H8: Instagram | I8: ImperialHal | J8: https://www.instagram.com/ImperialHal/ | K8: Followers | N8: manual | O8: =IF(ISBLANK(L8),"pending","estimated") -> pending | P8: Original entry was shorthand
B9: 5 | C9: Apex Legends | D9: Apex Legends | E9: ImperialHal | F9: Phillip Dosen | G9: Player | H9: Twitch | I9: imperialhal__ | J9: https://www.twitch.tv/imperialhal__ | K9: Followers | N9: manual | O9: =IF(ISBLANK(L9),"pending","estimated") -> pending
B10: 5 | C10: Apex Legends | D10: Apex Legends | E10: ImperialHal | F10: Phillip Dosen | G10: Player | H10: YouTube | I10: ImperialHal | J10: https://www.youtube.com/@ImperialHal | K10: Subscribers | N10: manual | O10: =IF(ISBLANK(L10),"pending","estimated") -> pending | P10: Original entry was shorthand; Channel format may need validation
B11: 7 | C11: Apex Legends | D11: Apex Legends | E11: Wxltzy | F11: Ben Walton | G11: Player | H11: X | I11: Wxltzy | J11: https://x.com/Wxltzy | K11: Followers | N11: manual | O11: =IF(ISBLANK(L11),"pending","estimated") -> pending
B12: 7 | C12: Apex Legends | D12: Apex Legends | E12: Wxltzy | F12: Ben Walton | G12: Player | H12: Instagram | I12: Wxltzy | J12: https://www.instagram.com/Wxltzy/ | K12: Followers | N12: manual | O12: =IF(ISBLANK(L12),"pending","estimated") -> pending | P12: Original entry was shorthand
B13: 7 | C13: Apex Legends | D13: Apex Legends | E13: Wxltzy | F13: Ben Walton | G13: Player | H13: Twitch | I13: wxltzy | J13: https://www.twitch.tv/wxltzy | K13: Followers | N13: manual | O13: =IF(ISBLANK(L13),"pending","estimated") -> pending
B14: 11 | C14: Call of Duty Black Ops 7 | D14: Riyadh Falcons | E14: Cellium | F14: McArthur Jovel | G14: Player | H14: X | I14: Cellium | J14: https://twitter.com/Cellium | K14: Followers | N14: manual | O14: =IF(ISBLANK(L14),"pending","estimated") -> pending
B15: 11 | C15: Call of Duty Black Ops 7 | D15: Riyadh Falcons | E15: Cellium | F15: McArthur Jovel | G15: Player | H15: Instagram | I15: cellium | J15: https://www.instagram.com/cellium/ | K15: Followers | N15: manual | O15: =IF(ISBLANK(L15),"pending","estimated") -> pending
B16: 11 | C16: Call of Duty Black Ops 7 | D16: Riyadh Falcons | E16: Cellium | F16: McArthur Jovel | G16: Player | H16: Twitch | I16: Cellium | J16: https://www.twitch.tv/Cellium | K16: Followers | N16: manual | O16: =IF(ISBLANK(L16),"pending","estimated") -> pending
B17: 12 | C17: Call of Duty Black Ops 7 | D17: Riyadh Falcons | E17: Exnid | F17: Saud Alati | G17: Player | H17: X | I17: Exnid_ | J17: https://x.com/Exnid_ | K17: Followers | N17: manual | O17: =IF(ISBLANK(L17),"pending","estimated") -> pending
B18: 12 | C18: Call of Duty Black Ops 7 | D18: Riyadh Falcons | E18: Exnid | F18: Saud Alati | G18: Player | H18: Twitch | I18: exnid | J18: https://www.twitch.tv/exnid | K18: Followers | N18: manual | O18: =IF(ISBLANK(L18),"pending","estimated") -> pending
B19: 13 | C19: Call of Duty Black Ops 7 | D19: Riyadh Falcons | E19: KiSMET | F19: Matthew Tinsley | G19: Player | H19: X | I19: KiSMET6_ | J19: https://twitter.com/KiSMET6_ | K19: Followers | N19: manual | O19: =IF(ISBLANK(L19),"pending","estimated") -> pending
B20: 13 | C20: Call of Duty Black Ops 7 | D20: Riyadh Falcons | E20: KiSMET | F20: Matthew Tinsley | G20: Player | H20: Instagram | I20: kismet6_ | J20: https://www.instagram.com/kismet6_ | K20: Followers | N20: manual | O20: =IF(ISBLANK(L20),"pending","estimated") -> pending
B21: 13 | C21: Call of Duty Black Ops 7 | D21: Riyadh Falcons | E21: KiSMET | F21: Matthew Tinsley | G21: Player | H21: Twitch | I21: kismet6_ | J21: https://www.twitch.tv/kismet6_ | K21: Followers | N21: manual | O21: =IF(ISBLANK(L21),"pending","estimated") -> pending
B22: 14 | C22: Call of Duty Black Ops 7 | D22: Riyadh Falcons | E22: Pred | F22: Amer Zulbeari | G22: Player | H22: X | I22: Pred | J22: https://x.com/Pred | K22: Followers | N22: manual | O22: =IF(ISBLANK(L22),"pending","estimated") -> pending
B23: 14 | C23: Call of Duty Black Ops 7 | D23: Riyadh Falcons | E23: Pred | F23: Amer Zulbeari | G23: Player | H23: Instagram | I23: amerzulbeariii | J23: https://www.instagram.com/amerzulbeariii | K23: Followers | N23: manual | O23: =IF(ISBLANK(L23),"pending","estimated") -> pending
B24: 14 | C24: Call of Duty Black Ops 7 | D24: Riyadh Falcons | E24: Pred | F24: Amer Zulbeari | G24: Player | H24: Twitch | I24: pred | J24: https://www.twitch.tv/pred | K24: Followers | N24: manual | O24: =IF(ISBLANK(L24),"pending","estimated") -> pending
... B82: 37 | C82: Counterstrike2 | D82: Team Falcons | E82: TeSeS | F82: René Madsen | G82: Player | H82: X | I82: tesescs | J82: https://x.com/tesescs | K82: Followers | N82: manual | O82: =IF(ISBLANK(L82),"pending","estimated") -> pending
B83: 37 | C83: Counterstrike2 | D83: Team Falcons | E83: TeSeS | F83: René Madsen | G83: Player | H83: Instagram | I83: TeseS | J83: https://www.instagram.com/TeseS/ | K83: Followers | N83: manual | O83: =IF(ISBLANK(L83),"pending","estimated") -> pending | P83: Original entry was shorthand
B84: 37 | C84: Counterstrike2 | D84: Team Falcons | E84: TeSeS | F84: René Madsen | G84: Player | H84: Twitch | I84: tesesss | J84: https://www.twitch.tv/tesesss | K84: Followers | N84: manual | O84: =IF(ISBLANK(L84),"pending","estimated") -> pending
B85: 40 | C85: Counterstrike2 | D85: Falcons Force | E85: Tapewaare | F85: Sindre Ellefsen | G85: Player | H85: X | I85: tapewaare | J85: https://x.com/tapewaare | K85: Followers | N85: manual | O85: =IF(ISBLANK(L85),"pending","estimated") -> pending
B86: 40 | C86: Counterstrike2 | D86: Falcons Force | E86: Tapewaare | F86: Sindre Ellefsen | G86: Player | H86: Twitch | I86: Tapewaare | J86: https://www.twitch.tv/Tapewaare | K86: Followers | N86: manual | O86: =IF(ISBLANK(L86),"pending","estimated") -> pending
B87: 41 | C87: Counterstrike2 | D87: Falcons Force | E87: clockzi | F87: Oskar Led Blæsbjerg | G87: Player | H87: X | I87: flcclockzi | J87: https://x.com/flcclockzi | K87: Followers | N87: manual | O87: =IF(ISBLANK(L87),"pending","estimated") -> pending
B88: 42 | C88: Counterstrike2 | D88: Falcons Force | E88: grecu | F88: Andrei Grecu | G88: Player | H88: X | I88: grecuflc | J88: https://x.com/grecuflc | K88: Followers | N88: manual | O88: =IF(ISBLANK(L88),"pending","estimated") -> pending
B89: 42 | C89: Counterstrike2 | D89: Falcons Force | E89: grecu | F89: Andrei Grecu | G89: Player | H89: Twitch | I89: gbcgrecu | J89: https://www.twitch.tv/gbcgrecu | K89: Followers | N89: manual | O89: =IF(ISBLANK(L89),"pending","estimated") -> pending
B90: 43 | C90: Counterstrike2 | D90: Falcons Force | E90: VENO | F90: Vladimir Stanković | G90: Player | H90: X | I90: venocs2 | J90: https://x.com/venocs2 | K90: Followers | N90: manual | O90: =IF(ISBLANK(L90),"pending","estimated") -> pending
B91: 43 | C91: Counterstrike2 | D91: Falcons Force | E91: VENO | F91: Vladimir Stanković | G91: Player | H91: Twitch | I91: venocs2 | J91: https://www.twitch.tv/venocs2 | K91: Followers | N91: manual | O91: =IF(ISBLANK(L91),"pending","estimated") -> pending
B92: 43 | C92: Counterstrike2 | D92: Falcons Force | E92: VENO | F92: Vladimir Stanković | G92: Player | H92: YouTube | I92: @venocs2 | J92: https://www.youtube.com/@venocs2 | K92: Subscribers | N92: manual | O92: =IF(ISBLANK(L92),"pending","estimated") -> pending
B93: 46 | C93: Counterstrike2 | D93: Falcons Force | E93: Nucleonz | F93: Matej Trajkoski | G93: Player | H93: X | I93: NucleonZz | J93: https://x.com/NucleonZz | K93: Followers | N93: manual | O93: =IF(ISBLANK(L93),"pending","estimated") -> pending
B94: 47 | C94: Dota2 | D94: Dota2 | E94: Skiter | F94: Oliver Lepko | G94: Player | H94: X | I94: skiter | J94: https://x.com/skiter | K94: Followers | N94: manual | O94: =IF(ISBLANK(L94),"pending","estimated") -> pending
B95: 47 | C95: Dota2 | D95: Dota2 | E95: Skiter | F95: Oliver Lepko | G95: Player | H95: Instagram | I95: Skiter | J95: https://www.instagram.com/Skiter/ | K95: Followers | N95: manual | O95: =IF(ISBLANK(L95),"pending","estimated") -> pending | P95: Original entry was shorthand
B96: 47 | C96: Dota2 | D96: Dota2 | E96: Skiter | F96: Oliver Lepko | G96: Player | H96: Facebook | I96: SkiterDota | J96: https://www.facebook.com/SkiterDota | K96: Followers / Likes | N96: manual | O96: =IF(ISBLANK(L96),"pending","estimated") -> pending
B97: 48 | C97: Dota2 | D97: Dota2 | E97: Malr1ne | F97: Stanislav Potorak | G97: Player | H97: X | I97: Malr1ne_ | J97: https://x.com/Malr1ne_ | K97: Followers | N97: manual | O97: =IF(ISBLANK(L97),"pending","estimated") -> pending
B98: 48 | C98: Dota2 | D98: Dota2 | E98: Malr1ne | F98: Stanislav Potorak | G98: Player | H98: Instagram | I98: Malr1ne | J98: https://www.instagram.com/Malr1ne/ | K98: Followers | N98: manual | O98: =IF(ISBLANK(L98),"pending","estimated") -> pending | P98: Original entry was shorthand
B99: 48 | C99: Dota2 | D99: Dota2 | E99: Malr1ne | F99: Stanislav Potorak | G99: Player | H99: Twitch | I99: malr1ne_dota | J99: https://www.twitch.tv/malr1ne_dota | K99: Followers | N99: manual | O99: =IF(ISBLANK(L99),"pending","estimated") -> pending
B100: 49 | C100: Dota2 | D100: Dota2 | E100: ATF | F100: Ammar Al-Assaf | G100: Player | H100: X | I100: AmmarAlassaf6 | J100: https://x.com/AmmarAlassaf6 | K100: Followers | N100: manual | O100: =IF(ISBLANK(L100),"pending","estimated") -> pending
B101: 49 | C101: Dota2 | D101: Dota2 | E101: ATF | F101: Ammar Al-Assaf | G101: Player | H101: Instagram | I101: Ammar | J101: https://www.instagram.com/Ammar/ | K101: Followers | N101: manual | O101: =IF(ISBLANK(L101),"pending","estimated") -> pending | P101: Original entry was shorthand
B102: 49 | C102: Dota2 | D102: Dota2 | E102: ATF | F102: Ammar Al-Assaf | G102: Player | H102: Twitch | I102: ammar_the_f | J102: https://www.twitch.tv/ammar_the_f | K102: Followers | N102: manual | O102: =IF(ISBLANK(L102),"pending","estimated") -> pending
B103: 50 | C103: Dota2 | D103: Dota2 | E103: Cr1t- | F103: Andreas Nielsen | G103: Player | H103: X | I103: Cr1tdota | J103: https://x.com/Cr1tdota | K103: Followers | N103: manual | O103: =IF(ISBLANK(L103),"pending","estimated") -> pending
B104: 50 | C104: Dota2 | D104: Dota2 | E104: Cr1t- | F104: Andreas Nielsen | G104: Player | H104: Instagram | I104: Cr1t | J104: https://www.instagram.com/Cr1t/ | K104: Followers | N104: manual | O104: =IF(ISBLANK(L104),"pending","estimated") -> pending | P104: Original entry was shorthand
B105: 50 | C105: Dota2 | D105: Dota2 | E105: Cr1t- | F105: Andreas Nielsen | G105: Player | H105: Twitch | I105: cr1tdota | J105: https://www.twitch.tv/cr1tdota | K105: Followers | N105: manual | O105: =IF(ISBLANK(L105),"pending","estimated") -> pending
B106: 50 | C106: Dota2 | D106: Dota2 | E106: Cr1t- | F106: Andreas Nielsen | G106: Player | H106: YouTube | I106: Cr1t | J106: https://www.youtube.com/@Cr1t | K106: Subscribers | N106: manual | O106: =IF(ISBLANK(L106),"pending","estimated") -> pending | P106: Original entry was shorthand; Channel format may need validation
B107: 50 | C107: Dota2 | D107: Dota2 | E107: Cr1t- | F107: Andreas Nielsen | G107: Player | H107: Facebook | I107: Cr1tdota | J107: https://www.facebook.com/Cr1tdota | K107: Followers / Likes | N107: manual | O107: =IF(ISBLANK(L107),"pending","estimated") -> pending
B108: 51 | C108: Dota2 | D108: Dota2 | E108: Sneyking | F108: Jingjun Wu | G108: Player | H108: X | I108: SneykingGaming | J108: https://x.com/SneykingGaming | K108: Followers | N108: manual | O108: =IF(ISBLANK(L108),"pending","estimated") -> pending
B109: 51 | C109: Dota2 | D109: Dota2 | E109: Sneyking | F109: Jingjun Wu | G109: Player | H109: Twitch | I109: sneykingdota | J109: https://www.twitch.tv/sneykingdota | K109: Followers | N109: manual | O109: =IF(ISBLANK(L109),"pending","estimated") -> pending
B110: 55 | C110: EAFC25 | D110: EA Sport FC | E110: GoatMoh | F110: Mohammed Alarfaj | G110: Player | H110: X | I110: GoatMoh_ | J110: https://x.com/GoatMoh_ | K110: Followers | N110: manual | O110: =IF(ISBLANK(L110),"pending","estimated") -> pending
B111: 55 | C111: EAFC25 | D111: EA Sport FC | E111: GoatMoh | F111: Mohammed Alarfaj | G111: Player | H111: Twitch | I111: goatmoh | J111: https://www.twitch.tv/goatmoh | K111: Followers | N111: manual | O111: =IF(ISBLANK(L111),"pending","estimated") -> pending
B112: 58 | C112: EAFC25 | D112: EA Sport FC | E112: Msdossary | F112: Mossad Aldossary | G112: Player | H112: X | I112: msdossary7 | J112: https://x.com/msdossary7 | K112: Followers | N112: manual | O112: =IF(ISBLANK(L112),"pending","estimated") -> pending
B113: 58 | C113: EAFC25 | D113: EA Sport FC | E113: Msdossary | F113: Mossad Aldossary | G113: Player | H113: Instagram | I113: Msdossary | J113: https://www.instagram.com/Msdossary/ | K113: Followers | N113: manual | O113: =IF(ISBLANK(L113),"pending","estimated") -> pending | P113: Original entry was shorthand
B114: 58 | C114: EAFC25 | D114: EA Sport FC | E114: Msdossary | F114: Mossad Aldossary | G114: Player | H114: YouTube | I114: Msdossary7 | J114: https://www.youtube.com/@Msdossary7 | K114: Subscribers | N114: manual | O114: =IF(ISBLANK(L114),"pending","estimated") -> pending | P114: Original entry was shorthand; Channel format may need validation
B115: 59 | C115: EAFC25 | D115: EA Sport FC | E115: Vejrgang | F115: Anders Vejrgang | G115: Player | H115: X | I115: FLC_Vejrgang | J115: https://twitter.com/FLC_Vejrgang | K115: Followers | N115: manual | O115: =IF(ISBLANK(L115),"pending","estimated") -> pending
B116: 59 | C116: EAFC25 | D116: EA Sport FC | E116: Vejrgang | F116: Anders Vejrgang | G116: Player | H116: Instagram | I116: rblz_vejrgang | J116: https://www.instagram.com/rblz_vejrgang | K116: Followers | N116: manual | O116: =IF(ISBLANK(L116),"pending","estimated") -> pending
B117: 59 | C117: EAFC25 | D117: EA Sport FC | E117: Vejrgang | F117: Anders Vejrgang | G117: Player | H117: Twitch | I117: anders_vejrgang | J117: https://www.twitch.tv/anders_vejrgang | K117: Followers | N117: manual | O117: =IF(ISBLANK(L117),"pending","estimated") -> pending
B118: 59 | C118: EAFC25 | D118: EA Sport FC | E118: Vejrgang | F118: Anders Vejrgang | G118: Player | H118: YouTube | I118: AndersVejrgangofficial | J118: https://www.youtube.com/AndersVejrgangofficial | K118: Subscribers | N118: manual | O118: =IF(ISBLANK(L118),"pending","estimated") -> pending
B119: 61 | C119: EAFC25 | D119: EA Sport FC | E119: Kiimo7 | F119: Abdulkareem Bamogaddam | G119: Player | H119: X | I119: kiimo__1 | J119: https://x.com/kiimo__1 | K119: Followers | N119: manual | O119: =IF(ISBLANK(L119),"pending","estimated") -> pending
B120: 61 | C120: EAFC25 | D120: EA Sport FC | E120: Kiimo7 | F120: Abdulkareem Bamogaddam | G120: Player | H120: Instagram | I120: kreemvv | J120: https://www.instagram.com/kreemvv/ | K120: Followers | N120: manual | O120: =IF(ISBLANK(L120),"pending","estimated") -> pending
B121: 62 | C121: EAFC25 | D121: EA Sport FC | E121: 1OS | F121: Osama Khamees | G121: Player | H121: X | I121: The1OS_ | J121: https://x.com/The1OS_ | K121: Followers | N121: manual | O121: =IF(ISBLANK(L121),"pending","estimated") -> pending
B122: 62 | C122: EAFC25 | D122: EA Sport FC | E122: 1OS | F122: Osama Khamees | G122: Player | H122: Kick | I122: the1os | J122: https://kick.com/the1os | K122: Followers | N122: manual | O122: =IF(ISBLANK(L122),"pending","estimated") -> pending
B123: 63 | C123: Fatal Fury | D123: Fatal Fury | E123: Abu Omar | F123: Wesam Alghamdi | G123: Player | H123: X | I123: wess21111 | J123: https://x.com/wess21111?lang=en | K123: Followers | N123: manual | O123: =IF(ISBLANK(L123),"pending","estimated") -> pending
B124: 64 | C124: Fatal Fury | D124: Fatal Fury | E124: E.T. | F124: Lin Chia-hung | G124: Player | H124: X | I124: et1120 | J124: https://x.com/et1120 | K124: Followers | N124: manual | O124: =IF(ISBLANK(L124),"pending","estimated") -> pending
B125: 64 | C125: Fatal Fury | D125: Fatal Fury | E125: E.T. | F125: Lin Chia-hung | G125: Player | H125: Instagram | I125: dbj_et | J125: https://www.instagram.com/dbj_et/# | K125: Followers | N125: manual | O125: =IF(ISBLANK(L125),"pending","estimated") -> pending
B126: 64 | C126: Fatal Fury | D126: Fatal Fury | E126: E.T. | F126: Lin Chia-hung | G126: Player | H126: Facebook | I126: Taiwan.1.ET | J126: https://www.facebook.com/Taiwan.1.ET | K126: Followers / Likes | N126: manual | O126: =IF(ISBLANK(L126),"pending","estimated") -> pending
... B275: 154 | C275: Rocket League | D275: Team Falcons | E275: Kiileerrz | F275: Yazeed Bakhashwin | G275: Player | H275: X | I275: kiileerrz | J275: https://x.com/kiileerrz | K275: Followers | N275: manual | O275: =IF(ISBLANK(L275),"pending","estimated") -> pending
B276: 154 | C276: Rocket League | D276: Team Falcons | E276: Kiileerrz | F276: Yazeed Bakhashwin | G276: Player | H276: Instagram | I276: Kiileerrz | J276: https://www.instagram.com/Kiileerrz/ | K276: Followers | N276: manual | O276: =IF(ISBLANK(L276),"pending","estimated") -> pending | P276: Original entry was shorthand
B277: 154 | C277: Rocket League | D277: Team Falcons | E277: Kiileerrz | F277: Yazeed Bakhashwin | G277: Player | H277: Twitch | I277: kiileerrz | J277: https://www.twitch.tv/kiileerrz | K277: Followers | N277: manual | O277: =IF(ISBLANK(L277),"pending","estimated") -> pending
B278: 155 | C278: Rocket League | D278: Team Falcons | E278: Rw9 | F278: Saleh Bakhashwin | G278: Player | H278: X | I278: Rw9_RL | J278: https://x.com/Rw9_RL | K278: Followers | N278: manual | O278: =IF(ISBLANK(L278),"pending","estimated") -> pending
B279: 155 | C279: Rocket League | D279: Team Falcons | E279: Rw9 | F279: Saleh Bakhashwin | G279: Player | H279: Twitch | I279: rl_rw9 | J279: https://www.twitch.tv/rl_rw9 | K279: Followers | N279: manual | O279: =IF(ISBLANK(L279),"pending","estimated") -> pending
B280: 156 | C280: Street Fighter | D280: Street Fighter | E280: Craime | F280: Jaime Bustos | G280: Player | H280: X | I280: CraimeCL | J280: https://x.com/CraimeCL | K280: Followers | N280: manual | O280: =IF(ISBLANK(L280),"pending","estimated") -> pending
B281: 157 | C281: Street Fighter | D281: Street Fighter | E281: Kusanagi | F281: Maivine Touiti | G281: Player | H281: X | I281: MaivineKusanagi | J281: https://twitter.com/MaivineKusanagi | K281: Followers | N281: manual | O281: =IF(ISBLANK(L281),"pending","estimated") -> pending
B282: 157 | C282: Street Fighter | D282: Street Fighter | E282: Kusanagi | F282: Maivine Touiti | G282: Player | H282: Twitch | I282: KusanagiSF6 | J282: https://www.twitch.tv/KusanagiSF6 | K282: Followers | N282: manual | O282: =IF(ISBLANK(L282),"pending","estimated") -> pending
B283: 158 | C283: Street Fighter | D283: Street Fighter | E283: Xiaohai | F283: Zeng Zhuojun | G283: Player | H283: X | I283: Xiaohai_ | J283: https://x.com/Xiaohai_ | K283: Followers | N283: manual | O283: =IF(ISBLANK(L283),"pending","estimated") -> pending
B284: 160 | C284: Tekken | D284: Tekken | E284: Aqeel9 | F284: Mishari Alaqeel | G284: Player | H284: X | I284: mka988 | J284: https://x.com/mka988 | K284: Followers | N284: manual | O284: =IF(ISBLANK(L284),"pending","estimated") -> pending
B285: 160 | C285: Tekken | D285: Tekken | E285: Aqeel9 | F285: Mishari Alaqeel | G285: Player | H285: Twitch | I285: aqeel9h | J285: https://www.twitch.tv/aqeel9h | K285: Followers | N285: manual | O285: =IF(ISBLANK(L285),"pending","estimated") -> pending
B286: 161 | C286: Tekken | D286: Tekken | E286: Atif Butt | F286: Atif Ijaz | G286: Player | H286: X | I286: AtifButt540 | J286: https://x.com/AtifButt540 | K286: Followers | N286: manual | O286: =IF(ISBLANK(L286),"pending","estimated") -> pending
B287: 162 | C287: Tekken | D287: Tekken | E287: Farzeen | F287: Muhammad Farzeen | G287: Player | H287: X | I287: Farzeen_tk | J287: https://x.com/Farzeen_tk | K287: Followers | N287: manual | O287: =IF(ISBLANK(L287),"pending","estimated") -> pending
B288: 162 | C288: Tekken | D288: Tekken | E288: Farzeen | F288: Muhammad Farzeen | G288: Player | H288: Instagram | I288: farzeen_tk | J288: https://www.instagram.com/farzeen_tk/ | K288: Followers | N288: manual | O288: =IF(ISBLANK(L288),"pending","estimated") -> pending
... B308: 178 | C308: Crossfire | D308: Team Falcons | E308: Shady | F308: Mai Thanh Phong | G308: Player | H308: Facebook | I308: Shadycrossfirevn | J308: https://www.facebook.com/Shadycrossfirevn | K308: Followers / Likes | N308: manual | O308: =IF(ISBLANK(L308),"pending","estimated") -> pending
B311: Team Falcons · Unified Talent Pricing OS v1.2 · Confidential

Sheet 11_Confidence
B2: 11 — MEASUREMENT CONFIDENCE & VERIFICATION
B3: Confidence is an enforcement layer, not decoration. Low confidence caps how aggressively premiums can stack, protecting Falcons from over-pricing weakly verified talent.
B5: CONFIDENCE LEVELS & CAPS
B6: Level | C6: Trigger | D6: Premium Policy | E6: Max Combined Stack
B7: exact | C7: Verified via Shikenso API or direct platform access. | D7: All multipliers allowed, no cap. | E7: Computed × 1.00
B8: rounded | C8: Manual verification — clean round numbers from recent check. | D8: All multipliers allowed, no cap. | E8: Computed × 1.00
B9: estimated | C9: Partial data / single-source public scrape. | D9: Eng ≤ 1.20, Authority ≤ 1.30, Season ≤ 1.25. | E9: Computed × 0.90
B10: pending | C10: No follower data yet — awaiting verification. | D10: All premiums forced to 1.00 (baseline). | E10: Computed × 0.75
B12: VERIFICATION WORKFLOW
B13: ① Sync handles | C13: Pull from 10_Social_Tracker — normalized URL + handle per platform
B14: ② Capture count | C14: Enter follower count + Retrieved-On date; source marked
B15: ③ Tag confidence | C15: Set level on 20/30 rate cards; default is 'pending' until data arrives
B16: ④ Quarterly review | C16: Re-pull; estimated → rounded upgrade if recent check passes
B17: ⑤ Shikenso cutover | C17: When API is connected, confidence auto-writes to 'exact'
B19: Confidence is also applied inside 40_Adjustment_Matrix as a gate. See 90_Methodology §5.
B22: Team Falcons · Unified Talent Pricing OS v1.2 · Confidential

Sheet 20_Player_Rate_Card
B2: 20 — PLAYER RATE CARD (v1.0)
B3: Baseline preserved from v7. Follower / CPM / Floor / Confidence extensions preserved from v8. Adjust rates here — every quote pulls from this card.
B4: Identity & Tier | J4: Organic Platform Rates (SAR) | T4: Add-On Fees | X4: Ops & Commercial | AA4: Identity & Handles | AM4: Followers (← fill as verified) | AT4: CPM (auto) | AY4: Authority Floor & Confidence
B5: # | C5: Nickname | D5: Role | E5: Game | F5: Team | G5: Nationality | H5: Platforms | I5: Tier | J5: IG Reel (SAR) | K5: IG Static (SAR) | L5: IG Story (SAR) | M5: TikTok Video (SAR) | N5: YT Short (SAR) | O5: X Post (SAR) | P5: FB Post/Video (SAR) | Q5: Twitch Stream 2h (SAR) | R5: Twitch Integ. (SAR) | S5: IRL / Appear. (SAR) | T5: Rights Fee (SAR) | U5: Exclusivity Fee (SAR) | V5: Rush Fee (SAR) | W5: WL Fee (SAR) | X5: Notes | Y5: Falcons Commission % | Z5: Markup % (on Player Cost) | AA5: Full Name | AB5: X / Twitter | AC5: Instagram | AD5: Twitch | AE5: YouTube | AF5: TikTok | AG5: Kick | AH5: Facebook | AI5: Snapchat | AJ5: Link-in-Bio | AK5: Date of Birth | AL5: Game Role | AM5: X Followers | AN5: IG Followers | AO5: Twitch Followers | AP5: YT Subs | AQ5: TikTok Followers | AR5: Kick Followers | AS5: FB Followers | AT5: IG CPM (SAR) | AU5: TikTok CPM (SAR) | AV5: X CPM (SAR) | AW5: YT CPM (SAR) | AX5: Twitch CPM (SAR) | AY5: Floor Share % | AZ5: Authority Factor | BA5: Default Seasonality | BB5: Default Language | BC5: Authority Floor Baseline (SAR) | BD5: Measurement Confidence | BE5: Tier Review Flag
B6: =IF($C6="","",COUNTA($C$6:C6)) -> 1 | C6: Bijw | D6: Influencer | E6: Esports Influencers | F6: Esports Influencers | G6: Saudi Arabia | H6: 6 | I6: Tier 3 | J6: 11000 | K6: 4600 | L6: =IF(J6="","",ROUND(J6*0.17,0)) -> 1870 | M6: 8600 | N6: 3500 | O6: 2200 | P6: 2200 | Q6: 15950 | R6: 7150 | S6: =IF(J6="","",ROUND(J6*2.2,0)) -> 24200 | T6: 3850 | U6: 3300 | V6: 2000 | W6: 1650 | X6: 6 platforms | Y6: 0.3 | Z6: 1 | AA6: Hisham Nasser | AB6: https://x.com/_bijw | AC6: https://www.instagram.com/bijjw | AD6: https://www.twitch.tv/bijw | AE6: https://www.youtube.com/@Bijw | AF6: https://www.tiktok.com/@biijw | AG6: https://kick.com/bijw | AI6: https://www.snapchat.com/add/bijjw | AJ6: https://linktr.ee/bijw | AT6: =IFERROR(IF(AND(AN6>0,J6>0),ROUND(J6*1000/(AN6*0.2),0),""),"") | AU6: =IFERROR(IF(AND(AQ6>0,M6>0),ROUND(M6*1000/(AQ6*0.3),0),""),"") | AV6: =IFERROR(IF(AND(AM6>0,O6>0),ROUND(O6*1000/(AM6*0.1),0),""),"") | AW6: =IFERROR(IF(AND(AP6>0,N6>0),ROUND(N6*1000/(AP6*0.25),0),""),"") | AX6: =IFERROR(IF(AND(AO6>0,Q6>0),ROUND(Q6*1000/(AO6*1),0),""),"") | AY6: =IFERROR(ifs(I6="Tier S",0.65,I6="Tier 1",0.55,I6="Tier 2",0.45,I6="Tier 3",0.35,I6="Tier 4",0.25),0.35) -> 0.35 | AZ6: 1 | BA6: 1 | BB6: 1 | BC6: =IFERROR(ROUND(S6*AY6*BA6*BB6*AZ6,0),0) -> 8470 | BD6: =IF(COUNT(AM6,AN6,AO6,AP6,AQ6,AR6,AS6)>0,"estimated","pending") -> pending
B7: =IF($C7="","",COUNTA($C$6:C7)) -> 2 | C7: Abo Najd | D7: Influencer | E7: Esports Influencers | F7: Esports Influencers | G7: Saudi Arabia | H7: 4 | I7: Tier 3 | J7: 8100 | K7: 3200 | L7: =IF(J7="","",ROUND(J7*0.17,0)) -> 1377 | M7: 6350 | N7: 2600 | O7: 1600 | P7: 1600 | Q7: 11800 | R7: 5300 | S7: =IF(J7="","",ROUND(J7*2.2,0)) -> 17820 | T7: 2850 | U7: 2450 | V7: 1450 | W7: 1215 | X7: 4 platforms | Y7: 0.3 | Z7: 1 | AA7: Riyad Alfahmi | AB7: https://x.com/K22N8 | AC7: https://www.instagram.com/k2nn8?igsh=ajJsNHoybDlpMzFo | AD7: https://www.twitch.tv/k2nnn8 | AE7: https://www.youtube.com/@k2nn8 | AJ7: https://linktr.ee/K2nnn8 (alt: https://heylink.me/k2nn8) | AT7: =IFERROR(IF(AND(AN7>0,J7>0),ROUND(J7*1000/(AN7*0.2),0),""),"") | AU7: =IFERROR(IF(AND(AQ7>0,M7>0),ROUND(M7*1000/(AQ7*0.3),0),""),"") | AV7: =IFERROR(IF(AND(AM7>0,O7>0),ROUND(O7*1000/(AM7*0.1),0),""),"") | AW7: =IFERROR(IF(AND(AP7>0,N7>0),ROUND(N7*1000/(AP7*0.25),0),""),"") | AX7: =IFERROR(IF(AND(AO7>0,Q7>0),ROUND(Q7*1000/(AO7*1),0),""),"") | AY7: =IFERROR(ifs(I7="Tier S",0.65,I7="Tier 1",0.55,I7="Tier 2",0.45,I7="Tier 3",0.35,I7="Tier 4",0.25),0.35) -> 0.35 | AZ7: 1 | BA7: 1 | BB7: 1 | BC7: =IFERROR(ROUND(S7*AY7*BA7*BB7*AZ7,0),0) -> 6237 | BD7: =IF(COUNT(AM7,AN7,AO7,AP7,AQ7,AR7,AS7)>0,"estimated","pending") -> pending
B8: =IF($C8="","",COUNTA($C$6:C8)) -> 3 | C8: FMG | D8: Influencer | E8: Esports Influencers | F8: Esports Influencers | G8: Saudi Arabia | H8: 4 | I8: Tier 3 | J8: 7450 | K8: 3150 | L8: =IF(J8="","",ROUND(J8*0.17,0)) -> 1267 | M8: 5850 | N8: 2400 | O8: 1500 | P8: 1500 | Q8: 10850 | R8: 4850 | S8: =IF(J8="","",ROUND(J8*2.2,0)) -> 16390 | T8: 2600 | U8: 2250 | V8: 1350 | W8: 1118 | X8: 4 platforms | Y8: 0.3 | Z8: 1 | AA8: Nasser alotaibi | AB8: https://x.com/iFMG_ | AC8: https://www.instagram.com/fm.g/ | AD8: https://www.twitch.tv/fmg_ | AG8: https://kick.com/ifmg | AT8: =IFERROR(IF(AND(AN8>0,J8>0),ROUND(J8*1000/(AN8*0.2),0),""),"") | AU8: =IFERROR(IF(AND(AQ8>0,M8>0),ROUND(M8*1000/(AQ8*0.3),0),""),"") | AV8: =IFERROR(IF(AND(AM8>0,O8>0),ROUND(O8*1000/(AM8*0.1),0),""),"") | AW8: =IFERROR(IF(AND(AP8>0,N8>0),ROUND(N8*1000/(AP8*0.25),0),""),"") | AX8: =IFERROR(IF(AND(AO8>0,Q8>0),ROUND(Q8*1000/(AO8*1),0),""),"") | AY8: =IFERROR(ifs(I8="Tier S",0.65,I8="Tier 1",0.55,I8="Tier 2",0.45,I8="Tier 3",0.35,I8="Tier 4",0.25),0.35) -> 0.35 | AZ8: 1 | BA8: 1 | BB8: 1 | BC8: =IFERROR(ROUND(S8*AY8*BA8*BB8*AZ8,0),0) -> 5737 | BD8: =IF(COUNT(AM8,AN8,AO8,AP8,AQ8,AR8,AS8)>0,"estimated","pending") -> pending
B9: =IF($C9="","",COUNTA($C$6:C9)) -> 4 | C9: Abo Ghazi | D9: Influencer | E9: Esports Influencers | F9: Esports Influencers | G9: Saudi Arabia | H9: 3 | I9: Tier 3 | J9: 5200 | K9: 2200 | L9: =IF(J9="","",ROUND(J9*0.17,0)) -> 884 | M9: 4050 | N9: 1650 | O9: 1050 | P9: 1050 | Q9: 7550 | R9: 3400 | S9: =IF(J9="","",ROUND(J9*2.2,0)) -> 11440 | T9: 1800 | U9: 1550 | V9: 950 | W9: 780 | X9: 3 platforms | Y9: 0.3 | Z9: 1 | AA9: Mohammed Albaqami | AB9: https://x.com/MohxamedZ | AD9: https://www.twitch.tv/ires | AG9: https://kick.com/iabughazi | AH9: https://www.facebook.com/AbuGhaziGaming93 | AI9: https://www.snapchat.com/add/faisalhajhasan | AJ9: https://linktr.ee/abughaazi | AT9: =IFERROR(IF(AND(AN9>0,J9>0),ROUND(J9*1000/(AN9*0.2),0),""),"") | AU9: =IFERROR(IF(AND(AQ9>0,M9>0),ROUND(M9*1000/(AQ9*0.3),0),""),"") | AV9: =IFERROR(IF(AND(AM9>0,O9>0),ROUND(O9*1000/(AM9*0.1),0),""),"") | AW9: =IFERROR(IF(AND(AP9>0,N9>0),ROUND(N9*1000/(AP9*0.25),0),""),"") | AX9: =IFERROR(IF(AND(AO9>0,Q9>0),ROUND(Q9*1000/(AO9*1),0),""),"") | AY9: =IFERROR(ifs(I9="Tier S",0.65,I9="Tier 1",0.55,I9="Tier 2",0.45,I9="Tier 3",0.35,I9="Tier 4",0.25),0.35) -> 0.35 | AZ9: 1 | BA9: 1 | BB9: 1 | BC9: =IFERROR(ROUND(S9*AY9*BA9*BB9*AZ9,0),0) -> 4004 | BD9: =IF(COUNT(AM9,AN9,AO9,AP9,AQ9,AR9,AS9)>0,"estimated","pending") -> pending
B10: =IF($C10="","",COUNTA($C$6:C10)) -> 5 | C10: Mary | D10: Influencer | E10: Esports Influencers | F10: Esports Influencers | G10: Bahraini | H10: 5 | I10: Tier 3 | J10: 8100 | K10: 3400 | L10: =IF(J10="","",ROUND(J10*0.17,0)) -> 1377 | M10: 6350 | N10: 2600 | O10: 1600 | P10: 1600 | Q10: 11800 | R10: 5300 | S10: =IF(J10="","",ROUND(J10*2.2,0)) -> 17820 | T10: 2850 | U10: 2450 | V10: 1450 | W10: 1215 | X10: 5 platforms | Y10: 0.3 | Z10: 1 | AA10: Maryam Maher | AB10: https://x.com/marypink | AC10: https://www.instagram.com/maryvalorantt/?hl=en | AD10: https://www.twitch.tv/mary | AE10: https://www.youtube.com/@maryvalorant/featured | AF10: https://www.tiktok.com/@maryvalorant | AJ10: https://linktr.ee/verymarygaming | AT10: =IFERROR(IF(AND(AN10>0,J10>0),ROUND(J10*1000/(AN10*0.2),0),""),"") | AU10: =IFERROR(IF(AND(AQ10>0,M10>0),ROUND(M10*1000/(AQ10*0.3),0),""),"") | AV10: =IFERROR(IF(AND(AM10>0,O10>0),ROUND(O10*1000/(AM10*0.1),0),""),"") | AW10: =IFERROR(IF(AND(AP10>0,N10>0),ROUND(N10*1000/(AP10*0.25),0),""),"") | AX10: =IFERROR(IF(AND(AO10>0,Q10>0),ROUND(Q10*1000/(AO10*1),0),""),"") | AY10: =IFERROR(ifs(I10="Tier S",0.65,I10="Tier 1",0.55,I10="Tier 2",0.45,I10="Tier 3",0.35,I10="Tier 4",0.25),0.35) -> 0.35 | AZ10: 1 | BA10: 1 | BB10: 1 | BC10: =IFERROR(ROUND(S10*AY10*BA10*BB10*AZ10,0),0) -> 6237 | BD10: =IF(COUNT(AM10,AN10,AO10,AP10,AQ10,AR10,AS10)>0,"estimated","pending") -> pending
B11: =IF($C11="","",COUNTA($C$6:C11)) -> 6 | C11: Ghala | D11: Influencer | E11: Esports Influencers | F11: Esports Influencers | G11: Saudi Arabia | H11: 5 | I11: Tier 3 | J11: 7450 | K11: 3150 | L11: =IF(J11="","",ROUND(J11*0.17,0)) -> 1267 | M11: 5850 | N11: 2400 | O11: 1500 | P11: 1500 | Q11: 10850 | R11: 4850 | S11: =IF(J11="","",ROUND(J11*2.2,0)) -> 16390 | T11: 2600 | U11: 2250 | V11: 1350 | W11: 1118 | X11: 5 platforms | Y11: 0.3 | Z11: 1 | AA11: Ghala Alqahtani | AB11: https://x.com/pg_ghala3?lang=en | AC11: https://www.instagram.com/pg_ghala3 | AE11: https://www.youtube.com/@pg_ghala3 | AF11: https://www.tiktok.com/@pg_ghala3 | AG11: https://kick.com/pg-ghala3 | AI11: https://snapchat.com/t/bLA2ZOsG | AJ11: https://linktr.ee/ga1lll | AT11: =IFERROR(IF(AND(AN11>0,J11>0),ROUND(J11*1000/(AN11*0.2),0),""),"") | AU11: =IFERROR(IF(AND(AQ11>0,M11>0),ROUND(M11*1000/(AQ11*0.3),0),""),"") | AV11: =IFERROR(IF(AND(AM11>0,O11>0),ROUND(O11*1000/(AM11*0.1),0),""),"") | AW11: =IFERROR(IF(AND(AP11>0,N11>0),ROUND(N11*1000/(AP11*0.25),0),""),"") | AX11: =IFERROR(IF(AND(AO11>0,Q11>0),ROUND(Q11*1000/(AO11*1),0),""),"") | AY11: =IFERROR(ifs(I11="Tier S",0.65,I11="Tier 1",0.55,I11="Tier 2",0.45,I11="Tier 3",0.35,I11="Tier 4",0.25),0.35) -> 0.35 | AZ11: 1 | BA11: 1 | BB11: 1 | BC11: =IFERROR(ROUND(S11*AY11*BA11*BB11*AZ11,0),0) -> 5737 | BD11: =IF(COUNT(AM11,AN11,AO11,AP11,AQ11,AR11,AS11)>0,"estimated","pending") -> pending
B12: =IF($C12="","",COUNTA($C$6:C12)) -> 7 | C12: Moaz | D12: Influencer | E12: Esports Influencers | F12: Esports Influencers | G12: Saudi Arabia | H12: 5 | I12: Tier 2 | J12: 6500 | K12: 5300 | L12: =IF(J12="","",ROUND(J12*0.17,0)) -> 1105 | M12: 3400 | N12: 4050 | O12: 2500 | P12: 2500 | Q12: 15950 | R12: 8200 | S12: =IF(J12="","",ROUND(J12*2.2,0)) -> 14300 | T12: 3800 | U12: 1900 | V12: 3150 | W12: 1250 | X12: 5 platforms | Y12: 0.3 | Z12: 1 | AA12: Moaz Asiri | AB12: https://x.com/mezostrong?s=21 | AC12: https://www.instagram.com/mezostrong | AE12: https://www.youtube.com/channel/UCZCgW8WW8K_vrHrO6sZ7oyg?app=desktop | AF12: https://www.tiktok.com/@mezostrong?_r=1&_t=zs-91bbrrsefwl | AG12: https://kick.com/MezoStrong | AT12: =IFERROR(IF(AND(AN12>0,J12>0),ROUND(J12*1000/(AN12*0.2),0),""),"") | AU12: =IFERROR(IF(AND(AQ12>0,M12>0),ROUND(M12*1000/(AQ12*0.3),0),""),"") | AV12: =IFERROR(IF(AND(AM12>0,O12>0),ROUND(O12*1000/(AM12*0.1),0),""),"") | AW12: =IFERROR(IF(AND(AP12>0,N12>0),ROUND(N12*1000/(AP12*0.25),0),""),"") | AX12: =IFERROR(IF(AND(AO12>0,Q12>0),ROUND(Q12*1000/(AO12*1),0),""),"") | AY12: =IFERROR(ifs(I12="Tier S",0.65,I12="Tier 1",0.55,I12="Tier 2",0.45,I12="Tier 3",0.35,I12="Tier 4",0.25),0.35) -> 0.35 | AZ12: 1 | BA12: 1 | BB12: 1 | BC12: =IFERROR(ROUND(S12*AY12*BA12*BB12*AZ12,0),0) -> 5005 | BD12: =IF(COUNT(AM12,AN12,AO12,AP12,AQ12,AR12,AS12)>0,"estimated","pending") -> pending
B13: =IF($C13="","",COUNTA($C$6:C13)) -> 8 | C13: vacwep | D13: Influencer | E13: Esports Influencers | F13: Esports Influencers | G13: Saudi Arabia | H13: 5 | I13: Tier 3 | J13: 7450 | K13: 3150 | L13: =IF(J13="","",ROUND(J13*0.17,0)) -> 1267 | M13: 5800 | N13: 2400 | O13: 1500 | P13: 1500 | Q13: 7500 | R13: 4850 | S13: =IF(J13="","",ROUND(J13*2.2,0)) -> 16390 | T13: 2250 | U13: 1100 | V13: 1850 | W13: 750 | X13: 5 platforms | Y13: 0.3 | Z13: 1 | AA13: Abdullah Mousa A Alsulaymi | AB13: https://x.com/vacwep?s=21&t=PiVx0_LPZgUm0TT5Ok_2Zw | AC13: https://www.instagram.com/vacwep_?igsh=Z28yMXRibTZ0OWlm&utm_source=qr | AF13: https://www.tiktok.com/@vacwep?_r=1&_t=ZS-94jrcxtNGEK | AG13: https://kick.com/vacwep | AH13: https://www.facebook.com/share/1BDLRfGMFS/?mibextid=wwXIfr | AK13: 12/07/1992 | AT13: =IFERROR(IF(AND(AN13>0,J13>0),ROUND(J13*1000/(AN13*0.2),0),""),"") | AU13: =IFERROR(IF(AND(AQ13>0,M13>0),ROUND(M13*1000/(AQ13*0.3),0),""),"") | AV13: =IFERROR(IF(AND(AM13>0,O13>0),ROUND(O13*1000/(AM13*0.1),0),""),"") | AW13: =IFERROR(IF(AND(AP13>0,N13>0),ROUND(N13*1000/(AP13*0.25),0),""),"") | AX13: =IFERROR(IF(AND(AO13>0,Q13>0),ROUND(Q13*1000/(AO13*1),0),""),"") | AY13: =IFERROR(ifs(I13="Tier S",0.65,I13="Tier 1",0.55,I13="Tier 2",0.45,I13="Tier 3",0.35,I13="Tier 4",0.25),0.35) -> 0.35 | AZ13: 1 | BA13: 1 | BB13: 1 | BC13: =IFERROR(ROUND(S13*AY13*BA13*BB13*AZ13,0),0) -> 5737 | BD13: =IF(COUNT(AM13,AN13,AO13,AP13,AQ13,AR13,AS13)>0,"estimated","pending") -> pending
B14: =IF($C14="","",COUNTA($C$6:C14)) -> 9 | C14: Cellium | D14: Player | E14: Call of Duty Black Ops 7 | F14: Riyadh Falcons | G14: American | H14: 3 | I14: Tier 2 | J14: 11250 | K14: 4500 | L14: =IF(J14="","",ROUND(J14*0.17,0)) -> 1913 | M14: 8000 | N14: 3500 | O14: 2000 | P14: 2000 | Q14: 13500 | R14: 6075 | S14: =IF(J14="","",ROUND(J14*2.2,0)) -> 24750 | T14: 4638 | U14: 4063 | V14: 2438 | W14: 2400 | X14: 3 platforms | Y14: 0.3 | Z14: 1 | AA14: McArthur Jovel | AB14: https://twitter.com/Cellium | AC14: https://www.instagram.com/cellium/ | AD14: https://www.twitch.tv/Cellium | AK14: 24/12/2000 | AL14: Assault Rifle / Main AR | AT14: =IFERROR(IF(AND(AN14>0,J14>0),ROUND(J14*1000/(AN14*0.2),0),""),"") | AU14: =IFERROR(IF(AND(AQ14>0,M14>0),ROUND(M14*1000/(AQ14*0.3),0),""),"") | AV14: =IFERROR(IF(AND(AM14>0,O14>0),ROUND(O14*1000/(AM14*0.1),0),""),"") | AW14: =IFERROR(IF(AND(AP14>0,N14>0),ROUND(N14*1000/(AP14*0.25),0),""),"") | AX14: =IFERROR(IF(AND(AO14>0,Q14>0),ROUND(Q14*1000/(AO14*1),0),""),"") | AY14: =IFERROR(ifs(I14="Tier S",0.65,I14="Tier 1",0.55,I14="Tier 2",0.45,I14="Tier 3",0.35,I14="Tier 4",0.25),0.35) -> 0.35 | AZ14: 1 | BA14: 1 | BB14: 1 | BC14: =IFERROR(ROUND(S14*AY14*BA14*BB14*AZ14,0),0) -> 8663 | BD14: =IF(COUNT(AM14,AN14,AO14,AP14,AQ14,AR14,AS14)>0,"estimated","pending") -> pending
B15: =IF($C15="","",COUNTA($C$6:C15)) -> 10 | C15: Exnid | D15: Player | E15: Call of Duty Black Ops 7 | F15: Riyadh Falcons | G15: Saudi Arabia | H15: 2 | I15: Tier 2 | J15: 11000 | K15: 4600 | L15: =IF(J15="","",ROUND(J15*0.17,0)) -> 1870 | M15: 8600 | N15: 3500 | O15: 2200 | P15: 2200 | Q15: 15950 | R15: 7150 | S15: =IF(J15="","",ROUND(J15*2.2,0)) -> 24200 | T15: 3850 | U15: 3300 | V15: 2000 | W15: 2400 | X15: 2 platforms | Y15: 0.3 | Z15: 1 | AA15: Saud Alati | AB15: https://x.com/Exnid_ | AD15: https://www.twitch.tv/exnid | AK15: 28/10/2002 | AL15: Sub-Machine Gun (SMG) | AT15: =IFERROR(IF(AND(AN15>0,J15>0),ROUND(J15*1000/(AN15*0.2),0),""),"") | AU15: =IFERROR(IF(AND(AQ15>0,M15>0),ROUND(M15*1000/(AQ15*0.3),0),""),"") | AV15: =IFERROR(IF(AND(AM15>0,O15>0),ROUND(O15*1000/(AM15*0.1),0),""),"") | AW15: =IFERROR(IF(AND(AP15>0,N15>0),ROUND(N15*1000/(AP15*0.25),0),""),"") | AX15: =IFERROR(IF(AND(AO15>0,Q15>0),ROUND(Q15*1000/(AO15*1),0),""),"") | AY15: =IFERROR(ifs(I15="Tier S",0.65,I15="Tier 1",0.55,I15="Tier 2",0.45,I15="Tier 3",0.35,I15="Tier 4",0.25),0.35) -> 0.35 | AZ15: 1 | BA15: 1 | BB15: 1 | BC15: =IFERROR(ROUND(S15*AY15*BA15*BB15*AZ15,0),0) -> 8470 | BD15: =IF(COUNT(AM15,AN15,AO15,AP15,AQ15,AR15,AS15)>0,"estimated","pending") -> pending
B16: =IF($C16="","",COUNTA($C$6:C16)) -> 11 | C16: KiSMET | D16: Player | E16: Call of Duty Black Ops 7 | F16: Riyadh Falcons | G16: American | H16: 3 | I16: Tier 2 | J16: 12100 | K16: 5100 | L16: =IF(J16="","",ROUND(J16*0.17,0)) -> 2057 | M16: 9450 | N16: 3850 | O16: 2400 | P16: 2400 | Q16: 17550 | R16: 7850 | S16: =IF(J16="","",ROUND(J16*2.2,0)) -> 26620 | T16: 4250 | U16: 3650 | V16: 2200 | W16: 2400 | X16: 3 platforms | Y16: 0.3 | Z16: 1 | AA16: Matthew Tinsley | AB16: https://twitter.com/KiSMET6_ | AC16: https://www.instagram.com/kismet6_ | AD16: https://www.twitch.tv/kismet6_ | AK16: 1999-11-11 00:00:00 | AL16: Assault Rifle / Flex | AT16: =IFERROR(IF(AND(AN16>0,J16>0),ROUND(J16*1000/(AN16*0.2),0),""),"") | AU16: =IFERROR(IF(AND(AQ16>0,M16>0),ROUND(M16*1000/(AQ16*0.3),0),""),"") | AV16: =IFERROR(IF(AND(AM16>0,O16>0),ROUND(O16*1000/(AM16*0.1),0),""),"") | AW16: =IFERROR(IF(AND(AP16>0,N16>0),ROUND(N16*1000/(AP16*0.25),0),""),"") | AX16: =IFERROR(IF(AND(AO16>0,Q16>0),ROUND(Q16*1000/(AO16*1),0),""),"") | AY16: =IFERROR(ifs(I16="Tier S",0.65,I16="Tier 1",0.55,I16="Tier 2",0.45,I16="Tier 3",0.35,I16="Tier 4",0.25),0.35) -> 0.35 | AZ16: 1 | BA16: 1 | BB16: 1 | BC16: =IFERROR(ROUND(S16*AY16*BA16*BB16*AZ16,0),0) -> 9317 | BD16: =IF(COUNT(AM16,AN16,AO16,AP16,AQ16,AR16,AS16)>0,"estimated","pending") -> pending
B17: =IF($C17="","",COUNTA($C$6:C17)) -> 12 | C17: Pred | D17: Player | E17: Call of Duty Black Ops 7 | F17: Riyadh Falcons | G17: American | H17: 3 | I17: Tier 2 | J17: 11000 | K17: 4600 | L17: =IF(J17="","",ROUND(J17*0.17,0)) -> 1870 | M17: 8600 | N17: 3500 | O17: 2200 | P17: 2200 | Q17: 15950 | R17: 7150 | S17: =IF(J17="","",ROUND(J17*2.2,0)) -> 24200 | T17: 3850 | U17: 3300 | V17: 2000 | W17: 2400 | X17: 3 platforms | Y17: 0.3 | Z17: 1 | AA17: Amer Zulbeari | AB17: https://x.com/Pred | AC17: https://www.instagram.com/amerzulbeariii | AD17: https://www.twitch.tv/pred | AK17: 19/08/2001 | AL17: Sub-Machine Gun (SMG) | AT17: =IFERROR(IF(AND(AN17>0,J17>0),ROUND(J17*1000/(AN17*0.2),0),""),"") | AU17: =IFERROR(IF(AND(AQ17>0,M17>0),ROUND(M17*1000/(AQ17*0.3),0),""),"") | AV17: =IFERROR(IF(AND(AM17>0,O17>0),ROUND(O17*1000/(AM17*0.1),0),""),"") | AW17: =IFERROR(IF(AND(AP17>0,N17>0),ROUND(N17*1000/(AP17*0.25),0),""),"") | AX17: =IFERROR(IF(AND(AO17>0,Q17>0),ROUND(Q17*1000/(AO17*1),0),""),"") | AY17: =IFERROR(ifs(I17="Tier S",0.65,I17="Tier 1",0.55,I17="Tier 2",0.45,I17="Tier 3",0.35,I17="Tier 4",0.25),0.35) -> 0.35 | AZ17: 1 | BA17: 1 | BB17: 1 | BC17: =IFERROR(ROUND(S17*AY17*BA17*BB17*AZ17,0),0) -> 8470 | BD17: =IF(COUNT(AM17,AN17,AO17,AP17,AQ17,AR17,AS17)>0,"estimated","pending") -> pending
B18: =IF($C18="","",COUNTA($C$6:C18)) -> 13 | C18: KingAbody | D18: Player | E18: Call of Duty Black Ops 7 | F18: FaZe Falcons | G18: Saudi Arabia | H18: 1 | I18: Tier 2 | J18: 11000 | K18: 4600 | L18: =IF(J18="","",ROUND(J18*0.17,0)) -> 1870 | M18: 8600 | N18: 3500 | O18: 2200 | P18: 2200 | Q18: 15950 | R18: 7150 | S18: =IF(J18="","",ROUND(J18*2.2,0)) -> 24200 | T18: 3850 | U18: 3300 | V18: 2000 | W18: 2400 | X18: 1 platform | Y18: 0.3 | Z18: 1 | AA18: Abdulelah Alrajhi | AB18: https://x.com/KingAbody_ | AK18: 2000-06-02 00:00:00 | AL18: Sub-Machine Gun (SMG) | AT18: =IFERROR(IF(AND(AN18>0,J18>0),ROUND(J18*1000/(AN18*0.2),0),""),"") | AU18: =IFERROR(IF(AND(AQ18>0,M18>0),ROUND(M18*1000/(AQ18*0.3),0),""),"") | AV18: =IFERROR(IF(AND(AM18>0,O18>0),ROUND(O18*1000/(AM18*0.1),0),""),"") | AW18: =IFERROR(IF(AND(AP18>0,N18>0),ROUND(N18*1000/(AP18*0.25),0),""),"") | AX18: =IFERROR(IF(AND(AO18>0,Q18>0),ROUND(Q18*1000/(AO18*1),0),""),"") | AY18: =IFERROR(ifs(I18="Tier S",0.65,I18="Tier 1",0.55,I18="Tier 2",0.45,I18="Tier 3",0.35,I18="Tier 4",0.25),0.35) -> 0.35 | AZ18: 1 | BA18: 1 | BB18: 1 | BC18: =IFERROR(ROUND(S18*AY18*BA18*BB18*AZ18,0),0) -> 8470 | BD18: =IF(COUNT(AM18,AN18,AO18,AP18,AQ18,AR18,AS18)>0,"estimated","pending") -> pending
B19: =IF($C19="","",COUNTA($C$6:C19)) -> 14 | C19: Arcitys | D19: Player | E19: Call of Duty Black Ops 7 | F19: Falcons Academy White | G19: American | H19: 3 | I19: Tier 2 | J19: 12100 | K19: 5100 | L19: =IF(J19="","",ROUND(J19*0.17,0)) -> 2057 | M19: 9450 | N19: 3850 | O19: 2400 | P19: 2400 | Q19: 17550 | R19: 7850 | S19: =IF(J19="","",ROUND(J19*2.2,0)) -> 26620 | T19: 4250 | U19: 3650 | V19: 2200 | W19: 2400 | X19: 3 platforms | Y19: 0.3 | Z19: 1 | AA19: Alec Sanderson | AB19: https://x.com/Arcitys | AC19: https://www.instagram.com/arcitys9 | AD19: https://www.twitch.tv/arcitys | AK19: 1998-09-07 00:00:00 | AL19: Assault Rifle / Main AR | AT19: =IFERROR(IF(AND(AN19>0,J19>0),ROUND(J19*1000/(AN19*0.2),0),""),"") | AU19: =IFERROR(IF(AND(AQ19>0,M19>0),ROUND(M19*1000/(AQ19*0.3),0),""),"") | AV19: =IFERROR(IF(AND(AM19>0,O19>0),ROUND(O19*1000/(AM19*0.1),0),""),"") | AW19: =IFERROR(IF(AND(AP19>0,N19>0),ROUND(N19*1000/(AP19*0.25),0),""),"") | AX19: =IFERROR(IF(AND(AO19>0,Q19>0),ROUND(Q19*1000/(AO19*1),0),""),"") | AY19: =IFERROR(ifs(I19="Tier S",0.65,I19="Tier 1",0.55,I19="Tier 2",0.45,I19="Tier 3",0.35,I19="Tier 4",0.25),0.35) -> 0.35 | AZ19: 1 | BA19: 1 | BB19: 1 | BC19: =IFERROR(ROUND(S19*AY19*BA19*BB19*AZ19,0),0) -> 9317 | BD19: =IF(COUNT(AM19,AN19,AO19,AP19,AQ19,AR19,AS19)>0,"estimated","pending") -> pending
B20: =IF($C20="","",COUNTA($C$6:C20)) -> 15 | C20: Paulehx | D20: Player | E20: Call of Duty Black Ops 7 | F20: Falcons Academy White | G20: American | H20: 2 | I20: Tier 2 | J20: 11000 | K20: 4600 | L20: =IF(J20="","",ROUND(J20*0.17,0)) -> 1870 | M20: 8600 | N20: 3500 | O20: 2200 | P20: 2200 | Q20: 15950 | R20: 7150 | S20: =IF(J20="","",ROUND(J20*2.2,0)) -> 24200 | T20: 3850 | U20: 3300 | V20: 2000 | W20: 2400 | X20: 2 platforms | Y20: 0.3 | Z20: 1 | AA20: Paul Avila | AB20: https://x.com/Paulehx_ | AD20: https://www.twitch.tv/paulehx | AK20: 21/01/2002 | AL20: Assault Rifle / Flex | AT20: =IFERROR(IF(AND(AN20>0,J20>0),ROUND(J20*1000/(AN20*0.2),0),""),"") | AU20: =IFERROR(IF(AND(AQ20>0,M20>0),ROUND(M20*1000/(AQ20*0.3),0),""),"") | AV20: =IFERROR(IF(AND(AM20>0,O20>0),ROUND(O20*1000/(AM20*0.1),0),""),"") | AW20: =IFERROR(IF(AND(AP20>0,N20>0),ROUND(N20*1000/(AP20*0.25),0),""),"") | AX20: =IFERROR(IF(AND(AO20>0,Q20>0),ROUND(Q20*1000/(AO20*1),0),""),"") | AY20: =IFERROR(ifs(I20="Tier S",0.65,I20="Tier 1",0.55,I20="Tier 2",0.45,I20="Tier 3",0.35,I20="Tier 4",0.25),0.35) -> 0.35 | AZ20: 1 | BA20: 1 | BB20: 1 | BC20: =IFERROR(ROUND(S20*AY20*BA20*BB20*AZ20,0),0) -> 8470 | BD20: =IF(COUNT(AM20,AN20,AO20,AP20,AQ20,AR20,AS20)>0,"estimated","pending") -> pending
B21: =IF($C21="","",COUNTA($C$6:C21)) -> 16 | C21: hmoodx | D21: Player | E21: Call of Duty Warzone | F21: Team Falcons MENA | G21: Saudi Arabia | H21: 2 | I21: Tier 2 | J21: 11000 | K21: 4600 | L21: =IF(J21="","",ROUND(J21*0.17,0)) -> 1870 | M21: 8600 | N21: 3500 | O21: 2200 | P21: 2200 | Q21: 15950 | R21: 7150 | S21: =IF(J21="","",ROUND(J21*2.2,0)) -> 24200 | T21: 3850 | U21: 3300 | V21: 2000 | W21: 2400 | X21: 2 platforms | Y21: 0.3 | Z21: 1 | AA21: Mohammed Altowairqi | AB21: https://x.com/xihamoodx | AD21: https://www.twitch.tv/i_hmoodx | AT21: =IFERROR(IF(AND(AN21>0,J21>0),ROUND(J21*1000/(AN21*0.2),0),""),"") | AU21: =IFERROR(IF(AND(AQ21>0,M21>0),ROUND(M21*1000/(AQ21*0.3),0),""),"") | AV21: =IFERROR(IF(AND(AM21>0,O21>0),ROUND(O21*1000/(AM21*0.1),0),""),"") | AW21: =IFERROR(IF(AND(AP21>0,N21>0),ROUND(N21*1000/(AP21*0.25),0),""),"") | AX21: =IFERROR(IF(AND(AO21>0,Q21>0),ROUND(Q21*1000/(AO21*1),0),""),"") | AY21: =IFERROR(ifs(I21="Tier S",0.65,I21="Tier 1",0.55,I21="Tier 2",0.45,I21="Tier 3",0.35,I21="Tier 4",0.25),0.35) -> 0.35 | AZ21: 1 | BA21: 1 | BB21: 1 | BC21: =IFERROR(ROUND(S21*AY21*BA21*BB21*AZ21,0),0) -> 8470 | BD21: =IF(COUNT(AM21,AN21,AO21,AP21,AQ21,AR21,AS21)>0,"estimated","pending") -> pending
B22: =IF($C22="","",COUNTA($C$6:C22)) -> 17 | C22: xizx7 | D22: Player | E22: Call of Duty Warzone | F22: Team Falcons MENA | G22: Saudi Arabia | H22: 4 | I22: Tier 1 | J22: 12100 | K22: 5100 | L22: =IF(J22="","",ROUND(J22*0.17,0)) -> 2057 | M22: 9450 | N22: 3850 | O22: 2400 | P22: 2400 | Q22: 17550 | R22: 7850 | S22: =IF(J22="","",ROUND(J22*2.2,0)) -> 26620 | T22: 4250 | U22: 3650 | V22: 2200 | W22: 2400 | X22: 4 platforms | Y22: 0.3 | Z22: 1 | AA22: Jawad Al-Thawab | AB22: https://x.com/Jawxd7 | AC22: https://www.instagram.com/Jawxd7 | AD22: https://www.twitch.tv/jawad | AE22: https://www.youtube.com/channel/UCUWL8dR-JyA4FXZ08aSjjcg/videos | AT22: =IFERROR(IF(AND(AN22>0,J22>0),ROUND(J22*1000/(AN22*0.2),0),""),"") | AU22: =IFERROR(IF(AND(AQ22>0,M22>0),ROUND(M22*1000/(AQ22*0.3),0),""),"") | AV22: =IFERROR(IF(AND(AM22>0,O22>0),ROUND(O22*1000/(AM22*0.1),0),""),"") | AW22: =IFERROR(IF(AND(AP22>0,N22>0),ROUND(N22*1000/(AP22*0.25),0),""),"") | AX22: =IFERROR(IF(AND(AO22>0,Q22>0),ROUND(Q22*1000/(AO22*1),0),""),"") | AY22: =IFERROR(ifs(I22="Tier S",0.65,I22="Tier 1",0.55,I22="Tier 2",0.45,I22="Tier 3",0.35,I22="Tier 4",0.25),0.35) -> 0.35 | AZ22: 1 | BA22: 1 | BB22: 1 | BC22: =IFERROR(ROUND(S22*AY22*BA22*BB22*AZ22,0),0) -> 9317 | BD22: =IF(COUNT(AM22,AN22,AO22,AP22,AQ22,AR22,AS22)>0,"estimated","pending") -> pending
B23: =IF($C23="","",COUNTA($C$6:C23)) -> 18 | C23: Alpine | D23: Manager | E23: Call of Duty Warzone | F23: Team Falcons | G23: American | H23: 1 | I23: Tier 3 | J23: 22750 | K23: 9550 | L23: =IF(J23="","",ROUND(J23*0.17,0)) -> 3868 | M23: 17750 | N23: 7300 | O23: 4550 | P23: 0 | Q23: 33000 | R23: 14800 | S23: =IF(J23="","",ROUND(J23*2.2,0)) -> 50050 | T23: 7950 | U23: 6850 | V23: 4100 | W23: 0 | X23: 1 platform | Y23: 0.3 | Z23: 1 | AA23: Alejandro Ayala | AB23: https://x.com/alpinedadog?lang=en | AK23: 24/02/1997 | AT23: =IFERROR(IF(AND(AN23>0,J23>0),ROUND(J23*1000/(AN23*0.2),0),""),"") | AU23: =IFERROR(IF(AND(AQ23>0,M23>0),ROUND(M23*1000/(AQ23*0.3),0),""),"") | AV23: =IFERROR(IF(AND(AM23>0,O23>0),ROUND(O23*1000/(AM23*0.1),0),""),"") | AW23: =IFERROR(IF(AND(AP23>0,N23>0),ROUND(N23*1000/(AP23*0.25),0),""),"") | AX23: =IFERROR(IF(AND(AO23>0,Q23>0),ROUND(Q23*1000/(AO23*1),0),""),"") | AY23: =IFERROR(ifs(I23="Tier S",0.65,I23="Tier 1",0.55,I23="Tier 2",0.45,I23="Tier 3",0.35,I23="Tier 4",0.25),0.35) -> 0.35 | AZ23: 1 | BA23: 1 | BB23: 1 | BC23: =IFERROR(ROUND(S23*AY23*BA23*BB23*AZ23,0),0) -> 17518 | BD23: =IF(COUNT(AM23,AN23,AO23,AP23,AQ23,AR23,AS23)>0,"estimated","pending") -> pending
B24: =IF($C24="","",COUNTA($C$6:C24)) -> 19 | C24: Newbz | D24: Player | E24: Call of Duty Warzone | F24: Team Falcons | G24: American | H24: 2 | I24: Tier 3 | J24: 20700 | K24: 8700 | L24: =IF(J24="","",ROUND(J24*0.17,0)) -> 3519 | M24: 16150 | N24: 6600 | O24: 4150 | P24: 4150 | Q24: 30000 | R24: 13450 | S24: =IF(J24="","",ROUND(J24*2.2,0)) -> 45540 | T24: 7250 | U24: 6200 | V24: 3750 | W24: 2400 | X24: 2 platforms | Y24: 0.2 | Z24: 1 | AA24: Edy Juan | AB24: https://x.com/TBE_Newbzz | AD24: https://www.twitch.tv/newbz | AK24: 2000-01-02 00:00:00 | AT24: =IFERROR(IF(AND(AN24>0,J24>0),ROUND(J24*1000/(AN24*0.2),0),""),"") | AU24: =IFERROR(IF(AND(AQ24>0,M24>0),ROUND(M24*1000/(AQ24*0.3),0),""),"") | AV24: =IFERROR(IF(AND(AM24>0,O24>0),ROUND(O24*1000/(AM24*0.1),0),""),"") | AW24: =IFERROR(IF(AND(AP24>0,N24>0),ROUND(N24*1000/(AP24*0.25),0),""),"") | AX24: =IFERROR(IF(AND(AO24>0,Q24>0),ROUND(Q24*1000/(AO24*1),0),""),"") | AY24: =IFERROR(ifs(I24="Tier S",0.65,I24="Tier 1",0.55,I24="Tier 2",0.45,I24="Tier 3",0.35,I24="Tier 4",0.25),0.35) -> 0.35 | AZ24: 1 | BA24: 1 | BB24: 1 | BC24: =IFERROR(ROUND(S24*AY24*BA24*BB24*AZ24,0),0) -> 15939 | BD24: =IF(COUNT(AM24,AN24,AO24,AP24,AQ24,AR24,AS24)>0,"estimated","pending") -> pending
B25: =IF($C25="","",COUNTA($C$6:C25)) -> 20 | C25: Dongy | D25: Player | E25: Call of Duty Warzone | F25: Team Falcons | G25: American | H25: 2 | I25: Tier 3 | J25: 6500 | K25: 2750 | L25: =IF(J25="","",ROUND(J25*0.17,0)) -> 1105 | M25: 5050 | N25: 2100 | O25: 1300 | P25: 1300 | Q25: 9400 | R25: 4200 | S25: =IF(J25="","",ROUND(J25*2.2,0)) -> 14300 | T25: 2300 | U25: 1950 | V25: 1150 | W25: 2400 | X25: 2 platforms | Y25: 0.2 | Z25: 1 | AA25: Christopher Ledbetter | AB25: https://x.com/zDongyy | AD25: https://www.twitch.tv/Dongy | AK25: 23/03/2004 | AT25: =IFERROR(IF(AND(AN25>0,J25>0),ROUND(J25*1000/(AN25*0.2),0),""),"") | AU25: =IFERROR(IF(AND(AQ25>0,M25>0),ROUND(M25*1000/(AQ25*0.3),0),""),"") | AV25: =IFERROR(IF(AND(AM25>0,O25>0),ROUND(O25*1000/(AM25*0.1),0),""),"") | AW25: =IFERROR(IF(AND(AP25>0,N25>0),ROUND(N25*1000/(AP25*0.25),0),""),"") | AX25: =IFERROR(IF(AND(AO25>0,Q25>0),ROUND(Q25*1000/(AO25*1),0),""),"") | AY25: =IFERROR(ifs(I25="Tier S",0.65,I25="Tier 1",0.55,I25="Tier 2",0.45,I25="Tier 3",0.35,I25="Tier 4",0.25),0.35) -> 0.35 | AZ25: 1 | BA25: 1 | BB25: 1 | BC25: =IFERROR(ROUND(S25*AY25*BA25*BB25*AZ25,0),0) -> 5005 | BD25: =IF(COUNT(AM25,AN25,AO25,AP25,AQ25,AR25,AS25)>0,"estimated","pending") -> pending
B26: =IF($C26="","",COUNTA($C$6:C26)) -> 21 | C26: Soka | D26: Player | E26: Call of Duty Warzone | F26: Team Falcons | G26: Tongan | H26: 5 | I26: Tier 1 | J26: 6500 | K26: 2750 | L26: =IF(J26="","",ROUND(J26*0.17,0)) -> 1105 | M26: 5050 | N26: 2100 | O26: 1300 | P26: 1300 | Q26: 9400 | R26: 4200 | S26: =IF(J26="","",ROUND(J26*2.2,0)) -> 14300 | T26: 2300 | U26: 1950 | V26: 1150 | W26: 2400 | X26: 5 platforms | Y26: 0.2 | Z26: 1 | AA26: Kasimili Tonga Tongamoa | AB26: https://twitter.com/HisokaT42 | AC26: https://www.instagram.com/hisokat42 | AD26: https://www.twitch.tv/HisokaT42 | AE26: https://www.youtube.com/channel/UCQDRE8aZRsrvF5OwMk_KmBg | AF26: https://tiktok.com/@missionarysoka | AK26: 28/01/2002 | AT26: =IFERROR(IF(AND(AN26>0,J26>0),ROUND(J26*1000/(AN26*0.2),0),""),"") | AU26: =IFERROR(IF(AND(AQ26>0,M26>0),ROUND(M26*1000/(AQ26*0.3),0),""),"") | AV26: =IFERROR(IF(AND(AM26>0,O26>0),ROUND(O26*1000/(AM26*0.1),0),""),"") | AW26: =IFERROR(IF(AND(AP26>0,N26>0),ROUND(N26*1000/(AP26*0.25),0),""),"") | AX26: =IFERROR(IF(AND(AO26>0,Q26>0),ROUND(Q26*1000/(AO26*1),0),""),"") | AY26: =IFERROR(ifs(I26="Tier S",0.65,I26="Tier 1",0.55,I26="Tier 2",0.45,I26="Tier 3",0.35,I26="Tier 4",0.25),0.35) -> 0.35 | AZ26: 1 | BA26: 1 | BB26: 1 | BC26: =IFERROR(ROUND(S26*AY26*BA26*BB26*AZ26,0),0) -> 5005 | BD26: =IF(COUNT(AM26,AN26,AO26,AP26,AQ26,AR26,AS26)>0,"estimated","pending") -> pending
B27: =IF($C27="","",COUNTA($C$6:C27)) -> 22 | C27: Alireza Firouzja | D27: Player | E27: Chess | F27: Chess | G27: French/Iranian | H27: 5 | I27: Tier 1 | J27: 20700 | K27: 8700 | L27: =IF(J27="","",ROUND(J27*0.17,0)) -> 3519 | M27: 16150 | N27: 6600 | O27: 4150 | P27: 4150 | Q27: 30000 | R27: 13450 | S27: =IF(J27="","",ROUND(J27*2.2,0)) -> 45540 | T27: 7250 | U27: 6200 | V27: 3750 | W27: 2400 | X27: 5 platforms | Y27: 0.5 | Z27: 1 | AA27: Alireza Firouzja | AB27: https://twitter.com/AlirezaFirouzja | AC27: https://www.instagram.com/alirezafirouzja | AD27: https://www.twitch.tv/alirezafirouzja | AE27: https://www.youtube.com/@alirezafirouzja4080 | AH27: https://www.facebook.com/login/?next=https%3A%2F%2Fwww.facebook.com%2FAlireza.Firouzja.chess%2F | AK27: 18/06/2003 | AT27: =IFERROR(IF(AND(AN27>0,J27>0),ROUND(J27*1000/(AN27*0.2),0),""),"") | AU27: =IFERROR(IF(AND(AQ27>0,M27>0),ROUND(M27*1000/(AQ27*0.3),0),""),"") | AV27: =IFERROR(IF(AND(AM27>0,O27>0),ROUND(O27*1000/(AM27*0.1),0),""),"") | AW27: =IFERROR(IF(AND(AP27>0,N27>0),ROUND(N27*1000/(AP27*0.25),0),""),"") | AX27: =IFERROR(IF(AND(AO27>0,Q27>0),ROUND(Q27*1000/(AO27*1),0),""),"") | AY27: =IFERROR(ifs(I27="Tier S",0.65,I27="Tier 1",0.55,I27="Tier 2",0.45,I27="Tier 3",0.35,I27="Tier 4",0.25),0.35) -> 0.35 | AZ27: 1 | BA27: 1 | BB27: 1 | BC27: =IFERROR(ROUND(S27*AY27*BA27*BB27*AZ27,0),0) -> 15939 | BD27: =IF(COUNT(AM27,AN27,AO27,AP27,AQ27,AR27,AS27)>0,"estimated","pending") -> pending
B28: =IF($C28="","",COUNTA($C$6:C28)) -> 23 | C28: Hikaru Nakamura | D28: Player | E28: Chess | F28: Chess | G28: American | H28: 6 | I28: Tier 1 | J28: 22500 | K28: 9450 | L28: =IF(J28="","",ROUND(J28*0.17,0)) -> 3825 | M28: 17550 | N28: 7200 | O28: 4500 | P28: 4500 | Q28: 32600 | R28: 14600 | S28: =IF(J28="","",ROUND(J28*2.2,0)) -> 49500 | T28: 7850 | U28: 6750 | V28: 4050 | W28: 2400 | X28: 6 platforms | Y28: 0.5 | Z28: 1 | AA28: Hikaru Nakamura | AB28: https://twitter.com/GMHikaru | AC28: https://www.instagram.com/gmhikaru | AD28: https://www.twitch.tv/gmhikaru | AE28: https://www.youtube.com/@gmhikaru | AG28: https://kick.com/gmhikaru | AH28: https://www.facebook.com/login/?next=https%3A%2F%2Fwww.facebook.com%2FGMHikaru%2F | AK28: 1987-12-09 00:00:00 | AT28: =IFERROR(IF(AND(AN28>0,J28>0),ROUND(J28*1000/(AN28*0.2),0),""),"") | AU28: =IFERROR(IF(AND(AQ28>0,M28>0),ROUND(M28*1000/(AQ28*0.3),0),""),"") | AV28: =IFERROR(IF(AND(AM28>0,O28>0),ROUND(O28*1000/(AM28*0.1),0),""),"") | AW28: =IFERROR(IF(AND(AP28>0,N28>0),ROUND(N28*1000/(AP28*0.25),0),""),"") | AX28: =IFERROR(IF(AND(AO28>0,Q28>0),ROUND(Q28*1000/(AO28*1),0),""),"") | AY28: =IFERROR(ifs(I28="Tier S",0.65,I28="Tier 1",0.55,I28="Tier 2",0.45,I28="Tier 3",0.35,I28="Tier 4",0.25),0.35) -> 0.35 | AZ28: 1 | BA28: 1 | BB28: 1 | BC28: =IFERROR(ROUND(S28*AY28*BA28*BB28*AZ28,0),0) -> 17325 | BD28: =IF(COUNT(AM28,AN28,AO28,AP28,AQ28,AR28,AS28)>0,"estimated","pending") -> pending
B29: =IF($C29="","",COUNTA($C$6:C29)) -> 24 | C29: Jon Ellis | D29: Manager | E29: Chess | F29: Chess | H29: 0 | I29: Tier 3 | J29: 22500 | K29: 9450 | L29: =IF(J29="","",ROUND(J29*0.17,0)) -> 3825 | M29: 17550 | N29: 7200 | O29: 4500 | P29: 0 | Q29: 32600 | R29: 14600 | S29: =IF(J29="","",ROUND(J29*2.2,0)) -> 49500 | T29: 7850 | U29: 6750 | V29: 4050 | W29: 0 | X29: 0 platforms | Y29: 0.3 | Z29: 1 | AA29: Jonathan Ellis | AT29: =IFERROR(IF(AND(AN29>0,J29>0),ROUND(J29*1000/(AN29*0.2),0),""),"") | AU29: =IFERROR(IF(AND(AQ29>0,M29>0),ROUND(M29*1000/(AQ29*0.3),0),""),"") | AV29: =IFERROR(IF(AND(AM29>0,O29>0),ROUND(O29*1000/(AM29*0.1),0),""),"") | AW29: =IFERROR(IF(AND(AP29>0,N29>0),ROUND(N29*1000/(AP29*0.25),0),""),"") | AX29: =IFERROR(IF(AND(AO29>0,Q29>0),ROUND(Q29*1000/(AO29*1),0),""),"") | AY29: =IFERROR(ifs(I29="Tier S",0.65,I29="Tier 1",0.55,I29="Tier 2",0.45,I29="Tier 3",0.35,I29="Tier 4",0.25),0.35) -> 0.35 | AZ29: 1 | BA29: 1 | BB29: 1 | BC29: =IFERROR(ROUND(S29*AY29*BA29*BB29*AZ29,0),0) -> 17325 | BD29: =IF(COUNT(AM29,AN29,AO29,AP29,AQ29,AR29,AS29)>0,"estimated","pending") -> pending
B30: =IF($C30="","",COUNTA($C$6:C30)) -> 25 | C30: kyousuke | D30: Player | E30: Counterstrike2 | F30: Team Falcons | G30: Russian | H30: 3 | I30: Tier 1 | J30: 15000 | K30: 6750 | L30: =IF(J30="","",ROUND(J30*0.17,0)) -> 2550 | M30: 11000 | N30: 5000 | O30: 3200 | P30: 3200 | Q30: 19500 | R30: 8775 | S30: =IF(J30="","",ROUND(J30*2.2,0)) -> 33000 | T30: 6800 | U30: 5950 | V30: 3570 | W30: 2400 | X30: 3 platforms | Y30: 0.75 | Z30: 1 | AA30: Maxim Lukin | AB30: https://twitter.com/FLCkyousuke | AC30: https://www.instagram.com/flckyousuke | AD30: https://www.twitch.tv/kyousuke999 | AK30: 30/01/2008 | AL30: Rifler | AT30: =IFERROR(IF(AND(AN30>0,J30>0),ROUND(J30*1000/(AN30*0.2),0),""),"") | AU30: =IFERROR(IF(AND(AQ30>0,M30>0),ROUND(M30*1000/(AQ30*0.3),0),""),"") | AV30: =IFERROR(IF(AND(AM30>0,O30>0),ROUND(O30*1000/(AM30*0.1),0),""),"") | AW30: =IFERROR(IF(AND(AP30>0,N30>0),ROUND(N30*1000/(AP30*0.25),0),""),"") | AX30: =IFERROR(IF(AND(AO30>0,Q30>0),ROUND(Q30*1000/(AO30*1),0),""),"") | AY30: =IFERROR(ifs(I30="Tier S",0.65,I30="Tier 1",0.55,I30="Tier 2",0.45,I30="Tier 3",0.35,I30="Tier 4",0.25),0.35) -> 0.35 | AZ30: 1 | BA30: 1 | BB30: 1 | BC30: =IFERROR(ROUND(S30*AY30*BA30*BB30*AZ30,0),0) -> 11550 | BD30: =IF(COUNT(AM30,AN30,AO30,AP30,AQ30,AR30,AS30)>0,"estimated","pending") -> pending
B31: =IF($C31="","",COUNTA($C$6:C31)) -> 26 | C31: kyxsan | D31: Player | E31: Counterstrike2 | F31: Team Falcons | G31: North Macedonia | H31: 2 | I31: Tier 1 | J31: 22500 | K31: 9450 | L31: =IF(J31="","",ROUND(J31*0.17,0)) -> 3825 | M31: 17550 | N31: 7200 | O31: 4500 | P31: 4500 | Q31: 32600 | R31: 14600 | S31: =IF(J31="","",ROUND(J31*2.2,0)) -> 49500 | T31: 7850 | U31: 6750 | V31: 4050 | W31: 2400 | X31: 2 platforms | Y31: 0.75 | Z31: 1 | AA31: Damjan Stoilkovski | AB31: https://x.com/kyxsancs | AC31: https://www.instagram.com/kyxsancs/ | AK31: 26/05/2000 | AL31: IGL | AT31: =IFERROR(IF(AND(AN31>0,J31>0),ROUND(J31*1000/(AN31*0.2),0),""),"") | AU31: =IFERROR(IF(AND(AQ31>0,M31>0),ROUND(M31*1000/(AQ31*0.3),0),""),"") | AV31: =IFERROR(IF(AND(AM31>0,O31>0),ROUND(O31*1000/(AM31*0.1),0),""),"") | AW31: =IFERROR(IF(AND(AP31>0,N31>0),ROUND(N31*1000/(AP31*0.25),0),""),"") | AX31: =IFERROR(IF(AND(AO31>0,Q31>0),ROUND(Q31*1000/(AO31*1),0),""),"") | AY31: =IFERROR(ifs(I31="Tier S",0.65,I31="Tier 1",0.55,I31="Tier 2",0.45,I31="Tier 3",0.35,I31="Tier 4",0.25),0.35) -> 0.35 | AZ31: 1 | BA31: 1 | BB31: 1 | BC31: =IFERROR(ROUND(S31*AY31*BA31*BB31*AZ31,0),0) -> 17325 | BD31: =IF(COUNT(AM31,AN31,AO31,AP31,AQ31,AR31,AS31)>0,"estimated","pending") -> pending
B32: =IF($C32="","",COUNTA($C$6:C32)) -> 27 | C32: m0NESY | D32: Player | E32: Counterstrike2 | F32: Team Falcons | G32: Russian | H32: 4 | I32: Tier 1 | J32: 22500 | K32: 9450 | L32: =IF(J32="","",ROUND(J32*0.17,0)) -> 3825 | M32: 17550 | N32: 7200 | O32: 4500 | P32: 4500 | Q32: 32600 | R32: 14600 | S32: =IF(J32="","",ROUND(J32*2.2,0)) -> 49500 | T32: 7850 | U32: 6750 | V32: 4050 | W32: 2400 | X32: 4 platforms | Y32: 0.2 | Z32: 1 | AA32: Ilya Osipov | AB32: https://x.com/FLCm0NESY | AC32: https://www.instagram.com/m0nesy13 | AD32: https://www.twitch.tv/m0nesyof | AE32: https://www.youtube.com/channel/UCJxjKA1Cl--4tCN1l_cHHvQ | AK32: 2005-01-05 00:00:00 | AL32: Awper | AT32: =IFERROR(IF(AND(AN32>0,J32>0),ROUND(J32*1000/(AN32*0.2),0),""),"") | AU32: =IFERROR(IF(AND(AQ32>0,M32>0),ROUND(M32*1000/(AQ32*0.3),0),""),"") | AV32: =IFERROR(IF(AND(AM32>0,O32>0),ROUND(O32*1000/(AM32*0.1),0),""),"") | AW32: =IFERROR(IF(AND(AP32>0,N32>0),ROUND(N32*1000/(AP32*0.25),0),""),"") | AX32: =IFERROR(IF(AND(AO32>0,Q32>0),ROUND(Q32*1000/(AO32*1),0),""),"") | AY32: =IFERROR(ifs(I32="Tier S",0.65,I32="Tier 1",0.55,I32="Tier 2",0.45,I32="Tier 3",0.35,I32="Tier 4",0.25),0.35) -> 0.35 | AZ32: 1 | BA32: 1 | BB32: 1 | BC32: =IFERROR(ROUND(S32*AY32*BA32*BB32*AZ32,0),0) -> 17325 | BD32: =IF(COUNT(AM32,AN32,AO32,AP32,AQ32,AR32,AS32)>0,"estimated","pending") -> pending
B33: =IF($C33="","",COUNTA($C$6:C33)) -> 28 | C33: NiKo | D33: Player | E33: Counterstrike2 | F33: Team Falcons | G33: Bosnian | H33: 5 | I33: Tier 1 | J33: 22500 | K33: 9450 | L33: =IF(J33="","",ROUND(J33*0.17,0)) -> 3825 | M33: 17550 | N33: 7200 | O33: 4500 | P33: 4500 | Q33: 32600 | R33: 14600 | S33: =IF(J33="","",ROUND(J33*2.2,0)) -> 49500 | T33: 7850 | U33: 6750 | V33: 4050 | W33: 2400 | X33: 5 platforms | Y33: 0.3 | Z33: 1 | AA33: Nikola Kovač | AB33: https://x.com/NiKoCS_ | AC33: https://www.instagram.com/csgoniko/# | AD33: https://www.twitch.tv/NiKo | AE33: https://www.youtube.com/@NiKo_cs | AH33: https://www.facebook.com/csgoNiKo | AK33: 16/02/1997 | AL33: Rifler | AT33: =IFERROR(IF(AND(AN33>0,J33>0),ROUND(J33*1000/(AN33*0.2),0),""),"") | AU33: =IFERROR(IF(AND(AQ33>0,M33>0),ROUND(M33*1000/(AQ33*0.3),0),""),"") | AV33: =IFERROR(IF(AND(AM33>0,O33>0),ROUND(O33*1000/(AM33*0.1),0),""),"") | AW33: =IFERROR(IF(AND(AP33>0,N33>0),ROUND(N33*1000/(AP33*0.25),0),""),"") | AX33: =IFERROR(IF(AND(AO33>0,Q33>0),ROUND(Q33*1000/(AO33*1),0),""),"") | AY33: =IFERROR(ifs(I33="Tier S",0.65,I33="Tier 1",0.55,I33="Tier 2",0.45,I33="Tier 3",0.35,I33="Tier 4",0.25),0.35) -> 0.35 | AZ33: 1 | BA33: 1 | BB33: 1 | BC33: =IFERROR(ROUND(S33*AY33*BA33*BB33*AZ33,0),0) -> 17325 | BD33: =IF(COUNT(AM33,AN33,AO33,AP33,AQ33,AR33,AS33)>0,"estimated","pending") -> pending
B34: =IF($C34="","",COUNTA($C$6:C34)) -> 29 | C34: OMYA | D34: Manager | E34: Counterstrike2 | F34: Team Falcons | G34: French | H34: 1 | I34: Tier 3 | J34: 22500 | K34: 9450 | L34: =IF(J34="","",ROUND(J34*0.17,0)) -> 3825 | M34: 17550 | N34: 7200 | O34: 4500 | P34: 0 | Q34: 32600 | R34: 14600 | S34: =IF(J34="","",ROUND(J34*2.2,0)) -> 49500 | T34: 7850 | U34: 6750 | V34: 4050 | W34: 0 | X34: 1 platform | Y34: 0.3 | Z34: 1 | AA34: Xavier Roussac | AB34: https://x.com/Xavier_Roussac | AK34: 20/05/1987 | AT34: =IFERROR(IF(AND(AN34>0,J34>0),ROUND(J34*1000/(AN34*0.2),0),""),"") | AU34: =IFERROR(IF(AND(AQ34>0,M34>0),ROUND(M34*1000/(AQ34*0.3),0),""),"") | AV34: =IFERROR(IF(AND(AM34>0,O34>0),ROUND(O34*1000/(AM34*0.1),0),""),"") | AW34: =IFERROR(IF(AND(AP34>0,N34>0),ROUND(N34*1000/(AP34*0.25),0),""),"") | AX34: =IFERROR(IF(AND(AO34>0,Q34>0),ROUND(Q34*1000/(AO34*1),0),""),"") | AY34: =IFERROR(ifs(I34="Tier S",0.65,I34="Tier 1",0.55,I34="Tier 2",0.45,I34="Tier 3",0.35,I34="Tier 4",0.25),0.35) -> 0.35 | AZ34: 1 | BA34: 1 | BB34: 1 | BC34: =IFERROR(ROUND(S34*AY34*BA34*BB34*AZ34,0),0) -> 17325 | BD34: =IF(COUNT(AM34,AN34,AO34,AP34,AQ34,AR34,AS34)>0,"estimated","pending") -> pending
B35: =IF($C35="","",COUNTA($C$6:C35)) -> 30 | C35: TeSeS | D35: Player | E35: Counterstrike2 | F35: Team Falcons | G35: Danish | H35: 2 | I35: Tier 2 | J35: 11250 | K35: 4500 | L35: =IF(J35="","",ROUND(J35*0.17,0)) -> 1913 | M35: 8000 | N35: 3500 | O35: 2000 | P35: 2000 | Q35: 13500 | R35: 6075 | S35: =IF(J35="","",ROUND(J35*2.2,0)) -> 24750 | T35: 4638 | U35: 4063 | V35: 2438 | W35: 2400 | X35: 2 platforms | Y35: 0.75 | Z35: 1 | AA35: René Madsen | AB35: https://x.com/tesescs | AC35: Instagram/TeseS | AD35: https://www.twitch.tv/tesesss | AK35: 2000-12-12 00:00:00 | AL35: Rifler | AT35: =IFERROR(IF(AND(AN35>0,J35>0),ROUND(J35*1000/(AN35*0.2),0),""),"") | AU35: =IFERROR(IF(AND(AQ35>0,M35>0),ROUND(M35*1000/(AQ35*0.3),0),""),"") | AV35: =IFERROR(IF(AND(AM35>0,O35>0),ROUND(O35*1000/(AM35*0.1),0),""),"") | AW35: =IFERROR(IF(AND(AP35>0,N35>0),ROUND(N35*1000/(AP35*0.25),0),""),"") | AX35: =IFERROR(IF(AND(AO35>0,Q35>0),ROUND(Q35*1000/(AO35*1),0),""),"") | AY35: =IFERROR(ifs(I35="Tier S",0.65,I35="Tier 1",0.55,I35="Tier 2",0.45,I35="Tier 3",0.35,I35="Tier 4",0.25),0.35) -> 0.35 | AZ35: 1 | BA35: 1 | BB35: 1 | BC35: =IFERROR(ROUND(S35*AY35*BA35*BB35*AZ35,0),0) -> 8663 | BD35: =IF(COUNT(AM35,AN35,AO35,AP35,AQ35,AR35,AS35)>0,"estimated","pending") -> pending
B36: =IF($C36="","",COUNTA($C$6:C36)) -> 31 | C36: Aymeinstein | D36: Assistant Coach | E36: Counterstrike2 | F36: Team Falcons | G36: French | H36: 2 | I36: Tier 2 | J36: 11000 | K36: 4600 | L36: =IF(J36="","",ROUND(J36*0.17,0)) -> 1870 | M36: 8600 | N36: 3500 | O36: 2200 | P36: 0 | Q36: 15950 | R36: 7150 | S36: =IF(J36="","",ROUND(J36*2.2,0)) -> 24200 | T36: 3850 | U36: 3300 | V36: 2000 | W36: 0 | X36: 2 platforms | Y36: 0.5 | Z36: 1 | AA36: Aymen Bencheikh | AB36: https://x.com/aymeinstein | AC36: https://www.instagram.com/aymeinsteintv | AK36: 22/04/1996 | AT36: =IFERROR(IF(AND(AN36>0,J36>0),ROUND(J36*1000/(AN36*0.2),0),""),"") | AU36: =IFERROR(IF(AND(AQ36>0,M36>0),ROUND(M36*1000/(AQ36*0.3),0),""),"") | AV36: =IFERROR(IF(AND(AM36>0,O36>0),ROUND(O36*1000/(AM36*0.1),0),""),"") | AW36: =IFERROR(IF(AND(AP36>0,N36>0),ROUND(N36*1000/(AP36*0.25),0),""),"") | AX36: =IFERROR(IF(AND(AO36>0,Q36>0),ROUND(Q36*1000/(AO36*1),0),""),"") | AY36: =IFERROR(ifs(I36="Tier S",0.65,I36="Tier 1",0.55,I36="Tier 2",0.45,I36="Tier 3",0.35,I36="Tier 4",0.25),0.35) -> 0.35 | AZ36: 1 | BA36: 1 | BB36: 1 | BC36: =IFERROR(ROUND(S36*AY36*BA36*BB36*AZ36,0),0) -> 8470 | BD36: =IF(COUNT(AM36,AN36,AO36,AP36,AQ36,AR36,AS36)>0,"estimated","pending") -> pending
B37: =IF($C37="","",COUNTA($C$6:C37)) -> 32 | C37: Zonic | D37: Head Coach | E37: Counterstrike2 | F37: Team Falcons | G37: Danish | H37: 2 | I37: Tier 1 | J37: 0 | K37: 0 | L37: =IF(J37="","",ROUND(J37*0.17,0)) -> 0 | M37: 0 | N37: 0 | O37: 0 | P37: 0 | Q37: 0 | R37: 0 | S37: =IF(J37="","",ROUND(J37*2.2,0)) -> 0 | T37: 0 | U37: 0 | V37: 2000 | W37: 0 | X37: 2 platforms | Y37: 0.5 | Z37: 1 | AA37: Danny Sørensen | AB37: https://x.com/zonic | AC37: Instagram/Zonic | AD37: https://www.twitch.tv/zonic | AH37: Facebook/Zonic | AK37: 30/07/1986 | AT37: =IFERROR(IF(AND(AN37>0,J37>0),ROUND(J37*1000/(AN37*0.2),0),""),"") | AU37: =IFERROR(IF(AND(AQ37>0,M37>0),ROUND(M37*1000/(AQ37*0.3),0),""),"") | AV37: =IFERROR(IF(AND(AM37>0,O37>0),ROUND(O37*1000/(AM37*0.1),0),""),"") | AW37: =IFERROR(IF(AND(AP37>0,N37>0),ROUND(N37*1000/(AP37*0.25),0),""),"") | AX37: =IFERROR(IF(AND(AO37>0,Q37>0),ROUND(Q37*1000/(AO37*1),0),""),"") | AY37: =IFERROR(ifs(I37="Tier S",0.65,I37="Tier 1",0.55,I37="Tier 2",0.45,I37="Tier 3",0.35,I37="Tier 4",0.25),0.35) -> 0.35 | AZ37: 1 | BA37: 1 | BB37: 1 | BC37: =IFERROR(ROUND(S37*AY37*BA37*BB37*AZ37,0),0) -> 0 | BD37: =IF(COUNT(AM37,AN37,AO37,AP37,AQ37,AR37,AS37)>0,"estimated","pending") -> pending
B38: =IF($C38="","",COUNTA($C$6:C38)) -> 33 | C38: clockzi | D38: Player | E38: Counterstrike2 | F38: Falcons Force | G38: Danish | H38: 1 | I38: Tier 3 | J38: 11000 | K38: 4600 | L38: =IF(J38="","",ROUND(J38*0.17,0)) -> 1870 | M38: 8600 | N38: 3500 | O38: 2200 | P38: 2200 | Q38: 15950 | R38: 7150 | S38: =IF(J38="","",ROUND(J38*2.2,0)) -> 24200 | T38: 3850 | U38: 3300 | V38: 2000 | W38: 2400 | X38: 1 platform | Y38: 0.75 | Z38: 1 | AA38: Oskar Led Blæsbjerg | AB38: https://x.com/flcclockzi | AK38: 21/04/2011 | AL38: Rifler | AT38: =IFERROR(IF(AND(AN38>0,J38>0),ROUND(J38*1000/(AN38*0.2),0),""),"") | AU38: =IFERROR(IF(AND(AQ38>0,M38>0),ROUND(M38*1000/(AQ38*0.3),0),""),"") | AV38: =IFERROR(IF(AND(AM38>0,O38>0),ROUND(O38*1000/(AM38*0.1),0),""),"") | AW38: =IFERROR(IF(AND(AP38>0,N38>0),ROUND(N38*1000/(AP38*0.25),0),""),"") | AX38: =IFERROR(IF(AND(AO38>0,Q38>0),ROUND(Q38*1000/(AO38*1),0),""),"") | AY38: =IFERROR(ifs(I38="Tier S",0.65,I38="Tier 1",0.55,I38="Tier 2",0.45,I38="Tier 3",0.35,I38="Tier 4",0.25),0.35) -> 0.35 | AZ38: 1 | BA38: 1 | BB38: 1 | BC38: =IFERROR(ROUND(S38*AY38*BA38*BB38*AZ38,0),0) -> 8470 | BD38: =IF(COUNT(AM38,AN38,AO38,AP38,AQ38,AR38,AS38)>0,"estimated","pending") -> pending
B39: =IF($C39="","",COUNTA($C$6:C39)) -> 34 | C39: grecu | D39: Player | E39: Counterstrike2 | F39: Falcons Force | G39: Romanian | H39: 2 | I39: Tier 2 | J39: 5200 | K39: 2200 | L39: =IF(J39="","",ROUND(J39*0.17,0)) -> 884 | M39: 4050 | N39: 1650 | O39: 1050 | P39: 1050 | Q39: 7550 | R39: 3400 | S39: =IF(J39="","",ROUND(J39*2.2,0)) -> 11440 | T39: 1800 | U39: 1550 | V39: 950 | W39: 2400 | X39: 2 platforms | Y39: 0.75 | Z39: 1 | AA39: Andrei Grecu | AB39: https://x.com/grecuflc | AD39: https://www.twitch.tv/gbcgrecu | AK39: 15/11/2007 | AL39: AWPer | AT39: =IFERROR(IF(AND(AN39>0,J39>0),ROUND(J39*1000/(AN39*0.2),0),""),"") | AU39: =IFERROR(IF(AND(AQ39>0,M39>0),ROUND(M39*1000/(AQ39*0.3),0),""),"") | AV39: =IFERROR(IF(AND(AM39>0,O39>0),ROUND(O39*1000/(AM39*0.1),0),""),"") | AW39: =IFERROR(IF(AND(AP39>0,N39>0),ROUND(N39*1000/(AP39*0.25),0),""),"") | AX39: =IFERROR(IF(AND(AO39>0,Q39>0),ROUND(Q39*1000/(AO39*1),0),""),"") | AY39: =IFERROR(ifs(I39="Tier S",0.65,I39="Tier 1",0.55,I39="Tier 2",0.45,I39="Tier 3",0.35,I39="Tier 4",0.25),0.35) -> 0.35 | AZ39: 1 | BA39: 1 | BB39: 1 | BC39: =IFERROR(ROUND(S39*AY39*BA39*BB39*AZ39,0),0) -> 4004 | BD39: =IF(COUNT(AM39,AN39,AO39,AP39,AQ39,AR39,AS39)>0,"estimated","pending") -> pending
B40: =IF($C40="","",COUNTA($C$6:C40)) -> 35 | C40: VENO | D40: Player | E40: Counterstrike2 | F40: Falcons Force | G40: Serbian | H40: 3 | I40: Tier 2 | J40: 12100 | K40: 5100 | L40: =IF(J40="","",ROUND(J40*0.17,0)) -> 2057 | M40: 9450 | N40: 3850 | O40: 2400 | P40: 2400 | Q40: 17550 | R40: 7850 | S40: =IF(J40="","",ROUND(J40*2.2,0)) -> 26620 | T40: 4250 | U40: 3650 | V40: 2200 | W40: 2400 | X40: 3 platforms | Y40: 0.75 | Z40: 1 | AA40: Vladimir Stanković | AB40: https://x.com/venocs2 | AD40: https://www.twitch.tv/venocs2 | AE40: https://www.youtube.com/@venocs2 | AK40: 30/04/2007 | AL40: Rifler | AT40: =IFERROR(IF(AND(AN40>0,J40>0),ROUND(J40*1000/(AN40*0.2),0),""),"") | AU40: =IFERROR(IF(AND(AQ40>0,M40>0),ROUND(M40*1000/(AQ40*0.3),0),""),"") | AV40: =IFERROR(IF(AND(AM40>0,O40>0),ROUND(O40*1000/(AM40*0.1),0),""),"") | AW40: =IFERROR(IF(AND(AP40>0,N40>0),ROUND(N40*1000/(AP40*0.25),0),""),"") | AX40: =IFERROR(IF(AND(AO40>0,Q40>0),ROUND(Q40*1000/(AO40*1),0),""),"") | AY40: =IFERROR(ifs(I40="Tier S",0.65,I40="Tier 1",0.55,I40="Tier 2",0.45,I40="Tier 3",0.35,I40="Tier 4",0.25),0.35) -> 0.35 | AZ40: 1 | BA40: 1 | BB40: 1 | BC40: =IFERROR(ROUND(S40*AY40*BA40*BB40*AZ40,0),0) -> 9317 | BD40: =IF(COUNT(AM40,AN40,AO40,AP40,AQ40,AR40,AS40)>0,"estimated","pending") -> pending
B41: =IF($C41="","",COUNTA($C$6:C41)) -> 36 | C41: NaToSaphiX | D41: Head Coach | E41: Counterstrike2 | F41: Falcons Force | G41: Danish | H41: 5 | I41: Tier 2 | J41: 11000 | K41: 4600 | L41: =IF(J41="","",ROUND(J41*0.17,0)) -> 1870 | M41: 8600 | N41: 3500 | O41: 2200 | P41: 0 | Q41: 15950 | R41: 7150 | S41: =IF(J41="","",ROUND(J41*2.2,0)) -> 24200 | T41: 3850 | U41: 3300 | V41: 2000 | W41: 0 | X41: 5 platforms | Y41: 0.2 | Z41: 1 | AA41: Niels Christian Sillassen | AB41: https://x.com/NaToSaphiX | AC41: https://www.instagram.com/natosaphix | AD41: https://www.twitch.tv/natosaphix | AE41: https://www.youtube.com/NaToSaphiX | AK41: 17/08/1996 | AT41: =IFERROR(IF(AND(AN41>0,J41>0),ROUND(J41*1000/(AN41*0.2),0),""),"") | AU41: =IFERROR(IF(AND(AQ41>0,M41>0),ROUND(M41*1000/(AQ41*0.3),0),""),"") | AV41: =IFERROR(IF(AND(AM41>0,O41>0),ROUND(O41*1000/(AM41*0.1),0),""),"") | AW41: =IFERROR(IF(AND(AP41>0,N41>0),ROUND(N41*1000/(AP41*0.25),0),""),"") | AX41: =IFERROR(IF(AND(AO41>0,Q41>0),ROUND(Q41*1000/(AO41*1),0),""),"") | AY41: =IFERROR(ifs(I41="Tier S",0.65,I41="Tier 1",0.55,I41="Tier 2",0.45,I41="Tier 3",0.35,I41="Tier 4",0.25),0.35) -> 0.35 | AZ41: 1 | BA41: 1 | BB41: 1 | BC41: =IFERROR(ROUND(S41*AY41*BA41*BB41*AZ41,0),0) -> 8470 | BD41: =IF(COUNT(AM41,AN41,AO41,AP41,AQ41,AR41,AS41)>0,"estimated","pending") -> pending
B42: =IF($C42="","",COUNTA($C$6:C42)) -> 37 | C42: Neoskai | D42: Manager | E42: Counterstrike2 | F42: Falcons Force | G42: French | H42: 2 | I42: Tier 2 | J42: 0 | K42: 0 | L42: =IF(J42="","",ROUND(J42*0.17,0)) -> 0 | M42: 0 | N42: 0 | O42: 0 | P42: 0 | Q42: 0 | R42: 0 | S42: =IF(J42="","",ROUND(J42*2.2,0)) -> 0 | T42: 0 | U42: 0 | V42: 1200 | W42: 0 | X42: 2 platforms | Y42: 0.2 | Z42: 1 | AA42: Loïc Potages | AB42: https://x.com/Neoskai | AC42: https://www.instagram.com/neoskai/ | AK42: 16/06/1994 | AT42: =IFERROR(IF(AND(AN42>0,J42>0),ROUND(J42*1000/(AN42*0.2),0),""),"") | AU42: =IFERROR(IF(AND(AQ42>0,M42>0),ROUND(M42*1000/(AQ42*0.3),0),""),"") | AV42: =IFERROR(IF(AND(AM42>0,O42>0),ROUND(O42*1000/(AM42*0.1),0),""),"") | AW42: =IFERROR(IF(AND(AP42>0,N42>0),ROUND(N42*1000/(AP42*0.25),0),""),"") | AX42: =IFERROR(IF(AND(AO42>0,Q42>0),ROUND(Q42*1000/(AO42*1),0),""),"") | AY42: =IFERROR(ifs(I42="Tier S",0.65,I42="Tier 1",0.55,I42="Tier 2",0.45,I42="Tier 3",0.35,I42="Tier 4",0.25),0.35) -> 0.35 | AZ42: 1 | BA42: 1 | BB42: 1 | BC42: =IFERROR(ROUND(S42*AY42*BA42*BB42*AZ42,0),0) -> 0 | BD42: =IF(COUNT(AM42,AN42,AO42,AP42,AQ42,AR42,AS42)>0,"estimated","pending") -> pending
B43: =IF($C43="","",COUNTA($C$6:C43)) -> 38 | C43: Nucleonz | D43: Player | E43: Counterstrike2 | F43: Falcons Force | G43: North Macedonian | H43: 1 | I43: Tier 3 | J43: 8750 | K43: 3000 | L43: =IF(J43="","",ROUND(J43*0.17,0)) -> 1488 | M43: 6000 | N43: 2500 | O43: 1200 | P43: 1200 | Q43: 9000 | R43: 4050 | S43: =IF(J43="","",ROUND(J43*2.2,0)) -> 19250 | T43: 2200 | U43: 1925 | V43: 1155 | W43: 2400 | X43: 1 platform | Y43: 0.75 | Z43: 1 | AA43: Matej Trajkoski | AB43: https://x.com/NucleonZz | AK43: 2008-10-01 00:00:00 | AL43: Rifler | AT43: =IFERROR(IF(AND(AN43>0,J43>0),ROUND(J43*1000/(AN43*0.2),0),""),"") | AU43: =IFERROR(IF(AND(AQ43>0,M43>0),ROUND(M43*1000/(AQ43*0.3),0),""),"") | AV43: =IFERROR(IF(AND(AM43>0,O43>0),ROUND(O43*1000/(AM43*0.1),0),""),"") | AW43: =IFERROR(IF(AND(AP43>0,N43>0),ROUND(N43*1000/(AP43*0.25),0),""),"") | AX43: =IFERROR(IF(AND(AO43>0,Q43>0),ROUND(Q43*1000/(AO43*1),0),""),"") | AY43: =IFERROR(ifs(I43="Tier S",0.65,I43="Tier 1",0.55,I43="Tier 2",0.45,I43="Tier 3",0.35,I43="Tier 4",0.25),0.35) -> 0.35 | AZ43: 1 | BA43: 1 | BB43: 1 | BC43: =IFERROR(ROUND(S43*AY43*BA43*BB43*AZ43,0),0) -> 6738 | BD43: =IF(COUNT(AM43,AN43,AO43,AP43,AQ43,AR43,AS43)>0,"estimated","pending") -> pending
B44: =IF($C44="","",COUNTA($C$6:C44)) -> 39 | C44: Skiter | D44: Player | E44: Dota2 | F44: Dota2 | G44: Slovakia | H44: 2 | I44: Tier 2 | J44: 5200 | K44: 2200 | L44: =IF(J44="","",ROUND(J44*0.17,0)) -> 884 | M44: 4050 | N44: 1650 | O44: 1050 | P44: 1050 | Q44: 7550 | R44: 3400 | S44: =IF(J44="","",ROUND(J44*2.2,0)) -> 11440 | T44: 1800 | U44: 1550 | V44: 950 | W44: 2400 | X44: 2 platforms | Y44: 0.75 | Z44: 1 | AA44: Oliver Lepko | AB44: https://x.com/skiter | AC44: Instagram/Skiter | AH44: https://www.facebook.com/SkiterDota | AK44: 1998-12-09 00:00:00 | AT44: =IFERROR(IF(AND(AN44>0,J44>0),ROUND(J44*1000/(AN44*0.2),0),""),"") | AU44: =IFERROR(IF(AND(AQ44>0,M44>0),ROUND(M44*1000/(AQ44*0.3),0),""),"") | AV44: =IFERROR(IF(AND(AM44>0,O44>0),ROUND(O44*1000/(AM44*0.1),0),""),"") | AW44: =IFERROR(IF(AND(AP44>0,N44>0),ROUND(N44*1000/(AP44*0.25),0),""),"") | AX44: =IFERROR(IF(AND(AO44>0,Q44>0),ROUND(Q44*1000/(AO44*1),0),""),"") | AY44: =IFERROR(ifs(I44="Tier S",0.65,I44="Tier 1",0.55,I44="Tier 2",0.45,I44="Tier 3",0.35,I44="Tier 4",0.25),0.35) -> 0.35 | AZ44: 1 | BA44: 1 | BB44: 1 | BC44: =IFERROR(ROUND(S44*AY44*BA44*BB44*AZ44,0),0) -> 4004 | BD44: =IF(COUNT(AM44,AN44,AO44,AP44,AQ44,AR44,AS44)>0,"estimated","pending") -> pending
B45: =IF($C45="","",COUNTA($C$6:C45)) -> 40 | C45: Malr1ne | D45: Player | E45: Dota2 | F45: Dota2 | G45: Russian | H45: 2 | I45: Tier 2 | J45: 11000 | K45: 4600 | L45: =IF(J45="","",ROUND(J45*0.17,0)) -> 1870 | M45: 8600 | N45: 3500 | O45: 2200 | P45: 2200 | Q45: 15950 | R45: 7150 | S45: =IF(J45="","",ROUND(J45*2.2,0)) -> 24200 | T45: 3850 | U45: 3300 | V45: 2000 | W45: 2400 | X45: 2 platforms | Y45: 0.75 | Z45: 1 | AA45: Stanislav Potorak | AB45: https://x.com/Malr1ne_ | AC45: Instagram/Malr1ne | AD45: https://www.twitch.tv/malr1ne_dota | AK45: 17/09/2004 | AT45: =IFERROR(IF(AND(AN45>0,J45>0),ROUND(J45*1000/(AN45*0.2),0),""),"") | AU45: =IFERROR(IF(AND(AQ45>0,M45>0),ROUND(M45*1000/(AQ45*0.3),0),""),"") | AV45: =IFERROR(IF(AND(AM45>0,O45>0),ROUND(O45*1000/(AM45*0.1),0),""),"") | AW45: =IFERROR(IF(AND(AP45>0,N45>0),ROUND(N45*1000/(AP45*0.25),0),""),"") | AX45: =IFERROR(IF(AND(AO45>0,Q45>0),ROUND(Q45*1000/(AO45*1),0),""),"") | AY45: =IFERROR(ifs(I45="Tier S",0.65,I45="Tier 1",0.55,I45="Tier 2",0.45,I45="Tier 3",0.35,I45="Tier 4",0.25),0.35) -> 0.35 | AZ45: 1 | BA45: 1 | BB45: 1 | BC45: =IFERROR(ROUND(S45*AY45*BA45*BB45*AZ45,0),0) -> 8470 | BD45: =IF(COUNT(AM45,AN45,AO45,AP45,AQ45,AR45,AS45)>0,"estimated","pending") -> pending
B46: =IF($C46="","",COUNTA($C$6:C46)) -> 41 | C46: ATF | D46: Player | E46: Dota2 | F46: Dota2 | G46: Jordanian | H46: 2 | I46: Tier 2 | J46: 11000 | K46: 4600 | L46: =IF(J46="","",ROUND(J46*0.17,0)) -> 1870 | M46: 8600 | N46: 3500 | O46: 2200 | P46: 2200 | Q46: 15950 | R46: 7150 | S46: =IF(J46="","",ROUND(J46*2.2,0)) -> 24200 | T46: 3850 | U46: 3300 | V46: 2000 | W46: 2400 | X46: 2 platforms | Y46: 0.75 | Z46: 1 | AA46: Ammar Al-Assaf | AB46: https://x.com/AmmarAlassaf6 | AC46: Instagram/Ammar | AD46: https://www.twitch.tv/ammar_the_f | AK46: 2005-03-05 00:00:00 | AT46: =IFERROR(IF(AND(AN46>0,J46>0),ROUND(J46*1000/(AN46*0.2),0),""),"") | AU46: =IFERROR(IF(AND(AQ46>0,M46>0),ROUND(M46*1000/(AQ46*0.3),0),""),"") | AV46: =IFERROR(IF(AND(AM46>0,O46>0),ROUND(O46*1000/(AM46*0.1),0),""),"") | AW46: =IFERROR(IF(AND(AP46>0,N46>0),ROUND(N46*1000/(AP46*0.25),0),""),"") | AX46: =IFERROR(IF(AND(AO46>0,Q46>0),ROUND(Q46*1000/(AO46*1),0),""),"") | AY46: =IFERROR(ifs(I46="Tier S",0.65,I46="Tier 1",0.55,I46="Tier 2",0.45,I46="Tier 3",0.35,I46="Tier 4",0.25),0.35) -> 0.35 | AZ46: 1 | BA46: 1 | BB46: 1 | BC46: =IFERROR(ROUND(S46*AY46*BA46*BB46*AZ46,0),0) -> 8470 | BD46: =IF(COUNT(AM46,AN46,AO46,AP46,AQ46,AR46,AS46)>0,"estimated","pending") -> pending
B47: =IF($C47="","",COUNTA($C$6:C47)) -> 42 | C47: Cr1t- | D47: Player | E47: Dota2 | F47: Dota2 | G47: Danish | H47: 3 | I47: Tier 1 | J47: 12100 | K47: 5100 | L47: =IF(J47="","",ROUND(J47*0.17,0)) -> 2057 | M47: 9450 | N47: 3850 | O47: 2400 | P47: 2400 | Q47: 17550 | R47: 7850 | S47: =IF(J47="","",ROUND(J47*2.2,0)) -> 26620 | T47: 4250 | U47: 3650 | V47: 2200 | W47: 2400 | X47: 3 platforms | Y47: 0.75 | Z47: 1 | AA47: Andreas Nielsen | AB47: https://x.com/Cr1tdota | AC47: Instagram/Cr1t | AD47: https://www.twitch.tv/cr1tdota | AE47: YT/Cr1t | AH47: https://www.facebook.com/Cr1tdota | AK47: 13/07/1996 | AT47: =IFERROR(IF(AND(AN47>0,J47>0),ROUND(J47*1000/(AN47*0.2),0),""),"") | AU47: =IFERROR(IF(AND(AQ47>0,M47>0),ROUND(M47*1000/(AQ47*0.3),0),""),"") | AV47: =IFERROR(IF(AND(AM47>0,O47>0),ROUND(O47*1000/(AM47*0.1),0),""),"") | AW47: =IFERROR(IF(AND(AP47>0,N47>0),ROUND(N47*1000/(AP47*0.25),0),""),"") | AX47: =IFERROR(IF(AND(AO47>0,Q47>0),ROUND(Q47*1000/(AO47*1),0),""),"") | AY47: =IFERROR(ifs(I47="Tier S",0.65,I47="Tier 1",0.55,I47="Tier 2",0.45,I47="Tier 3",0.35,I47="Tier 4",0.25),0.35) -> 0.35 | AZ47: 1 | BA47: 1 | BB47: 1 | BC47: =IFERROR(ROUND(S47*AY47*BA47*BB47*AZ47,0),0) -> 9317 | BD47: =IF(COUNT(AM47,AN47,AO47,AP47,AQ47,AR47,AS47)>0,"estimated","pending") -> pending
B48: =IF($C48="","",COUNTA($C$6:C48)) -> 43 | C48: Sneyking | D48: Player | E48: Dota2 | F48: Dota2 | G48: American / Chinese | H48: 2 | I48: Tier 2 | J48: 20700 | K48: 8700 | L48: =IF(J48="","",ROUND(J48*0.17,0)) -> 3519 | M48: 16150 | N48: 6600 | O48: 4150 | P48: 4150 | Q48: 30000 | R48: 13450 | S48: =IF(J48="","",ROUND(J48*2.2,0)) -> 45540 | T48: 7250 | U48: 6200 | V48: 3750 | W48: 2400 | X48: 2 platforms | Y48: 0.75 | Z48: 1 | AA48: Jingjun Wu | AB48: https://x.com/SneykingGaming | AD48: https://www.twitch.tv/sneykingdota | AK48: 1995-03-05 00:00:00 | AT48: =IFERROR(IF(AND(AN48>0,J48>0),ROUND(J48*1000/(AN48*0.2),0),""),"") | AU48: =IFERROR(IF(AND(AQ48>0,M48>0),ROUND(M48*1000/(AQ48*0.3),0),""),"") | AV48: =IFERROR(IF(AND(AM48>0,O48>0),ROUND(O48*1000/(AM48*0.1),0),""),"") | AW48: =IFERROR(IF(AND(AP48>0,N48>0),ROUND(N48*1000/(AP48*0.25),0),""),"") | AX48: =IFERROR(IF(AND(AO48>0,Q48>0),ROUND(Q48*1000/(AO48*1),0),""),"") | AY48: =IFERROR(ifs(I48="Tier S",0.65,I48="Tier 1",0.55,I48="Tier 2",0.45,I48="Tier 3",0.35,I48="Tier 4",0.25),0.35) -> 0.35 | AZ48: 1 | BA48: 1 | BB48: 1 | BC48: =IFERROR(ROUND(S48*AY48*BA48*BB48*AZ48,0),0) -> 15939 | BD48: =IF(COUNT(AM48,AN48,AO48,AP48,AQ48,AR48,AS48)>0,"estimated","pending") -> pending
B49: =IF($C49="","",COUNTA($C$6:C49)) -> 44 | C49: Aui_2000 | D49: Head Coach | E49: Dota2 | F49: Dota2 | G49: Canada | H49: 2 | I49: Tier 2 | J49: 11000 | K49: 4600 | L49: =IF(J49="","",ROUND(J49*0.17,0)) -> 1870 | M49: 8600 | N49: 3500 | O49: 2200 | P49: 0 | Q49: 15950 | R49: 7150 | S49: =IF(J49="","",ROUND(J49*2.2,0)) -> 24200 | T49: 3850 | U49: 3300 | V49: 2000 | W49: 0 | X49: 2 platforms | Y49: 0.75 | Z49: 1 | AA49: Kurtis Ling | AB49: https://x.com/Aui_2000 | AD49: https://www.twitch.tv/aui_2000 | AE49: YT/Aui_2000 | AK49: 1992-02-10 00:00:00 | AT49: =IFERROR(IF(AND(AN49>0,J49>0),ROUND(J49*1000/(AN49*0.2),0),""),"") | AU49: =IFERROR(IF(AND(AQ49>0,M49>0),ROUND(M49*1000/(AQ49*0.3),0),""),"") | AV49: =IFERROR(IF(AND(AM49>0,O49>0),ROUND(O49*1000/(AM49*0.1),0),""),"") | AW49: =IFERROR(IF(AND(AP49>0,N49>0),ROUND(N49*1000/(AP49*0.25),0),""),"") | AX49: =IFERROR(IF(AND(AO49>0,Q49>0),ROUND(Q49*1000/(AO49*1),0),""),"") | AY49: =IFERROR(ifs(I49="Tier S",0.65,I49="Tier 1",0.55,I49="Tier 2",0.45,I49="Tier 3",0.35,I49="Tier 4",0.25),0.35) -> 0.35 | AZ49: 1 | BA49: 1 | BB49: 1 | BC49: =IFERROR(ROUND(S49*AY49*BA49*BB49*AZ49,0),0) -> 8470 | BD49: =IF(COUNT(AM49,AN49,AO49,AP49,AQ49,AR49,AS49)>0,"estimated","pending") -> pending
B50: =IF($C50="","",COUNTA($C$6:C50)) -> 45 | C50: AfromOush | D50: Manager | E50: Dota2 | F50: Dota2 | G50: Jordanian | H50: 3 | I50: Tier 2 | J50: 0 | K50: 0 | L50: =IF(J50="","",ROUND(J50*0.17,0)) -> 0 | M50: 0 | N50: 0 | O50: 0 | P50: 0 | Q50: 0 | R50: 0 | S50: =IF(J50="","",ROUND(J50*2.2,0)) -> 0 | T50: 0 | U50: 0 | V50: 1200 | W50: 0 | X50: 3 platforms | Y50: 0.5 | Z50: 1 | AA50: Mohammad Abu Al Eis | AB50: https://x.com/AfrOmoush | AD50: https://www.twitch.tv/afromoush | AH50: https://www.facebook.com/RealAfrOmoush | AK50: 1996-06-12 00:00:00 | AT50: =IFERROR(IF(AND(AN50>0,J50>0),ROUND(J50*1000/(AN50*0.2),0),""),"") | AU50: =IFERROR(IF(AND(AQ50>0,M50>0),ROUND(M50*1000/(AQ50*0.3),0),""),"") | AV50: =IFERROR(IF(AND(AM50>0,O50>0),ROUND(O50*1000/(AM50*0.1),0),""),"") | AW50: =IFERROR(IF(AND(AP50>0,N50>0),ROUND(N50*1000/(AP50*0.25),0),""),"") | AX50: =IFERROR(IF(AND(AO50>0,Q50>0),ROUND(Q50*1000/(AO50*1),0),""),"") | AY50: =IFERROR(ifs(I50="Tier S",0.65,I50="Tier 1",0.55,I50="Tier 2",0.45,I50="Tier 3",0.35,I50="Tier 4",0.25),0.35) -> 0.35 | AZ50: 1 | BA50: 1 | BB50: 1 | BC50: =IFERROR(ROUND(S50*AY50*BA50*BB50*AZ50,0),0) -> 0 | BD50: =IF(COUNT(AM50,AN50,AO50,AP50,AQ50,AR50,AS50)>0,"estimated","pending") -> pending
B51: =IF($C51="","",COUNTA($C$6:C51)) -> 46 | C51: Bonkers | D51: Analyst | E51: Dota2 | F51: Dota2 | G51: British | H51: 1 | I51: Tier 3 | J51: 0 | K51: 0 | L51: =IF(J51="","",ROUND(J51*0.17,0)) -> 0 | M51: 0 | N51: 0 | O51: 0 | P51: 0 | Q51: 0 | R51: 0 | S51: =IF(J51="","",ROUND(J51*2.2,0)) -> 0 | T51: 0 | U51: 0 | V51: 600 | W51: 0 | X51: 1 platform | Y51: 0.5 | Z51: 1 | AA51: Allen Cook | AB51: https://x.com/thisisallencook | AK51: 15/02/1980 | AT51: =IFERROR(IF(AND(AN51>0,J51>0),ROUND(J51*1000/(AN51*0.2),0),""),"") | AU51: =IFERROR(IF(AND(AQ51>0,M51>0),ROUND(M51*1000/(AQ51*0.3),0),""),"") | AV51: =IFERROR(IF(AND(AM51>0,O51>0),ROUND(O51*1000/(AM51*0.1),0),""),"") | AW51: =IFERROR(IF(AND(AP51>0,N51>0),ROUND(N51*1000/(AP51*0.25),0),""),"") | AX51: =IFERROR(IF(AND(AO51>0,Q51>0),ROUND(Q51*1000/(AO51*1),0),""),"") | AY51: =IFERROR(ifs(I51="Tier S",0.65,I51="Tier 1",0.55,I51="Tier 2",0.45,I51="Tier 3",0.35,I51="Tier 4",0.25),0.35) -> 0.35 | AZ51: 1 | BA51: 1 | BB51: 1 | BC51: =IFERROR(ROUND(S51*AY51*BA51*BB51*AZ51,0),0) -> 0 | BD51: =IF(COUNT(AM51,AN51,AO51,AP51,AQ51,AR51,AS51)>0,"estimated","pending") -> pending
B52: =IF($C52="","",COUNTA($C$6:C52)) -> 47 | C52: GoatMoh | D52: Player | E52: EAFC25 | F52: EA Sport FC | G52: Saudi Arabia | H52: 2 | I52: Tier 2 | J52: 11250 | K52: 4500 | L52: =IF(J52="","",ROUND(J52*0.17,0)) -> 1913 | M52: 8000 | N52: 3500 | O52: 2000 | P52: 2000 | Q52: 13500 | R52: 6075 | S52: =IF(J52="","",ROUND(J52*2.2,0)) -> 24750 | T52: 4638 | U52: 4063 | V52: 2438 | W52: 2400 | X52: 2 platforms | Y52: 0.3 | Z52: 1 | AA52: Mohammed Alarfaj | AB52: https://x.com/GoatMoh_ | AD52: https://www.twitch.tv/goatmoh | AK52: 15/02/2000 | AT52: =IFERROR(IF(AND(AN52>0,J52>0),ROUND(J52*1000/(AN52*0.2),0),""),"") | AU52: =IFERROR(IF(AND(AQ52>0,M52>0),ROUND(M52*1000/(AQ52*0.3),0),""),"") | AV52: =IFERROR(IF(AND(AM52>0,O52>0),ROUND(O52*1000/(AM52*0.1),0),""),"") | AW52: =IFERROR(IF(AND(AP52>0,N52>0),ROUND(N52*1000/(AP52*0.25),0),""),"") | AX52: =IFERROR(IF(AND(AO52>0,Q52>0),ROUND(Q52*1000/(AO52*1),0),""),"") | AY52: =IFERROR(ifs(I52="Tier S",0.65,I52="Tier 1",0.55,I52="Tier 2",0.45,I52="Tier 3",0.35,I52="Tier 4",0.25),0.35) -> 0.35 | AZ52: 1 | BA52: 1 | BB52: 1 | BC52: =IFERROR(ROUND(S52*AY52*BA52*BB52*AZ52,0),0) -> 8663 | BD52: =IF(COUNT(AM52,AN52,AO52,AP52,AQ52,AR52,AS52)>0,"estimated","pending") -> pending
B53: =IF($C53="","",COUNTA($C$6:C53)) -> 48 | C53: Hafez | D53: Coach | E53: EAFC25 | F53: EA Sport FC | G53: Saudi Arabia | H53: 1 | I53: Tier 3 | J53: 12100 | K53: 5100 | L53: =IF(J53="","",ROUND(J53*0.17,0)) -> 2057 | M53: 9450 | N53: 3850 | O53: 2400 | P53: 0 | Q53: 17550 | R53: 7850 | S53: =IF(J53="","",ROUND(J53*2.2,0)) -> 26620 | T53: 4250 | U53: 3650 | V53: 2200 | W53: 0 | X53: 1 platform | Y53: 0.3 | Z53: 1 | AA53: Mohammad Hafiz | AB53: https://x.com/_Hafez10 | AK53: 29/12/1997 | AT53: =IFERROR(IF(AND(AN53>0,J53>0),ROUND(J53*1000/(AN53*0.2),0),""),"") | AU53: =IFERROR(IF(AND(AQ53>0,M53>0),ROUND(M53*1000/(AQ53*0.3),0),""),"") | AV53: =IFERROR(IF(AND(AM53>0,O53>0),ROUND(O53*1000/(AM53*0.1),0),""),"") | AW53: =IFERROR(IF(AND(AP53>0,N53>0),ROUND(N53*1000/(AP53*0.25),0),""),"") | AX53: =IFERROR(IF(AND(AO53>0,Q53>0),ROUND(Q53*1000/(AO53*1),0),""),"") | AY53: =IFERROR(ifs(I53="Tier S",0.65,I53="Tier 1",0.55,I53="Tier 2",0.45,I53="Tier 3",0.35,I53="Tier 4",0.25),0.35) -> 0.35 | AZ53: 1 | BA53: 1 | BB53: 1 | BC53: =IFERROR(ROUND(S53*AY53*BA53*BB53*AZ53,0),0) -> 9317 | BD53: =IF(COUNT(AM53,AN53,AO53,AP53,AQ53,AR53,AS53)>0,"estimated","pending") -> pending
B54: =IF($C54="","",COUNTA($C$6:C54)) -> 49 | C54: Javivillar7 | D54: Coach | E54: EAFC25 | F54: EA Sport FC | G54: Spanish | H54: 4 | I54: Tier 1 | J54: 0 | K54: 0 | L54: =IF(J54="","",ROUND(J54*0.17,0)) -> 0 | M54: 0 | N54: 0 | O54: 0 | P54: 0 | Q54: 0 | R54: 0 | S54: =IF(J54="","",ROUND(J54*2.2,0)) -> 0 | T54: 0 | U54: 0 | V54: 2000 | W54: 0 | X54: 4 platforms | Y54: 0.3 | Z54: 1 | AA54: Javier Villar Gómez | AB54: https://x.com/Javivillar7 | AC54: Instagram/Javivillar7 | AD54: https://www.twitch.tv/javivillar7/ | AE54: https://www.youtube.com/@javivillar7 | AF54: https://www.tiktok.com/@javivillar7?lang=en | AK54: 31/12/2002 | AT54: =IFERROR(IF(AND(AN54>0,J54>0),ROUND(J54*1000/(AN54*0.2),0),""),"") | AU54: =IFERROR(IF(AND(AQ54>0,M54>0),ROUND(M54*1000/(AQ54*0.3),0),""),"") | AV54: =IFERROR(IF(AND(AM54>0,O54>0),ROUND(O54*1000/(AM54*0.1),0),""),"") | AW54: =IFERROR(IF(AND(AP54>0,N54>0),ROUND(N54*1000/(AP54*0.25),0),""),"") | AX54: =IFERROR(IF(AND(AO54>0,Q54>0),ROUND(Q54*1000/(AO54*1),0),""),"") | AY54: =IFERROR(ifs(I54="Tier S",0.65,I54="Tier 1",0.55,I54="Tier 2",0.45,I54="Tier 3",0.35,I54="Tier 4",0.25),0.35) -> 0.35 | AZ54: 1 | BA54: 1 | BB54: 1 | BC54: =IFERROR(ROUND(S54*AY54*BA54*BB54*AZ54,0),0) -> 0 | BD54: =IF(COUNT(AM54,AN54,AO54,AP54,AQ54,AR54,AS54)>0,"estimated","pending") -> pending
B55: =IF($C55="","",COUNTA($C$6:C55)) -> 50 | C55: Msdossary | D55: Player | E55: EAFC25 | F55: EA Sport FC | G55: Saudi Arabia | H55: 1 | I55: Tier 2 | J55: 11250 | K55: 4500 | L55: =IF(J55="","",ROUND(J55*0.17,0)) -> 1913 | M55: 8000 | N55: 3500 | O55: 2000 | P55: 2000 | Q55: 13500 | R55: 6075 | S55: =IF(J55="","",ROUND(J55*2.2,0)) -> 24750 | T55: 4638 | U55: 4063 | V55: 2438 | W55: 2400 | X55: 1 platform | Y55: 0.3 | Z55: 1 | AA55: Mossad Aldossary | AB55: https://x.com/msdossary7 | AC55: Instagram/Msdossary | AE55: YT/Msdossary7 | AK55: 20/03/2000 | AT55: =IFERROR(IF(AND(AN55>0,J55>0),ROUND(J55*1000/(AN55*0.2),0),""),"") | AU55: =IFERROR(IF(AND(AQ55>0,M55>0),ROUND(M55*1000/(AQ55*0.3),0),""),"") | AV55: =IFERROR(IF(AND(AM55>0,O55>0),ROUND(O55*1000/(AM55*0.1),0),""),"") | AW55: =IFERROR(IF(AND(AP55>0,N55>0),ROUND(N55*1000/(AP55*0.25),0),""),"") | AX55: =IFERROR(IF(AND(AO55>0,Q55>0),ROUND(Q55*1000/(AO55*1),0),""),"") | AY55: =IFERROR(ifs(I55="Tier S",0.65,I55="Tier 1",0.55,I55="Tier 2",0.45,I55="Tier 3",0.35,I55="Tier 4",0.25),0.35) -> 0.35 | AZ55: 1 | BA55: 1 | BB55: 1 | BC55: =IFERROR(ROUND(S55*AY55*BA55*BB55*AZ55,0),0) -> 8663 | BD55: =IF(COUNT(AM55,AN55,AO55,AP55,AQ55,AR55,AS55)>0,"estimated","pending") -> pending
B56: =IF($C56="","",COUNTA($C$6:C56)) -> 51 | C56: Vejrgang | D56: Player | E56: EAFC25 | F56: EA Sport FC | G56: Danish | H56: 4 | I56: Tier 1 | J56: 12100 | K56: 5100 | L56: =IF(J56="","",ROUND(J56*0.17,0)) -> 2057 | M56: 9450 | N56: 3850 | O56: 2400 | P56: 2400 | Q56: 17550 | R56: 7850 | S56: =IF(J56="","",ROUND(J56*2.2,0)) -> 26620 | T56: 4250 | U56: 3650 | V56: 2200 | W56: 2400 | X56: 4 platforms | Y56: 0.3 | Z56: 1 | AA56: Anders Vejrgang | AB56: https://twitter.com/FLC_Vejrgang | AC56: https://www.instagram.com/rblz_vejrgang | AD56: https://www.twitch.tv/anders_vejrgang | AE56: https://www.youtube.com/AndersVejrgangofficial | AK56: 25/01/2006 | AT56: =IFERROR(IF(AND(AN56>0,J56>0),ROUND(J56*1000/(AN56*0.2),0),""),"") | AU56: =IFERROR(IF(AND(AQ56>0,M56>0),ROUND(M56*1000/(AQ56*0.3),0),""),"") | AV56: =IFERROR(IF(AND(AM56>0,O56>0),ROUND(O56*1000/(AM56*0.1),0),""),"") | AW56: =IFERROR(IF(AND(AP56>0,N56>0),ROUND(N56*1000/(AP56*0.25),0),""),"") | AX56: =IFERROR(IF(AND(AO56>0,Q56>0),ROUND(Q56*1000/(AO56*1),0),""),"") | AY56: =IFERROR(ifs(I56="Tier S",0.65,I56="Tier 1",0.55,I56="Tier 2",0.45,I56="Tier 3",0.35,I56="Tier 4",0.25),0.35) -> 0.35 | AZ56: 1 | BA56: 1 | BB56: 1 | BC56: =IFERROR(ROUND(S56*AY56*BA56*BB56*AZ56,0),0) -> 9317 | BD56: =IF(COUNT(AM56,AN56,AO56,AP56,AQ56,AR56,AS56)>0,"estimated","pending") -> pending
B57: =IF($C57="","",COUNTA($C$6:C57)) -> 52 | C57: A9 | D57: Manager | E57: EAFC25 | F57: EA Sport FC | G57: Saudi Arabia | H57: 0 | I57: Tier 3 | J57: 20700 | K57: 8700 | L57: =IF(J57="","",ROUND(J57*0.17,0)) -> 3519 | M57: 16150 | N57: 6600 | O57: 4150 | P57: 0 | Q57: 30000 | R57: 13450 | S57: =IF(J57="","",ROUND(J57*2.2,0)) -> 45540 | T57: 7250 | U57: 6200 | V57: 3750 | W57: 0 | X57: 0 platforms | Y57: 0.3 | Z57: 1 | AA57: Aseel Aldokheel | AK57: 1996-10-05 00:00:00 | AT57: =IFERROR(IF(AND(AN57>0,J57>0),ROUND(J57*1000/(AN57*0.2),0),""),"") | AU57: =IFERROR(IF(AND(AQ57>0,M57>0),ROUND(M57*1000/(AQ57*0.3),0),""),"") | AV57: =IFERROR(IF(AND(AM57>0,O57>0),ROUND(O57*1000/(AM57*0.1),0),""),"") | AW57: =IFERROR(IF(AND(AP57>0,N57>0),ROUND(N57*1000/(AP57*0.25),0),""),"") | AX57: =IFERROR(IF(AND(AO57>0,Q57>0),ROUND(Q57*1000/(AO57*1),0),""),"") | AY57: =IFERROR(ifs(I57="Tier S",0.65,I57="Tier 1",0.55,I57="Tier 2",0.45,I57="Tier 3",0.35,I57="Tier 4",0.25),0.35) -> 0.35 | AZ57: 1 | BA57: 1 | BB57: 1 | BC57: =IFERROR(ROUND(S57*AY57*BA57*BB57*AZ57,0),0) -> 15939 | BD57: =IF(COUNT(AM57,AN57,AO57,AP57,AQ57,AR57,AS57)>0,"estimated","pending") -> pending
B58: =IF($C58="","",COUNTA($C$6:C58)) -> 53 | C58: Kiimo7 | D58: Player | E58: EAFC25 | F58: EA Sport FC | G58: Saudi Arabia | H58: 2 | I58: Tier 2 | J58: 11250 | K58: 4500 | L58: =IF(J58="","",ROUND(J58*0.17,0)) -> 1913 | M58: 8000 | N58: 3500 | O58: 2000 | P58: 2000 | Q58: 13500 | R58: 6075 | S58: =IF(J58="","",ROUND(J58*2.2,0)) -> 24750 | T58: 4638 | U58: 4063 | V58: 2438 | W58: 2400 | X58: 2 platforms | Y58: 0.3 | Z58: 1 | AA58: Abdulkareem Bamogaddam | AB58: https://x.com/kiimo__1 | AC58: https://www.instagram.com/kreemvv/ | AK58: 2008-11-05 00:00:00 | AT58: =IFERROR(IF(AND(AN58>0,J58>0),ROUND(J58*1000/(AN58*0.2),0),""),"") | AU58: =IFERROR(IF(AND(AQ58>0,M58>0),ROUND(M58*1000/(AQ58*0.3),0),""),"") | AV58: =IFERROR(IF(AND(AM58>0,O58>0),ROUND(O58*1000/(AM58*0.1),0),""),"") | AW58: =IFERROR(IF(AND(AP58>0,N58>0),ROUND(N58*1000/(AP58*0.25),0),""),"") | AX58: =IFERROR(IF(AND(AO58>0,Q58>0),ROUND(Q58*1000/(AO58*1),0),""),"") | AY58: =IFERROR(ifs(I58="Tier S",0.65,I58="Tier 1",0.55,I58="Tier 2",0.45,I58="Tier 3",0.35,I58="Tier 4",0.25),0.35) -> 0.35 | AZ58: 1 | BA58: 1 | BB58: 1 | BC58: =IFERROR(ROUND(S58*AY58*BA58*BB58*AZ58,0),0) -> 8663 | BD58: =IF(COUNT(AM58,AN58,AO58,AP58,AQ58,AR58,AS58)>0,"estimated","pending") -> pending
B59: =IF($C59="","",COUNTA($C$6:C59)) -> 54 | C59: Rashed | D59: Manager | E59: Fortnite | F59: Fortnite | G59: Saudi | H59: 0 | I59: Tier 3 | J59: 12100 | K59: 5100 | L59: =IF(J59="","",ROUND(J59*0.17,0)) -> 2057 | M59: 9450 | N59: 3850 | O59: 2400 | P59: 0 | Q59: 17550 | R59: 7850 | S59: =IF(J59="","",ROUND(J59*2.2,0)) -> 26620 | T59: 4250 | U59: 3650 | V59: 2200 | W59: 0 | X59: 0 platforms | Y59: 0.3 | Z59: 1 | AA59: Rashed Aldmaikhi | AT59: =IFERROR(IF(AND(AN59>0,J59>0),ROUND(J59*1000/(AN59*0.2),0),""),"") | AU59: =IFERROR(IF(AND(AQ59>0,M59>0),ROUND(M59*1000/(AQ59*0.3),0),""),"") | AV59: =IFERROR(IF(AND(AM59>0,O59>0),ROUND(O59*1000/(AM59*0.1),0),""),"") | AW59: =IFERROR(IF(AND(AP59>0,N59>0),ROUND(N59*1000/(AP59*0.25),0),""),"") | AX59: =IFERROR(IF(AND(AO59>0,Q59>0),ROUND(Q59*1000/(AO59*1),0),""),"") | AY59: =IFERROR(ifs(I59="Tier S",0.65,I59="Tier 1",0.55,I59="Tier 2",0.45,I59="Tier 3",0.35,I59="Tier 4",0.25),0.35) -> 0.35 | AZ59: 1 | BA59: 1 | BB59: 1 | BC59: =IFERROR(ROUND(S59*AY59*BA59*BB59*AZ59,0),0) -> 9317 | BD59: =IF(COUNT(AM59,AN59,AO59,AP59,AQ59,AR59,AS59)>0,"estimated","pending") -> pending
B60: =IF($C60="","",COUNTA($C$6:C60)) -> 55 | C60: Abu Omar | D60: Player | E60: Fatal Fury | F60: Fatal Fury | G60: Saudi | H60: 1 | I60: Tier 3 | J60: 8750 | K60: 3000 | L60: =IF(J60="","",ROUND(J60*0.17,0)) -> 1488 | M60: 6000 | N60: 2500 | O60: 1200 | P60: 1200 | Q60: 9000 | R60: 4050 | S60: =IF(J60="","",ROUND(J60*2.2,0)) -> 19250 | T60: 2200 | U60: 1925 | V60: 1155 | W60: 2400 | X60: 1 platform | Y60: 0.3 | Z60: 1 | AA60: Wesam Alghamdi | AB60: https://x.com/wess21111?lang=en | AK60: 30/05/1987 | AT60: =IFERROR(IF(AND(AN60>0,J60>0),ROUND(J60*1000/(AN60*0.2),0),""),"") | AU60: =IFERROR(IF(AND(AQ60>0,M60>0),ROUND(M60*1000/(AQ60*0.3),0),""),"") | AV60: =IFERROR(IF(AND(AM60>0,O60>0),ROUND(O60*1000/(AM60*0.1),0),""),"") | AW60: =IFERROR(IF(AND(AP60>0,N60>0),ROUND(N60*1000/(AP60*0.25),0),""),"") | AX60: =IFERROR(IF(AND(AO60>0,Q60>0),ROUND(Q60*1000/(AO60*1),0),""),"") | AY60: =IFERROR(ifs(I60="Tier S",0.65,I60="Tier 1",0.55,I60="Tier 2",0.45,I60="Tier 3",0.35,I60="Tier 4",0.25),0.35) -> 0.35 | AZ60: 1 | BA60: 1 | BB60: 1 | BC60: =IFERROR(ROUND(S60*AY60*BA60*BB60*AZ60,0),0) -> 6738 | BD60: =IF(COUNT(AM60,AN60,AO60,AP60,AQ60,AR60,AS60)>0,"estimated","pending") -> pending
B61: =IF($C61="","",COUNTA($C$6:C61)) -> 56 | C61: E.T. | D61: Player | E61: Fatal Fury | F61: Fatal Fury | G61: Taiwan | H61: 3 | I61: Tier 2 | J61: 5700 | K61: 2400 | L61: =IF(J61="","",ROUND(J61*0.17,0)) -> 969 | M61: 4450 | N61: 1850 | O61: 1150 | P61: 1150 | Q61: 8300 | R61: 3700 | S61: =IF(J61="","",ROUND(J61*2.2,0)) -> 12540 | T61: 2000 | U61: 1700 | V61: 1050 | W61: 2400 | X61: 3 platforms | Y61: 0.1 | Z61: 1 | AA61: Lin Chia-hung | AB61: https://x.com/et1120 | AC61: https://www.instagram.com/dbj_et/# | AH61: https://www.facebook.com/Taiwan.1.ET | AK61: 20/11/1984 | AT61: =IFERROR(IF(AND(AN61>0,J61>0),ROUND(J61*1000/(AN61*0.2),0),""),"") | AU61: =IFERROR(IF(AND(AQ61>0,M61>0),ROUND(M61*1000/(AQ61*0.3),0),""),"") | AV61: =IFERROR(IF(AND(AM61>0,O61>0),ROUND(O61*1000/(AM61*0.1),0),""),"") | AW61: =IFERROR(IF(AND(AP61>0,N61>0),ROUND(N61*1000/(AP61*0.25),0),""),"") | AX61: =IFERROR(IF(AND(AO61>0,Q61>0),ROUND(Q61*1000/(AO61*1),0),""),"") | AY61: =IFERROR(ifs(I61="Tier S",0.65,I61="Tier 1",0.55,I61="Tier 2",0.45,I61="Tier 3",0.35,I61="Tier 4",0.25),0.35) -> 0.35 | AZ61: 1 | BA61: 1 | BB61: 1 | BC61: =IFERROR(ROUND(S61*AY61*BA61*BB61*AZ61,0),0) -> 4389 | BD61: =IF(COUNT(AM61,AN61,AO61,AP61,AQ61,AR61,AS61)>0,"estimated","pending") -> pending
B62: =IF($C62="","",COUNTA($C$6:C62)) -> 57 | C62: Ghirlanda | D62: Manager | E62: Fatal Fury | F62: Fatal Fury | G62: Italian | H62: 1 | I62: Tier 3 | J62: 11000 | K62: 4600 | L62: =IF(J62="","",ROUND(J62*0.17,0)) -> 1870 | M62: 8600 | N62: 3500 | O62: 2200 | P62: 0 | Q62: 15950 | R62: 7150 | S62: =IF(J62="","",ROUND(J62*2.2,0)) -> 24200 | T62: 3850 | U62: 3300 | V62: 2000 | W62: 0 | X62: 1 platform | Y62: 0.5 | Z62: 1 | AA62: Joshua Bianchi | AB62: https://x.com/ghirlandatekken | AK62: 26/02/1992 | AT62: =IFERROR(IF(AND(AN62>0,J62>0),ROUND(J62*1000/(AN62*0.2),0),""),"") | AU62: =IFERROR(IF(AND(AQ62>0,M62>0),ROUND(M62*1000/(AQ62*0.3),0),""),"") | AV62: =IFERROR(IF(AND(AM62>0,O62>0),ROUND(O62*1000/(AM62*0.1),0),""),"") | AW62: =IFERROR(IF(AND(AP62>0,N62>0),ROUND(N62*1000/(AP62*0.25),0),""),"") | AX62: =IFERROR(IF(AND(AO62>0,Q62>0),ROUND(Q62*1000/(AO62*1),0),""),"") | AY62: =IFERROR(ifs(I62="Tier S",0.65,I62="Tier 1",0.55,I62="Tier 2",0.45,I62="Tier 3",0.35,I62="Tier 4",0.25),0.35) -> 0.35 | AZ62: 1 | BA62: 1 | BB62: 1 | BC62: =IFERROR(ROUND(S62*AY62*BA62*BB62*AZ62,0),0) -> 8470 | BD62: =IF(COUNT(AM62,AN62,AO62,AP62,AQ62,AR62,AS62)>0,"estimated","pending") -> pending
B63: =IF($C63="","",COUNTA($C$6:C63)) -> 58 | C63: Kindevu | D63: Player | E63: Fatal Fury | F63: Fatal Fury | G63: Japanese | H63: 3 | I63: Tier 2 | J63: 11250 | K63: 4500 | L63: =IF(J63="","",ROUND(J63*0.17,0)) -> 1913 | M63: 8000 | N63: 3500 | O63: 2000 | P63: 2000 | Q63: 13500 | R63: 6075 | S63: =IF(J63="","",ROUND(J63*2.2,0)) -> 24750 | T63: 4638 | U63: 4063 | V63: 2438 | W63: 2400 | X63: 3 platforms | Y63: 0.75 | Z63: 1 | AA63: Yosuke Ito | AB63: https://x.com/kindevu | AD63: https://www.twitch.tv/kindevu0827 | AE63: https://www.youtube.com/channel/UCQevn7lvmrpl3ElLd58YsNQ | AK63: 27/08/1984 | AT63: =IFERROR(IF(AND(AN63>0,J63>0),ROUND(J63*1000/(AN63*0.2),0),""),"") | AU63: =IFERROR(IF(AND(AQ63>0,M63>0),ROUND(M63*1000/(AQ63*0.3),0),""),"") | AV63: =IFERROR(IF(AND(AM63>0,O63>0),ROUND(O63*1000/(AM63*0.1),0),""),"") | AW63: =IFERROR(IF(AND(AP63>0,N63>0),ROUND(N63*1000/(AP63*0.25),0),""),"") | AX63: =IFERROR(IF(AND(AO63>0,Q63>0),ROUND(Q63*1000/(AO63*1),0),""),"") | AY63: =IFERROR(ifs(I63="Tier S",0.65,I63="Tier 1",0.55,I63="Tier 2",0.45,I63="Tier 3",0.35,I63="Tier 4",0.25),0.35) -> 0.35 | AZ63: 1 | BA63: 1 | BB63: 1 | BC63: =IFERROR(ROUND(S63*AY63*BA63*BB63*AZ63,0),0) -> 8663 | BD63: =IF(COUNT(AM63,AN63,AO63,AP63,AQ63,AR63,AS63)>0,"estimated","pending") -> pending
B64: =IF($C64="","",COUNTA($C$6:C64)) -> 59 | C64: mok | D64: Player | E64: Fatal Fury | F64: Fatal Fury | G64: Japan | H64: 2 | I64: Tier 2 | J64: 11000 | K64: 4600 | L64: =IF(J64="","",ROUND(J64*0.17,0)) -> 1870 | M64: 8600 | N64: 3500 | O64: 2200 | P64: 2200 | Q64: 15950 | R64: 7150 | S64: =IF(J64="","",ROUND(J64*2.2,0)) -> 24200 | T64: 3850 | U64: 3300 | V64: 2000 | W64: 2400 | X64: 2 platforms | Y64: 0.75 | Z64: 1 | AA64: Hiroaki Hashizume | AB64: https://twitter.com/andytheworld320 | AE64: https://www.youtube.com/channel/UC-Ksra-atsz4eW5i9ZDAa8A | AK64: 20/03/1985 | AT64: =IFERROR(IF(AND(AN64>0,J64>0),ROUND(J64*1000/(AN64*0.2),0),""),"") | AU64: =IFERROR(IF(AND(AQ64>0,M64>0),ROUND(M64*1000/(AQ64*0.3),0),""),"") | AV64: =IFERROR(IF(AND(AM64>0,O64>0),ROUND(O64*1000/(AM64*0.1),0),""),"") | AW64: =IFERROR(IF(AND(AP64>0,N64>0),ROUND(N64*1000/(AP64*0.25),0),""),"") | AX64: =IFERROR(IF(AND(AO64>0,Q64>0),ROUND(Q64*1000/(AO64*1),0),""),"") | AY64: =IFERROR(ifs(I64="Tier S",0.65,I64="Tier 1",0.55,I64="Tier 2",0.45,I64="Tier 3",0.35,I64="Tier 4",0.25),0.35) -> 0.35 | AZ64: 1 | BA64: 1 | BB64: 1 | BC64: =IFERROR(ROUND(S64*AY64*BA64*BB64*AZ64,0),0) -> 8470 | BD64: =IF(COUNT(AM64,AN64,AO64,AP64,AQ64,AR64,AS64)>0,"estimated","pending") -> pending
B65: =IF($C65="","",COUNTA($C$6:C65)) -> 60 | C65: Sai | D65: Player | E65: Fatal Fury | F65: Fatal Fury | G65: Saudi | H65: 1 | I65: Tier 3 | J65: 11000 | K65: 4600 | L65: =IF(J65="","",ROUND(J65*0.17,0)) -> 1870 | M65: 8600 | N65: 3500 | O65: 2200 | P65: 2200 | Q65: 15950 | R65: 7150 | S65: =IF(J65="","",ROUND(J65*2.2,0)) -> 24200 | T65: 3850 | U65: 3300 | V65: 2000 | W65: 2400 | X65: 1 platform | Y65: 0.3 | Z65: 1 | AA65: Ali Abdullah Alduhaysh | AB65: https://x.com/Zenga83 | AK65: 26/11/1983 | AT65: =IFERROR(IF(AND(AN65>0,J65>0),ROUND(J65*1000/(AN65*0.2),0),""),"") | AU65: =IFERROR(IF(AND(AQ65>0,M65>0),ROUND(M65*1000/(AQ65*0.3),0),""),"") | AV65: =IFERROR(IF(AND(AM65>0,O65>0),ROUND(O65*1000/(AM65*0.1),0),""),"") | AW65: =IFERROR(IF(AND(AP65>0,N65>0),ROUND(N65*1000/(AP65*0.25),0),""),"") | AX65: =IFERROR(IF(AND(AO65>0,Q65>0),ROUND(Q65*1000/(AO65*1),0),""),"") | AY65: =IFERROR(ifs(I65="Tier S",0.65,I65="Tier 1",0.55,I65="Tier 2",0.45,I65="Tier 3",0.35,I65="Tier 4",0.25),0.35) -> 0.35 | AZ65: 1 | BA65: 1 | BB65: 1 | BC65: =IFERROR(ROUND(S65*AY65*BA65*BB65*AZ65,0),0) -> 8470 | BD65: =IF(COUNT(AM65,AN65,AO65,AP65,AQ65,AR65,AS65)>0,"estimated","pending") -> pending
B66: =IF($C66="","",COUNTA($C$6:C66)) -> 61 | C66: Shadow X | D66: Player | E66: Fatal Fury | F66: Fatal Fury | G66: Mexican | H66: 2 | I66: Tier 2 | J66: 5700 | K66: 2400 | L66: =IF(J66="","",ROUND(J66*0.17,0)) -> 969 | M66: 4450 | N66: 1850 | O66: 1150 | P66: 1150 | Q66: 8300 | R66: 3700 | S66: =IF(J66="","",ROUND(J66*2.2,0)) -> 12540 | T66: 2000 | U66: 1700 | V66: 1050 | W66: 2400 | X66: 2 platforms | Y66: 0.75 | Z66: 1 | AA66: Abraham Sanchez | AB66: https://x.com/ShadowX_FGC | AD66: https://www.twitch.tv/ChonFx | AK66: 14/03/1982 | AT66: =IFERROR(IF(AND(AN66>0,J66>0),ROUND(J66*1000/(AN66*0.2),0),""),"") | AU66: =IFERROR(IF(AND(AQ66>0,M66>0),ROUND(M66*1000/(AQ66*0.3),0),""),"") | AV66: =IFERROR(IF(AND(AM66>0,O66>0),ROUND(O66*1000/(AM66*0.1),0),""),"") | AW66: =IFERROR(IF(AND(AP66>0,N66>0),ROUND(N66*1000/(AP66*0.25),0),""),"") | AX66: =IFERROR(IF(AND(AO66>0,Q66>0),ROUND(Q66*1000/(AO66*1),0),""),"") | AY66: =IFERROR(ifs(I66="Tier S",0.65,I66="Tier 1",0.55,I66="Tier 2",0.45,I66="Tier 3",0.35,I66="Tier 4",0.25),0.35) -> 0.35 | AZ66: 1 | BA66: 1 | BB66: 1 | BC66: =IFERROR(ROUND(S66*AY66*BA66*BB66*AZ66,0),0) -> 4389 | BD66: =IF(COUNT(AM66,AN66,AO66,AP66,AQ66,AR66,AS66)>0,"estimated","pending") -> pending
B67: =IF($C67="","",COUNTA($C$6:C67)) -> 62 | C67: Tamago | D67: Player | E67: Fatal Fury | F67: Fatal Fury | G67: Mexican | H67: 1 | I67: Tier 3 | J67: 11000 | K67: 4600 | L67: =IF(J67="","",ROUND(J67*0.17,0)) -> 1870 | M67: 8600 | N67: 3500 | O67: 2200 | P67: 2200 | Q67: 15950 | R67: 7150 | S67: =IF(J67="","",ROUND(J67*2.2,0)) -> 24200 | T67: 3850 | U67: 3300 | V67: 2000 | W67: 2400 | X67: 1 platform | Y67: 0.75 | Z67: 1 | AA67: Ángel Chong | AB67: https://x.com/ChonFx | AK67: 1986-03-09 00:00:00 | AT67: =IFERROR(IF(AND(AN67>0,J67>0),ROUND(J67*1000/(AN67*0.2),0),""),"") | AU67: =IFERROR(IF(AND(AQ67>0,M67>0),ROUND(M67*1000/(AQ67*0.3),0),""),"") | AV67: =IFERROR(IF(AND(AM67>0,O67>0),ROUND(O67*1000/(AM67*0.1),0),""),"") | AW67: =IFERROR(IF(AND(AP67>0,N67>0),ROUND(N67*1000/(AP67*0.25),0),""),"") | AX67: =IFERROR(IF(AND(AO67>0,Q67>0),ROUND(Q67*1000/(AO67*1),0),""),"") | AY67: =IFERROR(ifs(I67="Tier S",0.65,I67="Tier 1",0.55,I67="Tier 2",0.45,I67="Tier 3",0.35,I67="Tier 4",0.25),0.35) -> 0.35 | AZ67: 1 | BA67: 1 | BB67: 1 | BC67: =IFERROR(ROUND(S67*AY67*BA67*BB67*AZ67,0),0) -> 8470 | BD67: =IF(COUNT(AM67,AN67,AO67,AP67,AQ67,AR67,AS67)>0,"estimated","pending") -> pending
B68: =IF($C68="","",COUNTA($C$6:C68)) -> 63 | C68: Xyzzy | D68: Player | E68: Fatal Fury | F68: Fatal Fury | G68: South Korean | H68: 2 | I68: Tier 2 | J68: 5200 | K68: 2200 | L68: =IF(J68="","",ROUND(J68*0.17,0)) -> 884 | M68: 4050 | N68: 1650 | O68: 1050 | P68: 1050 | Q68: 7550 | R68: 3400 | S68: =IF(J68="","",ROUND(J68*2.2,0)) -> 11440 | T68: 1800 | U68: 1550 | V68: 950 | W68: 2400 | X68: 2 platforms | Y68: 0.75 | Z68: 1 | AA68: Lee Hanbyul | AB68: https://x.com/xyzzylshift | AD68: https://www.twitch.tv/xyzzyshift | AK68: 1989-01-09 00:00:00 | AT68: =IFERROR(IF(AND(AN68>0,J68>0),ROUND(J68*1000/(AN68*0.2),0),""),"") | AU68: =IFERROR(IF(AND(AQ68>0,M68>0),ROUND(M68*1000/(AQ68*0.3),0),""),"") | AV68: =IFERROR(IF(AND(AM68>0,O68>0),ROUND(O68*1000/(AM68*0.1),0),""),"") | AW68: =IFERROR(IF(AND(AP68>0,N68>0),ROUND(N68*1000/(AP68*0.25),0),""),"") | AX68: =IFERROR(IF(AND(AO68>0,Q68>0),ROUND(Q68*1000/(AO68*1),0),""),"") | AY68: =IFERROR(ifs(I68="Tier S",0.65,I68="Tier 1",0.55,I68="Tier 2",0.45,I68="Tier 3",0.35,I68="Tier 4",0.25),0.35) -> 0.35 | AZ68: 1 | BA68: 1 | BB68: 1 | BC68: =IFERROR(ROUND(S68*AY68*BA68*BB68*AZ68,0),0) -> 4004 | BD68: =IF(COUNT(AM68,AN68,AO68,AP68,AQ68,AR68,AS68)>0,"estimated","pending") -> pending
B69: =IF($C69="","",COUNTA($C$6:C69)) -> 64 | C69: Xiaohai | D69: Player | E69: Fatal Fury | F69: Fatal Fury | G69: China | H69: 1 | I69: Tier 3 | J69: 11000 | K69: 4600 | L69: =IF(J69="","",ROUND(J69*0.17,0)) -> 1870 | M69: 8600 | N69: 3500 | O69: 2200 | P69: 2200 | Q69: 15950 | R69: 7150 | S69: =IF(J69="","",ROUND(J69*2.2,0)) -> 24200 | T69: 3850 | U69: 3300 | V69: 2000 | W69: 2400 | X69: 1 platform | Y69: 0.1 | Z69: 1 | AA69: Zeng Zhuojun | AB69: https://x.com/Xiaohai_ | AK69: 26/04/1989 | AT69: =IFERROR(IF(AND(AN69>0,J69>0),ROUND(J69*1000/(AN69*0.2),0),""),"") | AU69: =IFERROR(IF(AND(AQ69>0,M69>0),ROUND(M69*1000/(AQ69*0.3),0),""),"") | AV69: =IFERROR(IF(AND(AM69>0,O69>0),ROUND(O69*1000/(AM69*0.1),0),""),"") | AW69: =IFERROR(IF(AND(AP69>0,N69>0),ROUND(N69*1000/(AP69*0.25),0),""),"") | AX69: =IFERROR(IF(AND(AO69>0,Q69>0),ROUND(Q69*1000/(AO69*1),0),""),"") | AY69: =IFERROR(ifs(I69="Tier S",0.65,I69="Tier 1",0.55,I69="Tier 2",0.45,I69="Tier 3",0.35,I69="Tier 4",0.25),0.35) -> 0.35 | AZ69: 1 | BA69: 1 | BB69: 1 | BC69: =IFERROR(ROUND(S69*AY69*BA69*BB69*AZ69,0),0) -> 8470 | BD69: =IF(COUNT(AM69,AN69,AO69,AP69,AQ69,AR69,AS69)>0,"estimated","pending") -> pending
B70: =IF($C70="","",COUNTA($C$6:C70)) -> 65 | C70: Peterbot | D70: Player | E70: Fortnite | F70: Fortnite | G70: American/Hungarian | H70: 3 | I70: Tier 2 | J70: 11000 | K70: 4600 | L70: =IF(J70="","",ROUND(J70*0.17,0)) -> 1870 | M70: 8600 | N70: 3500 | O70: 2200 | P70: 2200 | Q70: 15950 | R70: 7150 | S70: =IF(J70="","",ROUND(J70*2.2,0)) -> 24200 | T70: 3850 | U70: 3300 | V70: 2000 | W70: 2400 | X70: 3 platforms | Y70: 0.5 | Z70: 1 | AA70: Peter Kata | AB70: https://x.com/PeterbotFN | AD70: https://www.twitch.tv/peterbot | AE70: https://www.youtube.com/channel/UC_RGYvZpoesD8yX-o677-xw | AK70: 20/06/2007 | AT70: =IFERROR(IF(AND(AN70>0,J70>0),ROUND(J70*1000/(AN70*0.2),0),""),"") | AU70: =IFERROR(IF(AND(AQ70>0,M70>0),ROUND(M70*1000/(AQ70*0.3),0),""),"") | AV70: =IFERROR(IF(AND(AM70>0,O70>0),ROUND(O70*1000/(AM70*0.1),0),""),"") | AW70: =IFERROR(IF(AND(AP70>0,N70>0),ROUND(N70*1000/(AP70*0.25),0),""),"") | AX70: =IFERROR(IF(AND(AO70>0,Q70>0),ROUND(Q70*1000/(AO70*1),0),""),"") | AY70: =IFERROR(ifs(I70="Tier S",0.65,I70="Tier 1",0.55,I70="Tier 2",0.45,I70="Tier 3",0.35,I70="Tier 4",0.25),0.35) -> 0.35 | AZ70: 1 | BA70: 1 | BB70: 1 | BC70: =IFERROR(ROUND(S70*AY70*BA70*BB70*AZ70,0),0) -> 8470 | BD70: =IF(COUNT(AM70,AN70,AO70,AP70,AQ70,AR70,AS70)>0,"estimated","pending") -> pending
B71: =IF($C71="","",COUNTA($C$6:C71)) -> 66 | C71: FHD | D71: Player | E71: Fortnite | F71: Fortnite | G71: Saudi | H71: 3 | I71: Tier 2 | J71: 11000 | K71: 4600 | L71: =IF(J71="","",ROUND(J71*0.17,0)) -> 1870 | M71: 8600 | N71: 3500 | O71: 2200 | P71: 2200 | Q71: 15950 | R71: 7150 | S71: =IF(J71="","",ROUND(J71*2.2,0)) -> 24200 | T71: 3850 | U71: 3300 | V71: 2000 | W71: 2400 | X71: 3 platforms | Y71: 0.3 | Z71: 1 | AA71: Fahad Almutairi | AB71: https://x.com/Fahadclipz | AC71: https://www.instagram.com/fahadclipz/?hl=en | AD71: https://www.twitch.tv/fahadfn | AK71: 31/03/2004 | AT71: =IFERROR(IF(AND(AN71>0,J71>0),ROUND(J71*1000/(AN71*0.2),0),""),"") | AU71: =IFERROR(IF(AND(AQ71>0,M71>0),ROUND(M71*1000/(AQ71*0.3),0),""),"") | AV71: =IFERROR(IF(AND(AM71>0,O71>0),ROUND(O71*1000/(AM71*0.1),0),""),"") | AW71: =IFERROR(IF(AND(AP71>0,N71>0),ROUND(N71*1000/(AP71*0.25),0),""),"") | AX71: =IFERROR(IF(AND(AO71>0,Q71>0),ROUND(Q71*1000/(AO71*1),0),""),"") | AY71: =IFERROR(ifs(I71="Tier S",0.65,I71="Tier 1",0.55,I71="Tier 2",0.45,I71="Tier 3",0.35,I71="Tier 4",0.25),0.35) -> 0.35 | AZ71: 1 | BA71: 1 | BB71: 1 | BC71: =IFERROR(ROUND(S71*AY71*BA71*BB71*AZ71,0),0) -> 8470 | BD71: =IF(COUNT(AM71,AN71,AO71,AP71,AQ71,AR71,AS71)>0,"estimated","pending") -> pending
B72: =IF($C72="","",COUNTA($C$6:C72)) -> 67 | C72: Gntl | D72: Player | E72: Call of Duty Black Ops 7 | F72: FaZe Falcons | G72: Saudi | H72: 4 | I72: Tier 3 | J72: 12100 | K72: 5100 | L72: =IF(J72="","",ROUND(J72*0.17,0)) -> 2057 | M72: 9450 | N72: 3850 | O72: 2400 | P72: 2400 | Q72: 17550 | R72: 7850 | S72: =IF(J72="","",ROUND(J72*2.2,0)) -> 26620 | T72: 4250 | U72: 3650 | V72: 2200 | W72: 2400 | X72: 4 platforms | Y72: 0.3 | Z72: 1 | AA72: Abdullah Albaqami | AB72: https://x.com/g1ntl | AC72: https://www.instagram.com/accounts/login/?next=%2Fg1ntl&source=omni_redirect | AD72: https://www.twitch.tv/GntL | AE72: https://www.youtube.com/c/g1ntl | AK72: 24/09/2002 | AT72: =IFERROR(IF(AND(AN72>0,J72>0),ROUND(J72*1000/(AN72*0.2),0),""),"") | AU72: =IFERROR(IF(AND(AQ72>0,M72>0),ROUND(M72*1000/(AQ72*0.3),0),""),"") | AV72: =IFERROR(IF(AND(AM72>0,O72>0),ROUND(O72*1000/(AM72*0.1),0),""),"") | AW72: =IFERROR(IF(AND(AP72>0,N72>0),ROUND(N72*1000/(AP72*0.25),0),""),"") | AX72: =IFERROR(IF(AND(AO72>0,Q72>0),ROUND(Q72*1000/(AO72*1),0),""),"") | AY72: =IFERROR(ifs(I72="Tier S",0.65,I72="Tier 1",0.55,I72="Tier 2",0.45,I72="Tier 3",0.35,I72="Tier 4",0.25),0.35) -> 0.35 | AZ72: 1 | BA72: 1 | BB72: 1 | BC72: =IFERROR(ROUND(S72*AY72*BA72*BB72*AZ72,0),0) -> 9317 | BD72: =IF(COUNT(AM72,AN72,AO72,AP72,AQ72,AR72,AS72)>0,"estimated","pending") -> pending
B73: =IF($C73="","",COUNTA($C$6:C73)) -> 68 | C73: NM7 | D73: Player | E73: Fortnite | F73: Fortnite | G73: Saudi | H73: 4 | I73: Tier 3 | J73: 5700 | K73: 2400 | L73: =IF(J73="","",ROUND(J73*0.17,0)) -> 969 | M73: 4450 | N73: 1850 | O73: 1150 | P73: 1150 | Q73: 8300 | R73: 3700 | S73: =IF(J73="","",ROUND(J73*2.2,0)) -> 12540 | T73: 2000 | U73: 1700 | V73: 1050 | W73: 2400 | X73: 4 platforms | Y73: 0.3 | Z73: 1 | AA73: Nawaf Alharthi | AB73: https://x.com/iNm7x | AC73: https://www.instagram.com/accounts/login/?next=%2Finm7x&source=omni_redirect | AD73: https://www.twitch.tv/iiNm7x | AE73: https://www.youtube.com/c/iNm7x | AK73: 2002-09-03 00:00:00 | AT73: =IFERROR(IF(AND(AN73>0,J73>0),ROUND(J73*1000/(AN73*0.2),0),""),"") | AU73: =IFERROR(IF(AND(AQ73>0,M73>0),ROUND(M73*1000/(AQ73*0.3),0),""),"") | AV73: =IFERROR(IF(AND(AM73>0,O73>0),ROUND(O73*1000/(AM73*0.1),0),""),"") | AW73: =IFERROR(IF(AND(AP73>0,N73>0),ROUND(N73*1000/(AP73*0.25),0),""),"") | AX73: =IFERROR(IF(AND(AO73>0,Q73>0),ROUND(Q73*1000/(AO73*1),0),""),"") | AY73: =IFERROR(ifs(I73="Tier S",0.65,I73="Tier 1",0.55,I73="Tier 2",0.45,I73="Tier 3",0.35,I73="Tier 4",0.25),0.35) -> 0.35 | AZ73: 1 | BA73: 1 | BB73: 1 | BC73: =IFERROR(ROUND(S73*AY73*BA73*BB73*AZ73,0),0) -> 4389 | BD73: =IF(COUNT(AM73,AN73,AO73,AP73,AQ73,AR73,AS73)>0,"estimated","pending") -> pending
B74: =IF($C74="","",COUNTA($C$6:C74)) -> 69 | C74: Spy | D74: Player | E74: Fortnite | F74: Fortnite | G74: Saudi | H74: 4 | I74: Tier 3 | J74: 5700 | K74: 2400 | L74: =IF(J74="","",ROUND(J74*0.17,0)) -> 969 | M74: 4450 | N74: 1850 | O74: 1150 | P74: 1150 | Q74: 8300 | R74: 3700 | S74: =IF(J74="","",ROUND(J74*2.2,0)) -> 12540 | T74: 2000 | U74: 1700 | V74: 1050 | W74: 2400 | X74: 4 platforms | Y74: 0.3 | Z74: 1 | AA74: Osama Almasad | AB74: https://x.com/spyerfrog | AC74: https://www.instagram.com/accounts/login/?next=%2Fspyerfrog&source=omni_redirect | AD74: https://www.twitch.tv/spyerfrog | AE74: https://www.youtube.com/channel/UCl9pp6XYMcjyVESzYD8myQg | AK74: 26/02/2002 | AT74: =IFERROR(IF(AND(AN74>0,J74>0),ROUND(J74*1000/(AN74*0.2),0),""),"") | AU74: =IFERROR(IF(AND(AQ74>0,M74>0),ROUND(M74*1000/(AQ74*0.3),0),""),"") | AV74: =IFERROR(IF(AND(AM74>0,O74>0),ROUND(O74*1000/(AM74*0.1),0),""),"") | AW74: =IFERROR(IF(AND(AP74>0,N74>0),ROUND(N74*1000/(AP74*0.25),0),""),"") | AX74: =IFERROR(IF(AND(AO74>0,Q74>0),ROUND(Q74*1000/(AO74*1),0),""),"") | AY74: =IFERROR(ifs(I74="Tier S",0.65,I74="Tier 1",0.55,I74="Tier 2",0.45,I74="Tier 3",0.35,I74="Tier 4",0.25),0.35) -> 0.35 | AZ74: 1 | BA74: 1 | BB74: 1 | BC74: =IFERROR(ROUND(S74*AY74*BA74*BB74*AZ74,0),0) -> 4389 | BD74: =IF(COUNT(AM74,AN74,AO74,AP74,AQ74,AR74,AS74)>0,"estimated","pending") -> pending
B75: =IF($C75="","",COUNTA($C$6:C75)) -> 70 | C75: Yonx | D75: Player | E75: Fortnite | F75: Fortnite | G75: Saudi | H75: 3 | I75: Tier 3 | J75: 5700 | K75: 2400 | L75: =IF(J75="","",ROUND(J75*0.17,0)) -> 969 | M75: 4450 | N75: 1850 | O75: 1150 | P75: 1150 | Q75: 8300 | R75: 3700 | S75: =IF(J75="","",ROUND(J75*2.2,0)) -> 12540 | T75: 2000 | U75: 1700 | V75: 1050 | W75: 2400 | X75: 3 platforms | Y75: 0.3 | Z75: 1 | AA75: Faisal Almusharraf | AB75: https://x.com/YonxFN | AD75: https://www.twitch.tv/YonxFN | AE75: https://www.youtube.com/channel/UCSKgsqUfo7vA4BuBvtf6vwg | AK75: 2004-11-04 00:00:00 | AT75: =IFERROR(IF(AND(AN75>0,J75>0),ROUND(J75*1000/(AN75*0.2),0),""),"") | AU75: =IFERROR(IF(AND(AQ75>0,M75>0),ROUND(M75*1000/(AQ75*0.3),0),""),"") | AV75: =IFERROR(IF(AND(AM75>0,O75>0),ROUND(O75*1000/(AM75*0.1),0),""),"") | AW75: =IFERROR(IF(AND(AP75>0,N75>0),ROUND(N75*1000/(AP75*0.25),0),""),"") | AX75: =IFERROR(IF(AND(AO75>0,Q75>0),ROUND(Q75*1000/(AO75*1),0),""),"") | AY75: =IFERROR(ifs(I75="Tier S",0.65,I75="Tier 1",0.55,I75="Tier 2",0.45,I75="Tier 3",0.35,I75="Tier 4",0.25),0.35) -> 0.35 | AZ75: 1 | BA75: 1 | BB75: 1 | BC75: =IFERROR(ROUND(S75*AY75*BA75*BB75*AZ75,0),0) -> 4389 | BD75: =IF(COUNT(AM75,AN75,AO75,AP75,AQ75,AR75,AS75)>0,"estimated","pending") -> pending
B76: =IF($C76="","",COUNTA($C$6:C76)) -> 71 | C76: Matteo | D76: Manager | E76: Fortnite | F76: Fortnite | G76: French | H76: 0 | I76: Tier 3 | J76: 0 | K76: 0 | L76: =IF(J76="","",ROUND(J76*0.17,0)) -> 0 | M76: 0 | N76: 0 | O76: 0 | P76: 0 | Q76: 0 | R76: 0 | S76: =IF(J76="","",ROUND(J76*2.2,0)) -> 0 | T76: 0 | U76: 0 | V76: 600 | W76: 0 | X76: 0 platforms | Y76: 0.3 | Z76: 1 | AA76: Matteo Paganin | AT76: =IFERROR(IF(AND(AN76>0,J76>0),ROUND(J76*1000/(AN76*0.2),0),""),"") | AU76: =IFERROR(IF(AND(AQ76>0,M76>0),ROUND(M76*1000/(AQ76*0.3),0),""),"") | AV76: =IFERROR(IF(AND(AM76>0,O76>0),ROUND(O76*1000/(AM76*0.1),0),""),"") | AW76: =IFERROR(IF(AND(AP76>0,N76>0),ROUND(N76*1000/(AP76*0.25),0),""),"") | AX76: =IFERROR(IF(AND(AO76>0,Q76>0),ROUND(Q76*1000/(AO76*1),0),""),"") | AY76: =IFERROR(ifs(I76="Tier S",0.65,I76="Tier 1",0.55,I76="Tier 2",0.45,I76="Tier 3",0.35,I76="Tier 4",0.25),0.35) -> 0.35 | AZ76: 1 | BA76: 1 | BB76: 1 | BC76: =IFERROR(ROUND(S76*AY76*BA76*BB76*AZ76,0),0) -> 0 | BD76: =IF(COUNT(AM76,AN76,AO76,AP76,AQ76,AR76,AS76)>0,"estimated","pending") -> pending
B77: =IF($C77="","",COUNTA($C$6:C77)) -> 72 | C77: Conan | D77: Head Coach | E77: Free Fire | F77: Team Falcons | G77: Thailand | H77: 2 | I77: Tier 2 | J77: 0 | K77: 0 | L77: =IF(J77="","",ROUND(J77*0.17,0)) -> 0 | M77: 0 | N77: 0 | O77: 0 | P77: 0 | Q77: 0 | R77: 0 | S77: =IF(J77="","",ROUND(J77*2.2,0)) -> 0 | T77: 0 | U77: 0 | V77: 1200 | W77: 0 | X77: 2 platforms | Y77: 0.3 | Z77: 1 | AA77: Tana Kamruang | AC77: https://www.instagram.com/thana_kamruang/ | AH77: https://facebook.com/profile.php?id=100006004232176 | AK77: 1993-02-03 00:00:00 | AT77: =IFERROR(IF(AND(AN77>0,J77>0),ROUND(J77*1000/(AN77*0.2),0),""),"") | AU77: =IFERROR(IF(AND(AQ77>0,M77>0),ROUND(M77*1000/(AQ77*0.3),0),""),"") | AV77: =IFERROR(IF(AND(AM77>0,O77>0),ROUND(O77*1000/(AM77*0.1),0),""),"") | AW77: =IFERROR(IF(AND(AP77>0,N77>0),ROUND(N77*1000/(AP77*0.25),0),""),"") | AX77: =IFERROR(IF(AND(AO77>0,Q77>0),ROUND(Q77*1000/(AO77*1),0),""),"") | AY77: =IFERROR(ifs(I77="Tier S",0.65,I77="Tier 1",0.55,I77="Tier 2",0.45,I77="Tier 3",0.35,I77="Tier 4",0.25),0.35) -> 0.35 | AZ77: 1 | BA77: 1 | BB77: 1 | BC77: =IFERROR(ROUND(S77*AY77*BA77*BB77*AZ77,0),0) -> 0 | BD77: =IF(COUNT(AM77,AN77,AO77,AP77,AQ77,AR77,AS77)>0,"estimated","pending") -> pending
B78: =IF($C78="","",COUNTA($C$6:C78)) -> 73 | C78: KERORO | D78: Player | E78: Free Fire | F78: Team Falcons | G78: Thailand | H78: 2 | I78: Tier 2 | J78: 11250 | K78: 4500 | L78: =IF(J78="","",ROUND(J78*0.17,0)) -> 1913 | M78: 8000 | N78: 3500 | O78: 2000 | P78: 2000 | Q78: 13500 | R78: 6075 | S78: =IF(J78="","",ROUND(J78*2.2,0)) -> 24750 | T78: 4638 | U78: 4063 | V78: 2438 | W78: 2400 | X78: 2 platforms | Y78: 0.3 | Z78: 1 | AA78: Natthaphong Phuangpriang | AC78: https://www.instagram.com/keroro_god | AH78: https://facebook.com/profile.php?id=100014997245027 | AK78: 13/01/2006 | AT78: =IFERROR(IF(AND(AN78>0,J78>0),ROUND(J78*1000/(AN78*0.2),0),""),"") | AU78: =IFERROR(IF(AND(AQ78>0,M78>0),ROUND(M78*1000/(AQ78*0.3),0),""),"") | AV78: =IFERROR(IF(AND(AM78>0,O78>0),ROUND(O78*1000/(AM78*0.1),0),""),"") | AW78: =IFERROR(IF(AND(AP78>0,N78>0),ROUND(N78*1000/(AP78*0.25),0),""),"") | AX78: =IFERROR(IF(AND(AO78>0,Q78>0),ROUND(Q78*1000/(AO78*1),0),""),"") | AY78: =IFERROR(ifs(I78="Tier S",0.65,I78="Tier 1",0.55,I78="Tier 2",0.45,I78="Tier 3",0.35,I78="Tier 4",0.25),0.35) -> 0.35 | AZ78: 1 | BA78: 1 | BB78: 1 | BC78: =IFERROR(ROUND(S78*AY78*BA78*BB78*AZ78,0),0) -> 8663 | BD78: =IF(COUNT(AM78,AN78,AO78,AP78,AQ78,AR78,AS78)>0,"estimated","pending") -> pending
B79: =IF($C79="","",COUNTA($C$6:C79)) -> 74 | C79: LIMIT | D79: Player | E79: Free Fire | F79: Team Falcons | G79: Thailand | H79: 3 | I79: Tier 2 | J79: 11000 | K79: 4600 | L79: =IF(J79="","",ROUND(J79*0.17,0)) -> 1870 | M79: 8600 | N79: 3500 | O79: 2200 | P79: 2200 | Q79: 15950 | R79: 7150 | S79: =IF(J79="","",ROUND(J79*2.2,0)) -> 24200 | T79: 3850 | U79: 3300 | V79: 2000 | W79: 2400 | X79: 3 platforms | Y79: 0.3 | Z79: 1 | AA79: Rachata Wanaphurksasilp | AC79: https://www.instagram.com/limit_juy | AF79: https://tiktok.com/@limitxstep8 | AH79: https://facebook.com/profile.php?id=100015743748929 | AK79: 20/02/2006 | AT79: =IFERROR(IF(AND(AN79>0,J79>0),ROUND(J79*1000/(AN79*0.2),0),""),"") | AU79: =IFERROR(IF(AND(AQ79>0,M79>0),ROUND(M79*1000/(AQ79*0.3),0),""),"") | AV79: =IFERROR(IF(AND(AM79>0,O79>0),ROUND(O79*1000/(AM79*0.1),0),""),"") | AW79: =IFERROR(IF(AND(AP79>0,N79>0),ROUND(N79*1000/(AP79*0.25),0),""),"") | AX79: =IFERROR(IF(AND(AO79>0,Q79>0),ROUND(Q79*1000/(AO79*1),0),""),"") | AY79: =IFERROR(ifs(I79="Tier S",0.65,I79="Tier 1",0.55,I79="Tier 2",0.45,I79="Tier 3",0.35,I79="Tier 4",0.25),0.35) -> 0.35 | AZ79: 1 | BA79: 1 | BB79: 1 | BC79: =IFERROR(ROUND(S79*AY79*BA79*BB79*AZ79,0),0) -> 8470 | BD79: =IF(COUNT(AM79,AN79,AO79,AP79,AQ79,AR79,AS79)>0,"estimated","pending") -> pending
B80: =IF($C80="","",COUNTA($C$6:C80)) -> 75 | C80: ONEMORE | D80: Player | E80: Free Fire | F80: Team Falcons | G80: Thailand | H80: 3 | I80: Tier 2 | J80: 11000 | K80: 4600 | L80: =IF(J80="","",ROUND(J80*0.17,0)) -> 1870 | M80: 8600 | N80: 3500 | O80: 2200 | P80: 2200 | Q80: 15950 | R80: 7150 | S80: =IF(J80="","",ROUND(J80*2.2,0)) -> 24200 | T80: 3850 | U80: 3300 | V80: 2000 | W80: 2400 | X80: 3 platforms | Y80: 0.3 | Z80: 1 | AA80: Rattapoom Sunthalunai | AC80: https://www.instagram.com/poomgohome_ | AF80: https://tiktok.com/@pm.rt | AH80: https://facebook.com/ratta.poom.790 | AK80: 2005-09-05 00:00:00 | AT80: =IFERROR(IF(AND(AN80>0,J80>0),ROUND(J80*1000/(AN80*0.2),0),""),"") | AU80: =IFERROR(IF(AND(AQ80>0,M80>0),ROUND(M80*1000/(AQ80*0.3),0),""),"") | AV80: =IFERROR(IF(AND(AM80>0,O80>0),ROUND(O80*1000/(AM80*0.1),0),""),"") | AW80: =IFERROR(IF(AND(AP80>0,N80>0),ROUND(N80*1000/(AP80*0.25),0),""),"") | AX80: =IFERROR(IF(AND(AO80>0,Q80>0),ROUND(Q80*1000/(AO80*1),0),""),"") | AY80: =IFERROR(ifs(I80="Tier S",0.65,I80="Tier 1",0.55,I80="Tier 2",0.45,I80="Tier 3",0.35,I80="Tier 4",0.25),0.35) -> 0.35 | AZ80: 1 | BA80: 1 | BB80: 1 | BC80: =IFERROR(ROUND(S80*AY80*BA80*BB80*AZ80,0),0) -> 8470 | BD80: =IF(COUNT(AM80,AN80,AO80,AP80,AQ80,AR80,AS80)>0,"estimated","pending") -> pending
B81: =IF($C81="","",COUNTA($C$6:C81)) -> 76 | C81: ONFIRE | D81: Player | E81: Free Fire | F81: Team Falcons | G81: Thailand | H81: 3 | I81: Tier 2 | J81: 11000 | K81: 4600 | L81: =IF(J81="","",ROUND(J81*0.17,0)) -> 1870 | M81: 8600 | N81: 3500 | O81: 2200 | P81: 2200 | Q81: 15950 | R81: 7150 | S81: =IF(J81="","",ROUND(J81*2.2,0)) -> 24200 | T81: 3850 | U81: 3300 | V81: 2000 | W81: 2400 | X81: 3 platforms | Y81: 0.3 | Z81: 1 | AA81: Phulipat Yosit | AC81: https://www.instagram.com/onfirebaby__ | AF81: https://tiktok.com/@onfireeieii | AH81: https://facebook.com/profile.php?id=100072006039523 | AK81: 27/09/2005 | AT81: =IFERROR(IF(AND(AN81>0,J81>0),ROUND(J81*1000/(AN81*0.2),0),""),"") | AU81: =IFERROR(IF(AND(AQ81>0,M81>0),ROUND(M81*1000/(AQ81*0.3),0),""),"") | AV81: =IFERROR(IF(AND(AM81>0,O81>0),ROUND(O81*1000/(AM81*0.1),0),""),"") | AW81: =IFERROR(IF(AND(AP81>0,N81>0),ROUND(N81*1000/(AP81*0.25),0),""),"") | AX81: =IFERROR(IF(AND(AO81>0,Q81>0),ROUND(Q81*1000/(AO81*1),0),""),"") | AY81: =IFERROR(ifs(I81="Tier S",0.65,I81="Tier 1",0.55,I81="Tier 2",0.45,I81="Tier 3",0.35,I81="Tier 4",0.25),0.35) -> 0.35 | AZ81: 1 | BA81: 1 | BB81: 1 | BC81: =IFERROR(ROUND(S81*AY81*BA81*BB81*AZ81,0),0) -> 8470 | BD81: =IF(COUNT(AM81,AN81,AO81,AP81,AQ81,AR81,AS81)>0,"estimated","pending") -> pending
B82: =IF($C82="","",COUNTA($C$6:C82)) -> 77 | C82: Penna | D82: Player | E82: Free Fire | F82: Team Falcons | G82: Thailand | H82: 2 | I82: Tier 2 | J82: 11000 | K82: 4600 | L82: =IF(J82="","",ROUND(J82*0.17,0)) -> 1870 | M82: 8600 | N82: 3500 | O82: 2200 | P82: 2200 | Q82: 15950 | R82: 7150 | S82: =IF(J82="","",ROUND(J82*2.2,0)) -> 24200 | T82: 3850 | U82: 3300 | V82: 2000 | W82: 2400 | X82: 2 platforms | Y82: 0.3 | Z82: 1 | AA82: Natthawut Srinaknil | AC82: https://www.instagram.com/pee_2006._?igsh=enRyOTlwbnV2bjg5 | AF82: https://www.tiktok.com/@peena._?_r=1&_t=ZS-93QJymJbPfx | AK82: 13/09/2006 | AT82: =IFERROR(IF(AND(AN82>0,J82>0),ROUND(J82*1000/(AN82*0.2),0),""),"") | AU82: =IFERROR(IF(AND(AQ82>0,M82>0),ROUND(M82*1000/(AQ82*0.3),0),""),"") | AV82: =IFERROR(IF(AND(AM82>0,O82>0),ROUND(O82*1000/(AM82*0.1),0),""),"") | AW82: =IFERROR(IF(AND(AP82>0,N82>0),ROUND(N82*1000/(AP82*0.25),0),""),"") | AX82: =IFERROR(IF(AND(AO82>0,Q82>0),ROUND(Q82*1000/(AO82*1),0),""),"") | AY82: =IFERROR(ifs(I82="Tier S",0.65,I82="Tier 1",0.55,I82="Tier 2",0.45,I82="Tier 3",0.35,I82="Tier 4",0.25),0.35) -> 0.35 | AZ82: 1 | BA82: 1 | BB82: 1 | BC82: =IFERROR(ROUND(S82*AY82*BA82*BB82*AZ82,0),0) -> 8470 | BD82: =IF(COUNT(AM82,AN82,AO82,AP82,AQ82,AR82,AS82)>0,"estimated","pending") -> pending
B83: =IF($C83="","",COUNTA($C$6:C83)) -> 78 | C83: PROTETO | D83: Player | E83: Free Fire | F83: Team Falcons | G83: Thailand | H83: 2 | I83: Tier 2 | J83: 11000 | K83: 4600 | L83: =IF(J83="","",ROUND(J83*0.17,0)) -> 1870 | M83: 8600 | N83: 3500 | O83: 2200 | P83: 2200 | Q83: 15950 | R83: 7150 | S83: =IF(J83="","",ROUND(J83*2.2,0)) -> 24200 | T83: 3850 | U83: 3300 | V83: 2000 | W83: 2400 | X83: 2 platforms | Y83: 0.3 | Z83: 1 | AA83: Ratchata Soonklang | AC83: https://www.instagram.com/protetae | AH83: https://facebook.com/pongsatorn.pongsatorn.754 | AK83: 2009-04-02 00:00:00 | AT83: =IFERROR(IF(AND(AN83>0,J83>0),ROUND(J83*1000/(AN83*0.2),0),""),"") | AU83: =IFERROR(IF(AND(AQ83>0,M83>0),ROUND(M83*1000/(AQ83*0.3),0),""),"") | AV83: =IFERROR(IF(AND(AM83>0,O83>0),ROUND(O83*1000/(AM83*0.1),0),""),"") | AW83: =IFERROR(IF(AND(AP83>0,N83>0),ROUND(N83*1000/(AP83*0.25),0),""),"") | AX83: =IFERROR(IF(AND(AO83>0,Q83>0),ROUND(Q83*1000/(AO83*1),0),""),"") | AY83: =IFERROR(ifs(I83="Tier S",0.65,I83="Tier 1",0.55,I83="Tier 2",0.45,I83="Tier 3",0.35,I83="Tier 4",0.25),0.35) -> 0.35 | AZ83: 1 | BA83: 1 | BB83: 1 | BC83: =IFERROR(ROUND(S83*AY83*BA83*BB83*AZ83,0),0) -> 8470 | BD83: =IF(COUNT(AM83,AN83,AO83,AP83,AQ83,AR83,AS83)>0,"estimated","pending") -> pending
B84: =IF($C84="","",COUNTA($C$6:C84)) -> 79 | C84: SAINOI | D84: Manager | E84: Free Fire | F84: Team Falcons | G84: Thailand | H84: 0 | I84: Tier 3 | J84: 11000 | K84: 4600 | L84: =IF(J84="","",ROUND(J84*0.17,0)) -> 1870 | M84: 8600 | N84: 3500 | O84: 2200 | P84: 0 | Q84: 15950 | R84: 7150 | S84: =IF(J84="","",ROUND(J84*2.2,0)) -> 24200 | T84: 3850 | U84: 3300 | V84: 2000 | W84: 0 | X84: 0 platforms | Y84: 0.3 | Z84: 1 | AA84: Worrawan Kasikarn | AT84: =IFERROR(IF(AND(AN84>0,J84>0),ROUND(J84*1000/(AN84*0.2),0),""),"") | AU84: =IFERROR(IF(AND(AQ84>0,M84>0),ROUND(M84*1000/(AQ84*0.3),0),""),"") | AV84: =IFERROR(IF(AND(AM84>0,O84>0),ROUND(O84*1000/(AM84*0.1),0),""),"") | AW84: =IFERROR(IF(AND(AP84>0,N84>0),ROUND(N84*1000/(AP84*0.25),0),""),"") | AX84: =IFERROR(IF(AND(AO84>0,Q84>0),ROUND(Q84*1000/(AO84*1),0),""),"") | AY84: =IFERROR(ifs(I84="Tier S",0.65,I84="Tier 1",0.55,I84="Tier 2",0.45,I84="Tier 3",0.35,I84="Tier 4",0.25),0.35) -> 0.35 | AZ84: 1 | BA84: 1 | BB84: 1 | BC84: =IFERROR(ROUND(S84*AY84*BA84*BB84*AZ84,0),0) -> 8470 | BD84: =IF(COUNT(AM84,AN84,AO84,AP84,AQ84,AR84,AS84)>0,"estimated","pending") -> pending
B85: =IF($C85="","",COUNTA($C$6:C85)) -> 80 | C85: Jose Serrano | D85: Player | E85: Gran Turismo | F85: Gran Turismo | G85: Spanish | H85: 3 | I85: Tier 2 | J85: 11250 | K85: 4500 | L85: =IF(J85="","",ROUND(J85*0.17,0)) -> 1913 | M85: 8000 | N85: 3500 | O85: 2000 | P85: 2000 | Q85: 13500 | R85: 6075 | S85: =IF(J85="","",ROUND(J85*2.2,0)) -> 24750 | T85: 4638 | U85: 4063 | V85: 2438 | W85: 2400 | X85: 3 platforms | Y85: 0.75 | Z85: 1 | AA85: Jose Serrano | AB85: https://x.com/JoseSerrano_16 | AC85: https://www.instagram.com/joseserranoo_/ | AD85: https://www.twitch.tv/JoseSerrano_16 | AK85: 25/09/2002 | AL85: Driver | AT85: =IFERROR(IF(AND(AN85>0,J85>0),ROUND(J85*1000/(AN85*0.2),0),""),"") | AU85: =IFERROR(IF(AND(AQ85>0,M85>0),ROUND(M85*1000/(AQ85*0.3),0),""),"") | AV85: =IFERROR(IF(AND(AM85>0,O85>0),ROUND(O85*1000/(AM85*0.1),0),""),"") | AW85: =IFERROR(IF(AND(AP85>0,N85>0),ROUND(N85*1000/(AP85*0.25),0),""),"") | AX85: =IFERROR(IF(AND(AO85>0,Q85>0),ROUND(Q85*1000/(AO85*1),0),""),"") | AY85: =IFERROR(ifs(I85="Tier S",0.65,I85="Tier 1",0.55,I85="Tier 2",0.45,I85="Tier 3",0.35,I85="Tier 4",0.25),0.35) -> 0.35 | AZ85: 1 | BA85: 1 | BB85: 1 | BC85: =IFERROR(ROUND(S85*AY85*BA85*BB85*AZ85,0),0) -> 8663 | BD85: =IF(COUNT(AM85,AN85,AO85,AP85,AQ85,AR85,AS85)>0,"estimated","pending") -> pending
B86: =IF($C86="","",COUNTA($C$6:C86)) -> 81 | C86: Naif Alfaleh | D86: Player | E86: Gran Turismo | F86: Gran Turismo | G86: Saudi | H86: 2 | I86: Tier 2 | J86: 11000 | K86: 4600 | L86: =IF(J86="","",ROUND(J86*0.17,0)) -> 1870 | M86: 8600 | N86: 3500 | O86: 2200 | P86: 2200 | Q86: 15950 | R86: 7150 | S86: =IF(J86="","",ROUND(J86*2.2,0)) -> 24200 | T86: 3850 | U86: 3300 | V86: 2000 | W86: 2400 | X86: 2 platforms | Y86: 0.3 | Z86: 1 | AA86: Naif Alfaleh | AB86: https://x.com/Falcon_Naifx | AC86: https://www.instagram.com/falcon_naifx/ | AK86: 30/06/2003 | AL86: Driver | AT86: =IFERROR(IF(AND(AN86>0,J86>0),ROUND(J86*1000/(AN86*0.2),0),""),"") | AU86: =IFERROR(IF(AND(AQ86>0,M86>0),ROUND(M86*1000/(AQ86*0.3),0),""),"") | AV86: =IFERROR(IF(AND(AM86>0,O86>0),ROUND(O86*1000/(AM86*0.1),0),""),"") | AW86: =IFERROR(IF(AND(AP86>0,N86>0),ROUND(N86*1000/(AP86*0.25),0),""),"") | AX86: =IFERROR(IF(AND(AO86>0,Q86>0),ROUND(Q86*1000/(AO86*1),0),""),"") | AY86: =IFERROR(ifs(I86="Tier S",0.65,I86="Tier 1",0.55,I86="Tier 2",0.45,I86="Tier 3",0.35,I86="Tier 4",0.25),0.35) -> 0.35 | AZ86: 1 | BA86: 1 | BB86: 1 | BC86: =IFERROR(ROUND(S86*AY86*BA86*BB86*AZ86,0),0) -> 8470 | BD86: =IF(COUNT(AM86,AN86,AO86,AP86,AQ86,AR86,AS86)>0,"estimated","pending") -> pending
B87: =IF($C87="","",COUNTA($C$6:C87)) -> 82 | C87: Pol Urra | D87: Player | E87: Gran Turismo | F87: Gran Turismo | G87: Spanish | H87: 2 | I87: Tier 2 | J87: 12100 | K87: 5100 | L87: =IF(J87="","",ROUND(J87*0.17,0)) -> 2057 | M87: 9450 | N87: 3850 | O87: 2400 | P87: 2400 | Q87: 17550 | R87: 7850 | S87: =IF(J87="","",ROUND(J87*2.2,0)) -> 26620 | T87: 4250 | U87: 3650 | V87: 2200 | W87: 2400 | X87: 2 platforms | Y87: 0.75 | Z87: 1 | AA87: Pol Urra | AB87: https://x.com/polurra | AC87: https://www.instagram.com/pol_urra/ | AK87: 21/02/2005 | AL87: Driver | AT87: =IFERROR(IF(AND(AN87>0,J87>0),ROUND(J87*1000/(AN87*0.2),0),""),"") | AU87: =IFERROR(IF(AND(AQ87>0,M87>0),ROUND(M87*1000/(AQ87*0.3),0),""),"") | AV87: =IFERROR(IF(AND(AM87>0,O87>0),ROUND(O87*1000/(AM87*0.1),0),""),"") | AW87: =IFERROR(IF(AND(AP87>0,N87>0),ROUND(N87*1000/(AP87*0.25),0),""),"") | AX87: =IFERROR(IF(AND(AO87>0,Q87>0),ROUND(Q87*1000/(AO87*1),0),""),"") | AY87: =IFERROR(ifs(I87="Tier S",0.65,I87="Tier 1",0.55,I87="Tier 2",0.45,I87="Tier 3",0.35,I87="Tier 4",0.25),0.35) -> 0.35 | AZ87: 1 | BA87: 1 | BB87: 1 | BC87: =IFERROR(ROUND(S87*AY87*BA87*BB87*AZ87,0),0) -> 9317 | BD87: =IF(COUNT(AM87,AN87,AO87,AP87,AQ87,AR87,AS87)>0,"estimated","pending") -> pending
B88: =IF($C88="","",COUNTA($C$6:C88)) -> 83 | C88: Wesam Khalil | D88: Player | E88: Gran Turismo | F88: Gran Turismo | G88: Saudi | H88: 2 | I88: Tier 2 | J88: 11000 | K88: 4600 | L88: =IF(J88="","",ROUND(J88*0.17,0)) -> 1870 | M88: 8600 | N88: 3500 | O88: 2200 | P88: 2200 | Q88: 15950 | R88: 7150 | S88: =IF(J88="","",ROUND(J88*2.2,0)) -> 24200 | T88: 3850 | U88: 3300 | V88: 2000 | W88: 2400 | X88: 2 platforms | Y88: 0.3 | Z88: 1 | AA88: Wesam Khalil | AB88: https://x.com/Falcon_Wesam | AC88: https://www.instagram.com/falcon_wesam/ | AK88: 17/06/1999 | AL88: Driver | AT88: =IFERROR(IF(AND(AN88>0,J88>0),ROUND(J88*1000/(AN88*0.2),0),""),"") | AU88: =IFERROR(IF(AND(AQ88>0,M88>0),ROUND(M88*1000/(AQ88*0.3),0),""),"") | AV88: =IFERROR(IF(AND(AM88>0,O88>0),ROUND(O88*1000/(AM88*0.1),0),""),"") | AW88: =IFERROR(IF(AND(AP88>0,N88>0),ROUND(N88*1000/(AP88*0.25),0),""),"") | AX88: =IFERROR(IF(AND(AO88>0,Q88>0),ROUND(Q88*1000/(AO88*1),0),""),"") | AY88: =IFERROR(ifs(I88="Tier S",0.65,I88="Tier 1",0.55,I88="Tier 2",0.45,I88="Tier 3",0.35,I88="Tier 4",0.25),0.35) -> 0.35 | AZ88: 1 | BA88: 1 | BB88: 1 | BC88: =IFERROR(ROUND(S88*AY88*BA88*BB88*AZ88,0),0) -> 8470 | BD88: =IF(COUNT(AM88,AN88,AO88,AP88,AQ88,AR88,AS88)>0,"estimated","pending") -> pending
B89: =IF($C89="","",COUNTA($C$6:C89)) -> 84 | C89: Skwal | D89: Manager | E89: Gran Turismo | F89: Gran Turismo | G89: French | H89: 2 | I89: Tier 2 | J89: 12100 | K89: 5100 | L89: =IF(J89="","",ROUND(J89*0.17,0)) -> 2057 | M89: 9450 | N89: 3850 | O89: 2400 | P89: 0 | Q89: 17550 | R89: 7850 | S89: =IF(J89="","",ROUND(J89*2.2,0)) -> 26620 | T89: 4250 | U89: 3650 | V89: 2200 | W89: 0 | X89: 2 platforms | Y89: 0.3 | Z89: 1 | AA89: Nicolas Sautron | AB89: https://x.com/SkwalGG | AC89: https://www.instagram.com/skwalgg/ | AK89: 28/03/1992 | AT89: =IFERROR(IF(AND(AN89>0,J89>0),ROUND(J89*1000/(AN89*0.2),0),""),"") | AU89: =IFERROR(IF(AND(AQ89>0,M89>0),ROUND(M89*1000/(AQ89*0.3),0),""),"") | AV89: =IFERROR(IF(AND(AM89>0,O89>0),ROUND(O89*1000/(AM89*0.1),0),""),"") | AW89: =IFERROR(IF(AND(AP89>0,N89>0),ROUND(N89*1000/(AP89*0.25),0),""),"") | AX89: =IFERROR(IF(AND(AO89>0,Q89>0),ROUND(Q89*1000/(AO89*1),0),""),"") | AY89: =IFERROR(ifs(I89="Tier S",0.65,I89="Tier 1",0.55,I89="Tier 2",0.45,I89="Tier 3",0.35,I89="Tier 4",0.25),0.35) -> 0.35 | AZ89: 1 | BA89: 1 | BB89: 1 | BC89: =IFERROR(ROUND(S89*AY89*BA89*BB89*AZ89,0),0) -> 9317 | BD89: =IF(COUNT(AM89,AN89,AO89,AP89,AQ89,AR89,AS89)>0,"estimated","pending") -> pending
B90: =IF($C90="","",COUNTA($C$6:C90)) -> 85 | C90: Boyet | D90: Player | E90: Mobile Legends Bang Bang | F90: Team Falcons MENA | G90: Philippines | H90: 1 | I90: Tier 3 | J90: 8750 | K90: 3000 | L90: =IF(J90="","",ROUND(J90*0.17,0)) -> 1488 | M90: 6000 | N90: 2500 | O90: 1200 | P90: 1200 | Q90: 9000 | R90: 4050 | S90: =IF(J90="","",ROUND(J90*2.2,0)) -> 19250 | T90: 2200 | U90: 1925 | V90: 1155 | W90: 2400 | X90: 1 platform | Y90: 0.3 | Z90: 1 | AA90: Bien Salvador C Chumacera | AC90: https://www.instagram.com/boyetdr_ | AK90: 29/01/2003 | AL90: Jungler | AT90: =IFERROR(IF(AND(AN90>0,J90>0),ROUND(J90*1000/(AN90*0.2),0),""),"") | AU90: =IFERROR(IF(AND(AQ90>0,M90>0),ROUND(M90*1000/(AQ90*0.3),0),""),"") | AV90: =IFERROR(IF(AND(AM90>0,O90>0),ROUND(O90*1000/(AM90*0.1),0),""),"") | AW90: =IFERROR(IF(AND(AP90>0,N90>0),ROUND(N90*1000/(AP90*0.25),0),""),"") | AX90: =IFERROR(IF(AND(AO90>0,Q90>0),ROUND(Q90*1000/(AO90*1),0),""),"") | AY90: =IFERROR(ifs(I90="Tier S",0.65,I90="Tier 1",0.55,I90="Tier 2",0.45,I90="Tier 3",0.35,I90="Tier 4",0.25),0.35) -> 0.35 | AZ90: 1 | BA90: 1 | BB90: 1 | BC90: =IFERROR(ROUND(S90*AY90*BA90*BB90*AZ90,0),0) -> 6738 | BD90: =IF(COUNT(AM90,AN90,AO90,AP90,AQ90,AR90,AS90)>0,"estimated","pending") -> pending
B91: =IF($C91="","",COUNTA($C$6:C91)) -> 86 | C91: Cuffin | D91: Player | E91: Mobile Legends Bang Bang | F91: Team Falcons MENA | G91: Saudi Arabia | H91: 1 | I91: Tier 3 | J91: 5200 | K91: 2200 | L91: =IF(J91="","",ROUND(J91*0.17,0)) -> 884 | M91: 4050 | N91: 1650 | O91: 1050 | P91: 1050 | Q91: 7550 | R91: 3400 | S91: =IF(J91="","",ROUND(J91*2.2,0)) -> 11440 | T91: 1800 | U91: 1550 | V91: 950 | W91: 2400 | X91: 1 platform | Y91: 0.3 | Z91: 1 | AA91: Muath saad alquraini | AC91: https://www.instagram.com/accounts/login/?next=%2Fcuffin_ml&source=omni_redirect | AK91: 19/10/2002 | AL91: Middle | AT91: =IFERROR(IF(AND(AN91>0,J91>0),ROUND(J91*1000/(AN91*0.2),0),""),"") | AU91: =IFERROR(IF(AND(AQ91>0,M91>0),ROUND(M91*1000/(AQ91*0.3),0),""),"") | AV91: =IFERROR(IF(AND(AM91>0,O91>0),ROUND(O91*1000/(AM91*0.1),0),""),"") | AW91: =IFERROR(IF(AND(AP91>0,N91>0),ROUND(N91*1000/(AP91*0.25),0),""),"") | AX91: =IFERROR(IF(AND(AO91>0,Q91>0),ROUND(Q91*1000/(AO91*1),0),""),"") | AY91: =IFERROR(ifs(I91="Tier S",0.65,I91="Tier 1",0.55,I91="Tier 2",0.45,I91="Tier 3",0.35,I91="Tier 4",0.25),0.35) -> 0.35 | AZ91: 1 | BA91: 1 | BB91: 1 | BC91: =IFERROR(ROUND(S91*AY91*BA91*BB91*AZ91,0),0) -> 4004 | BD91: =IF(COUNT(AM91,AN91,AO91,AP91,AQ91,AR91,AS91)>0,"estimated","pending") -> pending
B92: =IF($C92="","",COUNTA($C$6:C92)) -> 87 | C92: Kakashi | D92: Manager | E92: Mobile Legends Bang Bang | F92: Team Falcons MENA | G92: Egypt | H92: 1 | I92: Tier 3 | J92: 5700 | K92: 2400 | L92: =IF(J92="","",ROUND(J92*0.17,0)) -> 969 | M92: 4450 | N92: 1850 | O92: 1150 | P92: 0 | Q92: 8300 | R92: 3700 | S92: =IF(J92="","",ROUND(J92*2.2,0)) -> 12540 | T92: 2000 | U92: 1700 | V92: 1050 | W92: 0 | X92: 1 platform | Y92: 0.3 | Z92: 1 | AA92: AMR WAFED YASSIN | AC92: https://www.instagram.com/cuffin_ml | AK92: 2001-06-08 00:00:00 | AT92: =IFERROR(IF(AND(AN92>0,J92>0),ROUND(J92*1000/(AN92*0.2),0),""),"") | AU92: =IFERROR(IF(AND(AQ92>0,M92>0),ROUND(M92*1000/(AQ92*0.3),0),""),"") | AV92: =IFERROR(IF(AND(AM92>0,O92>0),ROUND(O92*1000/(AM92*0.1),0),""),"") | AW92: =IFERROR(IF(AND(AP92>0,N92>0),ROUND(N92*1000/(AP92*0.25),0),""),"") | AX92: =IFERROR(IF(AND(AO92>0,Q92>0),ROUND(Q92*1000/(AO92*1),0),""),"") | AY92: =IFERROR(ifs(I92="Tier S",0.65,I92="Tier 1",0.55,I92="Tier 2",0.45,I92="Tier 3",0.35,I92="Tier 4",0.25),0.35) -> 0.35 | AZ92: 1 | BA92: 1 | BB92: 1 | BC92: =IFERROR(ROUND(S92*AY92*BA92*BB92*AZ92,0),0) -> 4389 | BD92: =IF(COUNT(AM92,AN92,AO92,AP92,AQ92,AR92,AS92)>0,"estimated","pending") -> pending
B93: =IF($C93="","",COUNTA($C$6:C93)) -> 88 | C93: Kakashi | D93: Manager | E93: Mobile Legends Bang Bang | F93: Falcons Vega MENA | G93: Egypt | H93: 1 | I93: Tier 3 | J93: 0 | K93: 0 | L93: =IF(J93="","",ROUND(J93*0.17,0)) -> 0 | M93: 0 | N93: 0 | O93: 0 | P93: 0 | Q93: 0 | R93: 0 | S93: =IF(J93="","",ROUND(J93*2.2,0)) -> 0 | T93: 0 | U93: 0 | V93: 600 | W93: 0 | X93: 1 platform | Y93: 0.3 | Z93: 1 | AA93: AMR WAFED YASSIN | AC93: https://www.instagram.com/cuffin_ml | AK93: 2001-06-08 00:00:00 | AT93: =IFERROR(IF(AND(AN93>0,J93>0),ROUND(J93*1000/(AN93*0.2),0),""),"") | AU93: =IFERROR(IF(AND(AQ93>0,M93>0),ROUND(M93*1000/(AQ93*0.3),0),""),"") | AV93: =IFERROR(IF(AND(AM93>0,O93>0),ROUND(O93*1000/(AM93*0.1),0),""),"") | AW93: =IFERROR(IF(AND(AP93>0,N93>0),ROUND(N93*1000/(AP93*0.25),0),""),"") | AX93: =IFERROR(IF(AND(AO93>0,Q93>0),ROUND(Q93*1000/(AO93*1),0),""),"") | AY93: =IFERROR(ifs(I93="Tier S",0.65,I93="Tier 1",0.55,I93="Tier 2",0.45,I93="Tier 3",0.35,I93="Tier 4",0.25),0.35) -> 0.35 | AZ93: 1 | BA93: 1 | BB93: 1 | BC93: =IFERROR(ROUND(S93*AY93*BA93*BB93*AZ93,0),0) -> 0 | BD93: =IF(COUNT(AM93,AN93,AO93,AP93,AQ93,AR93,AS93)>0,"estimated","pending") -> pending
B94: =IF($C94="","",COUNTA($C$6:C94)) -> 89 | C94: Saano | D94: Player | E94: Mobile Legends Bang Bang | F94: Team Falcons MENA | G94: Saudi Arabia | H94: 0 | I94: Tier 3 | J94: 8750 | K94: 3000 | L94: =IF(J94="","",ROUND(J94*0.17,0)) -> 1488 | M94: 6000 | N94: 2500 | O94: 1200 | P94: 1200 | Q94: 9000 | R94: 4050 | S94: =IF(J94="","",ROUND(J94*2.2,0)) -> 19250 | T94: 2200 | U94: 1925 | V94: 1155 | W94: 2400 | X94: 0 platforms | Y94: 0.3 | Z94: 1 | AA94: SULAIMAN MUSALLAM ALRASHDI | AK94: 30/06/2004 | AL94: Gold Lane | AT94: =IFERROR(IF(AND(AN94>0,J94>0),ROUND(J94*1000/(AN94*0.2),0),""),"") | AU94: =IFERROR(IF(AND(AQ94>0,M94>0),ROUND(M94*1000/(AQ94*0.3),0),""),"") | AV94: =IFERROR(IF(AND(AM94>0,O94>0),ROUND(O94*1000/(AM94*0.1),0),""),"") | AW94: =IFERROR(IF(AND(AP94>0,N94>0),ROUND(N94*1000/(AP94*0.25),0),""),"") | AX94: =IFERROR(IF(AND(AO94>0,Q94>0),ROUND(Q94*1000/(AO94*1),0),""),"") | AY94: =IFERROR(ifs(I94="Tier S",0.65,I94="Tier 1",0.55,I94="Tier 2",0.45,I94="Tier 3",0.35,I94="Tier 4",0.25),0.35) -> 0.35 | AZ94: 1 | BA94: 1 | BB94: 1 | BC94: =IFERROR(ROUND(S94*AY94*BA94*BB94*AZ94,0),0) -> 6738 | BD94: =IF(COUNT(AM94,AN94,AO94,AP94,AQ94,AR94,AS94)>0,"estimated","pending") -> pending
B95: =IF($C95="","",COUNTA($C$6:C95)) -> 90 | C95: Sanji | D95: Player | E95: Mobile Legends Bang Bang | F95: Team Falcons MENA | G95: Saudi Arabia | H95: 1 | I95: Tier 3 | J95: 5700 | K95: 2400 | L95: =IF(J95="","",ROUND(J95*0.17,0)) -> 969 | M95: 4450 | N95: 1850 | O95: 1150 | P95: 1150 | Q95: 8300 | R95: 3700 | S95: =IF(J95="","",ROUND(J95*2.2,0)) -> 12540 | T95: 2000 | U95: 1700 | V95: 1050 | W95: 2400 | X95: 1 platform | Y95: 0.3 | Z95: 1 | AA95: Ayman Othman Alqarni | AC95: https://www.instagram.com/trolll_ml | AK95: 2003-03-02 00:00:00 | AL95: EXP Lane | AT95: =IFERROR(IF(AND(AN95>0,J95>0),ROUND(J95*1000/(AN95*0.2),0),""),"") | AU95: =IFERROR(IF(AND(AQ95>0,M95>0),ROUND(M95*1000/(AQ95*0.3),0),""),"") | AV95: =IFERROR(IF(AND(AM95>0,O95>0),ROUND(O95*1000/(AM95*0.1),0),""),"") | AW95: =IFERROR(IF(AND(AP95>0,N95>0),ROUND(N95*1000/(AP95*0.25),0),""),"") | AX95: =IFERROR(IF(AND(AO95>0,Q95>0),ROUND(Q95*1000/(AO95*1),0),""),"") | AY95: =IFERROR(ifs(I95="Tier S",0.65,I95="Tier 1",0.55,I95="Tier 2",0.45,I95="Tier 3",0.35,I95="Tier 4",0.25),0.35) -> 0.35 | AZ95: 1 | BA95: 1 | BB95: 1 | BC95: =IFERROR(ROUND(S95*AY95*BA95*BB95*AZ95,0),0) -> 4389 | BD95: =IF(COUNT(AM95,AN95,AO95,AP95,AQ95,AR95,AS95)>0,"estimated","pending") -> pending
B96: =IF($C96="","",COUNTA($C$6:C96)) -> 91 | C96: Tarzaan | D96: Player | E96: Mobile Legends Bang Bang | F96: Team Falcons MENA | G96: Saudi Arabia | H96: 0 | I96: Tier 3 | J96: 5700 | K96: 2400 | L96: =IF(J96="","",ROUND(J96*0.17,0)) -> 969 | M96: 4450 | N96: 1850 | O96: 1150 | P96: 1150 | Q96: 8300 | R96: 3700 | S96: =IF(J96="","",ROUND(J96*2.2,0)) -> 12540 | T96: 2000 | U96: 1700 | V96: 1050 | W96: 2400 | X96: 0 platforms | Y96: 0.3 | Z96: 1 | AA96: Mohammed Ayman Kharabah | AK96: 14/05/2000 | AL96: Jungler | AT96: =IFERROR(IF(AND(AN96>0,J96>0),ROUND(J96*1000/(AN96*0.2),0),""),"") | AU96: =IFERROR(IF(AND(AQ96>0,M96>0),ROUND(M96*1000/(AQ96*0.3),0),""),"") | AV96: =IFERROR(IF(AND(AM96>0,O96>0),ROUND(O96*1000/(AM96*0.1),0),""),"") | AW96: =IFERROR(IF(AND(AP96>0,N96>0),ROUND(N96*1000/(AP96*0.25),0),""),"") | AX96: =IFERROR(IF(AND(AO96>0,Q96>0),ROUND(Q96*1000/(AO96*1),0),""),"") | AY96: =IFERROR(ifs(I96="Tier S",0.65,I96="Tier 1",0.55,I96="Tier 2",0.45,I96="Tier 3",0.35,I96="Tier 4",0.25),0.35) -> 0.35 | AZ96: 1 | BA96: 1 | BB96: 1 | BC96: =IFERROR(ROUND(S96*AY96*BA96*BB96*AZ96,0),0) -> 4389 | BD96: =IF(COUNT(AM96,AN96,AO96,AP96,AQ96,AR96,AS96)>0,"estimated","pending") -> pending
B97: =IF($C97="","",COUNTA($C$6:C97)) -> 92 | C97: Troll | D97: Player | E97: Mobile Legends Bang Bang | F97: Team Falcons MENA | G97: Saudi Arabia | H97: 0 | I97: Tier 3 | J97: 5700 | K97: 2400 | L97: =IF(J97="","",ROUND(J97*0.17,0)) -> 969 | M97: 4450 | N97: 1850 | O97: 1150 | P97: 1150 | Q97: 8300 | R97: 3700 | S97: =IF(J97="","",ROUND(J97*2.2,0)) -> 12540 | T97: 2000 | U97: 1700 | V97: 1050 | W97: 2400 | X97: 0 platforms | Y97: 0.3 | Z97: 1 | AA97: Moayed ayman kharaba | AK97: 31/01/2007 | AL97: Roamer | AT97: =IFERROR(IF(AND(AN97>0,J97>0),ROUND(J97*1000/(AN97*0.2),0),""),"") | AU97: =IFERROR(IF(AND(AQ97>0,M97>0),ROUND(M97*1000/(AQ97*0.3),0),""),"") | AV97: =IFERROR(IF(AND(AM97>0,O97>0),ROUND(O97*1000/(AM97*0.1),0),""),"") | AW97: =IFERROR(IF(AND(AP97>0,N97>0),ROUND(N97*1000/(AP97*0.25),0),""),"") | AX97: =IFERROR(IF(AND(AO97>0,Q97>0),ROUND(Q97*1000/(AO97*1),0),""),"") | AY97: =IFERROR(ifs(I97="Tier S",0.65,I97="Tier 1",0.55,I97="Tier 2",0.45,I97="Tier 3",0.35,I97="Tier 4",0.25),0.35) -> 0.35 | AZ97: 1 | BA97: 1 | BB97: 1 | BC97: =IFERROR(ROUND(S97*AY97*BA97*BB97*AZ97,0),0) -> 4389 | BD97: =IF(COUNT(AM97,AN97,AO97,AP97,AQ97,AR97,AS97)>0,"estimated","pending") -> pending
B98: =IF($C98="","",COUNTA($C$6:C98)) -> 93 | C98: Owgwen | D98: Player | E98: Mobile Legends Bang Bang | F98: Team Falcons PH | G98: Philippines | H98: 4 | I98: Tier 1 | J98: 11000 | K98: 4600 | L98: =IF(J98="","",ROUND(J98*0.17,0)) -> 1870 | M98: 8600 | N98: 3500 | O98: 2200 | P98: 2200 | Q98: 15950 | R98: 7150 | S98: =IF(J98="","",ROUND(J98*2.2,0)) -> 24200 | T98: 3850 | U98: 3300 | V98: 2000 | W98: 2400 | X98: 4 platforms | Y98: 0.3 | Z98: 1 | AA98: Rowgien Stimpson Unigo | AB98: https://twitter.com/Ogiiiieeen | AC98: https://www.instagram.com/flcn.owgwen | AF98: https://www.tiktok.com/@ogiiiieeen | AH98: https://facebook.com/Ogiiiieeen | AK98: 25/04/2001 | AL98: Roamer | AT98: =IFERROR(IF(AND(AN98>0,J98>0),ROUND(J98*1000/(AN98*0.2),0),""),"") | AU98: =IFERROR(IF(AND(AQ98>0,M98>0),ROUND(M98*1000/(AQ98*0.3),0),""),"") | AV98: =IFERROR(IF(AND(AM98>0,O98>0),ROUND(O98*1000/(AM98*0.1),0),""),"") | AW98: =IFERROR(IF(AND(AP98>0,N98>0),ROUND(N98*1000/(AP98*0.25),0),""),"") | AX98: =IFERROR(IF(AND(AO98>0,Q98>0),ROUND(Q98*1000/(AO98*1),0),""),"") | AY98: =IFERROR(ifs(I98="Tier S",0.65,I98="Tier 1",0.55,I98="Tier 2",0.45,I98="Tier 3",0.35,I98="Tier 4",0.25),0.35) -> 0.35 | AZ98: 1 | BA98: 1 | BB98: 1 | BC98: =IFERROR(ROUND(S98*AY98*BA98*BB98*AZ98,0),0) -> 8470 | BD98: =IF(COUNT(AM98,AN98,AO98,AP98,AQ98,AR98,AS98)>0,"estimated","pending") -> pending
B99: =IF($C99="","",COUNTA($C$6:C99)) -> 94 | C99: Super Marco | D99: Player | E99: Mobile Legends Bang Bang | F99: Team Falcons PH | G99: Philippines | H99: 3 | I99: Tier 2 | J99: 18000 | K99: 7550 | L99: =IF(J99="","",ROUND(J99*0.17,0)) -> 3060 | M99: 14050 | N99: 5750 | O99: 3600 | P99: 3600 | Q99: 26100 | R99: 11700 | S99: =IF(J99="","",ROUND(J99*2.2,0)) -> 39600 | T99: 6300 | U99: 5400 | V99: 3250 | W99: 2400 | X99: 3 platforms | Y99: 0.3 | Z99: 1 | AA99: Marco Stephen Requitiano | AC99: https://www.tiktok.com/@flcnsupermarco | AF99: https://www.tiktok.com/@flcnsupermarco | AH99: https://www.facebook.com/FLCNSupermarco | AK99: 2000-06-10 00:00:00 | AL99: Gold Lane | AT99: =IFERROR(IF(AND(AN99>0,J99>0),ROUND(J99*1000/(AN99*0.2),0),""),"") | AU99: =IFERROR(IF(AND(AQ99>0,M99>0),ROUND(M99*1000/(AQ99*0.3),0),""),"") | AV99: =IFERROR(IF(AND(AM99>0,O99>0),ROUND(O99*1000/(AM99*0.1),0),""),"") | AW99: =IFERROR(IF(AND(AP99>0,N99>0),ROUND(N99*1000/(AP99*0.25),0),""),"") | AX99: =IFERROR(IF(AND(AO99>0,Q99>0),ROUND(Q99*1000/(AO99*1),0),""),"") | AY99: =IFERROR(ifs(I99="Tier S",0.65,I99="Tier 1",0.55,I99="Tier 2",0.45,I99="Tier 3",0.35,I99="Tier 4",0.25),0.35) -> 0.35 | AZ99: 1 | BA99: 1 | BB99: 1 | BC99: =IFERROR(ROUND(S99*AY99*BA99*BB99*AZ99,0),0) -> 13860 | BD99: =IF(COUNT(AM99,AN99,AO99,AP99,AQ99,AR99,AS99)>0,"estimated","pending") -> pending
B100: =IF($C100="","",COUNTA($C$6:C100)) -> 95 | C100: Hadji | D100: Player | E100: Mobile Legends Bang Bang | F100: Team Falcons PH | G100: Philippines | H100: 3 | I100: Tier 2 | J100: 11000 | K100: 4600 | L100: =IF(J100="","",ROUND(J100*0.17,0)) -> 1870 | M100: 8600 | N100: 3500 | O100: 2200 | P100: 2200 | Q100: 15950 | R100: 7150 | S100: =IF(J100="","",ROUND(J100*2.2,0)) -> 24200 | T100: 3850 | U100: 3300 | V100: 2000 | W100: 2400 | X100: 3 platforms | Y100: 0.3 | Z100: 1 | AA100: Salic Imam | AC100: https://www.instagram.com/hadjizy | AF100: https://www.tiktok.com/@hadjizy_ | AH100: https://facebook.com/Hadjizyyyyy | AK100: 23/04/2003 | AL100: Middle | AT100: =IFERROR(IF(AND(AN100>0,J100>0),ROUND(J100*1000/(AN100*0.2),0),""),"") | AU100: =IFERROR(IF(AND(AQ100>0,M100>0),ROUND(M100*1000/(AQ100*0.3),0),""),"") | AV100: =IFERROR(IF(AND(AM100>0,O100>0),ROUND(O100*1000/(AM100*0.1),0),""),"") | AW100: =IFERROR(IF(AND(AP100>0,N100>0),ROUND(N100*1000/(AP100*0.25),0),""),"") | AX100: =IFERROR(IF(AND(AO100>0,Q100>0),ROUND(Q100*1000/(AO100*1),0),""),"") | AY100: =IFERROR(ifs(I100="Tier S",0.65,I100="Tier 1",0.55,I100="Tier 2",0.45,I100="Tier 3",0.35,I100="Tier 4",0.25),0.35) -> 0.35 | AZ100: 1 | BA100: 1 | BB100: 1 | BC100: =IFERROR(ROUND(S100*AY100*BA100*BB100*AZ100,0),0) -> 8470 | BD100: =IF(COUNT(AM100,AN100,AO100,AP100,AQ100,AR100,AS100)>0,"estimated","pending") -> pending
B101: =IF($C101="","",COUNTA($C$6:C101)) -> 96 | C101: Moody | D101: Assistant Coach | E101: Mobile Legends Bang Bang | F101: Team Falcons PH | G101: Philippines | H101: 3 | I101: Tier 2 | J101: 0 | K101: 0 | L101: =IF(J101="","",ROUND(J101*0.17,0)) -> 0 | M101: 0 | N101: 0 | O101: 0 | P101: 0 | Q101: 0 | R101: 0 | S101: =IF(J101="","",ROUND(J101*2.2,0)) -> 0 | T101: 0 | U101: 0 | V101: 1200 | W101: 0 | X101: 3 platforms | Y101: 0.3 | Z101: 1 | AA101: Mohammad Samal | AC101: https://www.instagram.com/moodysamal | AF101: https://www.tiktok.com/@flcn.moody | AH101: https://www.facebook.com/liquidcoachmoody/ | AK101: 26/08/1996 | AT101: =IFERROR(IF(AND(AN101>0,J101>0),ROUND(J101*1000/(AN101*0.2),0),""),"") | AU101: =IFERROR(IF(AND(AQ101>0,M101>0),ROUND(M101*1000/(AQ101*0.3),0),""),"") | AV101: =IFERROR(IF(AND(AM101>0,O101>0),ROUND(O101*1000/(AM101*0.1),0),""),"") | AW101: =IFERROR(IF(AND(AP101>0,N101>0),ROUND(N101*1000/(AP101*0.25),0),""),"") | AX101: =IFERROR(IF(AND(AO101>0,Q101>0),ROUND(Q101*1000/(AO101*1),0),""),"") | AY101: =IFERROR(ifs(I101="Tier S",0.65,I101="Tier 1",0.55,I101="Tier 2",0.45,I101="Tier 3",0.35,I101="Tier 4",0.25),0.35) -> 0.35 | AZ101: 1 | BA101: 1 | BB101: 1 | BC101: =IFERROR(ROUND(S101*AY101*BA101*BB101*AZ101,0),0) -> 0 | BD101: =IF(COUNT(AM101,AN101,AO101,AP101,AQ101,AR101,AS101)>0,"estimated","pending") -> pending
...

Sheet 30_Creator_Rate_Card
B2: 30 — CREATOR RATE CARD (v1.0)
B3: Ceiling rates anchored to Falcons creator cap. Opening offer = Ceiling × Opening Factor. Creator lane shares the 40_Adjustment_Matrix governance spine.
B4: Identity & Tier | F4: Ceiling Platform Rates (SAR) | U4: Ref / Ops | Z4: Followers | AF4: Authority Floor & Confidence
B5: # | C5: Creator | D5: Weighted Score | E5: Tier | F5: X Post / Quote | G5: X Repost | H5: IG Post | I5: IG Story | J5: IG Reels | K5: YT Full Video | L5: YT 1–2min Pre-roll | M5: YT Shorts | N5: Snapchat | O5: TikTok Our-side | P5: TikTok Client Vids | Q5: Event + Snap | R5: Twitch / Kick Live | S5: Kick IRL | T5: Telegram | U5: Legacy 1M Usage Rights (ref) | V5: Notes | W5: Opening Factor | X5: Falcons Commission % | Y5: Markup % (on Creator Cost) | Z5: X Followers | AA5: IG Followers | AB5: Twitch Followers | AC5: YT Subs | AD5: TikTok Followers | AE5: Kick Followers | AF5: Floor Share % | AG5: Authority Factor | AH5: Default Seasonality | AI5: Default Language | AJ5: Authority Floor Baseline (SAR) | AK5: Measurement Confidence | AL5: Tier Review Flag
B6: =IF($C6="","",COUNTA($C$6:C6)) -> 1 | C6: BanderitaX | D6: 75659 | E6: Tier 1 | F6: 37500 | G6: 18750 | H6: 60000 | I6: 41250 | J6: 56250 | K6: 165000 | L6: 82500 | M6: 41250 | N6: 56250 | O6: 56250 | P6: 37500 | Q6: 120000 | R6: 0 | S6: 0 | T6: 0 | U6: 300000 | V6: Legacy rights ceiling preserved for reference; quote builder uses structured rights bundles instead. | W6: 0.75 | X6: 0.15 | Y6: 0.2 | AF6: =IFERROR(ifs(E6="Tier 1",0.55,E6="Tier 2",0.45,E6="Tier 3",0.35,E6="Tier 4",0.25),0.35) -> 0.35 | AG6: 1 | AH6: 1 | AI6: 1 | AJ6: =IFERROR(ROUND(Q6*AF6*AH6*AI6*AG6,0),0) -> 42000 | AK6: =IF(COUNT(Z6,AA6,AB6,AC6,AD6,AE6)>0,"estimated","pending") -> pending
B7: =IF($C7="","",COUNTA($C$6:C7)) -> 2 | C7: oPiiLz | D7: 39210 | E7: Tier 2 | F7: 11250 | G7: 5625 | H7: 22500 | I7: 16875 | J7: 26250 | K7: 90000 | L7: 45000 | M7: 26250 | N7: 26250 | O7: 26250 | P7: 15000 | Q7: 75000 | R7: 0 | S7: 0 | T7: 0 | U7: 75000 | V7: Legacy rights ceiling preserved for reference; quote builder uses structured rights bundles instead. | W7: 0.75 | X7: 0.15 | Y7: 0.2 | AF7: =IFERROR(ifs(E7="Tier 1",0.55,E7="Tier 2",0.45,E7="Tier 3",0.35,E7="Tier 4",0.25),0.35) -> 0.35 | AG7: 1 | AH7: 1 | AI7: 1 | AJ7: =IFERROR(ROUND(Q7*AF7*AH7*AI7*AG7,0),0) -> 26250 | AK7: =IF(COUNT(Z7,AA7,AB7,AC7,AD7,AE7)>0,"estimated","pending") -> pending
B8: =IF($C8="","",COUNTA($C$6:C8)) -> 3 | C8: Msdossary7 | D8: 27400 | E8: Tier 2 | F8: 10000 | G8: 0 | H8: 8000 | I8: 7000 | J8: 0 | K8: 0 | L8: 0 | M8: 0 | N8: 25000 | O8: 0 | P8: 0 | Q8: 60000 | R8: 0 | S8: 0 | T8: 0 | U8: 75000 | V8: Legacy rights ceiling preserved for reference; quote builder uses structured rights bundles instead. | W8: 0.75 | X8: 0.15 | Y8: 0.2 | AF8: =IFERROR(ifs(E8="Tier 1",0.55,E8="Tier 2",0.45,E8="Tier 3",0.35,E8="Tier 4",0.25),0.35) -> 0.35 | AG8: 1 | AH8: 1 | AI8: 1 | AJ8: =IFERROR(ROUND(Q8*AF8*AH8*AI8*AG8,0),0) -> 21000 | AK8: =IF(COUNT(Z8,AA8,AB8,AC8,AD8,AE8)>0,"estimated","pending") -> pending
B9: =IF($C9="","",COUNTA($C$6:C9)) -> 4 | C9: Aziz | D9: 18657 | E9: Tier 3 | F9: 7500 | G9: 3750 | H9: 7500 | I9: 5625 | J9: 13125 | K9: 45000 | L9: 20625 | M9: 11250 | N9: 16875 | O9: 13125 | P9: 5625 | Q9: 39375 | R9: 13125 | S9: 0 | T9: 0 | U9: 45000 | V9: Legacy rights ceiling preserved for reference; quote builder uses structured rights bundles instead. | W9: 0.75 | X9: 0.15 | Y9: 0.2 | AF9: =IFERROR(ifs(E9="Tier 1",0.55,E9="Tier 2",0.45,E9="Tier 3",0.35,E9="Tier 4",0.25),0.35) -> 0.35 | AG9: 1 | AH9: 1 | AI9: 1 | AJ9: =IFERROR(ROUND(Q9*AF9*AH9*AI9*AG9,0),0) -> 13781 | AK9: =IF(COUNT(Z9,AA9,AB9,AC9,AD9,AE9)>0,"estimated","pending") -> pending
B10: =IF($C10="","",COUNTA($C$6:C10)) -> 5 | C10: Bo3omar22 | D10: 34084 | E10: Tier 2 | F10: 7500 | G10: 3750 | H10: 16875 | I10: 13125 | J10: 20625 | K10: 120000 | L10: 30000 | M10: 15000 | N10: 20000 | O10: 30000 | P10: 9375 | Q10: 45000 | R10: 22500 | S10: 0 | T10: 0 | U10: 48750 | V10: Legacy rights ceiling preserved for reference; quote builder uses structured rights bundles instead. | W10: 0.75 | X10: 0.15 | Y10: 0.2 | AF10: =IFERROR(ifs(E10="Tier 1",0.55,E10="Tier 2",0.45,E10="Tier 3",0.35,E10="Tier 4",0.25),0.35) -> 0.35 | AG10: 1 | AH10: 1 | AI10: 1 | AJ10: =IFERROR(ROUND(Q10*AF10*AH10*AI10*AG10,0),0) -> 15750 | AK10: =IF(COUNT(Z10,AA10,AB10,AC10,AD10,AE10)>0,"estimated","pending") -> pending
B11: =IF($C11="","",COUNTA($C$6:C11)) -> 6 | C11: Abu abeer | D11: 20365 | E11: Tier 2 | F11: 7500 | G11: 3750 | H11: 11250 | I11: 5625 | J11: 13125 | K11: 45000 | L11: 24375 | M11: 11250 | N11: 16875 | O11: 13125 | P11: 5625 | Q11: 39375 | R11: 24375 | S11: 0 | T11: 0 | U11: 48750 | V11: Legacy rights ceiling preserved for reference; quote builder uses structured rights bundles instead. | W11: 0.75 | X11: 0.15 | Y11: 0.2 | AF11: =IFERROR(ifs(E11="Tier 1",0.55,E11="Tier 2",0.45,E11="Tier 3",0.35,E11="Tier 4",0.25),0.35) -> 0.35 | AG11: 1 | AH11: 1 | AI11: 1 | AJ11: =IFERROR(ROUND(Q11*AF11*AH11*AI11*AG11,0),0) -> 13781 | AK11: =IF(COUNT(Z11,AA11,AB11,AC11,AD11,AE11)>0,"estimated","pending") -> pending
B12: =IF($C12="","",COUNTA($C$6:C12)) -> 7 | C12: LLE | D12: 27149 | E12: Tier 2 | F12: 7500 | G12: 3750 | H12: 15000 | I12: 10000 | J12: 28000 | K12: 45000 | L12: 30000 | M12: 28000 | N12: 20000 | O12: 28000 | P12: 25000 | Q12: 36000 | R12: 30000 | S12: 0 | T12: 0 | U12: 50000 | V12: Legacy rights ceiling preserved for reference; quote builder uses structured rights bundles instead. | W12: 0.75 | X12: 0.15 | Y12: 0.2 | AF12: =IFERROR(ifs(E12="Tier 1",0.55,E12="Tier 2",0.45,E12="Tier 3",0.35,E12="Tier 4",0.25),0.35) -> 0.35 | AG12: 1 | AH12: 1 | AI12: 1 | AJ12: =IFERROR(ROUND(Q12*AF12*AH12*AI12*AG12,0),0) -> 12600 | AK12: =IF(COUNT(Z12,AA12,AB12,AC12,AD12,AE12)>0,"estimated","pending") -> pending
B13: =IF($C13="","",COUNTA($C$6:C13)) -> 8 | C13: Oden | D13: 16467 | E13: Tier 3 | F13: 7500 | G13: 3750 | H13: 9375 | I13: 5625 | J13: 7500 | K13: 37500 | L13: 18750 | M13: 11250 | N13: 15000 | O13: 15000 | P13: 5625 | Q13: 31875 | R13: 13125 | S13: 0 | T13: 0 | U13: 48750 | V13: Legacy rights ceiling preserved for reference; quote builder uses structured rights bundles instead. | W13: 0.75 | X13: 0.15 | Y13: 0.2 | AF13: =IFERROR(ifs(E13="Tier 1",0.55,E13="Tier 2",0.45,E13="Tier 3",0.35,E13="Tier 4",0.25),0.35) -> 0.35 | AG13: 1 | AH13: 1 | AI13: 1 | AJ13: =IFERROR(ROUND(Q13*AF13*AH13*AI13*AG13,0),0) -> 11156 | AK13: =IF(COUNT(Z13,AA13,AB13,AC13,AD13,AE13)>0,"estimated","pending") -> pending
B14: =IF($C14="","",COUNTA($C$6:C14)) -> 9 | C14: xSMA333 | D14: 16741 | E14: Tier 3 | F14: 9375 | G14: 5625 | H14: 10500 | I14: 7500 | J14: 9375 | K14: 37500 | L14: 18750 | M14: 9375 | N14: 13125 | O14: 9375 | P14: 7500 | Q14: 39375 | R14: 9375 | S14: 0 | T14: 0 | U14: 48750 | V14: Legacy rights ceiling preserved for reference; quote builder uses structured rights bundles instead. | W14: 0.75 | X14: 0.15 | Y14: 0.2 | AF14: =IFERROR(ifs(E14="Tier 1",0.55,E14="Tier 2",0.45,E14="Tier 3",0.35,E14="Tier 4",0.25),0.35) -> 0.35 | AG14: 1 | AH14: 1 | AI14: 1 | AJ14: =IFERROR(ROUND(Q14*AF14*AH14*AI14*AG14,0),0) -> 13781 | AK14: =IF(COUNT(Z14,AA14,AB14,AC14,AD14,AE14)>0,"estimated","pending") -> pending
B15: =IF($C15="","",COUNTA($C$6:C15)) -> 10 | C15: 3ADEL | D15: 21386 | E15: Tier 2 | F15: 7500 | G15: 5625 | H15: 15000 | I15: 11250 | J15: 18750 | K15: 48750 | L15: 24375 | M15: 16875 | N15: 16875 | O15: 20625 | P15: 11250 | Q15: 31875 | R15: 11250 | S15: 0 | T15: 0 | U15: 48750 | V15: Legacy rights ceiling preserved for reference; quote builder uses structured rights bundles instead. | W15: 0.75 | X15: 0.15 | Y15: 0.2 | AF15: =IFERROR(ifs(E15="Tier 1",0.55,E15="Tier 2",0.45,E15="Tier 3",0.35,E15="Tier 4",0.25),0.35) -> 0.35 | AG15: 1 | AH15: 1 | AI15: 1 | AJ15: =IFERROR(ROUND(Q15*AF15*AH15*AI15*AG15,0),0) -> 11156 | AK15: =IF(COUNT(Z15,AA15,AB15,AC15,AD15,AE15)>0,"estimated","pending") -> pending
B16: =IF($C16="","",COUNTA($C$6:C16)) -> 11 | C16: RAED | D16: 20402 | E16: Tier 2 | F16: 11250 | G16: 5625 | H16: 15000 | I16: 9375 | J16: 9375 | K16: 52500 | L16: 26250 | M16: 13125 | N16: 15000 | O16: 13125 | P16: 7500 | Q16: 39375 | R16: 9375 | S16: 0 | T16: 0 | U16: 48750 | V16: Legacy rights ceiling preserved for reference; quote builder uses structured rights bundles instead. | W16: 0.75 | X16: 0.15 | Y16: 0.2 | AF16: =IFERROR(ifs(E16="Tier 1",0.55,E16="Tier 2",0.45,E16="Tier 3",0.35,E16="Tier 4",0.25),0.35) -> 0.35 | AG16: 1 | AH16: 1 | AI16: 1 | AJ16: =IFERROR(ROUND(Q16*AF16*AH16*AI16*AG16,0),0) -> 13781 | AK16: =IF(COUNT(Z16,AA16,AB16,AC16,AD16,AE16)>0,"estimated","pending") -> pending
B17: =IF($C17="","",COUNTA($C$6:C17)) -> 12 | C17: Falcons | D17: 60974 | E17: Tier 1 | F17: 18750 | G17: 9375 | H17: 15000 | I17: 9375 | J17: 56250 | K17: 165000 | L17: 82500 | M17: 50625 | N17: 0 | O17: 56250 | P17: 37500 | Q17: 0 | R17: 0 | S17: 0 | T17: 11250 | U17: 0 | V17: Legacy rights ceiling preserved for reference; quote builder uses structured rights bundles instead. | W17: 0.75 | X17: 0.15 | Y17: 0.2 | AF17: =IFERROR(ifs(E17="Tier 1",0.55,E17="Tier 2",0.45,E17="Tier 3",0.35,E17="Tier 4",0.25),0.35) -> 0.35 | AG17: 1 | AH17: 1 | AI17: 1 | AJ17: =IFERROR(ROUND(Q17*AF17*AH17*AI17*AG17,0),0) -> 0 | AK17: =IF(COUNT(Z17,AA17,AB17,AC17,AD17,AE17)>0,"estimated","pending") -> pending
... B22: =IF($C22="","",COUNTA($C$6:C22)) -> 17 | C22: 9leeh | D22: 12733 | E22: Tier 3 | F22: 3750 | G22: 2625 | H22: 5625 | I22: 4125 | J22: 9375 | K22: 30000 | L22: 13125 | M22: 7500 | N22: 11250 | O22: 9375 | P22: 3750 | Q22: 18750 | R22: 13125 | S22: 18750 | T22: 0 | U22: 18750 | V22: Legacy rights ceiling preserved for reference; quote builder uses structured rights bundles instead. | W22: 0.75 | X22: 0.15 | Y22: 0.2 | AF22: =IFERROR(ifs(E22="Tier 1",0.55,E22="Tier 2",0.45,E22="Tier 3",0.35,E22="Tier 4",0.25),0.35) -> 0.35 | AG22: 1 | AH22: 1 | AI22: 1 | AJ22: =IFERROR(ROUND(Q22*AF22*AH22*AI22*AG22,0),0) -> 6563 | AK22: =IF(COUNT(Z22,AA22,AB22,AC22,AD22,AE22)>0,"estimated","pending") -> pending
B25: Team Falcons · Unified Talent Pricing OS v1.2 · Confidential

Sheet 40_Adjustment_Matrix
B2: 40 — ADJUSTMENT MATRIX · 9-AXIS COMMERCIAL DECISION SYSTEM
B3: A serious commercial engine — not a decorative multiplier sheet. Confidence gates premiums. Authority floor protects dignity. Rights are additive and separated from organic.
B5: SECTION 1 — THE 9 AXES
B6: Axis | C6: Name | D6: Role | E6: Source Lookup | F6: Commercial Logic
B7: A | C7: Engagement | D7: Highest-weight real value driver | E7: LKP_Engagement | F7: Interactions ÷ followers. Rewards real audience reaction over raw size.
B8: B | C8: Audience Quality | D8: Fit with target persona | E8: LKP_Audience | F8: Esports/Gaming/MENA alignment. Reduces premium for off-target audiences.
B9: C | C9: Campaign Objective | D9: Awareness / Conversion / Trust | E9: LKP_Objective | F9: ObjectiveWeight scales how aggressively Authority compounds (ObjWeight × AuthMult).
B10: D | C10: Authority / Status | D10: Player prestige or creator clout | E10: LKP_Authority | F10: AuthorityFactor = 1 + ObjWeight × (AuthMult − 1). Trust campaigns scale authority most.
B11: E | C11: Language / Region | D11: Linguistic & cultural fit | E11: LKP_Language | F11: Dialect & bilingual capability earn premium in MENA campaigns.
B12: F | C12: Seasonality | D12: Campaign timing vs calendar peaks | E12: LKP_Season | F12: EWC / Worlds / Ramadan spikes. Off-season discounts.
B13: G | C13: Measurement Confidence | D13: ENFORCEMENT GATE (new) | E13: LKP_Confidence | F13: Low confidence caps how high Eng / Authority / Season can go. See §3.
B14: H | C14: Authority Floor | D14: Dignity floor below which we don't drop | E14: LKP_Floor | F14: Floor = IRL × FloorShare × Season × Lang × AuthorityFactor. Max(social, floor).
B15: I | C15: Rights & Add-Ons | D15: Additive uplift AFTER organic | E15: 41_Add_On_Rights | F15: Organic fee is computed first, then (1 + AddOnUplift%) is applied.
B17: SECTION 2 — FORMULA SPINE
B18: SocialPrice | C18: SocialPrice = BaseFee × Eng × Aud × Season × ContentType × Lang × AuthorityFactor
B19: AuthorityFactor | C19: AuthorityFactor = 1 + ObjWeight × (AuthMult − 1)
B20: AuthorityFloor | C20: AuthorityFloor = IRL × FloorShare × Season × Lang × AuthorityFactor
B21: PreAddOn | C21: PreAddOn = MAX(SocialPrice, AuthorityFloor)
B22: FinalOrganic | C22: FinalOrganic = PreAddOn × ConfidenceCap
B23: Final | C23: Final = FinalOrganic × (1 + AddOnUplift%)
B25: SECTION 3 — CONFIDENCE GATE (HARD-CAPS PREMIUMS)
B26: Confidence | C26: Eng Cap | D26: Authority Cap | E26: Season Cap | F26: Final × ConfCap
B27: exact | C27: — | D27: — | E27: — | F27: 1
B28: rounded | C28: — | D28: — | E28: — | F28: 1
B29: estimated | C29: 1.2 | D29: 1.3 | E29: 1.25 | F29: 0.9
B30: pending | C30: 1 | D30: 1 | E30: 1 | F30: 0.75
B32: SECTION 4 — WORKED EXAMPLE (governance reference — not a calculator)
B33: The Matrix tab is documentation. For live what-if testing, use 42_Preview (the Benchmark Calculator).
B35: Step | C35: Input / Formula | D35: Example Value | E35: Notes
B36: Talent | C36: Cellium — Tier 2 player | D36: — | E36: Rate card lookup
B37: Base Fee | C37: 20_Player_Rate_Card → IG Reel | D37: 11,250 | E37: Pulled from column J
B38: IRL Anchor | C38: 20_Player_Rate_Card → IRL col | D38: 24,750 | E38: Drives floor
B39: Engagement | C39: 4–6% Baseline | D39: 1.00x | E39: Below gated cap
B40: Audience Fit | C40: Core Gaming | D40: 1.20x
B41: Objective | C41: Conversion | D41: 0.40 | E41: Weight
B42: Authority | C42: Proven / Established | D42: 1.15x
B43: Language | C43: Bilingual | D43: 1.15x
B44: Seasonality | C44: Regional Major | D44: 1.25x
B45: Content Type | C45: Integrated (Player-led) | D45: 1.00x
B46: Confidence | C46: estimated → gated | D46: cap 0.9 | E46: Gates premiums
B47: AuthFactor | C47: 1 + 0.40 × (1.15 − 1) | D47: 1.06
B48: Social Price | C48: Base × Eng × Aud × Seas × CType × Lang × AuthFactor | D48: 20,571
B49: Authority Floor | C49: IRL × FloorShare × Seas × Lang × AuthFactor | D49: 18,856
B50: Pre-AddOn | C50: MAX(Social, Floor) | D50: 20,571
B51: Final Organic | C51: Pre-AddOn × 0.9 (conf cap) | D51: 18,514
B52: Add-On Uplift | C52: 40% (Whitelisting 60d) | D52: +40% | E52: From 41_Add_On_Rights
B53: FINAL (w/ rights) | C53: FinalOrganic × (1 + 0.40) | D53: 25,920 | E53: Matches 42_Preview
B56: See 42_Preview for a live interactive version of this example — switch talent, platform, axes and add-ons; numbers recalc instantly.
B61: Team Falcons · Unified Talent Pricing OS v1.2 · Confidential

Sheet 41_Add_On_Rights
B2: 41 — ADD-ON RIGHTS & USAGE PACKAGES
B3: All rights, exclusivity, and usage packages live here — separate from the organic fee. Each row is an additive uplift % applied AFTER the organic price is finalized.
B5: RIGHTS & ADD-ONS CATALOGUE
B6: Package | C6: Uplift % | D6: Territory | E6: Duration | F6: Notes / Scope
B7: Organic Social Only (baseline) | C7: 0 | D7: — | E7: — | F7: No usage rights beyond talent's own socials. Default.
B8: Whitelisting / Dark Posts — 30d | C8: 0.25 | D8: KSA/MENA | E8: 30 days | F8: Brand can boost on talent's handle for 30d.
B9: Whitelisting / Dark Posts — 60d | C9: 0.4 | D9: KSA/MENA | E9: 60 days | F9: Whitelisting extended to 60d.
B10: Whitelisting / Dark Posts — 90d | C10: 0.6 | D10: KSA/MENA | E10: 90 days | F10: Whitelisting extended to 90d.
B11: Paid Media Usage — 1M Views | C11: 0.45 | D11: Regional | E11: 90 days | F11: Content used in paid campaigns up to 1M impressions.
B12: Paid Media Usage — 5M Views | C12: 0.9 | D12: Regional | E12: 90 days | F12: Up to 5M impressions. Scales with reach commitment.
B13: Organic Rights — 6 months | C13: 0.3 | D13: Global | E13: 6 months | F13: Brand retains rights on owned + earned channels.
B14: Organic Rights — 12 months | C14: 0.55 | D14: Global | E14: 12 months | F14: Brand retains rights on owned + earned channels.
B15: Exclusivity — Category (90d) | C15: 0.35 | D15: — | E15: 90 days | F15: Player cannot promote competitors in the same category.
B16: Exclusivity — Category (6 months) | C16: 0.65 | D16: — | E16: 6 months | F16: Requires legal approval per 01_Settings.
B17: Exclusivity — Category (12 months) | C17: 1 | D17: — | E17: 12 months | F17: Premium; requires legal approval + Falcons sign-off.
B18: Exclusivity — Brand-wide (6 months) | C18: 1.5 | D18: — | E18: 6 months | F18: Player cannot promote ANY brand outside the client. Requires legal.
... B24: NDA / Confidentiality | C24: 0.05 | D24: — | E24: — | F24: Campaign under NDA until launch.
B26: QUICK STACKS — TYPICAL COMMERCIAL BUNDLES
B27: Bundle | C27: Uplift % | D27: Components | E27: Territory | F27: Notes
B28: Standard Social-Only | C28: 0 | D28: Organic only | E28: — | F28: Floor bundle.
B29: Social + 30d WL | C29: 0.25 | D29: Organic + Whitelisting 30d | E29: KSA/MENA | F29: Most common.
B30: Paid-Media Campaign (1M) | C30: 0.7 | D30: WL 30d + Paid Media 1M | E30: Regional | F30: Typical paid social launch.
B31: Category Exclusive + Paid | C31: 1.25 | D31: WL 90d + Paid 5M + Exclusivity 90d | E31: Regional | F31: Heavyweight campaign.
B32: Full TV Commercial | C32: 1.85 | D32: WL 90d + Ad VO + Shoot + Exclusivity 6m | E32: Regional | F32: Premium brand campaign.
B35: Team Falcons · Unified Talent Pricing OS v1.2 · Confidential

Sheet 42_Preview
B2: 42 — BENCHMARK CALCULATOR · LIVE PLAYER / CREATOR SCENARIO
B3: Pick Player or Creator, a platform, adjust axes, toggle add-ons in §5 — all numbers recalc live. This is the what-if tab before the formal quote.
B5: SECTION 1 — TALENT SELECTION
B6: Input | C6: Value | D6: Pulled | E6: Source / Notes
B7: Talent Type | C7: Player | E7: Toggle the matrix between Player (20_…) and Creator (30_…) rate cards
B8: Talent Name | C8: Cellium | E8: Dropdown — populated from the selected rate card
B9: Role / Segment | C9: =IF($C$7="Player",IFERROR(VLOOKUP($C$8,'20_Player_Rate_Card'!$C$6:$I$500,2,FALSE()),"—"),"Creator") -> Player | E9: Players → role; Creators → Creator
B10: Game / Category | C10: =IF($C$7="Player",IFERROR(VLOOKUP($C$8,'20_Player_Rate_Card'!$C$6:$I$500,3,FALSE()),"—"),"Gaming / Lifestyle") -> Call of Duty Black Ops 7 | E10: Players → game; Creators → Gaming / Lifestyle
B11: Team / Handle | C11: =IF($C$7="Player",IFERROR(VLOOKUP($C$8,'20_Player_Rate_Card'!$C$6:$I$500,4,FALSE()),"—"),"—") -> Riyadh Falcons | E11: Players → team; Creators → n/a
B12: Tier | C12: =IF($C$7="Player",IFERROR(VLOOKUP($C$8,'20_Player_Rate_Card'!$C$6:$I$500,7,FALSE()),"—"),IFERROR(VLOOKUP($C$8,'30_Creator_Rate_Card'!$C$6:$E$500,3,FALSE()),"—")) -> Tier 2 | E12: Both cards expose Tier
B13: Platform / Deliverable | C13: IG Reel | D13: =IF($C$7="Player",IFERROR(INDEX('20_Player_Rate_Card'!$J$6:$R$500,MATCH($C$8,'20_Player_Rate_Card'!$C$6:$C$500,0),MATCH($C$13&"*",'20_Player_Rate_Card'!$J$5:$R$5,0)),0),IFERROR(INDEX('30_Creator_Rate_Card'!$F$6:$T$500,MATCH($C$8,'30_Creator_Rate_Card'!$C$6:$C$500,0),MATCH($C$13&"*",'30_Creator_Rate_Card'!$F$5:$T$5,0)),0)) -> 11250 | E13: Auto-pulls from the correct rate card based on Talent Type
B14: Base Fee (SAR) — override | C14: =D13 -> 11250 | D14: =D13 -> 11250 | E14: Defaults to rate-card rate; overwrite to test scenarios
B15: IRL / Appearance Anchor (SAR) | C15: =IF($C$7="Player",IFERROR(VLOOKUP($C$8,'20_Player_Rate_Card'!$C$6:$S$500,17,FALSE()),0),0) -> 24750 | E15: Drives Authority Floor (Players only — Creators use zero floor by default)
B16: SECTION 2 — CAMPAIGN AXES
B17: Axis | C17: Value (editable) | D17: Resolved Multiplier | E17: Source
B18: Engagement Level | C18: 4–6% — Baseline | D18: =IFERROR(VLOOKUP($C18,'02_Lookups'!$B:$C,2,FALSE()),1) -> 1 | E18: ER band from 02_Lookups
B19: Audience Quality / Fit | C19: Core Gaming | D19: =IFERROR(VLOOKUP($C19,'02_Lookups'!$B:$C,2,FALSE()),1) -> 1.2 | E19: Fit multiplier
B20: Campaign Objective | C20: Conversion | D20: =IFERROR(VLOOKUP($C20,'02_Lookups'!$B:$C,2,FALSE()),1) -> 0.4 | E20: ObjectiveWeight
B21: Authority / Status | C21: Proven / Established | D21: =IFERROR(VLOOKUP($C21,'02_Lookups'!$B:$C,2,FALSE()),1) -> 1.15 | E21: AuthMult — gated by confidence
B22: Language / Region | C22: Bilingual | D22: =IFERROR(VLOOKUP($C22,'02_Lookups'!$B:$C,2,FALSE()),1) -> 1.15 | E22: Cultural / dialect fit
B23: Seasonality / Timing | C23: Regional Major | D23: =IFERROR(VLOOKUP($C23,'02_Lookups'!$B:$C,2,FALSE()),1) -> 1.25 | E23: Timing multiplier
B24: Content Type | C24: Integrated (Player-led) | D24: =IFERROR(VLOOKUP($C24,'02_Lookups'!$B:$C,2,FALSE()),1) -> 1 | E24: Integrated vs Dedicated
B25: Measurement Confidence | C25: estimated — partial data | D25: =IFERROR(VLOOKUP($C25,'02_Lookups'!$B:$C,2,FALSE()),1) -> 0.9 | E25: Enforcement gate — see §3 of Matrix
B26: Authority Floor — FloorShare | C26: Standard floor | D26: =IFERROR(VLOOKUP($C26,'02_Lookups'!$B:$C,2,FALSE()),1) -> 0.5 | E26: 0.4–0.8 (default pulled in §3)
B27: Rights / Add-On Uplift % (auto-sums from §5 toggles) | C27: =C83 -> 0 | D27: — | E27: Σ of add-ons marked Yes in §5
B29: SECTION 3 — RATE-CARD DEFAULTS FOR THIS PLAYER
B30: Default Floor Share % | C30: =IF($C$7="Player",IFERROR(VLOOKUP($C$8,'20_Player_Rate_Card'!$C$6:$BE$500,49,FALSE()),"—"),0) -> 0.35 | E30: Pulled from col AY of rate card
B31: Default Authority Factor | C31: =IF($C$7="Player",IFERROR(VLOOKUP($C$8,'20_Player_Rate_Card'!$C$6:$BE$500,50,FALSE()),"—"),1) -> 1 | E31: Pulled from col AZ of rate card
B32: Default Seasonality | C32: =IF($C$7="Player",IFERROR(VLOOKUP($C$8,'20_Player_Rate_Card'!$C$6:$BE$500,51,FALSE()),"—"),1) -> 1 | E32: Pulled from col BA of rate card
B33: Default Language | C33: =IF($C$7="Player",IFERROR(VLOOKUP($C$8,'20_Player_Rate_Card'!$C$6:$BE$500,52,FALSE()),"—"),1) -> 1 | E33: Pulled from col BB of rate card
B34: Authority Floor Baseline (SAR) | C34: =IF($C$7="Player",IFERROR(VLOOKUP($C$8,'20_Player_Rate_Card'!$C$6:$BE$500,53,FALSE()),"—"),0) -> 8663 | E34: Pulled from col BC of rate card
B35: Measurement Confidence (card) | C35: =IF($C$7="Player",IFERROR(VLOOKUP($C$8,'20_Player_Rate_Card'!$C$6:$BE$500,54,FALSE()),"—"),"estimated — partial data") -> pending | E35: Pulled from col BD of rate card
B37: SECTION 4 — LIVE OUTPUTS
B38: Output | C38: Value | D38: Factor | E38: Formula / Logic
B39: AuthorityFactor (uncapped) | C39: =ROUND(1+D20*(D21-1),3) -> 1.06 | D39: — | E39: 1 + ObjWeight × (AuthMult − 1)
B40: Engagement (confidence-gated) | C40: =IF(ISNUMBER(SEARCH("pending",C25)),1,IF(ISNUMBER(SEARCH("estimated",C25)),MIN(D18,1.2),D18)) -> 1 | D40: — | E40: Pending=1, Estimated capped at 1.2x
B41: AuthorityFactor (confidence-gated) | C41: =IF(ISNUMBER(SEARCH("pending",C25)),1,IF(ISNUMBER(SEARCH("estimated",C25)),MIN(1+D20*(D21-1),1.3),1+D20*(D21-1))) -> 1.06 | D41: — | E41: Estimated capped at 1.3x
B42: Seasonality (confidence-gated) | C42: =IF(ISNUMBER(SEARCH("pending",C25)),1,IF(ISNUMBER(SEARCH("estimated",C25)),MIN(D23,1.25),D23)) -> 1.25 | D42: — | E42: Estimated capped at 1.25x
B43: ConfidenceCap multiplier | C43: =D25 -> 0.9 | D43: — | E43: Applied AFTER MAX(Social, Floor)
B44: Social Price (pre-floor) | C44: =ROUND(C14*C40*D19*C42*D24*D22*C41,0) -> 20571 | E44: Base × Eng(gated) × Aud × Seas(gated) × CType × Lang × AuthFactor(gated)
B45: Authority Floor (computed) | C45: =ROUND(C15*D26*C42*D22*C41,0) -> 18856 | E45: IRL × FloorShare × Seas(gated) × Lang × AuthFactor(gated)
B46: Pre-AddOn (MAX of the two) | C46: =MAX(C44,C45) -> 20571 | E46: Dignity protection — we don't drop below floor
B47: Final Organic | C47: =ROUND(C46*C43,0) -> 18514 | E47: PreAddOn × ConfidenceCap
B48: FINAL (with Add-Ons) | C48: =ROUND(C47*(1+C27),0) -> 18514 | E48: FinalOrganic × (1 + Rights %)
B52: Scenario preview — switch Talent Type at the top to test Player vs Creator. All numbers here are what the Apps Script backend (computeLine) produces for the quote.
B60: SECTION 5 — ADD-ONS & RIGHTS TOGGLE
B61: Toggle ON any add-on to stack its uplift onto Final Organic. Total appears in §2 Rights/Add-On row (C27) and flows into 51_Quote_Preview.
B63: On? | C63: Package | D63: Uplift % | E63: Territory | F63: Duration
B64: No | C64: ='41_Add_On_Rights'!B7 -> Organic Social Only (baseline) | D64: ='41_Add_On_Rights'!C7 -> 0 | E64: ='41_Add_On_Rights'!D7 -> — | F64: ='41_Add_On_Rights'!E7 -> —
B65: No | C65: ='41_Add_On_Rights'!B8 -> Whitelisting / Dark Posts — 30d | D65: ='41_Add_On_Rights'!C8 -> 0.25 | E65: ='41_Add_On_Rights'!D8 -> KSA/MENA | F65: ='41_Add_On_Rights'!E8 -> 30 days
B66: No | C66: ='41_Add_On_Rights'!B9 -> Whitelisting / Dark Posts — 60d | D66: ='41_Add_On_Rights'!C9 -> 0.4 | E66: ='41_Add_On_Rights'!D9 -> KSA/MENA | F66: ='41_Add_On_Rights'!E9 -> 60 days
B67: No | C67: ='41_Add_On_Rights'!B10 -> Whitelisting / Dark Posts — 90d | D67: ='41_Add_On_Rights'!C10 -> 0.6 | E67: ='41_Add_On_Rights'!D10 -> KSA/MENA | F67: ='41_Add_On_Rights'!E10 -> 90 days
B68: No | C68: ='41_Add_On_Rights'!B11 -> Paid Media Usage — 1M Views | D68: ='41_Add_On_Rights'!C11 -> 0.45 | E68: ='41_Add_On_Rights'!D11 -> Regional | F68: ='41_Add_On_Rights'!E11 -> 90 days
B69: No | C69: ='41_Add_On_Rights'!B12 -> Paid Media Usage — 5M Views | D69: ='41_Add_On_Rights'!C12 -> 0.9 | E69: ='41_Add_On_Rights'!D12 -> Regional | F69: ='41_Add_On_Rights'!E12 -> 90 days
B70: No | C70: ='41_Add_On_Rights'!B13 -> Organic Rights — 6 months | D70: ='41_Add_On_Rights'!C13 -> 0.3 | E70: ='41_Add_On_Rights'!D13 -> Global | F70: ='41_Add_On_Rights'!E13 -> 6 months
B71: No | C71: ='41_Add_On_Rights'!B14 -> Organic Rights — 12 months | D71: ='41_Add_On_Rights'!C14 -> 0.55 | E71: ='41_Add_On_Rights'!D14 -> Global | F71: ='41_Add_On_Rights'!E14 -> 12 months
B72: No | C72: ='41_Add_On_Rights'!B15 -> Exclusivity — Category (90d) | D72: ='41_Add_On_Rights'!C15 -> 0.35 | E72: ='41_Add_On_Rights'!D15 -> — | F72: ='41_Add_On_Rights'!E15 -> 90 days
B73: No | C73: ='41_Add_On_Rights'!B16 -> Exclusivity — Category (6 months) | D73: ='41_Add_On_Rights'!C16 -> 0.65 | E73: ='41_Add_On_Rights'!D16 -> — | F73: ='41_Add_On_Rights'!E16 -> 6 months
B74: No | C74: ='41_Add_On_Rights'!B17 -> Exclusivity — Category (12 months) | D74: ='41_Add_On_Rights'!C17 -> 1 | E74: ='41_Add_On_Rights'!D17 -> — | F74: ='41_Add_On_Rights'!E17 -> 12 months
B75: No | C75: ='41_Add_On_Rights'!B18 -> Exclusivity — Brand-wide (6 months) | D75: ='41_Add_On_Rights'!C18 -> 1.5 | E75: ='41_Add_On_Rights'!D18 -> — | F75: ='41_Add_On_Rights'!E18 -> 6 months
... B81: No | C81: ='41_Add_On_Rights'!B24 -> NDA / Confidentiality | D81: ='41_Add_On_Rights'!C24 -> 0.05 | E81: ='41_Add_On_Rights'!D24 -> — | F81: ='41_Add_On_Rights'!E24 -> —
B83: Σ selected uplift | C83: =SUMPRODUCT((B64:B81="Yes")*D64:D81) -> 0

Sheet 51_Quote_Preview
D2: Prepared by | E2: Team Falcons Commercial
D3: Approved by | E3: Finance & Legal
D4: Date | E4: =TEXT(TODAY(),"DD MMM YYYY") -> 18 Apr 2026
D5: Quote # | E5: ="TF-Q-"&TEXT(TODAY(),"YYMMDD")&"-001" -> TF-Q-260418-001
D6: Client | E6: — TBD —
D7: Currency | E7: SAR (Saudi Riyal)
B10: QUOTATION
B11: Unified Talent Pricing OS v1.3 · Riyadh, KSA · Live-linked to 42_Preview
B13: Description | E13: Unit Cost | F13: Qty | G13: Amount
B15: ="Live scenario — "&'42_Preview'!$C$8&" — "&'42_Preview'!$C$13&" "&IF('42_Preview'!$C$7="Creator","(Creator)","(Integrated)") -> Live scenario — Cellium — IG Reel (Integrated) | E15: ='42_Preview'!$C$47 -> 18514 | F15: 1 | G15: =E15*F15 -> 18514
B16: =" └─ from Base "&TEXT('42_Preview'!$C$14,"#,##0")&" × Combined "&TEXT(IFERROR('42_Preview'!$C$47/'42_Preview'!$C$14,1),"0.00")&"x" -> └─ from Base 11,250 × Combined 1.65x
B20: ADD-ONS & USAGE RIGHTS
B21: Add-on rights (sum) — pulled from 42_Preview §2 (row 27) | G21: ='42_Preview'!$C$27 -> 0
B25: Subtotal | F25: =SUM(G15) -> 18514
B26: Add-On Uplift % | F26: ='42_Preview'!$C$27 -> 0
B27: Pre-VAT Total | F27: =F25*(1+F26) -> 18514
B28: Tax Rate | F28: ='01_Settings'!$C$15 -> 0.15
B29: VAT | F29: =F27*F28 -> 2777.1
B30: TOTAL (SAR, incl. VAT) | F30: =F27+F29 -> 21291.1
B33: PRICING MULTIPLIERS BREAKDOWN
B34: Multiplier | D34: Selected Value | F34: Factor | G34: Impact
B35: Content Type | D35: ='42_Preview'!$C$24 -> Integrated (Player-led) | F35: ='42_Preview'!$D$24 -> 1 | G35: =IF(F35=1,"baseline",TEXT(F35-1,"+0%;-0%")) -> baseline
B36: Engagement | D36: ='42_Preview'!$C$18 -> 4–6% — Baseline | F36: ='42_Preview'!$D$18 -> 1 | G36: =IF(F36=1,"baseline",TEXT(F36-1,"+0%;-0%")) -> baseline
B37: Audience Fit | D37: ='42_Preview'!$C$19 -> Core Gaming | F37: ='42_Preview'!$D$19 -> 1.2 | G37: =IF(F37=1,"baseline",TEXT(F37-1,"+0%;-0%")) -> +20%
B38: Seasonality | D38: ='42_Preview'!$C$23 -> Regional Major | F38: ='42_Preview'!$D$23 -> 1.25 | G38: =IF(F38=1,"baseline",TEXT(F38-1,"+0%;-0%")) -> +25%
B39: Language | D39: ='42_Preview'!$C$22 -> Bilingual | F39: ='42_Preview'!$D$22 -> 1.15 | G39: =IF(F39=1,"baseline",TEXT(F39-1,"+0%;-0%")) -> +15%
B40: Authority | D40: ='42_Preview'!$C$21 -> Proven / Established | F40: ='42_Preview'!$D$21 -> 1.15 | G40: =IF(F40=1,"baseline",TEXT(F40-1,"+0%;-0%")) -> +15%
B41: Objective | D41: ='42_Preview'!$C$20 -> Conversion | F41: ='42_Preview'!$D$20 -> 0.4 | G41: =IF(F41=1,"baseline",TEXT(F41-1,"+0%;-0%")) -> -60%
B42: COMBINED MULTIPLIER (applied to Base Fee) | F42: =ROUND(PRODUCT(F35:F41),2) -> 0.79
B43: Final = BaseFee × CType × Eng × Audience × Season × Language × AuthorityFactor × (1 + AddOnUplift%) × ConfidenceCap
B46: Team Falcons · Riyadh, Kingdom of Saudi Arabia · commercial@teamfalcons.gg · Bank: Al Rajhi · Valid 30 days from Quote Date · Confidential — For Client Review

Sheet 52_Quote_Log
B2: 52 — QUOTE LOG (audit trail for all finalized quotes)
B3: Every quote sent to a client is logged here. Apps Script (Phase 2) will auto-append on export. For now, operate as a manual ledger.
B4: Quote ID | C4: Quote Date | D4: Client / Brand | E4: Campaign | F4: Objective | G4: Territory | H4: # Talents | I4: Subtotal (SAR) | J4: Mgmt Fee (SAR) | K4: VAT (SAR) | L4: Total (SAR) | M4: Status | N4: Sent On | O4: Accepted On | P4: Contract Ref | Q4: Invoice # | R4: Account Owner | S4: Notes
B5: 20260115-042 | C5: 2026-01-15 | D5: Aramco Digital | E5: Ramadan Campaign 2026 | F5: Conversion | G5: KSA | H5: 4 | I5: 520000 | J5: 52000 | K5: 85800 | L5: 657800 | M5: Won | N5: 2026-01-16 | O5: 2026-01-22 | P5: TF-CTR-0042 | Q5: INV-2026-004 | R5: Omar A. | S5: Delivered — renewed for Q2
B6: 20260222-117 | C6: 2026-02-22 | D6: STC Gaming | E6: Call of Duty Launch | F6: Awareness | G6: MENA | H6: 6 | I6: 780000 | J6: 78000 | K6: 128700 | L6: 986700 | M6: Negotiation | N6: 2026-02-23 | R6: Nasser K. | S6: Awaiting legal on exclusivity
B7: 20260310-203 | C7: 2026-03-10 | D7: NEOM Sports | E7: EWC 2026 Hospitality | F7: Trust | G7: Global | H7: 3 | I7: 1450000 | J7: 145000 | K7: 239250 | L7: 1834250 | M7: Sent | N7: 2026-03-11 | R7: Huda S. | S7: High-value — legal approval flagged
B10: Team Falcons · Unified Talent Pricing OS v1.2 · Confidential

Sheet 53_Inquiry_Log
B2: 53 — INQUIRY LOG · INBOUND PIPELINE & APPROVALS
B3: One row per inbound. Weighted value feeds pipeline forecasts. Stage + Status + Assignment drive weekly ops.
B4: Inquiry ID | C4: Inbound Date | D4: Client / Agency | E4: Contact | F4: Email | G4: Phone | H4: Request Summary | I4: Requested Talent | J4: Budget Range (SAR) | K4: Timeline | L4: Stage | M4: Status | N4: Assigned To | O4: Next Action | P4: Next Action By | Q4: Est. Value (SAR) | R4: Confidence % | S4: Weighted Value (SAR) | T4: Notes
B5: INQ-20260410-001 | C5: 2026-04-10 | D5: PepsiCo KSA | E5: Sara Al Fahad | F5: s.alfahad@pepsi.com | G5: +966555111222 | H5: Want 2 Falcons players for Ramadan TVC | I5: Tier 1 CS player + streamer | J5: 800K–1.2M | K5: 30 days | L5: Qualified | M5: In Progress | N5: Omar A. | O5: Send full brief + rate card | P5: 2026-04-14 | Q5: 1000000 | R5: =ROUND(P5*Q5,0) -> 46126000000 | S5: 600000 | T5: Likely contract
B6: INQ-20260411-002 | C6: 2026-04-11 | D6: Riyadh Air | E6: Faisal Noor | F6: f.noor@riyadhair.com | G6: +966555333444 | H6: Single IG Reel + WL 60d | I6: Dota 2 captain | J6: 150K–200K | K6: 14 days | L6: Proposal Sent | M6: In Progress | N6: Nasser K. | O6: Follow up on feedback | P6: 2026-04-16 | Q6: 175000 | R6: =ROUND(P6*Q6,0) -> 8072400000 | S6: 96250
B7: INQ-20260412-003 | C7: 2026-04-12 | D7: Savvy Games Group | E7: Huda Al Qahtani | F7: h.alqahtani@savvy.gg | G7: +966555555666 | H7: Event appearance + Snap content | I7: Creator + player pair | J7: 300K–450K | K7: 2 weeks | L7: Lead | M7: In Progress | N7: Huda S. | O7: Discovery call Apr 15 | P7: 2026-04-15 | Q7: 375000 | R7: =ROUND(P7*Q7,0) -> 17297625000 | S7: 150000 | T7: Early-stage
B10: Team Falcons · Unified Talent Pricing OS v1.2 · Confidential

Sheet 90_Methodology
B2: 90 — METHODOLOGY · THE COMMERCIAL SPINE
B3: How Team Falcons prices talent. Plain language; every other tab implements this.
B5: §1 — PRINCIPLES
B6: Talent dignity first | C6: No Falcons talent is ever priced below their authority floor. Status protects the floor; the market decides the ceiling.
B7: Data = authority | C7: A multiplier is only as credible as the data behind it. Weak data = capped multipliers.
B8: Simple inputs, strong logic | C8: Operators should not need a PhD. Pick the talent, the platform, the quantity, the rights. The engine handles the rest.
B9: Organic and rights are different products | C9: Organic fee compensates the talent's audience. Rights/usage compensate the brand's commercial leverage. They are not blended.
B10: One OS, two lanes | C10: Players and Creators share the same governance and engine, but their rate cards remain distinct.
B12: §2 — WHY THIS ARCHITECTURE
B13: v7 → operating baseline | C13: Clean 189-player card and premium front-end. This is what works today. We kept the structure and fees.
B14: v8 → upgrade layer | C14: Added follower tracking, CPM auto-calc, Authority Floor, Confidence tiering, 5-tier scheme. We kept the logic, not the clutter.
B15: Tracker → source of truth | C15: Handles and follower counts normalize here. Rate cards read from the tracker. Shikenso (Phase 2) plugs into the same slot.
B16: Unified Quote Builder | C16: One sheet serves Player, Creator, and Mixed quotes — previously three forms. Line-item schema is stable for future automation.
B18: §3 — THE 9 AXES
B19: See 40_Adjustment_Matrix for the live multipliers. Summary: each axis contributes one multiplier; confidence gates how aggressively those multipliers compound.
B20: A. Engagement | C20: Interactions ÷ followers. 4–6% = 1.00. Heaviest single lever.
B21: B. Audience Quality | C21: Fit with campaign persona. Generic 0.85 → Esports-elite 1.50.
B22: C. Objective | C22: Awareness 0.20 / Conversion 0.40 / Trust 0.70. Weights authority impact.
B23: D. Authority | C23: AuthorityFactor = 1 + ObjWeight × (AuthMult − 1). A global star on a Trust campaign drives much higher premium than on Awareness.
B24: E. Language | C24: Bilingual 1.15 in MENA campaigns.
B25: F. Seasonality | C25: EWC 1.50, Ramadan 1.35, Regional Major 1.25, Off-season 0.80.
B26: G. Confidence | C26: HARD GATE. exact 1.00 cap / estimated 0.90 + eng cap 1.20 / pending 0.75 + all premiums 1.00.
B27: H. Authority Floor | C27: IRL × FloorShare × Seasonality × Language × AuthorityFactor. A hard minimum.
B28: I. Rights / Add-Ons | C28: Additive uplift %. Separate catalogue in 41_Add_On_Rights. Applied AFTER organic fee.
B30: §4 — FORMULA FLOW
B31: Step 1 — SocialPrice | C31: BaseFee × Eng × Aud × Season × ContentType × Lang × AuthorityFactor
B32: Step 2 — AuthorityFloor | C32: IRL × FloorShare × Season × Lang × AuthorityFactor
B33: Step 3 — PreAddOn | C33: MAX(SocialPrice, AuthorityFloor)
B34: Step 4 — FinalOrganic | C34: PreAddOn × ConfidenceCap
B35: Step 5 — Final | C35: FinalOrganic × (1 + AddOnUplift%)
B37: §5 — CONFIDENCE AS ENFORCEMENT
B38: Confidence is not a footnote; it is wired into the engine.
B39: exact / rounded | C39: All premiums allowed. Multipliers stack freely. Cap 1.00.
B40: estimated | C40: Engagement ≤ 1.20, Authority ≤ 1.30, Seasonality ≤ 1.25. Cap 0.90.
B41: pending | C41: All premiums forced to 1.00 — baseline fee only. Cap 0.75.
B42: Rationale | C42: Protects Falcons from overselling weakly verified talent, and creates real incentive to verify handles.
B44: §6 — PLAYER vs CREATOR LANE DIFFERENCES
B45: Player lane | C45: 5-tier structure (S,1,2,3,4). Rate card preserves v7 fees. IRL/Appearance drives Authority Floor. Higher default markup.
B46: Creator lane | C46: 4-tier structure (1-4). Ceiling-first logic — Opening Factor sets starting offer. Event + Snap drives Authority Floor. Lower commission, lower markup.
B47: Shared | C47: Governance backbone, 9-axis matrix, Confidence, Add-Ons, Quote Builder, Logs.
B49: §7 — DATA SOURCES & VERIFICATION
B50: Primary source | C50: 10_Social_Tracker (normalized from Website tracker). Handle + platform + follower count + retrieved-on date.
B51: Manual tier | C51: Today, 'estimated' or 'pending' for most rows. Quarterly review upgrades verified rows.
B52: Shikenso | C52: Phase-2 API cutover. On integration, confidence auto-writes to 'exact' for API-covered platforms.
B54: §8 — GOVERNANCE
B55: High-value approvals | C55: Quotes ≥ SAR 150K auto-flag for legal per 01_Settings threshold.
B56: Exclusivity approvals | C56: Any exclusivity add-on requires legal sign-off — locked in 01_Settings.
B57: Ledger | C57: Every finalized quote lives in 52_Quote_Log; every inbound in 53_Inquiry_Log.
B59: §9 — DOCUMENTATION & HAND-OFF
B60: Named ranges | C60: All cross-sheet anchors are named. Apps Script binds to names, not addresses. See 99_Script_Map.
B61: Schema version | C61: Stamped on 01_Settings as Workbook Version and Schema Stable Until. Bump only on breaking changes.
B62: Bilingual guide | C62: 95_Guide_EN and 96_Guide_AR.
B65: Team Falcons · Unified Talent Pricing OS v1.2 · Confidential

Sheet 91_Roadmap
B2: 91 — ROADMAP · PHASED EVOLUTION
B3: V1 ships the governance + engine + quotation layer. Phases 2–4 unlock automation, rolling pricing, and proactive intelligence.
B5: Phase | C5: Target | D5: Status | E5: Owner | F5: Scope
B6: Phase 1 · V1.0 | C6: Apr 2026 | D6: Shipping | E6: Falcons BD + Ops | F6: Unified OS. Governance. 9-axis matrix. Unified quote builder. Confidence enforcement. Bilingual methodology.
B7: Phase 1.5 · Hardening | C7: May 2026 | D7: Planned | E7: Ops | F7: Internal rollout. Quarterly handle verification campaign. Legal review of rights catalogue.
B8: Phase 2 · Shikenso | C8: Q3 2026 | D8: Planned | E8: Data Eng | F8: API ingest into 10_Social_Tracker. Confidence auto → 'exact' for covered platforms. Daily refresh.
B9: Phase 2.5 · Apps Script | C9: Q3 2026 | D9: Planned | E9: Data Eng | F9: PDF export from 51_Quote_Preview. Auto-append to 52_Quote_Log on send. Approval routing from 01_Settings.
B10: Phase 3 · Rolling prices | C10: Q4 2026 | D10: Planned | E10: Data Eng + BD | F10: Auto-recompute rate card cells on follower drift. Tier-up / tier-down flags.
B11: Phase 3.5 · Pipeline ML | C11: Q1 2027 | D11: Research | E11: Data Science | F11: Weighted-value model learns from 52_Quote_Log close rates. Replaces static confidence %.
B12: Phase 4 · Open API | C12: Q2 2027 | D12: Research | E12: Eng | F12: Brands submit briefs via API; engine returns indicative quote + legal flags. Human BD approves.
B14: DESIGN DECISIONS THAT UNLOCK THE FUTURE
B15: Named ranges everywhere | C15: Apps Script and future APIs bind to names, not addresses. Safe to refactor.
B16: Stable line-item schema | C16: Quote Builder line rows keep column order locked. Phase 2.5 PDF + log writer depend on this.
B17: Shared backbone | C17: Adding a third talent type (e.g., coaches) = add a rate card + extend LKP_TalentType. No engine rewrite.
B18: Confidence as gate | C18: Any ingestion pipeline (Shikenso, manual, future partners) flows through the same gate.
B21: Team Falcons · Unified Talent Pricing OS v1.2 · Confidential

Sheet 95_Guide_EN
B2: 95 — USER GUIDE · ENGLISH
B5: WHO IS THIS FOR
B6: BD, Ops, Finance, and Falcons leadership. Non-technical. If you can fill a form, you can use this.
B8: QUICK PATH — PRICE A CAMPAIGN IN 5 MINUTES
B9: 1) Open 50_Quote_Builder. 2) Fill the header (client, campaign, objective). 3) For each deliverable, pick Talent Type (Player / Creator), pick the talent name, pick the platform, enter quantity. 4) Base fee auto-pulls. 5) Adjust multipliers if you need to — defaults are safe. 6) Add rights/add-on uplift %. 7) Totals auto-compute. 8) Check 51_Quote_Preview — this is what the client sees. 9) Paste the row into 52_Quote_Log when you send it.
B11: WHEN TO TOUCH WHICH TAB
