Workbook

Sheet 00_Cover
B3: TEAM FALCONS
B4: Talent Commercial Rate Card · 2026
B5: Global Esports Pricing & Monetization Framework
B6: Updated: 14 April, 2026 · Currency: SAR · 1 USD = 3.75 SAR
B7: ="Total Talent: "&COUNTA('01_Player_Rate_Card'!$C$5:$C$500)+COUNTA('02_Creator_Rate_Card'!$C$5:$C$500)&" entries · "&COUNTA('01_Player_Rate_Card'!$C$5:$C$500)&" players · "&COUNTA('02_Creator_Rate_Card'!$C$5:$C$500)&" creators · Confidential — Internal Use Only" -> Total Talent: 206 entries · 189 players · 17 creators · Confidential — Internal Use Only
B10: =COUNTA('01_Player_Rate_Card'!$C$5:$C$500) -> 189 | D10: =COUNTIF('01_Player_Rate_Card'!$D$5:$D$500,"Player") -> 131 | F10: =COUNTIF('01_Player_Rate_Card'!$D$5:$D$500,"Influencer") -> 8 | H10: =COUNTA('01_Player_Rate_Card'!$C$5:$C$500)-COUNTIF('01_Player_Rate_Card'!$D$5:$D$500,"Player")-COUNTIF('01_Player_Rate_Card'!$D$5:$D$500,"Influencer") -> 50 | J10: =COUNTIF('01_Player_Rate_Card'!$I$5:$I$500,"Tier 1")&"/"&COUNTIF('01_Player_Rate_Card'!$I$5:$I$500,"Tier 2")&"/"&COUNTIF('01_Player_Rate_Card'!$I$5:$I$500,"Tier 3") -> 25/106/58
B11: Total Entries | D11: Players | F11: Esports Influencers | H11: Staff & Coaches | J11: T1 / T2 / T3
B13: SHEET NAVIGATION
B14: 01_Player_Rate_Card | D14: ="All "&COUNTA('01_Player_Rate_Card'!$C$5:$C$500)&" entries · rates per platform · filterable by role/game/team/tier" -> All 189 entries · rates per platform · filterable by role/game/team/tier
B15: 02_Creator_Rate_Card | D15: ="All "&COUNTA('02_Creator_Rate_Card'!$C$5:$C$500)&" content creators · ceiling rates" -> All 17 content creators · ceiling rates
B16: 03_Adjustment_Matrix | D16: Engagement · Audience · Seasonality · Confidence + Live Calculator
B17: 04_Add_On_Rights | D17: Rights packages with uplift % + toggle grid
B18: 05_Quote_Template | D18: KFC-style quotation template — Apps Script outputs to here
B19: 06_Quote_Log | D19: Archive of all issued quotes (auto-populated)
B20: 07_Settings | D20: Global config · VAT · USD · approvers · bank
B21: 08_Benchmarks | D21: Market benchmarks — Tier 1 / MENA / platform CPMs
B22: 09_Guide_EN | D22: Pricing methodology, formula, best practices (English)
B23: 10_Guide_AR | D23: دليل التسعير الكامل بالعربي
B24: 11_Methodology | D24: Why this pricing OS works — principles + decision flows
B26: COLOR LEGEND
B27: Tier S — Superstar | D27: 1M+ followers · Global icon · World-class anchor
B28: Tier 1 — Premium | D28: 250K–1M followers · 8%+ engagement · Established
B29: Tier 2 — Target | D29: 50K–250K followers · 5–8% engagement · Core pros
B30: Tier 3 — Emerging | D30: 10K–50K followers · High engagement · Rising stars
B31: Tier 4 — Entry / Staff | D31: Support roles · Appearance rates
B32: Coach / Head Coach | D32: Coaching staff — rates apply for appearances & content
B33: Manager | D33: Management staff — rates apply for appearances
B34: Analyst | D34: Analyst staff — rates apply for appearances
B35: Influencer | D35: Esports influencers — social-first creators
B36: Creator | D36: Content creators — ceiling-based pricing

Sheet 01_Player_Rate_Card
B2: ="TALENT RATE CARD — ALL "&COUNTA($C$5:$C$500)&" ENTRIES" -> TALENT RATE CARD — ALL 189 ENTRIES
A3: ROLE LEGEND | B3: ● Player | C3: ● Head Coach | D3: ● Coach | E3: ● Manager | F3: ● Analyst | G3: ● Influencer | H3: ● Coach
B4: # | C4: Nickname | D4: Role | E4: Game | F4: Team | G4: Nationality | H4: Platforms | I4: Tier | J4: IG Reel (SAR) | K4: IG Static (SAR) | L4: IG Story (SAR) | M4: TikTok Video | N4: YT Short (SAR) | O4: X Post (SAR) | P4: FB Post/Video (SAR) | Q4: Twitch Stream 2h | R4: Twitch Integ. | S4: IRL / Appear. | T4: Rights Fee | U4: Exclusivity Fee | V4: Rush Fee | W4: WL Fee | X4: Notes | Y4: Falcons Commission % | Z4: Markup % (on Player Cost) | AA4: Full Name | AB4: X / Twitter | AC4: Instagram | AD4: Twitch | AE4: YouTube | AF4: TikTok | AG4: Kick | AH4: Facebook | AI4: Snapchat | AJ4: Link-in-Bio | AK4: Date of Birth | AL4: Game Role
B5: =IF($C5="","",COUNTA($C$5:C5)) -> 1 | C5: Bijw | D5: Influencer | E5: Esports Influencers | F5: Esports Influencers | G5: Saudi Arabia | H5: 6 | I5: Tier 3 | J5: 11000 | K5: 4600 | L5: =IF($C5="","",ROUND($J5*0.17,0)) -> 1870 | M5: 8600 | N5: 3500 | O5: 2200 | P5: 2200 | Q5: 15950 | R5: 7150 | S5: =IF($C5="","",ROUND($J5*2.2,0)) -> 24200 | T5: 3850 | U5: 3300 | V5: 2000 | W5: 1650 | X5: 6 platforms | Y5: 0.3 | Z5: 1 | AA5: Hisham Nasser | AB5: https://x.com/_bijw | AC5: https://www.instagram.com/bijjw | AD5: https://www.twitch.tv/bijw | AE5: https://www.youtube.com/@Bijw | AF5: https://www.tiktok.com/@biijw | AG5: https://kick.com/bijw | AI5: https://www.snapchat.com/add/bijjw | AJ5: https://linktr.ee/bijw
B6: =IF($C6="","",COUNTA($C$5:C6)) -> 2 | C6: Abo Najd | D6: Influencer | E6: Esports Influencers | F6: Esports Influencers | G6: Saudi Arabia | H6: 4 | I6: Tier 3 | J6: 8100 | K6: 3200 | L6: =IF($C6="","",ROUND($J6*0.17,0)) -> 1377 | M6: 6350 | N6: 2600 | O6: 1600 | P6: 1600 | Q6: 11800 | R6: 5300 | S6: =IF($C6="","",ROUND($J6*2.2,0)) -> 17820 | T6: 2850 | U6: 2450 | V6: 1450 | W6: 1215 | X6: 4 platforms | Y6: 0.3 | Z6: 1 | AA6: Riyad Alfahmi | AB6: https://x.com/K22N8 | AC6: https://www.instagram.com/k2nn8?igsh=ajJsNHoybDlpMzFo | AD6: https://www.twitch.tv/k2nnn8 | AE6: https://www.youtube.com/@k2nn8 | AJ6: https://linktr.ee/K2nnn8 (alt: https://heylink.me/k2nn8)
B7: =IF($C7="","",COUNTA($C$5:C7)) -> 3 | C7: FMG | D7: Influencer | E7: Esports Influencers | F7: Esports Influencers | G7: Saudi Arabia | H7: 4 | I7: Tier 3 | J7: 7450 | K7: 3150 | L7: =IF($C7="","",ROUND($J7*0.17,0)) -> 1267 | M7: 5850 | N7: 2400 | O7: 1500 | P7: 1500 | Q7: 10850 | R7: 4850 | S7: =IF($C7="","",ROUND($J7*2.2,0)) -> 16390 | T7: 2600 | U7: 2250 | V7: 1350 | W7: 1118 | X7: 4 platforms | Y7: 0.3 | Z7: 1 | AA7: Nasser alotaibi | AB7: https://x.com/iFMG_ | AC7: https://www.instagram.com/fm.g/ | AD7: https://www.twitch.tv/fmg_ | AG7: https://kick.com/ifmg
B8: =IF($C8="","",COUNTA($C$5:C8)) -> 4 | C8: Abo Ghazi | D8: Influencer | E8: Esports Influencers | F8: Esports Influencers | G8: Saudi Arabia | H8: 3 | I8: Tier 3 | J8: 5200 | K8: 2200 | L8: =IF($C8="","",ROUND($J8*0.17,0)) -> 884 | M8: 4050 | N8: 1650 | O8: 1050 | P8: 1050 | Q8: 7550 | R8: 3400 | S8: =IF($C8="","",ROUND($J8*2.2,0)) -> 11440 | T8: 1800 | U8: 1550 | V8: 950 | W8: 780 | X8: 3 platforms | Y8: 0.3 | Z8: 1 | AA8: Mohammed Albaqami | AB8: https://x.com/MohxamedZ | AD8: https://www.twitch.tv/ires | AG8: https://kick.com/iabughazi | AH8: https://www.facebook.com/AbuGhaziGaming93 | AI8: https://www.snapchat.com/add/faisalhajhasan | AJ8: https://linktr.ee/abughaazi
B9: =IF($C9="","",COUNTA($C$5:C9)) -> 5 | C9: Mary | D9: Influencer | E9: Esports Influencers | F9: Esports Influencers | G9: Bahraini | H9: 5 | I9: Tier 3 | J9: 8100 | K9: 3400 | L9: =IF($C9="","",ROUND($J9*0.17,0)) -> 1377 | M9: 6350 | N9: 2600 | O9: 1600 | P9: 1600 | Q9: 11800 | R9: 5300 | S9: =IF($C9="","",ROUND($J9*2.2,0)) -> 17820 | T9: 2850 | U9: 2450 | V9: 1450 | W9: 1215 | X9: 5 platforms | Y9: 0.3 | Z9: 1 | AA9: Maryam Maher | AB9: https://x.com/marypink | AC9: https://www.instagram.com/maryvalorantt/?hl=en | AD9: https://www.twitch.tv/mary | AE9: https://www.youtube.com/@maryvalorant/featured | AF9: https://www.tiktok.com/@maryvalorant | AJ9: https://linktr.ee/verymarygaming
B10: =IF($C10="","",COUNTA($C$5:C10)) -> 6 | C10: Ghala | D10: Influencer | E10: Esports Influencers | F10: Esports Influencers | G10: Saudi Arabia | H10: 5 | I10: Tier 3 | J10: 7450 | K10: 3150 | L10: =IF($C10="","",ROUND($J10*0.17,0)) -> 1267 | M10: 5850 | N10: 2400 | O10: 1500 | P10: 1500 | Q10: 10850 | R10: 4850 | S10: =IF($C10="","",ROUND($J10*2.2,0)) -> 16390 | T10: 2600 | U10: 2250 | V10: 1350 | W10: 1118 | X10: 5 platforms | Y10: 0.3 | Z10: 1 | AA10: Ghala Alqahtani | AB10: https://x.com/pg_ghala3?lang=en | AC10: https://www.instagram.com/pg_ghala3 | AE10: https://www.youtube.com/@pg_ghala3 | AF10: https://www.tiktok.com/@pg_ghala3 | AG10: https://kick.com/pg-ghala3 | AI10: https://snapchat.com/t/bLA2ZOsG | AJ10: https://linktr.ee/ga1lll
B11: =IF($C11="","",COUNTA($C$5:C11)) -> 7 | C11: Moaz | D11: Influencer | E11: Esports Influencers | F11: Esports Influencers | G11: Saudi Arabia | H11: 5 | I11: Tier 2 | J11: 6500 | K11: 5300 | L11: =IF($C11="","",ROUND($J11*0.17,0)) -> 1105 | M11: 3400 | N11: 4050 | O11: 2500 | P11: 2500 | Q11: 15950 | R11: 8200 | S11: =IF($C11="","",ROUND($J11*2.2,0)) -> 14300 | T11: 3800 | U11: 1900 | V11: 3150 | W11: 1250 | X11: 5 platforms | Y11: 0.3 | Z11: 1 | AA11: Moaz Asiri | AB11: https://x.com/mezostrong?s=21 | AC11: https://www.instagram.com/mezostrong | AE11: https://www.youtube.com/channel/UCZCgW8WW8K_vrHrO6sZ7oyg?app=desktop | AF11: https://www.tiktok.com/@mezostrong?_r=1&_t=zs-91bbrrsefwl | AG11: https://kick.com/MezoStrong
B12: =IF($C12="","",COUNTA($C$5:C12)) -> 8 | C12: vacwep | D12: Influencer | E12: Esports Influencers | F12: Esports Influencers | G12: Saudi Arabia | H12: 5 | I12: Tier 3 | J12: 7450 | K12: 3150 | L12: =IF($C12="","",ROUND($J12*0.17,0)) -> 1267 | M12: 5800 | N12: 2400 | O12: 1500 | P12: 1500 | Q12: 7500 | R12: 4850 | S12: =IF($C12="","",ROUND($J12*2.2,0)) -> 16390 | T12: 2250 | U12: 1100 | V12: 1850 | W12: 750 | X12: 5 platforms | Y12: 0.3 | Z12: 1 | AA12: Abdullah Mousa A Alsulaymi | AB12: https://x.com/vacwep?s=21&t=PiVx0_LPZgUm0TT5Ok_2Zw | AC12: https://www.instagram.com/vacwep_?igsh=Z28yMXRibTZ0OWlm&utm_source=qr | AF12: https://www.tiktok.com/@vacwep?_r=1&_t=ZS-94jrcxtNGEK | AG12: https://kick.com/vacwep | AH12: https://www.facebook.com/share/1BDLRfGMFS/?mibextid=wwXIfr | AK12: 12/07/1992
B13: =IF($C13="","",COUNTA($C$5:C13)) -> 9 | C13: Cellium | D13: Player | E13: Call of Duty Black Ops 7 | F13: Riyadh Falcons | G13: American | H13: 3 | I13: Tier 2 | J13: 11250 | K13: 4500 | L13: =IF($C13="","",ROUND($J13*0.17,0)) -> 1913 | M13: 8000 | N13: 3500 | O13: 2000 | P13: 2000 | Q13: 13500 | R13: 6075 | S13: =IF($C13="","",ROUND($J13*2.2,0)) -> 24750 | T13: 4638 | U13: 4063 | V13: 2438 | W13: 2400 | X13: 3 platforms | Y13: 0.3 | Z13: 1 | AA13: McArthur Jovel | AB13: https://twitter.com/Cellium | AC13: https://www.instagram.com/cellium/ | AD13: https://www.twitch.tv/Cellium | AK13: 24/12/2000 | AL13: Assault Rifle / Main AR
B14: =IF($C14="","",COUNTA($C$5:C14)) -> 10 | C14: Exnid | D14: Player | E14: Call of Duty Black Ops 7 | F14: Riyadh Falcons | G14: Saudi Arabia | H14: 2 | I14: Tier 2 | J14: 11000 | K14: 4600 | L14: =IF($C14="","",ROUND($J14*0.17,0)) -> 1870 | M14: 8600 | N14: 3500 | O14: 2200 | P14: 2200 | Q14: 15950 | R14: 7150 | S14: =IF($C14="","",ROUND($J14*2.2,0)) -> 24200 | T14: 3850 | U14: 3300 | V14: 2000 | W14: 2400 | X14: 2 platforms | Y14: 0.3 | Z14: 1 | AA14: Saud Alati | AB14: https://x.com/Exnid_ | AD14: https://www.twitch.tv/exnid | AK14: 28/10/2002 | AL14: Sub-Machine Gun (SMG)
B15: =IF($C15="","",COUNTA($C$5:C15)) -> 11 | C15: KiSMET | D15: Player | E15: Call of Duty Black Ops 7 | F15: Riyadh Falcons | G15: American | H15: 3 | I15: Tier 2 | J15: 12100 | K15: 5100 | L15: =IF($C15="","",ROUND($J15*0.17,0)) -> 2057 | M15: 9450 | N15: 3850 | O15: 2400 | P15: 2400 | Q15: 17550 | R15: 7850 | S15: =IF($C15="","",ROUND($J15*2.2,0)) -> 26620 | T15: 4250 | U15: 3650 | V15: 2200 | W15: 2400 | X15: 3 platforms | Y15: 0.3 | Z15: 1 | AA15: Matthew Tinsley | AB15: https://twitter.com/KiSMET6_ | AC15: https://www.instagram.com/kismet6_ | AD15: https://www.twitch.tv/kismet6_ | AK15: 36475 | AL15: Assault Rifle / Flex
B16: =IF($C16="","",COUNTA($C$5:C16)) -> 12 | C16: Pred | D16: Player | E16: Call of Duty Black Ops 7 | F16: Riyadh Falcons | G16: American | H16: 3 | I16: Tier 2 | J16: 11000 | K16: 4600 | L16: =IF($C16="","",ROUND($J16*0.17,0)) -> 1870 | M16: 8600 | N16: 3500 | O16: 2200 | P16: 2200 | Q16: 15950 | R16: 7150 | S16: =IF($C16="","",ROUND($J16*2.2,0)) -> 24200 | T16: 3850 | U16: 3300 | V16: 2000 | W16: 2400 | X16: 3 platforms | Y16: 0.3 | Z16: 1 | AA16: Amer Zulbeari | AB16: https://x.com/Pred | AC16: https://www.instagram.com/amerzulbeariii | AD16: https://www.twitch.tv/pred | AK16: 19/08/2001 | AL16: Sub-Machine Gun (SMG)
B17: =IF($C17="","",COUNTA($C$5:C17)) -> 13 | C17: KingAbody | D17: Player | E17: Call of Duty Black Ops 7 | F17: FaZe Falcons | G17: Saudi Arabia | H17: 1 | I17: Tier 2 | J17: 11000 | K17: 4600 | L17: =IF($C17="","",ROUND($J17*0.17,0)) -> 1870 | M17: 8600 | N17: 3500 | O17: 2200 | P17: 2200 | Q17: 15950 | R17: 7150 | S17: =IF($C17="","",ROUND($J17*2.2,0)) -> 24200 | T17: 3850 | U17: 3300 | V17: 2000 | W17: 2400 | X17: 1 platform | Y17: 0.3 | Z17: 1 | AA17: Abdulelah Alrajhi | AB17: https://x.com/KingAbody_ | AK17: 36679 | AL17: Sub-Machine Gun (SMG)
B18: =IF($C18="","",COUNTA($C$5:C18)) -> 14 | C18: Arcitys | D18: Player | E18: Call of Duty Black Ops 7 | F18: Falcons Academy White | G18: American | H18: 3 | I18: Tier 2 | J18: 12100 | K18: 5100 | L18: =IF($C18="","",ROUND($J18*0.17,0)) -> 2057 | M18: 9450 | N18: 3850 | O18: 2400 | P18: 2400 | Q18: 17550 | R18: 7850 | S18: =IF($C18="","",ROUND($J18*2.2,0)) -> 26620 | T18: 4250 | U18: 3650 | V18: 2200 | W18: 2400 | X18: 3 platforms | Y18: 0.3 | Z18: 1 | AA18: Alec Sanderson | AB18: https://x.com/Arcitys | AC18: https://www.instagram.com/arcitys9 | AD18: https://www.twitch.tv/arcitys | AK18: 36045 | AL18: Assault Rifle / Main AR
B19: =IF($C19="","",COUNTA($C$5:C19)) -> 15 | C19: Paulehx | D19: Player | E19: Call of Duty Black Ops 7 | F19: Falcons Academy White | G19: American | H19: 2 | I19: Tier 2 | J19: 11000 | K19: 4600 | L19: =IF($C19="","",ROUND($J19*0.17,0)) -> 1870 | M19: 8600 | N19: 3500 | O19: 2200 | P19: 2200 | Q19: 15950 | R19: 7150 | S19: =IF($C19="","",ROUND($J19*2.2,0)) -> 24200 | T19: 3850 | U19: 3300 | V19: 2000 | W19: 2400 | X19: 2 platforms | Y19: 0.3 | Z19: 1 | AA19: Paul Avila | AB19: https://x.com/Paulehx_ | AD19: https://www.twitch.tv/paulehx | AK19: 21/01/2002 | AL19: Assault Rifle / Flex
B20: =IF($C20="","",COUNTA($C$5:C20)) -> 16 | C20: hmoodx | D20: Player | E20: Call of Duty Warzone | F20: Team Falcons MENA | G20: Saudi Arabia | H20: 2 | I20: Tier 2 | J20: 11000 | K20: 4600 | L20: =IF($C20="","",ROUND($J20*0.17,0)) -> 1870 | M20: 8600 | N20: 3500 | O20: 2200 | P20: 2200 | Q20: 15950 | R20: 7150 | S20: =IF($C20="","",ROUND($J20*2.2,0)) -> 24200 | T20: 3850 | U20: 3300 | V20: 2000 | W20: 2400 | X20: 2 platforms | Y20: 0.3 | Z20: 1 | AA20: Mohammed Altowairqi | AB20: https://x.com/xihamoodx | AD20: https://www.twitch.tv/i_hmoodx
B21: =IF($C21="","",COUNTA($C$5:C21)) -> 17 | C21: xizx7 | D21: Player | E21: Call of Duty Warzone | F21: Team Falcons MENA | G21: Saudi Arabia | H21: 4 | I21: Tier 1 | J21: 12100 | K21: 5100 | L21: =IF($C21="","",ROUND($J21*0.17,0)) -> 2057 | M21: 9450 | N21: 3850 | O21: 2400 | P21: 2400 | Q21: 17550 | R21: 7850 | S21: =IF($C21="","",ROUND($J21*2.2,0)) -> 26620 | T21: 4250 | U21: 3650 | V21: 2200 | W21: 2400 | X21: 4 platforms | Y21: 0.3 | Z21: 1 | AA21: Jawad Al-Thawab | AB21: https://x.com/Jawxd7 | AC21: https://www.instagram.com/Jawxd7 | AD21: https://www.twitch.tv/jawad | AE21: https://www.youtube.com/channel/UCUWL8dR-JyA4FXZ08aSjjcg/videos
B22: =IF($C22="","",COUNTA($C$5:C22)) -> 18 | C22: Alpine | D22: Manager | E22: Call of Duty Warzone | F22: Team Falcons | G22: American | H22: 1 | I22: Tier 3 | J22: 22750 | K22: 9550 | L22: =IF($C22="","",ROUND($J22*0.17,0)) -> 3868 | M22: 17750 | N22: 7300 | O22: 4550 | P22: 0 | Q22: 33000 | R22: 14800 | S22: =IF($C22="","",ROUND($J22*2.2,0)) -> 50050 | T22: 7950 | U22: 6850 | V22: 4100 | W22: 0 | X22: 1 platform | Y22: 0.3 | Z22: 1 | AA22: Alejandro Ayala | AB22: https://x.com/alpinedadog?lang=en | AK22: 24/02/1997
B23: =IF($C23="","",COUNTA($C$5:C23)) -> 19 | C23: Newbz | D23: Player | E23: Call of Duty Warzone | F23: Team Falcons | G23: American | H23: 2 | I23: Tier 3 | J23: 20700 | K23: 8700 | L23: =IF($C23="","",ROUND($J23*0.17,0)) -> 3519 | M23: 16150 | N23: 6600 | O23: 4150 | P23: 4150 | Q23: 30000 | R23: 13450 | S23: =IF($C23="","",ROUND($J23*2.2,0)) -> 45540 | T23: 7250 | U23: 6200 | V23: 3750 | W23: 2400 | X23: 2 platforms | Y23: 0.2 | Z23: 1 | AA23: Edy Juan | AB23: https://x.com/TBE_Newbzz | AD23: https://www.twitch.tv/newbz | AK23: 36527
B24: =IF($C24="","",COUNTA($C$5:C24)) -> 20 | C24: Dongy | D24: Player | E24: Call of Duty Warzone | F24: Team Falcons | G24: American | H24: 2 | I24: Tier 3 | J24: 6500 | K24: 2750 | L24: =IF($C24="","",ROUND($J24*0.17,0)) -> 1105 | M24: 5050 | N24: 2100 | O24: 1300 | P24: 1300 | Q24: 9400 | R24: 4200 | S24: =IF($C24="","",ROUND($J24*2.2,0)) -> 14300 | T24: 2300 | U24: 1950 | V24: 1150 | W24: 2400 | X24: 2 platforms | Y24: 0.2 | Z24: 1 | AA24: Christopher Ledbetter | AB24: https://x.com/zDongyy | AD24: https://www.twitch.tv/Dongy | AK24: 23/03/2004
B25: =IF($C25="","",COUNTA($C$5:C25)) -> 21 | C25: Soka | D25: Player | E25: Call of Duty Warzone | F25: Team Falcons | G25: Tongan | H25: 5 | I25: Tier 1 | J25: 6500 | K25: 2750 | L25: =IF($C25="","",ROUND($J25*0.17,0)) -> 1105 | M25: 5050 | N25: 2100 | O25: 1300 | P25: 1300 | Q25: 9400 | R25: 4200 | S25: =IF($C25="","",ROUND($J25*2.2,0)) -> 14300 | T25: 2300 | U25: 1950 | V25: 1150 | W25: 2400 | X25: 5 platforms | Y25: 0.2 | Z25: 1 | AA25: Kasimili Tonga Tongamoa | AB25: https://twitter.com/HisokaT42 | AC25: https://www.instagram.com/hisokat42 | AD25: https://www.twitch.tv/HisokaT42 | AE25: https://www.youtube.com/channel/UCQDRE8aZRsrvF5OwMk_KmBg | AF25: https://tiktok.com/@missionarysoka | AK25: 28/01/2002
B26: =IF($C26="","",COUNTA($C$5:C26)) -> 22 | C26: Alireza Firouzja | D26: Player | E26: Chess | F26: Chess | G26: French/Iranian | H26: 5 | I26: Tier 1 | J26: 20700 | K26: 8700 | L26: =IF($C26="","",ROUND($J26*0.17,0)) -> 3519 | M26: 16150 | N26: 6600 | O26: 4150 | P26: 4150 | Q26: 30000 | R26: 13450 | S26: =IF($C26="","",ROUND($J26*2.2,0)) -> 45540 | T26: 7250 | U26: 6200 | V26: 3750 | W26: 2400 | X26: 5 platforms | Y26: 0.5 | Z26: 1 | AA26: Alireza Firouzja | AB26: https://twitter.com/AlirezaFirouzja | AC26: https://www.instagram.com/alirezafirouzja | AD26: https://www.twitch.tv/alirezafirouzja | AE26: https://www.youtube.com/@alirezafirouzja4080 | AH26: https://www.facebook.com/login/?next=https%3A%2F%2Fwww.facebook.com%2FAlireza.Firouzja.chess%2F | AK26: 18/06/2003
B27: =IF($C27="","",COUNTA($C$5:C27)) -> 23 | C27: Hikaru Nakamura | D27: Player | E27: Chess | F27: Chess | G27: American | H27: 6 | I27: Tier 1 | J27: 22500 | K27: 9450 | L27: =IF($C27="","",ROUND($J27*0.17,0)) -> 3825 | M27: 17550 | N27: 7200 | O27: 4500 | P27: 4500 | Q27: 32600 | R27: 14600 | S27: =IF($C27="","",ROUND($J27*2.2,0)) -> 49500 | T27: 7850 | U27: 6750 | V27: 4050 | W27: 2400 | X27: 6 platforms | Y27: 0.5 | Z27: 1 | AA27: Hikaru Nakamura | AB27: https://twitter.com/GMHikaru | AC27: https://www.instagram.com/gmhikaru | AD27: https://www.twitch.tv/gmhikaru | AE27: https://www.youtube.com/@gmhikaru | AG27: https://kick.com/gmhikaru | AH27: https://www.facebook.com/login/?next=https%3A%2F%2Fwww.facebook.com%2FGMHikaru%2F | AK27: 32120
B28: =IF($C28="","",COUNTA($C$5:C28)) -> 24 | C28: Jon Ellis | D28: Manager | E28: Chess | F28: Chess | H28: 0 | I28: Tier 3 | J28: 22500 | K28: 9450 | L28: =IF($C28="","",ROUND($J28*0.17,0)) -> 3825 | M28: 17550 | N28: 7200 | O28: 4500 | P28: 0 | Q28: 32600 | R28: 14600 | S28: =IF($C28="","",ROUND($J28*2.2,0)) -> 49500 | T28: 7850 | U28: 6750 | V28: 4050 | W28: 0 | X28: 0 platforms | Y28: 0.3 | Z28: 1 | AA28: Jonathan Ellis
B29: =IF($C29="","",COUNTA($C$5:C29)) -> 25 | C29: kyousuke | D29: Player | E29: Counterstrike2 | F29: Team Falcons | G29: Russian | H29: 3 | I29: Tier 1 | J29: 15000 | K29: 6750 | L29: =IF($C29="","",ROUND($J29*0.17,0)) -> 2550 | M29: 11000 | N29: 5000 | O29: 3200 | P29: 3200 | Q29: 19500 | R29: 8775 | S29: =IF($C29="","",ROUND($J29*2.2,0)) -> 33000 | T29: 6800 | U29: 5950 | V29: 3570 | W29: 2400 | X29: 3 platforms | Y29: 0.75 | Z29: 1 | AA29: Maxim Lukin | AB29: https://twitter.com/FLCkyousuke | AC29: https://www.instagram.com/flckyousuke | AD29: https://www.twitch.tv/kyousuke999 | AK29: 30/01/2008 | AL29: Rifler
B30: =IF($C30="","",COUNTA($C$5:C30)) -> 26 | C30: kyxsan | D30: Player | E30: Counterstrike2 | F30: Team Falcons | G30: North Macedonia | H30: 2 | I30: Tier 1 | J30: 22500 | K30: 9450 | L30: =IF($C30="","",ROUND($J30*0.17,0)) -> 3825 | M30: 17550 | N30: 7200 | O30: 4500 | P30: 4500 | Q30: 32600 | R30: 14600 | S30: =IF($C30="","",ROUND($J30*2.2,0)) -> 49500 | T30: 7850 | U30: 6750 | V30: 4050 | W30: 2400 | X30: 2 platforms | Y30: 0.75 | Z30: 1 | AA30: Damjan Stoilkovski | AB30: https://x.com/kyxsancs | AC30: https://www.instagram.com/kyxsancs/ | AK30: 26/05/2000 | AL30: IGL
B31: =IF($C31="","",COUNTA($C$5:C31)) -> 27 | C31: m0NESY | D31: Player | E31: Counterstrike2 | F31: Team Falcons | G31: Russian | H31: 4 | I31: Tier 1 | J31: 22500 | K31: 9450 | L31: =IF($C31="","",ROUND($J31*0.17,0)) -> 3825 | M31: 17550 | N31: 7200 | O31: 4500 | P31: 4500 | Q31: 32600 | R31: 14600 | S31: =IF($C31="","",ROUND($J31*2.2,0)) -> 49500 | T31: 7850 | U31: 6750 | V31: 4050 | W31: 2400 | X31: 4 platforms | Y31: 0.2 | Z31: 1 | AA31: Ilya Osipov | AB31: https://x.com/FLCm0NESY | AC31: https://www.instagram.com/m0nesy13 | AD31: https://www.twitch.tv/m0nesyof | AE31: https://www.youtube.com/channel/UCJxjKA1Cl--4tCN1l_cHHvQ | AK31: 38357 | AL31: Awper
B32: =IF($C32="","",COUNTA($C$5:C32)) -> 28 | C32: NiKo | D32: Player | E32: Counterstrike2 | F32: Team Falcons | G32: Bosnian | H32: 5 | I32: Tier 1 | J32: 22500 | K32: 9450 | L32: =IF($C32="","",ROUND($J32*0.17,0)) -> 3825 | M32: 17550 | N32: 7200 | O32: 4500 | P32: 4500 | Q32: 32600 | R32: 14600 | S32: =IF($C32="","",ROUND($J32*2.2,0)) -> 49500 | T32: 7850 | U32: 6750 | V32: 4050 | W32: 2400 | X32: 5 platforms | Y32: 0.3 | Z32: 1 | AA32: Nikola Kovač | AB32: https://x.com/NiKoCS_ | AC32: https://www.instagram.com/csgoniko/# | AD32: https://www.twitch.tv/NiKo | AE32: https://www.youtube.com/@NiKo_cs | AH32: https://www.facebook.com/csgoNiKo | AK32: 16/02/1997 | AL32: Rifler
B33: =IF($C33="","",COUNTA($C$5:C33)) -> 29 | C33: OMYA | D33: Manager | E33: Counterstrike2 | F33: Team Falcons | G33: French | H33: 1 | I33: Tier 3 | J33: 22500 | K33: 9450 | L33: =IF($C33="","",ROUND($J33*0.17,0)) -> 3825 | M33: 17550 | N33: 7200 | O33: 4500 | P33: 0 | Q33: 32600 | R33: 14600 | S33: =IF($C33="","",ROUND($J33*2.2,0)) -> 49500 | T33: 7850 | U33: 6750 | V33: 4050 | W33: 0 | X33: 1 platform | Y33: 0.3 | Z33: 1 | AA33: Xavier Roussac | AB33: https://x.com/Xavier_Roussac | AK33: 20/05/1987
B34: =IF($C34="","",COUNTA($C$5:C34)) -> 30 | C34: TeSeS | D34: Player | E34: Counterstrike2 | F34: Team Falcons | G34: Danish | H34: 2 | I34: Tier 2 | J34: 11250 | K34: 4500 | L34: =IF($C34="","",ROUND($J34*0.17,0)) -> 1913 | M34: 8000 | N34: 3500 | O34: 2000 | P34: 2000 | Q34: 13500 | R34: 6075 | S34: =IF($C34="","",ROUND($J34*2.2,0)) -> 24750 | T34: 4638 | U34: 4063 | V34: 2438 | W34: 2400 | X34: 2 platforms | Y34: 0.75 | Z34: 1 | AA34: René Madsen | AB34: https://x.com/tesescs | AC34: Instagram/TeseS | AD34: https://www.twitch.tv/tesesss | AK34: 36872 | AL34: Rifler
B35: =IF($C35="","",COUNTA($C$5:C35)) -> 31 | C35: Aymeinstein | D35: Assistant Coach | E35: Counterstrike2 | F35: Team Falcons | G35: French | H35: 2 | I35: Tier 2 | J35: 11000 | K35: 4600 | L35: =IF($C35="","",ROUND($J35*0.17,0)) -> 1870 | M35: 8600 | N35: 3500 | O35: 2200 | P35: 0 | Q35: 15950 | R35: 7150 | S35: =IF($C35="","",ROUND($J35*2.2,0)) -> 24200 | T35: 3850 | U35: 3300 | V35: 2000 | W35: 0 | X35: 2 platforms | Y35: 0.5 | Z35: 1 | AA35: Aymen Bencheikh | AB35: https://x.com/aymeinstein | AC35: https://www.instagram.com/aymeinsteintv | AK35: 22/04/1996
B36: =IF($C36="","",COUNTA($C$5:C36)) -> 32 | C36: Zonic | D36: Head Coach | E36: Counterstrike2 | F36: Team Falcons | G36: Danish | H36: 2 | I36: Tier 1 | J36: 0 | K36: 0 | L36: =IF($C36="","",ROUND($J36*0.17,0)) -> 0 | M36: 0 | N36: 0 | O36: 0 | P36: 0 | Q36: 0 | R36: 0 | S36: =IF($C36="","",ROUND($J36*2.2,0)) -> 0 | T36: 0 | U36: 0 | V36: 2000 | W36: 0 | X36: 2 platforms | Y36: 0.5 | Z36: 1 | AA36: Danny Sørensen | AB36: https://x.com/zonic | AC36: Instagram/Zonic | AD36: https://www.twitch.tv/zonic | AH36: Facebook/Zonic | AK36: 30/07/1986
B37: =IF($C37="","",COUNTA($C$5:C37)) -> 33 | C37: clockzi | D37: Player | E37: Counterstrike2 | F37: Falcons Force | G37: Danish | H37: 1 | I37: Tier 3 | J37: 11000 | K37: 4600 | L37: =IF($C37="","",ROUND($J37*0.17,0)) -> 1870 | M37: 8600 | N37: 3500 | O37: 2200 | P37: 2200 | Q37: 15950 | R37: 7150 | S37: =IF($C37="","",ROUND($J37*2.2,0)) -> 24200 | T37: 3850 | U37: 3300 | V37: 2000 | W37: 2400 | X37: 1 platform | Y37: 0.75 | Z37: 1 | AA37: Oskar Led Blæsbjerg | AB37: https://x.com/flcclockzi | AK37: 21/04/2011 | AL37: Rifler
B38: =IF($C38="","",COUNTA($C$5:C38)) -> 34 | C38: grecu | D38: Player | E38: Counterstrike2 | F38: Falcons Force | G38: Romanian | H38: 2 | I38: Tier 2 | J38: 5200 | K38: 2200 | L38: =IF($C38="","",ROUND($J38*0.17,0)) -> 884 | M38: 4050 | N38: 1650 | O38: 1050 | P38: 1050 | Q38: 7550 | R38: 3400 | S38: =IF($C38="","",ROUND($J38*2.2,0)) -> 11440 | T38: 1800 | U38: 1550 | V38: 950 | W38: 2400 | X38: 2 platforms | Y38: 0.75 | Z38: 1 | AA38: Andrei Grecu | AB38: https://x.com/grecuflc | AD38: https://www.twitch.tv/gbcgrecu | AK38: 15/11/2007 | AL38: AWPer
B39: =IF($C39="","",COUNTA($C$5:C39)) -> 35 | C39: VENO | D39: Player | E39: Counterstrike2 | F39: Falcons Force | G39: Serbian | H39: 3 | I39: Tier 2 | J39: 12100 | K39: 5100 | L39: =IF($C39="","",ROUND($J39*0.17,0)) -> 2057 | M39: 9450 | N39: 3850 | O39: 2400 | P39: 2400 | Q39: 17550 | R39: 7850 | S39: =IF($C39="","",ROUND($J39*2.2,0)) -> 26620 | T39: 4250 | U39: 3650 | V39: 2200 | W39: 2400 | X39: 3 platforms | Y39: 0.75 | Z39: 1 | AA39: Vladimir Stanković | AB39: https://x.com/venocs2 | AD39: https://www.twitch.tv/venocs2 | AE39: https://www.youtube.com/@venocs2 | AK39: 30/04/2007 | AL39: Rifler
B40: =IF($C40="","",COUNTA($C$5:C40)) -> 36 | C40: NaToSaphiX | D40: Head Coach | E40: Counterstrike2 | F40: Falcons Force | G40: Danish | H40: 5 | I40: Tier 2 | J40: 11000 | K40: 4600 | L40: =IF($C40="","",ROUND($J40*0.17,0)) -> 1870 | M40: 8600 | N40: 3500 | O40: 2200 | P40: 0 | Q40: 15950 | R40: 7150 | S40: =IF($C40="","",ROUND($J40*2.2,0)) -> 24200 | T40: 3850 | U40: 3300 | V40: 2000 | W40: 0 | X40: 5 platforms | Y40: 0.2 | Z40: 1 | AA40: Niels Christian Sillassen | AB40: https://x.com/NaToSaphiX | AC40: https://www.instagram.com/natosaphix | AD40: https://www.twitch.tv/natosaphix | AE40: https://www.youtube.com/NaToSaphiX | AK40: 17/08/1996
B41: =IF($C41="","",COUNTA($C$5:C41)) -> 37 | C41: Neoskai | D41: Manager | E41: Counterstrike2 | F41: Falcons Force | G41: French | H41: 2 | I41: Tier 2 | J41: 0 | K41: 0 | L41: =IF($C41="","",ROUND($J41*0.17,0)) -> 0 | M41: 0 | N41: 0 | O41: 0 | P41: 0 | Q41: 0 | R41: 0 | S41: =IF($C41="","",ROUND($J41*2.2,0)) -> 0 | T41: 0 | U41: 0 | V41: 1200 | W41: 0 | X41: 2 platforms | Y41: 0.2 | Z41: 1 | AA41: Loïc Potages | AB41: https://x.com/Neoskai | AC41: https://www.instagram.com/neoskai/ | AK41: 16/06/1994
B42: =IF($C42="","",COUNTA($C$5:C42)) -> 38 | C42: Nucleonz | D42: Player | E42: Counterstrike2 | F42: Falcons Force | G42: North Macedonian | H42: 1 | I42: Tier 3 | J42: 8750 | K42: 3000 | L42: =IF($C42="","",ROUND($J42*0.17,0)) -> 1488 | M42: 6000 | N42: 2500 | O42: 1200 | P42: 1200 | Q42: 9000 | R42: 4050 | S42: =IF($C42="","",ROUND($J42*2.2,0)) -> 19250 | T42: 2200 | U42: 1925 | V42: 1155 | W42: 2400 | X42: 1 platform | Y42: 0.75 | Z42: 1 | AA42: Matej Trajkoski | AB42: https://x.com/NucleonZz | AK42: 39722 | AL42: Rifler
B43: =IF($C43="","",COUNTA($C$5:C43)) -> 39 | C43: Skiter | D43: Player | E43: Dota2 | F43: Dota2 | G43: Slovakia | H43: 2 | I43: Tier 2 | J43: 5200 | K43: 2200 | L43: =IF($C43="","",ROUND($J43*0.17,0)) -> 884 | M43: 4050 | N43: 1650 | O43: 1050 | P43: 1050 | Q43: 7550 | R43: 3400 | S43: =IF($C43="","",ROUND($J43*2.2,0)) -> 11440 | T43: 1800 | U43: 1550 | V43: 950 | W43: 2400 | X43: 2 platforms | Y43: 0.75 | Z43: 1 | AA43: Oliver Lepko | AB43: https://x.com/skiter | AC43: Instagram/Skiter | AH43: https://www.facebook.com/SkiterDota | AK43: 36138
B44: =IF($C44="","",COUNTA($C$5:C44)) -> 40 | C44: Malr1ne | D44: Player | E44: Dota2 | F44: Dota2 | G44: Russian | H44: 2 | I44: Tier 2 | J44: 11000 | K44: 4600 | L44: =IF($C44="","",ROUND($J44*0.17,0)) -> 1870 | M44: 8600 | N44: 3500 | O44: 2200 | P44: 2200 | Q44: 15950 | R44: 7150 | S44: =IF($C44="","",ROUND($J44*2.2,0)) -> 24200 | T44: 3850 | U44: 3300 | V44: 2000 | W44: 2400 | X44: 2 platforms | Y44: 0.75 | Z44: 1 | AA44: Stanislav Potorak | AB44: https://x.com/Malr1ne_ | AC44: Instagram/Malr1ne | AD44: https://www.twitch.tv/malr1ne_dota | AK44: 17/09/2004
B45: =IF($C45="","",COUNTA($C$5:C45)) -> 41 | C45: ATF | D45: Player | E45: Dota2 | F45: Dota2 | G45: Jordanian | H45: 2 | I45: Tier 2 | J45: 11000 | K45: 4600 | L45: =IF($C45="","",ROUND($J45*0.17,0)) -> 1870 | M45: 8600 | N45: 3500 | O45: 2200 | P45: 2200 | Q45: 15950 | R45: 7150 | S45: =IF($C45="","",ROUND($J45*2.2,0)) -> 24200 | T45: 3850 | U45: 3300 | V45: 2000 | W45: 2400 | X45: 2 platforms | Y45: 0.75 | Z45: 1 | AA45: Ammar Al-Assaf | AB45: https://x.com/AmmarAlassaf6 | AC45: Instagram/Ammar | AD45: https://www.twitch.tv/ammar_the_f | AK45: 38416
B46: =IF($C46="","",COUNTA($C$5:C46)) -> 42 | C46: Cr1t- | D46: Player | E46: Dota2 | F46: Dota2 | G46: Danish | H46: 3 | I46: Tier 1 | J46: 12100 | K46: 5100 | L46: =IF($C46="","",ROUND($J46*0.17,0)) -> 2057 | M46: 9450 | N46: 3850 | O46: 2400 | P46: 2400 | Q46: 17550 | R46: 7850 | S46: =IF($C46="","",ROUND($J46*2.2,0)) -> 26620 | T46: 4250 | U46: 3650 | V46: 2200 | W46: 2400 | X46: 3 platforms | Y46: 0.75 | Z46: 1 | AA46: Andreas Nielsen | AB46: https://x.com/Cr1tdota | AC46: Instagram/Cr1t | AD46: https://www.twitch.tv/cr1tdota | AE46: YT/Cr1t | AH46: https://www.facebook.com/Cr1tdota | AK46: 13/07/1996
B47: =IF($C47="","",COUNTA($C$5:C47)) -> 43 | C47: Sneyking | D47: Player | E47: Dota2 | F47: Dota2 | G47: American / Chinese | H47: 2 | I47: Tier 2 | J47: 20700 | K47: 8700 | L47: =IF($C47="","",ROUND($J47*0.17,0)) -> 3519 | M47: 16150 | N47: 6600 | O47: 4150 | P47: 4150 | Q47: 30000 | R47: 13450 | S47: =IF($C47="","",ROUND($J47*2.2,0)) -> 45540 | T47: 7250 | U47: 6200 | V47: 3750 | W47: 2400 | X47: 2 platforms | Y47: 0.75 | Z47: 1 | AA47: Jingjun Wu | AB47: https://x.com/SneykingGaming | AD47: https://www.twitch.tv/sneykingdota | AK47: 34763
B48: =IF($C48="","",COUNTA($C$5:C48)) -> 44 | C48: Aui_2000 | D48: Head Coach | E48: Dota2 | F48: Dota2 | G48: Canada | H48: 2 | I48: Tier 2 | J48: 11000 | K48: 4600 | L48: =IF($C48="","",ROUND($J48*0.17,0)) -> 1870 | M48: 8600 | N48: 3500 | O48: 2200 | P48: 0 | Q48: 15950 | R48: 7150 | S48: =IF($C48="","",ROUND($J48*2.2,0)) -> 24200 | T48: 3850 | U48: 3300 | V48: 2000 | W48: 0 | X48: 2 platforms | Y48: 0.75 | Z48: 1 | AA48: Kurtis Ling | AB48: https://x.com/Aui_2000 | AD48: https://www.twitch.tv/aui_2000 | AE48: YT/Aui_2000 | AK48: 33644
B49: =IF($C49="","",COUNTA($C$5:C49)) -> 45 | C49: AfromOush | D49: Manager | E49: Dota2 | F49: Dota2 | G49: Jordanian | H49: 3 | I49: Tier 2 | J49: 0 | K49: 0 | L49: =IF($C49="","",ROUND($J49*0.17,0)) -> 0 | M49: 0 | N49: 0 | O49: 0 | P49: 0 | Q49: 0 | R49: 0 | S49: =IF($C49="","",ROUND($J49*2.2,0)) -> 0 | T49: 0 | U49: 0 | V49: 1200 | W49: 0 | X49: 3 platforms | Y49: 0.5 | Z49: 1 | AA49: Mohammad Abu Al Eis | AB49: https://x.com/AfrOmoush | AD49: https://www.twitch.tv/afromoush | AH49: https://www.facebook.com/RealAfrOmoush | AK49: 35228
B50: =IF($C50="","",COUNTA($C$5:C50)) -> 46 | C50: Bonkers | D50: Analyst | E50: Dota2 | F50: Dota2 | G50: British | H50: 1 | I50: Tier 3 | J50: 0 | K50: 0 | L50: =IF($C50="","",ROUND($J50*0.17,0)) -> 0 | M50: 0 | N50: 0 | O50: 0 | P50: 0 | Q50: 0 | R50: 0 | S50: =IF($C50="","",ROUND($J50*2.2,0)) -> 0 | T50: 0 | U50: 0 | V50: 600 | W50: 0 | X50: 1 platform | Y50: 0.5 | Z50: 1 | AA50: Allen Cook | AB50: https://x.com/thisisallencook | AK50: 15/02/1980
B51: =IF($C51="","",COUNTA($C$5:C51)) -> 47 | C51: GoatMoh | D51: Player | E51: EAFC25 | F51: EA Sport FC | G51: Saudi Arabia | H51: 2 | I51: Tier 2 | J51: 11250 | K51: 4500 | L51: =IF($C51="","",ROUND($J51*0.17,0)) -> 1913 | M51: 8000 | N51: 3500 | O51: 2000 | P51: 2000 | Q51: 13500 | R51: 6075 | S51: =IF($C51="","",ROUND($J51*2.2,0)) -> 24750 | T51: 4638 | U51: 4063 | V51: 2438 | W51: 2400 | X51: 2 platforms | Y51: 0.3 | Z51: 1 | AA51: Mohammed Alarfaj | AB51: https://x.com/GoatMoh_ | AD51: https://www.twitch.tv/goatmoh | AK51: 15/02/2000
B52: =IF($C52="","",COUNTA($C$5:C52)) -> 48 | C52: Hafez | D52: Coach | E52: EAFC25 | F52: EA Sport FC | G52: Saudi Arabia | H52: 1 | I52: Tier 3 | J52: 12100 | K52: 5100 | L52: =IF($C52="","",ROUND($J52*0.17,0)) -> 2057 | M52: 9450 | N52: 3850 | O52: 2400 | P52: 0 | Q52: 17550 | R52: 7850 | S52: =IF($C52="","",ROUND($J52*2.2,0)) -> 26620 | T52: 4250 | U52: 3650 | V52: 2200 | W52: 0 | X52: 1 platform | Y52: 0.3 | Z52: 1 | AA52: Mohammad Hafiz | AB52: https://x.com/_Hafez10 | AK52: 29/12/1997
B53: =IF($C53="","",COUNTA($C$5:C53)) -> 49 | C53: Javivillar7 | D53: Coach | E53: EAFC25 | F53: EA Sport FC | G53: Spanish | H53: 4 | I53: Tier 1 | J53: 0 | K53: 0 | L53: =IF($C53="","",ROUND($J53*0.17,0)) -> 0 | M53: 0 | N53: 0 | O53: 0 | P53: 0 | Q53: 0 | R53: 0 | S53: =IF($C53="","",ROUND($J53*2.2,0)) -> 0 | T53: 0 | U53: 0 | V53: 2000 | W53: 0 | X53: 4 platforms | Y53: 0.3 | Z53: 1 | AA53: Javier Villar Gómez | AB53: https://x.com/Javivillar7 | AC53: Instagram/Javivillar7 | AD53: https://www.twitch.tv/javivillar7/ | AE53: https://www.youtube.com/@javivillar7 | AF53: https://www.tiktok.com/@javivillar7?lang=en | AK53: 31/12/2002
B54: =IF($C54="","",COUNTA($C$5:C54)) -> 50 | C54: Msdossary | D54: Player | E54: EAFC25 | F54: EA Sport FC | G54: Saudi Arabia | H54: 1 | I54: Tier 2 | J54: 11250 | K54: 4500 | L54: =IF($C54="","",ROUND($J54*0.17,0)) -> 1913 | M54: 8000 | N54: 3500 | O54: 2000 | P54: 2000 | Q54: 13500 | R54: 6075 | S54: =IF($C54="","",ROUND($J54*2.2,0)) -> 24750 | T54: 4638 | U54: 4063 | V54: 2438 | W54: 2400 | X54: 1 platform | Y54: 0.3 | Z54: 1 | AA54: Mossad Aldossary | AB54: https://x.com/msdossary7 | AC54: Instagram/Msdossary | AE54: YT/Msdossary7 | AK54: 20/03/2000
B55: =IF($C55="","",COUNTA($C$5:C55)) -> 51 | C55: Vejrgang | D55: Player | E55: EAFC25 | F55: EA Sport FC | G55: Danish | H55: 4 | I55: Tier 1 | J55: 12100 | K55: 5100 | L55: =IF($C55="","",ROUND($J55*0.17,0)) -> 2057 | M55: 9450 | N55: 3850 | O55: 2400 | P55: 2400 | Q55: 17550 | R55: 7850 | S55: =IF($C55="","",ROUND($J55*2.2,0)) -> 26620 | T55: 4250 | U55: 3650 | V55: 2200 | W55: 2400 | X55: 4 platforms | Y55: 0.3 | Z55: 1 | AA55: Anders Vejrgang | AB55: https://twitter.com/FLC_Vejrgang | AC55: https://www.instagram.com/rblz_vejrgang | AD55: https://www.twitch.tv/anders_vejrgang | AE55: https://www.youtube.com/AndersVejrgangofficial | AK55: 25/01/2006
B56: =IF($C56="","",COUNTA($C$5:C56)) -> 52 | C56: A9 | D56: Manager | E56: EAFC25 | F56: EA Sport FC | G56: Saudi Arabia | H56: 0 | I56: Tier 3 | J56: 20700 | K56: 8700 | L56: =IF($C56="","",ROUND($J56*0.17,0)) -> 3519 | M56: 16150 | N56: 6600 | O56: 4150 | P56: 0 | Q56: 30000 | R56: 13450 | S56: =IF($C56="","",ROUND($J56*2.2,0)) -> 45540 | T56: 7250 | U56: 6200 | V56: 3750 | W56: 0 | X56: 0 platforms | Y56: 0.3 | Z56: 1 | AA56: Aseel Aldokheel | AK56: 35343
B57: =IF($C57="","",COUNTA($C$5:C57)) -> 53 | C57: Kiimo7 | D57: Player | E57: EAFC25 | F57: EA Sport FC | G57: Saudi Arabia | H57: 2 | I57: Tier 2 | J57: 11250 | K57: 4500 | L57: =IF($C57="","",ROUND($J57*0.17,0)) -> 1913 | M57: 8000 | N57: 3500 | O57: 2000 | P57: 2000 | Q57: 13500 | R57: 6075 | S57: =IF($C57="","",ROUND($J57*2.2,0)) -> 24750 | T57: 4638 | U57: 4063 | V57: 2438 | W57: 2400 | X57: 2 platforms | Y57: 0.3 | Z57: 1 | AA57: Abdulkareem Bamogaddam | AB57: https://x.com/kiimo__1 | AC57: https://www.instagram.com/kreemvv/ | AK57: 39757
B58: =IF($C58="","",COUNTA($C$5:C58)) -> 54 | C58: Rashed | D58: Manager | E58: Fortnite | F58: Fortnite | G58: Saudi | H58: 0 | I58: Tier 3 | J58: 12100 | K58: 5100 | L58: =IF($C58="","",ROUND($J58*0.17,0)) -> 2057 | M58: 9450 | N58: 3850 | O58: 2400 | P58: 0 | Q58: 17550 | R58: 7850 | S58: =IF($C58="","",ROUND($J58*2.2,0)) -> 26620 | T58: 4250 | U58: 3650 | V58: 2200 | W58: 0 | X58: 0 platforms | Y58: 0.3 | Z58: 1 | AA58: Rashed Aldmaikhi
B59: =IF($C59="","",COUNTA($C$5:C59)) -> 55 | C59: Abu Omar | D59: Player | E59: Fatal Fury | F59: Fatal Fury | G59: Saudi | H59: 1 | I59: Tier 3 | J59: 8750 | K59: 3000 | L59: =IF($C59="","",ROUND($J59*0.17,0)) -> 1488 | M59: 6000 | N59: 2500 | O59: 1200 | P59: 1200 | Q59: 9000 | R59: 4050 | S59: =IF($C59="","",ROUND($J59*2.2,0)) -> 19250 | T59: 2200 | U59: 1925 | V59: 1155 | W59: 2400 | X59: 1 platform | Y59: 0.3 | Z59: 1 | AA59: Wesam Alghamdi | AB59: https://x.com/wess21111?lang=en | AK59: 30/05/1987
B60: =IF($C60="","",COUNTA($C$5:C60)) -> 56 | C60: E.T. | D60: Player | E60: Fatal Fury | F60: Fatal Fury | G60: Taiwan | H60: 3 | I60: Tier 2 | J60: 5700 | K60: 2400 | L60: =IF($C60="","",ROUND($J60*0.17,0)) -> 969 | M60: 4450 | N60: 1850 | O60: 1150 | P60: 1150 | Q60: 8300 | R60: 3700 | S60: =IF($C60="","",ROUND($J60*2.2,0)) -> 12540 | T60: 2000 | U60: 1700 | V60: 1050 | W60: 2400 | X60: 3 platforms | Y60: 0.1 | Z60: 1 | AA60: Lin Chia-hung | AB60: https://x.com/et1120 | AC60: https://www.instagram.com/dbj_et/# | AH60: https://www.facebook.com/Taiwan.1.ET | AK60: 20/11/1984
B61: =IF($C61="","",COUNTA($C$5:C61)) -> 57 | C61: Ghirlanda | D61: Manager | E61: Fatal Fury | F61: Fatal Fury | G61: Italian | H61: 1 | I61: Tier 3 | J61: 11000 | K61: 4600 | L61: =IF($C61="","",ROUND($J61*0.17,0)) -> 1870 | M61: 8600 | N61: 3500 | O61: 2200 | P61: 0 | Q61: 15950 | R61: 7150 | S61: =IF($C61="","",ROUND($J61*2.2,0)) -> 24200 | T61: 3850 | U61: 3300 | V61: 2000 | W61: 0 | X61: 1 platform | Y61: 0.5 | Z61: 1 | AA61: Joshua Bianchi | AB61: https://x.com/ghirlandatekken | AK61: 26/02/1992
B62: =IF($C62="","",COUNTA($C$5:C62)) -> 58 | C62: Kindevu | D62: Player | E62: Fatal Fury | F62: Fatal Fury | G62: Japanese | H62: 3 | I62: Tier 2 | J62: 11250 | K62: 4500 | L62: =IF($C62="","",ROUND($J62*0.17,0)) -> 1913 | M62: 8000 | N62: 3500 | O62: 2000 | P62: 2000 | Q62: 13500 | R62: 6075 | S62: =IF($C62="","",ROUND($J62*2.2,0)) -> 24750 | T62: 4638 | U62: 4063 | V62: 2438 | W62: 2400 | X62: 3 platforms | Y62: 0.75 | Z62: 1 | AA62: Yosuke Ito | AB62: https://x.com/kindevu | AD62: https://www.twitch.tv/kindevu0827 | AE62: https://www.youtube.com/channel/UCQevn7lvmrpl3ElLd58YsNQ | AK62: 27/08/1984
B63: =IF($C63="","",COUNTA($C$5:C63)) -> 59 | C63: mok | D63: Player | E63: Fatal Fury | F63: Fatal Fury | G63: Japan | H63: 2 | I63: Tier 2 | J63: 11000 | K63: 4600 | L63: =IF($C63="","",ROUND($J63*0.17,0)) -> 1870 | M63: 8600 | N63: 3500 | O63: 2200 | P63: 2200 | Q63: 15950 | R63: 7150 | S63: =IF($C63="","",ROUND($J63*2.2,0)) -> 24200 | T63: 3850 | U63: 3300 | V63: 2000 | W63: 2400 | X63: 2 platforms | Y63: 0.75 | Z63: 1 | AA63: Hiroaki Hashizume | AB63: https://twitter.com/andytheworld320 | AE63: https://www.youtube.com/channel/UC-Ksra-atsz4eW5i9ZDAa8A | AK63: 20/03/1985
B64: =IF($C64="","",COUNTA($C$5:C64)) -> 60 | C64: Sai | D64: Player | E64: Fatal Fury | F64: Fatal Fury | G64: Saudi | H64: 1 | I64: Tier 3 | J64: 11000 | K64: 4600 | L64: =IF($C64="","",ROUND($J64*0.17,0)) -> 1870 | M64: 8600 | N64: 3500 | O64: 2200 | P64: 2200 | Q64: 15950 | R64: 7150 | S64: =IF($C64="","",ROUND($J64*2.2,0)) -> 24200 | T64: 3850 | U64: 3300 | V64: 2000 | W64: 2400 | X64: 1 platform | Y64: 0.3 | Z64: 1 | AA64: Ali Abdullah Alduhaysh | AB64: https://x.com/Zenga83 | AK64: 26/11/1983
B65: =IF($C65="","",COUNTA($C$5:C65)) -> 61 | C65: Shadow X | D65: Player | E65: Fatal Fury | F65: Fatal Fury | G65: Mexican | H65: 2 | I65: Tier 2 | J65: 5700 | K65: 2400 | L65: =IF($C65="","",ROUND($J65*0.17,0)) -> 969 | M65: 4450 | N65: 1850 | O65: 1150 | P65: 1150 | Q65: 8300 | R65: 3700 | S65: =IF($C65="","",ROUND($J65*2.2,0)) -> 12540 | T65: 2000 | U65: 1700 | V65: 1050 | W65: 2400 | X65: 2 platforms | Y65: 0.75 | Z65: 1 | AA65: Abraham Sanchez | AB65: https://x.com/ShadowX_FGC | AD65: https://www.twitch.tv/ChonFx | AK65: 14/03/1982
B66: =IF($C66="","",COUNTA($C$5:C66)) -> 62 | C66: Tamago | D66: Player | E66: Fatal Fury | F66: Fatal Fury | G66: Mexican | H66: 1 | I66: Tier 3 | J66: 11000 | K66: 4600 | L66: =IF($C66="","",ROUND($J66*0.17,0)) -> 1870 | M66: 8600 | N66: 3500 | O66: 2200 | P66: 2200 | Q66: 15950 | R66: 7150 | S66: =IF($C66="","",ROUND($J66*2.2,0)) -> 24200 | T66: 3850 | U66: 3300 | V66: 2000 | W66: 2400 | X66: 1 platform | Y66: 0.75 | Z66: 1 | AA66: Ángel Chong | AB66: https://x.com/ChonFx | AK66: 31480
B67: =IF($C67="","",COUNTA($C$5:C67)) -> 63 | C67: Xyzzy | D67: Player | E67: Fatal Fury | F67: Fatal Fury | G67: South Korean | H67: 2 | I67: Tier 2 | J67: 5200 | K67: 2200 | L67: =IF($C67="","",ROUND($J67*0.17,0)) -> 884 | M67: 4050 | N67: 1650 | O67: 1050 | P67: 1050 | Q67: 7550 | R67: 3400 | S67: =IF($C67="","",ROUND($J67*2.2,0)) -> 11440 | T67: 1800 | U67: 1550 | V67: 950 | W67: 2400 | X67: 2 platforms | Y67: 0.75 | Z67: 1 | AA67: Lee Hanbyul | AB67: https://x.com/xyzzylshift | AD67: https://www.twitch.tv/xyzzyshift | AK67: 32517
B68: =IF($C68="","",COUNTA($C$5:C68)) -> 64 | C68: Xiaohai | D68: Player | E68: Fatal Fury | F68: Fatal Fury | G68: China | H68: 1 | I68: Tier 3 | J68: 11000 | K68: 4600 | L68: =IF($C68="","",ROUND($J68*0.17,0)) -> 1870 | M68: 8600 | N68: 3500 | O68: 2200 | P68: 2200 | Q68: 15950 | R68: 7150 | S68: =IF($C68="","",ROUND($J68*2.2,0)) -> 24200 | T68: 3850 | U68: 3300 | V68: 2000 | W68: 2400 | X68: 1 platform | Y68: 0.1 | Z68: 1 | AA68: Zeng Zhuojun | AB68: https://x.com/Xiaohai_ | AK68: 26/04/1989
B69: =IF($C69="","",COUNTA($C$5:C69)) -> 65 | C69: Peterbot | D69: Player | E69: Fortnite | F69: Fortnite | G69: American/Hungarian | H69: 3 | I69: Tier 2 | J69: 11000 | K69: 4600 | L69: =IF($C69="","",ROUND($J69*0.17,0)) -> 1870 | M69: 8600 | N69: 3500 | O69: 2200 | P69: 2200 | Q69: 15950 | R69: 7150 | S69: =IF($C69="","",ROUND($J69*2.2,0)) -> 24200 | T69: 3850 | U69: 3300 | V69: 2000 | W69: 2400 | X69: 3 platforms | Y69: 0.5 | Z69: 1 | AA69: Peter Kata | AB69: https://x.com/PeterbotFN | AD69: https://www.twitch.tv/peterbot | AE69: https://www.youtube.com/channel/UC_RGYvZpoesD8yX-o677-xw | AK69: 20/06/2007
B70: =IF($C70="","",COUNTA($C$5:C70)) -> 66 | C70: FHD | D70: Player | E70: Fortnite | F70: Fortnite | G70: Saudi | H70: 3 | I70: Tier 2 | J70: 11000 | K70: 4600 | L70: =IF($C70="","",ROUND($J70*0.17,0)) -> 1870 | M70: 8600 | N70: 3500 | O70: 2200 | P70: 2200 | Q70: 15950 | R70: 7150 | S70: =IF($C70="","",ROUND($J70*2.2,0)) -> 24200 | T70: 3850 | U70: 3300 | V70: 2000 | W70: 2400 | X70: 3 platforms | Y70: 0.3 | Z70: 1 | AA70: Fahad Almutairi | AB70: https://x.com/Fahadclipz | AC70: https://www.instagram.com/fahadclipz/?hl=en | AD70: https://www.twitch.tv/fahadfn | AK70: 31/03/2004
B71: =IF($C71="","",COUNTA($C$5:C71)) -> 67 | C71: Gntl | D71: Player | E71: Call of Duty Black Ops 7 | F71: FaZe Falcons | G71: Saudi | H71: 4 | I71: Tier 3 | J71: 12100 | K71: 5100 | L71: =IF($C71="","",ROUND($J71*0.17,0)) -> 2057 | M71: 9450 | N71: 3850 | O71: 2400 | P71: 2400 | Q71: 17550 | R71: 7850 | S71: =IF($C71="","",ROUND($J71*2.2,0)) -> 26620 | T71: 4250 | U71: 3650 | V71: 2200 | W71: 2400 | X71: 4 platforms | Y71: 0.3 | Z71: 1 | AA71: Abdullah Albaqami | AB71: https://x.com/g1ntl | AC71: https://www.instagram.com/accounts/login/?next=%2Fg1ntl&source=omni_redirect | AD71: https://www.twitch.tv/GntL | AE71: https://www.youtube.com/c/g1ntl | AK71: 24/09/2002
B72: =IF($C72="","",COUNTA($C$5:C72)) -> 68 | C72: NM7 | D72: Player | E72: Fortnite | F72: Fortnite | G72: Saudi | H72: 4 | I72: Tier 3 | J72: 5700 | K72: 2400 | L72: =IF($C72="","",ROUND($J72*0.17,0)) -> 969 | M72: 4450 | N72: 1850 | O72: 1150 | P72: 1150 | Q72: 8300 | R72: 3700 | S72: =IF($C72="","",ROUND($J72*2.2,0)) -> 12540 | T72: 2000 | U72: 1700 | V72: 1050 | W72: 2400 | X72: 4 platforms | Y72: 0.3 | Z72: 1 | AA72: Nawaf Alharthi | AB72: https://x.com/iNm7x | AC72: https://www.instagram.com/accounts/login/?next=%2Finm7x&source=omni_redirect | AD72: https://www.twitch.tv/iiNm7x | AE72: https://www.youtube.com/c/iNm7x | AK72: 37502
B73: =IF($C73="","",COUNTA($C$5:C73)) -> 69 | C73: Spy | D73: Player | E73: Fortnite | F73: Fortnite | G73: Saudi | H73: 4 | I73: Tier 3 | J73: 5700 | K73: 2400 | L73: =IF($C73="","",ROUND($J73*0.17,0)) -> 969 | M73: 4450 | N73: 1850 | O73: 1150 | P73: 1150 | Q73: 8300 | R73: 3700 | S73: =IF($C73="","",ROUND($J73*2.2,0)) -> 12540 | T73: 2000 | U73: 1700 | V73: 1050 | W73: 2400 | X73: 4 platforms | Y73: 0.3 | Z73: 1 | AA73: Osama Almasad | AB73: https://x.com/spyerfrog | AC73: https://www.instagram.com/accounts/login/?next=%2Fspyerfrog&source=omni_redirect | AD73: https://www.twitch.tv/spyerfrog | AE73: https://www.youtube.com/channel/UCl9pp6XYMcjyVESzYD8myQg | AK73: 26/02/2002
B74: =IF($C74="","",COUNTA($C$5:C74)) -> 70 | C74: Yonx | D74: Player | E74: Fortnite | F74: Fortnite | G74: Saudi | H74: 3 | I74: Tier 3 | J74: 5700 | K74: 2400 | L74: =IF($C74="","",ROUND($J74*0.17,0)) -> 969 | M74: 4450 | N74: 1850 | O74: 1150 | P74: 1150 | Q74: 8300 | R74: 3700 | S74: =IF($C74="","",ROUND($J74*2.2,0)) -> 12540 | T74: 2000 | U74: 1700 | V74: 1050 | W74: 2400 | X74: 3 platforms | Y74: 0.3 | Z74: 1 | AA74: Faisal Almusharraf | AB74: https://x.com/YonxFN | AD74: https://www.twitch.tv/YonxFN | AE74: https://www.youtube.com/channel/UCSKgsqUfo7vA4BuBvtf6vwg | AK74: 38295
B75: =IF($C75="","",COUNTA($C$5:C75)) -> 71 | C75: Matteo | D75: Manager | E75: Fortnite | F75: Fortnite | G75: French | H75: 0 | I75: Tier 3 | J75: 0 | K75: 0 | L75: =IF($C75="","",ROUND($J75*0.17,0)) -> 0 | M75: 0 | N75: 0 | O75: 0 | P75: 0 | Q75: 0 | R75: 0 | S75: =IF($C75="","",ROUND($J75*2.2,0)) -> 0 | T75: 0 | U75: 0 | V75: 600 | W75: 0 | X75: 0 platforms | Y75: 0.3 | Z75: 1 | AA75: Matteo Paganin
B76: =IF($C76="","",COUNTA($C$5:C76)) -> 72 | C76: Conan | D76: Head Coach | E76: Free Fire | F76: Team Falcons | G76: Thailand | H76: 2 | I76: Tier 2 | J76: 0 | K76: 0 | L76: =IF($C76="","",ROUND($J76*0.17,0)) -> 0 | M76: 0 | N76: 0 | O76: 0 | P76: 0 | Q76: 0 | R76: 0 | S76: =IF($C76="","",ROUND($J76*2.2,0)) -> 0 | T76: 0 | U76: 0 | V76: 1200 | W76: 0 | X76: 2 platforms | Y76: 0.3 | Z76: 1 | AA76: Tana Kamruang | AC76: https://www.instagram.com/thana_kamruang/ | AH76: https://facebook.com/profile.php?id=100006004232176 | AK76: 34003
B77: =IF($C77="","",COUNTA($C$5:C77)) -> 73 | C77: KERORO | D77: Player | E77: Free Fire | F77: Team Falcons | G77: Thailand | H77: 2 | I77: Tier 2 | J77: 11250 | K77: 4500 | L77: =IF($C77="","",ROUND($J77*0.17,0)) -> 1913 | M77: 8000 | N77: 3500 | O77: 2000 | P77: 2000 | Q77: 13500 | R77: 6075 | S77: =IF($C77="","",ROUND($J77*2.2,0)) -> 24750 | T77: 4638 | U77: 4063 | V77: 2438 | W77: 2400 | X77: 2 platforms | Y77: 0.3 | Z77: 1 | AA77: Natthaphong Phuangpriang | AC77: https://www.instagram.com/keroro_god | AH77: https://facebook.com/profile.php?id=100014997245027 | AK77: 13/01/2006
B78: =IF($C78="","",COUNTA($C$5:C78)) -> 74 | C78: LIMIT | D78: Player | E78: Free Fire | F78: Team Falcons | G78: Thailand | H78: 3 | I78: Tier 2 | J78: 11000 | K78: 4600 | L78: =IF($C78="","",ROUND($J78*0.17,0)) -> 1870 | M78: 8600 | N78: 3500 | O78: 2200 | P78: 2200 | Q78: 15950 | R78: 7150 | S78: =IF($C78="","",ROUND($J78*2.2,0)) -> 24200 | T78: 3850 | U78: 3300 | V78: 2000 | W78: 2400 | X78: 3 platforms | Y78: 0.3 | Z78: 1 | AA78: Rachata Wanaphurksasilp | AC78: https://www.instagram.com/limit_juy | AF78: https://tiktok.com/@limitxstep8 | AH78: https://facebook.com/profile.php?id=100015743748929 | AK78: 20/02/2006
B79: =IF($C79="","",COUNTA($C$5:C79)) -> 75 | C79: ONEMORE | D79: Player | E79: Free Fire | F79: Team Falcons | G79: Thailand | H79: 3 | I79: Tier 2 | J79: 11000 | K79: 4600 | L79: =IF($C79="","",ROUND($J79*0.17,0)) -> 1870 | M79: 8600 | N79: 3500 | O79: 2200 | P79: 2200 | Q79: 15950 | R79: 7150 | S79: =IF($C79="","",ROUND($J79*2.2,0)) -> 24200 | T79: 3850 | U79: 3300 | V79: 2000 | W79: 2400 | X79: 3 platforms | Y79: 0.3 | Z79: 1 | AA79: Rattapoom Sunthalunai | AC79: https://www.instagram.com/poomgohome_ | AF79: https://tiktok.com/@pm.rt | AH79: https://facebook.com/ratta.poom.790 | AK79: 38600
B80: =IF($C80="","",COUNTA($C$5:C80)) -> 76 | C80: ONFIRE | D80: Player | E80: Free Fire | F80: Team Falcons | G80: Thailand | H80: 3 | I80: Tier 2 | J80: 11000 | K80: 4600 | L80: =IF($C80="","",ROUND($J80*0.17,0)) -> 1870 | M80: 8600 | N80: 3500 | O80: 2200 | P80: 2200 | Q80: 15950 | R80: 7150 | S80: =IF($C80="","",ROUND($J80*2.2,0)) -> 24200 | T80: 3850 | U80: 3300 | V80: 2000 | W80: 2400 | X80: 3 platforms | Y80: 0.3 | Z80: 1 | AA80: Phulipat Yosit | AC80: https://www.instagram.com/onfirebaby__ | AF80: https://tiktok.com/@onfireeieii | AH80: https://facebook.com/profile.php?id=100072006039523 | AK80: 27/09/2005
B81: =IF($C81="","",COUNTA($C$5:C81)) -> 77 | C81: Penna | D81: Player | E81: Free Fire | F81: Team Falcons | G81: Thailand | H81: 2 | I81: Tier 2 | J81: 11000 | K81: 4600 | L81: =IF($C81="","",ROUND($J81*0.17,0)) -> 1870 | M81: 8600 | N81: 3500 | O81: 2200 | P81: 2200 | Q81: 15950 | R81: 7150 | S81: =IF($C81="","",ROUND($J81*2.2,0)) -> 24200 | T81: 3850 | U81: 3300 | V81: 2000 | W81: 2400 | X81: 2 platforms | Y81: 0.3 | Z81: 1 | AA81: Natthawut Srinaknil | AC81: https://www.instagram.com/pee_2006._?igsh=enRyOTlwbnV2bjg5 | AF81: https://www.tiktok.com/@peena._?_r=1&_t=ZS-93QJymJbPfx | AK81: 13/09/2006
B82: =IF($C82="","",COUNTA($C$5:C82)) -> 78 | C82: PROTETO | D82: Player | E82: Free Fire | F82: Team Falcons | G82: Thailand | H82: 2 | I82: Tier 2 | J82: 11000 | K82: 4600 | L82: =IF($C82="","",ROUND($J82*0.17,0)) -> 1870 | M82: 8600 | N82: 3500 | O82: 2200 | P82: 2200 | Q82: 15950 | R82: 7150 | S82: =IF($C82="","",ROUND($J82*2.2,0)) -> 24200 | T82: 3850 | U82: 3300 | V82: 2000 | W82: 2400 | X82: 2 platforms | Y82: 0.3 | Z82: 1 | AA82: Ratchata Soonklang | AC82: https://www.instagram.com/protetae | AH82: https://facebook.com/pongsatorn.pongsatorn.754 | AK82: 39905
B83: =IF($C83="","",COUNTA($C$5:C83)) -> 79 | C83: SAINOI | D83: Manager | E83: Free Fire | F83: Team Falcons | G83: Thailand | H83: 0 | I83: Tier 3 | J83: 11000 | K83: 4600 | L83: =IF($C83="","",ROUND($J83*0.17,0)) -> 1870 | M83: 8600 | N83: 3500 | O83: 2200 | P83: 0 | Q83: 15950 | R83: 7150 | S83: =IF($C83="","",ROUND($J83*2.2,0)) -> 24200 | T83: 3850 | U83: 3300 | V83: 2000 | W83: 0 | X83: 0 platforms | Y83: 0.3 | Z83: 1 | AA83: Worrawan Kasikarn
B84: =IF($C84="","",COUNTA($C$5:C84)) -> 80 | C84: Jose Serrano | D84: Player | E84: Gran Turismo | F84: Gran Turismo | G84: Spanish | H84: 3 | I84: Tier 2 | J84: 11250 | K84: 4500 | L84: =IF($C84="","",ROUND($J84*0.17,0)) -> 1913 | M84: 8000 | N84: 3500 | O84: 2000 | P84: 2000 | Q84: 13500 | R84: 6075 | S84: =IF($C84="","",ROUND($J84*2.2,0)) -> 24750 | T84: 4638 | U84: 4063 | V84: 2438 | W84: 2400 | X84: 3 platforms | Y84: 0.75 | Z84: 1 | AA84: Jose Serrano | AB84: https://x.com/JoseSerrano_16 | AC84: https://www.instagram.com/joseserranoo_/ | AD84: https://www.twitch.tv/JoseSerrano_16 | AK84: 25/09/2002 | AL84: Driver
B85: =IF($C85="","",COUNTA($C$5:C85)) -> 81 | C85: Naif Alfaleh | D85: Player | E85: Gran Turismo | F85: Gran Turismo | G85: Saudi | H85: 2 | I85: Tier 2 | J85: 11000 | K85: 4600 | L85: =IF($C85="","",ROUND($J85*0.17,0)) -> 1870 | M85: 8600 | N85: 3500 | O85: 2200 | P85: 2200 | Q85: 15950 | R85: 7150 | S85: =IF($C85="","",ROUND($J85*2.2,0)) -> 24200 | T85: 3850 | U85: 3300 | V85: 2000 | W85: 2400 | X85: 2 platforms | Y85: 0.3 | Z85: 1 | AA85: Naif Alfaleh | AB85: https://x.com/Falcon_Naifx | AC85: https://www.instagram.com/falcon_naifx/ | AK85: 30/06/2003 | AL85: Driver
B86: =IF($C86="","",COUNTA($C$5:C86)) -> 82 | C86: Pol Urra | D86: Player | E86: Gran Turismo | F86: Gran Turismo | G86: Spanish | H86: 2 | I86: Tier 2 | J86: 12100 | K86: 5100 | L86: =IF($C86="","",ROUND($J86*0.17,0)) -> 2057 | M86: 9450 | N86: 3850 | O86: 2400 | P86: 2400 | Q86: 17550 | R86: 7850 | S86: =IF($C86="","",ROUND($J86*2.2,0)) -> 26620 | T86: 4250 | U86: 3650 | V86: 2200 | W86: 2400 | X86: 2 platforms | Y86: 0.75 | Z86: 1 | AA86: Pol Urra | AB86: https://x.com/polurra | AC86: https://www.instagram.com/pol_urra/ | AK86: 21/02/2005 | AL86: Driver
B87: =IF($C87="","",COUNTA($C$5:C87)) -> 83 | C87: Wesam Khalil | D87: Player | E87: Gran Turismo | F87: Gran Turismo | G87: Saudi | H87: 2 | I87: Tier 2 | J87: 11000 | K87: 4600 | L87: =IF($C87="","",ROUND($J87*0.17,0)) -> 1870 | M87: 8600 | N87: 3500 | O87: 2200 | P87: 2200 | Q87: 15950 | R87: 7150 | S87: =IF($C87="","",ROUND($J87*2.2,0)) -> 24200 | T87: 3850 | U87: 3300 | V87: 2000 | W87: 2400 | X87: 2 platforms | Y87: 0.3 | Z87: 1 | AA87: Wesam Khalil | AB87: https://x.com/Falcon_Wesam | AC87: https://www.instagram.com/falcon_wesam/ | AK87: 17/06/1999 | AL87: Driver
B88: =IF($C88="","",COUNTA($C$5:C88)) -> 84 | C88: Skwal | D88: Manager | E88: Gran Turismo | F88: Gran Turismo | G88: French | H88: 2 | I88: Tier 2 | J88: 12100 | K88: 5100 | L88: =IF($C88="","",ROUND($J88*0.17,0)) -> 2057 | M88: 9450 | N88: 3850 | O88: 2400 | P88: 0 | Q88: 17550 | R88: 7850 | S88: =IF($C88="","",ROUND($J88*2.2,0)) -> 26620 | T88: 4250 | U88: 3650 | V88: 2200 | W88: 0 | X88: 2 platforms | Y88: 0.3 | Z88: 1 | AA88: Nicolas Sautron | AB88: https://x.com/SkwalGG | AC88: https://www.instagram.com/skwalgg/ | AK88: 28/03/1992
B89: =IF($C89="","",COUNTA($C$5:C89)) -> 85 | C89: Boyet | D89: Player | E89: Mobile Legends Bang Bang | F89: Team Falcons MENA | G89: Philippines | H89: 1 | I89: Tier 3 | J89: 8750 | K89: 3000 | L89: =IF($C89="","",ROUND($J89*0.17,0)) -> 1488 | M89: 6000 | N89: 2500 | O89: 1200 | P89: 1200 | Q89: 9000 | R89: 4050 | S89: =IF($C89="","",ROUND($J89*2.2,0)) -> 19250 | T89: 2200 | U89: 1925 | V89: 1155 | W89: 2400 | X89: 1 platform | Y89: 0.3 | Z89: 1 | AA89: Bien Salvador C Chumacera | AC89: https://www.instagram.com/boyetdr_ | AK89: 29/01/2003 | AL89: Jungler
B90: =IF($C90="","",COUNTA($C$5:C90)) -> 86 | C90: Cuffin | D90: Player | E90: Mobile Legends Bang Bang | F90: Team Falcons MENA | G90: Saudi Arabia | H90: 1 | I90: Tier 3 | J90: 5200 | K90: 2200 | L90: =IF($C90="","",ROUND($J90*0.17,0)) -> 884 | M90: 4050 | N90: 1650 | O90: 1050 | P90: 1050 | Q90: 7550 | R90: 3400 | S90: =IF($C90="","",ROUND($J90*2.2,0)) -> 11440 | T90: 1800 | U90: 1550 | V90: 950 | W90: 2400 | X90: 1 platform | Y90: 0.3 | Z90: 1 | AA90: Muath saad alquraini | AC90: https://www.instagram.com/accounts/login/?next=%2Fcuffin_ml&source=omni_redirect | AK90: 19/10/2002 | AL90: Middle
B91: =IF($C91="","",COUNTA($C$5:C91)) -> 87 | C91: Kakashi | D91: Manager | E91: Mobile Legends Bang Bang | F91: Team Falcons MENA | G91: Egypt | H91: 1 | I91: Tier 3 | J91: 5700 | K91: 2400 | L91: =IF($C91="","",ROUND($J91*0.17,0)) -> 969 | M91: 4450 | N91: 1850 | O91: 1150 | P91: 0 | Q91: 8300 | R91: 3700 | S91: =IF($C91="","",ROUND($J91*2.2,0)) -> 12540 | T91: 2000 | U91: 1700 | V91: 1050 | W91: 0 | X91: 1 platform | Y91: 0.3 | Z91: 1 | AA91: AMR WAFED YASSIN | AC91: https://www.instagram.com/cuffin_ml | AK91: 37050
B92: =IF($C92="","",COUNTA($C$5:C92)) -> 88 | C92: Kakashi | D92: Manager | E92: Mobile Legends Bang Bang | F92: Falcons Vega MENA | G92: Egypt | H92: 1 | I92: Tier 3 | J92: 0 | K92: 0 | L92: =IF($C92="","",ROUND($J92*0.17,0)) -> 0 | M92: 0 | N92: 0 | O92: 0 | P92: 0 | Q92: 0 | R92: 0 | S92: =IF($C92="","",ROUND($J92*2.2,0)) -> 0 | T92: 0 | U92: 0 | V92: 600 | W92: 0 | X92: 1 platform | Y92: 0.3 | Z92: 1 | AA92: AMR WAFED YASSIN | AC92: https://www.instagram.com/cuffin_ml | AK92: 37050
B93: =IF($C93="","",COUNTA($C$5:C93)) -> 89 | C93: Saano | D93: Player | E93: Mobile Legends Bang Bang | F93: Team Falcons MENA | G93: Saudi Arabia | H93: 0 | I93: Tier 3 | J93: 8750 | K93: 3000 | L93: =IF($C93="","",ROUND($J93*0.17,0)) -> 1488 | M93: 6000 | N93: 2500 | O93: 1200 | P93: 1200 | Q93: 9000 | R93: 4050 | S93: =IF($C93="","",ROUND($J93*2.2,0)) -> 19250 | T93: 2200 | U93: 1925 | V93: 1155 | W93: 2400 | X93: 0 platforms | Y93: 0.3 | Z93: 1 | AA93: SULAIMAN MUSALLAM ALRASHDI | AK93: 30/06/2004 | AL93: Gold Lane
B94: =IF($C94="","",COUNTA($C$5:C94)) -> 90 | C94: Sanji | D94: Player | E94: Mobile Legends Bang Bang | F94: Team Falcons MENA | G94: Saudi Arabia | H94: 1 | I94: Tier 3 | J94: 5700 | K94: 2400 | L94: =IF($C94="","",ROUND($J94*0.17,0)) -> 969 | M94: 4450 | N94: 1850 | O94: 1150 | P94: 1150 | Q94: 8300 | R94: 3700 | S94: =IF($C94="","",ROUND($J94*2.2,0)) -> 12540 | T94: 2000 | U94: 1700 | V94: 1050 | W94: 2400 | X94: 1 platform | Y94: 0.3 | Z94: 1 | AA94: Ayman Othman Alqarni | AC94: https://www.instagram.com/trolll_ml | AK94: 37682 | AL94: EXP Lane
B95: =IF($C95="","",COUNTA($C$5:C95)) -> 91 | C95: Tarzaan | D95: Player | E95: Mobile Legends Bang Bang | F95: Team Falcons MENA | G95: Saudi Arabia | H95: 0 | I95: Tier 3 | J95: 5700 | K95: 2400 | L95: =IF($C95="","",ROUND($J95*0.17,0)) -> 969 | M95: 4450 | N95: 1850 | O95: 1150 | P95: 1150 | Q95: 8300 | R95: 3700 | S95: =IF($C95="","",ROUND($J95*2.2,0)) -> 12540 | T95: 2000 | U95: 1700 | V95: 1050 | W95: 2400 | X95: 0 platforms | Y95: 0.3 | Z95: 1 | AA95: Mohammed Ayman Kharabah | AK95: 14/05/2000 | AL95: Jungler
B96: =IF($C96="","",COUNTA($C$5:C96)) -> 92 | C96: Troll | D96: Player | E96: Mobile Legends Bang Bang | F96: Team Falcons MENA | G96: Saudi Arabia | H96: 0 | I96: Tier 3 | J96: 5700 | K96: 2400 | L96: =IF($C96="","",ROUND($J96*0.17,0)) -> 969 | M96: 4450 | N96: 1850 | O96: 1150 | P96: 1150 | Q96: 8300 | R96: 3700 | S96: =IF($C96="","",ROUND($J96*2.2,0)) -> 12540 | T96: 2000 | U96: 1700 | V96: 1050 | W96: 2400 | X96: 0 platforms | Y96: 0.3 | Z96: 1 | AA96: Moayed ayman kharaba | AK96: 31/01/2007 | AL96: Roamer
B97: =IF($C97="","",COUNTA($C$5:C97)) -> 93 | C97: Owgwen | D97: Player | E97: Mobile Legends Bang Bang | F97: Team Falcons PH | G97: Philippines | H97: 4 | I97: Tier 1 | J97: 11000 | K97: 4600 | L97: =IF($C97="","",ROUND($J97*0.17,0)) -> 1870 | M97: 8600 | N97: 3500 | O97: 2200 | P97: 2200 | Q97: 15950 | R97: 7150 | S97: =IF($C97="","",ROUND($J97*2.2,0)) -> 24200 | T97: 3850 | U97: 3300 | V97: 2000 | W97: 2400 | X97: 4 platforms | Y97: 0.3 | Z97: 1 | AA97: Rowgien Stimpson Unigo | AB97: https://twitter.com/Ogiiiieeen | AC97: https://www.instagram.com/flcn.owgwen | AF97: https://www.tiktok.com/@ogiiiieeen | AH97: https://facebook.com/Ogiiiieeen | AK97: 25/04/2001 | AL97: Roamer
B98: =IF($C98="","",COUNTA($C$5:C98)) -> 94 | C98: Super Marco | D98: Player | E98: Mobile Legends Bang Bang | F98: Team Falcons PH | G98: Philippines | H98: 3 | I98: Tier 2 | J98: 18000 | K98: 7550 | L98: =IF($C98="","",ROUND($J98*0.17,0)) -> 3060 | M98: 14050 | N98: 5750 | O98: 3600 | P98: 3600 | Q98: 26100 | R98: 11700 | S98: =IF($C98="","",ROUND($J98*2.2,0)) -> 39600 | T98: 6300 | U98: 5400 | V98: 3250 | W98: 2400 | X98: 3 platforms | Y98: 0.3 | Z98: 1 | AA98: Marco Stephen Requitiano | AC98: https://www.tiktok.com/@flcnsupermarco | AF98: https://www.tiktok.com/@flcnsupermarco | AH98: https://www.facebook.com/FLCNSupermarco | AK98: 36687 | AL98: Gold Lane
B99: =IF($C99="","",COUNTA($C$5:C99)) -> 95 | C99: Hadji | D99: Player | E99: Mobile Legends Bang Bang | F99: Team Falcons PH | G99: Philippines | H99: 3 | I99: Tier 2 | J99: 11000 | K99: 4600 | L99: =IF($C99="","",ROUND($J99*0.17,0)) -> 1870 | M99: 8600 | N99: 3500 | O99: 2200 | P99: 2200 | Q99: 15950 | R99: 7150 | S99: =IF($C99="","",ROUND($J99*2.2,0)) -> 24200 | T99: 3850 | U99: 3300 | V99: 2000 | W99: 2400 | X99: 3 platforms | Y99: 0.3 | Z99: 1 | AA99: Salic Imam | AC99: https://www.instagram.com/hadjizy | AF99: https://www.tiktok.com/@hadjizy_ | AH99: https://facebook.com/Hadjizyyyyy | AK99: 23/04/2003 | AL99: Middle
B100: =IF($C100="","",COUNTA($C$5:C100)) -> 96 | C100: Moody | D100: Assistant Coach | E100: Mobile Legends Bang Bang | F100: Team Falcons PH | G100: Philippines | H100: 3 | I100: Tier 2 | J100: 0 | K100: 0 | L100: =IF($C100="","",ROUND($J100*0.17,0)) -> 0 | M100: 0 | N100: 0 | O100: 0 | P100: 0 | Q100: 0 | R100: 0 | S100: =IF($C100="","",ROUND($J100*2.2,0)) -> 0 | T100: 0 | U100: 0 | V100: 1200 | W100: 0 | X100: 3 platforms | Y100: 0.3 | Z100: 1 | AA100: Mohammad Samal | AC100: https://www.instagram.com/moodysamal | AF100: https://www.tiktok.com/@flcn.moody | AH100: https://www.facebook.com/liquidcoachmoody/ | AK100: 26/08/1996
B101: =IF($C101="","",COUNTA($C$5:C101)) -> 97 | C101: VR3N | D101: Analyst | E101: Mobile Legends Bang Bang | F101: Team Falcons PH | G101: Philippines | H101: 3 | I101: Tier 2 | J101: 0 | K101: 0 | L101: =IF($C101="","",ROUND($J101*0.17,0)) -> 0 | M101: 0 | N101: 0 | O101: 0 | P101: 0 | Q101: 0 | R101: 0 | S101: =IF($C101="","",ROUND($J101*2.2,0)) -> 0 | T101: 0 | U101: 0 | V101: 1200 | W101: 0 | X101: 3 platforms | Y101: 0.3 | Z101: 1 | AA101: Vrendon Pesebre | AC101: https://www.instagram.com/vrendonlin | AF101: https://www.tiktok.com/@vrendonlin | AH101: https://www.facebook.com/kutspogi | AK101: 22/04/1991
...

Sheet 02_Creator_Rate_Card
B2: ="CREATOR RATE CARD — "&COUNTA($C$5:$C$500)&" ENTRIES" -> CREATOR RATE CARD — 17 ENTRIES
A3: ROLE LEGEND | B3: ● Creator
B4: # | C4: Creator | D4: Weighted Score | E4: Tier | F4: X Post/Quote | G4: X Repost | H4: IG Post | I4: IG Story | J4: IG Reels | K4: YT Full Video | L4: YT 1-2min Pre-roll | M4: TikTok Our-side | N4: TikTok Client Vids | O4: Kick IRL | P4: Twitch/Kick Live | Q4: Telegram | R4: Event + Snap
B5: =IF($C5="","",COUNTA($C$5:C5)) -> 1 | C5: BanderitaX | D5: 98 | E5: Tier S | F5: 56250 | G5: 22500 | H5: 28125 | I5: 16875 | J5: 28125 | K5: 67500 | L5: 50625 | M5: 39375 | N5: 31500 | O5: 14063 | P5: 28125 | Q5: 11250 | R5: 39375
B6: =IF($C6="","",COUNTA($C$5:C6)) -> 2 | C6: oPiiLz | D6: 72 | E6: Tier 1 | F6: 22500 | G6: 9000 | H6: 11250 | I6: 6750 | J6: 11250 | K6: 27000 | L6: 20250 | M6: 15750 | N6: 12600 | O6: 5625 | P6: 11250 | Q6: 4500 | R6: 15750
B7: =IF($C7="","",COUNTA($C$5:C7)) -> 3 | C7: Msdossary7 | D7: 72 | E7: Tier 1 | F7: 22500 | G7: 9000 | H7: 11250 | I7: 6750 | J7: 11250 | K7: 27000 | L7: 20250 | M7: 15750 | N7: 12600 | O7: 5625 | P7: 11250 | Q7: 4500 | R7: 15750
B8: =IF($C8="","",COUNTA($C$5:C8)) -> 4 | C8: Aziz | D8: 68 | E8: Tier 1 | F8: 18000 | G8: 7200 | H8: 9000 | I8: 5400 | J8: 9000 | K8: 21600 | L8: 16200 | M8: 12600 | N8: 10080 | O8: 4500 | P8: 9000 | Q8: 3600 | R8: 12600
B9: =IF($C9="","",COUNTA($C$5:C9)) -> 5 | C9: Bo3omar22 | D9: 68 | E9: Tier 1 | F9: 18000 | G9: 7200 | H9: 9000 | I9: 5400 | J9: 9000 | K9: 21600 | L9: 16200 | M9: 12600 | N9: 10080 | O9: 4500 | P9: 9000 | Q9: 3600 | R9: 12600
B10: =IF($C10="","",COUNTA($C$5:C10)) -> 6 | C10: Abu abeer | D10: 60 | E10: Tier 2 | F10: 11250 | G10: 4500 | H10: 5625 | I10: 3375 | J10: 5625 | K10: 13500 | L10: 10125 | M10: 7875 | N10: 6300 | O10: 2813 | P10: 5625 | Q10: 2250 | R10: 7875
B11: =IF($C11="","",COUNTA($C$5:C11)) -> 7 | C11: LLE | D11: 58 | E11: Tier 2 | F11: 10125 | G11: 4050 | H11: 5063 | I11: 3038 | J11: 5063 | K11: 12150 | L11: 9113 | M11: 7088 | N11: 5670 | O11: 2531 | P11: 5063 | Q11: 2025 | R11: 7088
B12: =IF($C12="","",COUNTA($C$5:C12)) -> 8 | C12: Oden | D12: 55 | E12: Tier 2 | F12: 9000 | G12: 3600 | H12: 4500 | I12: 2700 | J12: 4500 | K12: 10800 | L12: 8100 | M12: 6300 | N12: 5040 | O12: 2250 | P12: 4500 | Q12: 1800 | R12: 6300
B13: =IF($C13="","",COUNTA($C$5:C13)) -> 9 | C13: xSMA333 | D13: 52 | E13: Tier 2 | F13: 7875 | G13: 3150 | H13: 3938 | I13: 2363 | J13: 3938 | K13: 9450 | L13: 7088 | M13: 5513 | N13: 4410 | O13: 1969 | P13: 3938 | Q13: 1575 | R13: 5513
B14: =IF($C14="","",COUNTA($C$5:C14)) -> 10 | C14: 3ADEL | D14: 50 | E14: Tier 2 | F14: 6750 | G14: 2700 | H14: 3375 | I14: 2025 | J14: 3375 | K14: 8100 | L14: 6075 | M14: 4725 | N14: 3780 | O14: 1688 | P14: 3375 | Q14: 1350 | R14: 4725
B15: =IF($C15="","",COUNTA($C$5:C15)) -> 11 | C15: RAED | D15: 48 | E15: Tier 2 | F15: 6188 | G15: 2475 | H15: 3094 | I15: 1856 | J15: 3094 | K15: 7425 | L15: 5569 | M15: 4331 | N15: 3465 | O15: 1547 | P15: 3094 | Q15: 1238 | R15: 4331
B16: =IF($C16="","",COUNTA($C$5:C16)) -> 12 | C16: Falcons | D16: 45 | E16: Tier 2 | F16: 5625 | G16: 2250 | H16: 2813 | I16: 1688 | J16: 2813 | K16: 6750 | L16: 5063 | M16: 3938 | N16: 3150 | O16: 1406 | P16: 2813 | Q16: 1125 | R16: 3938
... B21: =IF($C21="","",COUNTA($C$5:C21)) -> 17 | C21: 9leeh | D21: 32 | E21: Tier 3 | F21: 2250 | G21: 900 | H21: 1125 | I21: 675 | J21: 1125 | K21: 2700 | L21: 2025 | M21: 1575 | N21: 1260 | O21: 563 | P21: 1125 | Q21: 450 | R21: 1575

Sheet 03_Adjustment_Matrix
B2: DYNAMIC PRICING ADJUSTMENT MATRIX
B3: Select a player → choose an asset → adjust multipliers → get the final price
B5: 🔍 Search Player | D5: moaz | F5: =IFERROR(__xludf.dummyfunction("IF(TRIM(D5)="""","""",IFERROR(INDEX(FILTER('01_Player_Rate_Card'!C$5:C1016,REGEXMATCH(LOWER('01_Player_Rate_Card'!C$5:C1016),LOWER(TRIM(D5)))) ,1),""No match — check spelling""))"),"Moaz") -> Moaz | H5: Type a full or partial name in D5 → best matching player appears in F5 → selection syncs automatically below
B7: ① PLAYER SELECTOR
B8: Select Player | C8: Game | D8: Team | E8: Role | F8: Tier | G8: Nationality | H8: Platforms
B9: =IF(OR($F$5="",$F$5="No match — check spelling"),"",$F$5) -> Moaz | C9: =IFERROR(VLOOKUP(B9,'01_Player_Rate_Card'!$C$5:$AL$500,3,0),"") -> Esports Influencers | D9: =IFERROR(VLOOKUP(B9,'01_Player_Rate_Card'!$C$5:$AL$500,4,0),"") -> Esports Influencers | E9: =IFERROR(VLOOKUP(B9,'01_Player_Rate_Card'!$C$5:$AL$500,2,0),"") -> Influencer | F9: =IFERROR(VLOOKUP(B9,'01_Player_Rate_Card'!$C$5:$AL$500,7,0),"") -> Tier 2 | G9: =IFERROR(VLOOKUP(B9,'01_Player_Rate_Card'!$C$5:$AL$500,5,0),"") -> Saudi Arabia | H9: =IFERROR(VLOOKUP(B9,'01_Player_Rate_Card'!$C$5:$AL$500,6,0),"") -> 5
B10: ② PLAYER RATE CARD (all values in SAR)
B11: IG Reel | C11: IG Static | D11: IG Story | E11: TikTok Video | F11: YT Short | G11: X Post | H11: FB Post/Video | I11: Twitch 2h | J11: Twitch Integ. | K11: IRL / Appear. | L11: Rights Fee | M11: Exclusivity | N11: Rush Fee | O11: WL Fee | P11: Repost
B12: =IFERROR(VLOOKUP(B9,'01_Player_Rate_Card'!$C$5:$AL$500,8,0),"N/A") -> 6500 | C12: =IFERROR(VLOOKUP(B9,'01_Player_Rate_Card'!$C$5:$AL$500,9,0),"N/A") -> 5300 | D12: =IFERROR(VLOOKUP(B9,'01_Player_Rate_Card'!$C$5:$AL$500,10,0),"N/A") -> 1105 | E12: =IFERROR(VLOOKUP(B9,'01_Player_Rate_Card'!$C$5:$AL$500,11,0),"N/A") -> 3400 | F12: =IFERROR(VLOOKUP(B9,'01_Player_Rate_Card'!$C$5:$AL$500,12,0),"N/A") -> 4050 | G12: =IFERROR(VLOOKUP(B9,'01_Player_Rate_Card'!$C$5:$AL$500,13,0),"N/A") -> 2500 | H12: =IFERROR(VLOOKUP(B9,'01_Player_Rate_Card'!$C$5:$AL$500,14,0),"N/A") -> 2500 | I12: =IFERROR(VLOOKUP(B9,'01_Player_Rate_Card'!$C$5:$AL$500,15,0),"N/A") -> 15950 | J12: =IFERROR(VLOOKUP(B9,'01_Player_Rate_Card'!$C$5:$AL$500,16,0),"N/A") -> 8200 | K12: =IFERROR(VLOOKUP(B9,'01_Player_Rate_Card'!$C$5:$AL$500,17,0),"N/A") -> 14300 | L12: =IFERROR(VLOOKUP(B9,'01_Player_Rate_Card'!$C$5:$AL$500,18,0),"N/A") -> 3800 | M12: =IFERROR(VLOOKUP(B9,'01_Player_Rate_Card'!$C$5:$AL$500,19,0),"N/A") -> 1900 | N12: =IFERROR(VLOOKUP(B9,'01_Player_Rate_Card'!$C$5:$AL$500,20,0),"N/A") -> 3150 | O12: =IFERROR(VLOOKUP(B9,'01_Player_Rate_Card'!$C$5:$AL$500,21,0),"N/A") -> 1250 | P12: =IFERROR(ROUND(IFERROR(VLOOKUP(B9,'01_Player_Rate_Card'!$C$5:$AL$500,8,0),0)*0.15,0),"N/A") -> 975
B14: ③ ASSET SELECTOR — Choose the deliverable type
B15: Asset Type | D15: Base Fee (SAR) | F15: Notes / Basis
B16: Podcast Guesting | D16: {=IFERROR(xlookup(B16,$B$17:$B$34,$D$17:$D$34,0),0)} -> 0
B17: IG Reel | D17: =IFERROR(VLOOKUP($B$9,'01_Player_Rate_Card'!$C$5:$AL$500,8,FALSE()),0) -> 6500 | F17: Player IG Reel rate from Rate Card
B18: IG Static Post | D18: =IFERROR(VLOOKUP($B$9,'01_Player_Rate_Card'!$C$5:$AL$500,9,FALSE()),0) -> 5300 | F18: Player IG Static rate
B19: IG Story | D19: =IFERROR(VLOOKUP($B$9,'01_Player_Rate_Card'!$C$5:$AL$500,10,FALSE()),0) -> 1105 | F19: Player IG Story rate
B20: TikTok Video | D20: =IFERROR(VLOOKUP($B$9,'01_Player_Rate_Card'!$C$5:$AL$500,11,FALSE()),0) -> 3400 | F20: Player TikTok rate
B21: YT Short | D21: =IFERROR(VLOOKUP($B$9,'01_Player_Rate_Card'!$C$5:$AL$500,12,FALSE()),0) -> 4050 | F21: Player YT Short rate
B22: X Post | D22: =IFERROR(VLOOKUP($B$9,'01_Player_Rate_Card'!$C$5:$AL$500,13,FALSE()),0) -> 2500 | F22: Player X Post rate
B23: FB Post / Video | D23: =IFERROR(VLOOKUP($B$9,'01_Player_Rate_Card'!$C$5:$AL$500,14,FALSE()),0) -> 2500 | F23: Player FB rate
B24: Content Repost | D24: =IFERROR(VLOOKUP($B$9,'01_Player_Rate_Card'!$C$5:$AL$500,8,FALSE())*0.15,0) -> 975 | F24: 15% of IG Reel rate
B25: — LIVE & STREAM —
B26: Twitch Stream 2h | D26: =IFERROR(VLOOKUP($B$9,'01_Player_Rate_Card'!$C$5:$AL$500,15,FALSE()),0) -> 15950 | F26: Player Twitch 2h rate
B27: Twitch Integration | D27: =IFERROR(VLOOKUP($B$9,'01_Player_Rate_Card'!$C$5:$AL$500,16,FALSE()),0) -> 8200 | F27: Player Twitch Integ. rate
B28: — ON-GROUND & EVENTS —
B29: IRL Appearance | D29: =IFERROR(VLOOKUP($B$9,'01_Player_Rate_Card'!$C$5:$AL$500,17,FALSE()),0) -> 14300 | F29: Player IRL rate
B30: Podcast Guesting | D30: =IFERROR(VLOOKUP($B$9,'01_Player_Rate_Card'!$C$5:$AL$500,17,FALSE())*0.5,0) -> 7150 | F30: 50% of IRL — 1-2h time commitment
B31: PR Appearance / CSR | D31: =IFERROR(VLOOKUP($B$9,'01_Player_Rate_Card'!$C$5:$AL$500,17,FALSE()),0) -> 14300 | F31: Full IRL rate — brand presence + media
B32: Fan Meet & Greet | D32: =IFERROR(VLOOKUP($B$9,'01_Player_Rate_Card'!$C$5:$AL$500,17,FALSE())*0.7,0) -> 10010 | F32: 70% of IRL — structured 2-4h fan interaction
B33: — OTHER —
B34: Photo Shoot (Brand) | D34: =IFERROR(VLOOKUP($B$9,'01_Player_Rate_Card'!$C$5:$AL$500,17,FALSE())*0.75,0) -> 10725 | F34: 75% of IRL — half-day shoot, brand usage rights incl. | H34: Weight | I34: Description
B35: < 2% | D35: 0.70x | E35: Below average — audience not engaged | F35: Awareness | H35: 0.2 | I35: Brand visibility — social reach matters most
B36: 2% – 4% | D36: 0.90x | E36: Average — slight discount from baseline | F36: Conversion | H36: 0.4 | I36: Direct response — engagement + credibility
B37: 4% – 6% | D37: 1.00x | E37: Baseline — standard market rate | F37: Trust (Pro Authority) | H37: 0.7 | I37: Credibility campaigns — pro status is the product
B38: 6% – 8% | D38: 1.20x | E38: Good — 20% premium
B39: 8% – 10% | D39: 1.40x | E39: Excellent — strong audience connection | F39: AUTHORITY MULTIPLIER PRESETS | H39: Value | I39: Profile
B40: > 10% | D40: 1.60x | E40: Premium micro-influencer effect | F40: Normal | H40: 1 | I40: Content creator / standard player
F41: Proven / Established | H41: 1.15 | I41: Regional champion, 2+ years pro
B42: AUDIENCE QUALITY | D42: Multiplier | E42: Notes | F42: Elite Contender | H42: 1.3 | I42: Top-10 world ranking, major finalist
B43: Generic / Broad | D43: 0.85x | E43: Mixed interests, low targeting | F43: Global Star / Major Winner | H43: 1.5 | I43: World champion, iconic pro name
B44: Gaming-adjacent | D44: 1.00x | E44: Baseline — general gaming
B45: Core Gaming | D45: 1.20x | E45: Dedicated gamers, high purchase intent | F45: LANGUAGE MULTIPLIER | H45: Value | I45: Context
B46: Esports-focused | D46: 1.40x | E46: Competitive gaming — premium targeting | F46: English | H46: 1 | I46: Global / English-language content
B47: MENA / Saudi focus | D47: 1.30x | E47: Regional premium — cultural relevance | F47: Arabic | H47: 1.05 | I47: MENA-specific Arabic content (+5% regional premium)
B48: Global Esports Elite | D48: 1.50x | E48: Maximum premium — top-tier audience | F48: Bilingual | H48: 1.15 | I48: Dual-language content — maximum MENA reach
B50: SEASONALITY & TIMING | D50: Multiplier | E50: Context | F50: AUTHORITY FLOOR (FloorShare) | H50: Range | I50: Use When
B51: Off-season | D51: 0.80x | E51: Low viewership period | F51: Not used | H51: 0 | I51: Standard content campaigns
B52: Regular season | D52: 1.00x | E52: Baseline — standard competition | F52: Partial floor | H52: 0.30–0.50 | I52: Hardware / peripherals ("pro choice" campaigns)
B53: Regional Major | D53: 1.25x | E53: Regional championship | F53: Strong floor | H53: 0.60–0.80 | I53: Credibility campaigns, tournament windows
B54: Global Major / Worlds | D54: 1.40x | E54: Peak esports interest
B55: Game launch | D55: 1.30x | E55: New title release | F55: AuthorityFactor formula: | H55: AuthorityFactor = 1 + ObjWeight x (AuthMult - 1)
B56: Holiday season (Q4) | D56: 1.20x | E56: Year-end peak
B57: Ramadan (MENA) | D57: 1.35x | E57: Peak MENA consumption — highest regional multiplier
B58: Ewc/Mega Peak | D58: 1.50x | E58: esports world cup highest multiplier
B59: ⑥ LIVE PRICE CALCULATOR — Authority Patch v1 — Enter values in blue cells
B60: Input | D60: Value | E60: [parsed]
B61: Base Fee (SAR) | D61: =IF(ISNUMBER(D16),D16,0) -> 0 | E61: Auto-pulled from player + asset selection above
B62: Engagement Multiplier | D62: 0.70 — Below average (< 2%) | E62: =IFERROR(IF(ISNUMBER(D62),D62,VALUE(TRIM(LEFT(TRIM(D62),FIND(" ",TRIM(D62)&" ")-1)))),1) -> 0.7
B63: Audience Quality Multiplier | D63: 0.85 — Generic / Broad | E63: =IFERROR(IF(ISNUMBER(D63),D63,VALUE(TRIM(LEFT(TRIM(D63),FIND(" ",TRIM(D63)&" ")-1)))),1) -> 0.85
B64: Seasonality Multiplier | D64: 0.80 — Off-season | E64: =IFERROR(IF(ISNUMBER(D64),D64,VALUE(TRIM(LEFT(TRIM(D64),FIND(" ",TRIM(D64)&" ")-1)))),1) -> 0.8
B65: Content Type Multiplier | D65: 1.00 — Integrated (Player-led) | E65: =IFERROR(IF(ISNUMBER(D65),D65,VALUE(TRIM(LEFT(TRIM(D65),FIND(" ",TRIM(D65)&" ")-1)))),1) -> 1
B66: Add-on Uplift (total %) | D66: ='04_Add_On_Rights'!$C$1021 -> 0 | E66: Sum of selected add-ons from 03_Add_On_Rights
B67: Campaign Objective | D67: Conversion | E67: Drives ObjectiveWeight — see Authority table →
B68: Authority Multiplier | D68: 1.10 — Proven / Established | E68: =IFERROR(IF(ISNUMBER(D68),D68,VALUE(TRIM(LEFT(TRIM(D68),FIND(" ",TRIM(D68)&" ")-1)))),1) -> 1.1
B69: Language Multiplier | D69: 1.00 — English | E69: =IFERROR(IF(ISNUMBER(D69),D69,VALUE(TRIM(LEFT(TRIM(D69),FIND(" ",TRIM(D69)&" ")-1)))),1) -> 1
B70: Authority Floor Share | D70: 0.50 — Standard floor | E70: =IFERROR(IF(ISNUMBER(D70),D70,VALUE(TRIM(LEFT(TRIM(D70),FIND(" ",TRIM(D70)&" ")-1)))),0) -> 0.5
B71: IRL Appearance Fee (SAR) | D71: =IFERROR(VLOOKUP($B$9,'01_Player_Rate_Card'!$C$5:$AL$500,17,FALSE()),0) -> 14300 | E71: Auto-pulled from selected player's IRL / Appear. column
B73: AuthorityFactor | D73: =IFERROR(1+IF(TRIM(D67)="Awareness",0.3,IF(TRIM(D67)="Conversion",0.6,IF(TRIM(D67)="Trust (Pro Authority)",0.9,0.6)))*(IFERROR(IF(ISNUMBER(D68),D68,VALUE(TRIM(LEFT(TRIM(D68),FIND(" ",TRIM(D68)&" ")-1)))),1)-1),1) -> 1.06 | E73: Objective-weighted authority premium
B74: SocialPrice (pre-floor, pre-add-on) | D74: =IFERROR(D61*IFERROR(IF(ISNUMBER(D62),D62,VALUE(TRIM(LEFT(TRIM(D62),FIND(" ",TRIM(D62)&" ")-1)))),1)*IFERROR(IF(ISNUMBER(D63),D63,VALUE(TRIM(LEFT(TRIM(D63),FIND(" ",TRIM(D63)&" ")-1)))),1)*IFERROR(IF(ISNUMBER(D64),D64,VALUE(TRIM(LEFT(TRIM(D64),FIND(" ",TRIM(D64)&" ")-1)))),1)*E65*IFERROR(IF(ISNUMBER(D69),D69,VALUE(TRIM(LEFT(TRIM(D69),FIND(" ",TRIM(D69)&" ")-1)))),1)*D73,0) -> 0 | E74: BaseFee x Eng x Aud x Season x ContentType x Language x AuthorityFactor
B75: AuthorityFloor | D75: =IFERROR(D71*IFERROR(IF(ISNUMBER(D70),D70,VALUE(TRIM(LEFT(TRIM(D70),FIND(" ",TRIM(D70)&" ")-1)))),0)*IFERROR(IF(ISNUMBER(D64),D64,VALUE(TRIM(LEFT(TRIM(D64),FIND(" ",TRIM(D64)&" ")-1)))),1)*IFERROR(IF(ISNUMBER(D69),D69,VALUE(TRIM(LEFT(TRIM(D69),FIND(" ",TRIM(D69)&" ")-1)))),1)*D73,0) -> 6063.2 | E75: IRL Fee x FloorShare x Seasonality x Language x AuthorityFactor
B76: PreAddOnPrice = MAX(Social, Floor) | D76: =IFERROR(MAX(D74,D75),0) -> 6063.2 | E76: Higher of SocialPrice or AuthorityFloor — floor protects pro pricing
B78: FINAL ADJUSTED PRICE (SAR) | D78: =IFERROR(ROUND(D76*(1+IF(ISNUMBER(D66),D66,IFERROR(VALUE(TRIM(SUBSTITUTE(TEXT(D66,"0.00%"),"%","")))/100,0))),0),0) -> 6063 | E78: =IFERROR("~= USD","~= USD") -> ~= USD | F78: =IFERROR("$"&TEXT(ROUND(D78/3.75,0),"#,##0"),"—") -> $1,617
B80: Falcons Commission % | D80: =IFERROR(VLOOKUP($B$9,'01_Player_Rate_Card'!$C$5:$AL$500,23,FALSE()),0) -> 0.3 | E80: Auto-pulled from player's Commission % · edit to override
B81: Markup % (on Player Cost) | D81: =IFERROR(VLOOKUP($B$9,'01_Player_Rate_Card'!$C$5:$AL$500,24,FALSE()),0) -> 1 | E81: Auto-pulled from player's Markup % · edit to override
B83: Player Cost (SAR) | D83: =IFERROR(IF(ISNUMBER(D81),D78/(1+D81),D78/1.75),0) -> 3031.5 | E83: What Falcons pays the player
B84: Falcons Revenue (SAR) | D84: =IFERROR(D78-D83,0) -> 3031.5 | E84: Falcons earnings on this deal
B85: Client Price incl. VAT (SAR) | D85: =IFERROR(D78*1.15,0) -> 6972.45 | E85: Final invoice to client (15% VAT)
B86: Client Price incl. VAT (USD) | D86: =IFERROR(D85/3.75,0) -> 1859.32 | E86: ~= USD equivalent
C87: 1
B91: ⚡ HOW THE AUTHORITY FORMULA WORKS — Pricing Logic Explained
B92: FINAL PRICE = MAX(SocialPrice, AuthorityFloor) x (1 + Add-on %)
B93: Where: SocialPrice = BaseFee x Engagement x Audience x Seasonality x ContentType x Language x AuthorityFactor
B94: And: AuthorityFloor = IRL_Fee x FloorShare x Seasonality x Language x AuthorityFactor
B95: And: AuthorityFactor = 1 + ObjectiveWeight x (AuthorityMultiplier - 1)
B96: ⚡ KEY PRINCIPLES
B97: 1. Never negotiate below the Base Fee
B98: 2. Engagement beats follower count
B99: 3. MENA / Saudi audiences carry a premium
B100: 4. Ramadan is the highest-value window
B101: 5. Exclusivity must always be charged separately
B103: 📊 GLOBAL BENCHMARK
B106: ⑨ CONTENT TYPE MULTIPLIER — Dedicated vs. Integrated
B107: Content Type | D107: Multiplier | E107: Description
B108: Integrated (Player-led) | D108: 1.00x | E108: Player creates and posts content organically — standard rate
B109: Dedicated (Brand-led) | D109: 1.30x | E109: Brand directs the content, dedicated channel focus — +30% premium
B111: 📌 HOW TO USE
B112: Apply this multiplier on top of the social price when the brand is buying a dedicated post
B113: (i.e. brand controls the creative, the post is 100% focused on the brand, not organically integrated)

Sheet 04_Add_On_Rights
B2: ADD-ON RIGHTS PACKAGES
B3: Select applicable add-ons and sum the uplift percentages · Enter total in cell C35 of the Live Calculator (02_Adjustment_Matrix)
B5: RIGHTS PACKAGES — PRICE UPLIFT TABLE
B6: Add-on Type | C6: Uplift % | D6: Description
B7: Organic Repost — Min | C7: 0.15 | D7: Single repost, 1 month
B8: Organic Repost — Std | C8: 0.35 | D8: 3-5 reposts, 3 months
B9: Organic Repost — Max | C9: 0.6 | D9: Unlimited + takeover, 6 months
B10: Paid Usage — Min | C10: 0.25 | D10: Limited, SAR 25K cap
B11: Paid Usage — Std | C11: 0.5 | D11: Standard, SAR 75K cap
B12: Paid Usage — Max | C12: 1 | D12: Unlimited paid media
B13: Whitelisting — Std | C13: 0.4 | D13: 30 days, single platform
B14: Whitelisting — Extended | C14: 0.75 | D14: 90 days, multi-platform
B15: Whitelisting — Premium | C15: 1.2 | D15: 180 days, dark posts included
B16: Territory — MENA | C16: 0.2 | D16: MENA rights, 3 months
B17: Territory — Global | C17: 0.75 | D17: Worldwide, 6 months
B18: Exclusivity — Category | C18: 1.5 | D18: Exclusive category, 12 months
B19: Exclusivity — Full | C19: 2 | D19: Full exclusivity, 12 months
B22: BUNDLE PRESETS — READY TO PITCH
B23: Bundle Tier | C23: Included Add-ons | D23: Total Uplift
B24: Basic | C24: Organic Repost Min | D24: 15%
B25: Standard | C25: Organic Repost Std + Paid Usage Min | D25: 60%
B26: Premium | C26: Organic Repost Max + Paid Usage Std + MENA Territory | D26: 115%
B27: Full | C27: Organic Max + Paid Max + Whitelisting Std + MENA Territory | D27: 170%
B28: Exclusive | C28: All above + Category Exclusivity (12 months) | D28: 320%
B1003: ⑥ ADD-ON TOGGLE GRID · flip to Yes to include in live calculator
B1005: Include? | C1005: Add-On / Rights | D1005: Uplift % | E1005: Description
B1006: No | C1006: Paid Usage 30d MENA | D1006: 0.1 | E1006: Media spend boost, MENA region, 30 days
B1007: No | C1007: Paid Usage 30d Global | D1007: 0.15 | E1007: Media spend boost, Global, 30 days
B1008: No | C1008: Paid Usage 60d MENA | D1008: 0.2 | E1008: Media spend boost, MENA region, 60 days
B1009: No | C1009: Paid Usage 60d Global | D1009: 0.3 | E1009: Media spend boost, Global, 60 days
B1010: No | C1010: Paid Usage 90d MENA | D1010: 0.3 | E1010: Media spend boost, MENA region, 90 days
B1011: No | C1011: Paid Usage 90d Global | D1011: 0.45 | E1011: Media spend boost, Global, 90 days
B1012: No | C1012: Whitelisting / Spark Ads | D1012: 0.1 | E1012: Enable brand to run Spark Ads from talent handle
B1013: No | C1013: Exclusivity 30d (category) | D1013: 0.15 | E1013: No competing brand in category for 30 days
B1014: No | C1014: Exclusivity 90d (category) | D1014: 0.35 | E1014: No competing brand in category for 90 days
B1015: No | C1015: Brand Lockup / Logo Usage | D1015: 0.1 | E1015: Talent image + brand lockup for OOH/print
B1016: No | C1016: Licensing (image, 1 year) | D1016: 0.25 | E1016: Likeness license for brand assets, 12 months
B1017: No | C1017: Dedicated Content (non-integrated) | D1017: 0.2 | E1017: Stand-alone brand content, not integration
... B1020: No | C1020: Cross-post to Team Falcons org | D1020: 0.1 | E1020: Re-post from official Team Falcons channels
B1021: TOTAL UPLIFT | C1021: =SUMPRODUCT((B1006:B1020="Yes")*D1006:D1020) -> 0 | E1021: → pulled into 03_Adjustment_Matrix D66 (Add-on Uplift)

Sheet 05_Quote_Template
B2: TEAM FALCONS | D2: Prepared by: | E2: Abdalrahman
D3: Approved by: | E3: TBD
D4: Date: | E4: 14/04/2026
D5: Quote #: | E5: QT-20260414-477
D6: Client: | E6: asdasd
D7: Currency: | E7: SAR
B12: Description | C12: Unit Cost (SAR) | D12: Qty | E12: Amount (SAR)
B14: ImperialHal — IG Static [Dedicated (Brand-led)] | C14: SAR 5,980 | D14: 1 | E14: SAR 5,980
B15: Skiter — Twitch Integration [Dedicated (Brand-led)] | C15: SAR 4,420 | D15: 1 | E15: SAR 4,420
B16: Special notes and instructions | D16: SUBTOTAL | E16: SAR 10,400
B17: asdsddsadsaf | D17: (TAX RATE) | E17: 0.15
D18: TAX | E18: SAR 1,560
D20: TOTAL | E20: SAR 11,960
B23: PRICING MULTIPLIERS BREAKDOWN
B24: Multiplier | C24: Selected Value | D24: Factor | E24: Impact
B25: ① Content Type | C25: Dedicated (Brand-led) | D25: 1.30× | E25: ▲ Premium
B26: ② Engagement Rate | C26: 4% – 6% (1×) | D26: 1.00× | E26: — Baseline
B27: ③ Audience Quality | C27: Gaming-adjacent (1×) | D27: 1.00× | E27: — Baseline
B28: ④ Seasonality | C28: Regular season (1×) | D28: 1.00× | E28: — Baseline
B29: ⑤ Language | C29: English (1×) | D29: 1.00× | E29: — Baseline
B30: ⑥ Authority Level | C30: Normal (1×) | D30: 1.00× | E30: — Baseline
B31: ⑦ Campaign Objective | C31: Awareness (Wt 0.2) | D31: 1.00× | E31: — Baseline
B32: COMBINED PRICE MULTIPLIER | D32: 1.300× | E32: Applied to Base Fee
B34: Formula: Base Fee × ContentType × Engagement × Audience × Seasonality × Language × AuthorityFactor + Add-On Uplifts
B37: King Abdulaziz Road, Riyadh, Saudi Arabia, Al-Yasmeen District Phone: +966 53370 4233 | Sales@falcons.sa | store.falcons.sa
B38: [INTERNAL] ImperialHal: 15% comm | Skiter: 75% comm

Sheet 06_Quote_Log
B2: QUOTE LOG — ARCHIVE OF ISSUED QUOTES
B3: Every quote issued to a client is logged here. Apps Script writes new rows automatically.
B4: Quote ID | C4: Date | D4: Client | E4: Campaign | F4: Owner | G4: Currency | H4: # Lines | I4: Subtotal | J4: Add-Ons % | K4: Pre-VAT | L4: VAT | M4: TOTAL | N4: Confidence | O4: Sheet Name
B5: TF-Q-20260418-001 | C5: 2026-04-18 | D5: Aramco Digital | E5: Ramadan 2026 | F5: commercial@teamfalcons.gg | G5: SAR | H5: 3 | I5: 125000 | J5: 10% | K5: 137500 | L5: 20625 | M5: 158125 | N5: estimated | O5: Quote_TF-Q-20260418-001

Sheet 07_Settings
A1: A (Key) | B1: B (Value)
A2: output_folder_id | B2: (Drive folder ID where PDFs go)
A3: legal_approver_email | B3: legal@…
A4: finance_approver_email | B4: finance@…
A5: client_email | B5: (optional default)
A6: approval_secret | B6: (any random word like falcons2026)

Sheet 08_Benchmarks
A1: 09 — MARKET BENCHMARKS & COMPETITIVE INTELLIGENCE 2025/2026
A2: Industry rate benchmarks, multiplier standards, and competitive positioning for Team Falcons talent monetisation
A4: SECTION 1 — GLOBAL TIER 1 ESPORTS ORG BENCHMARKS
A5: Organisation | B5: Region | C5: Tier | D5: Avg Followers (Key Talent) | E5: Avg Base Fee / Post (USD) | F5: Avg Stream Deal (USD) | G5: Avg Annual Sponsorship (USD) | H5: Exclusivity Premium | I5: Engagement Benchmark | J5: Source / Notes
A6: T1 Esports | B6: Global | C6: Tier 1 | D6: 2M–8M | E6: $8,000–$25,000 | F6: $20,000–$80,000 | G6: $500K–$2M | H6: '+50-100% | I6: 4–7% avg ER | J6: Newzoo 2025; public deal disclosures
A7: FaZe Clan | B7: Global | C7: Tier 1 | D7: 3M–15M | E7: $10,000–$40,000 | F7: $30,000–$120,000 | G7: $1M–$5M | H7: '+40-75% | I7: 3–6% avg ER | J7: Newzoo 2025; SEC filing data
A8: Natus Vincere (NaVi) | B8: EMEA | C8: Tier 1 | D8: 1M–5M | E8: $5,000–$20,000 | F8: $15,000–$60,000 | G8: $300K–$1.5M | H8: '+35-60% | I8: 4–8% avg ER | J8: Shikenso Esports Sponsorship Report 2025
A9: Fnatic | B9: EMEA | C9: Tier 1 | D9: 500K–3M | E9: $4,000–$15,000 | F9: $10,000–$45,000 | G9: $200K–$800K | H9: '+30-50% | I9: 5–9% avg ER | J9: Influencity 2026 Rate Benchmarks
A10: Cloud9 | B10: NA | C10: Tier 1 | D10: 1M–6M | E10: $6,000–$22,000 | F10: $18,000–$70,000 | G10: $400K–$1.8M | H10: '+30-50% | I10: 3–6% avg ER | J10: Nielsen Esports Audience Report 2025
A11: 100 Thieves | B11: NA | C11: Tier 1 | D11: 500K–4M | E11: $5,000–$18,000 | F11: $15,000–$55,000 | G11: $350K–$1.2M | H11: '+40-70% | I11: 5–10% avg ER | J11: Porter Wills Esports Marketing Guide 2025
A13: SECTION 2 — MENA ESPORTS ORG BENCHMARKS
A14: Organisation | B14: Region | C14: Tier | D14: Avg Followers (Key Talent) | E14: Avg Base Fee / Post (SAR) | F14: Avg Stream Deal (SAR) | G14: Avg Annual Sponsorship (SAR) | H14: Exclusivity Premium | I14: Engagement Benchmark | J14: Source / Notes
A15: Team Falcons | B15: KSA / MENA | C15: Tier 1 | D15: 200K–2M | E15: SAR 8,000–60,000 | F15: SAR 20,000–120,000 | G15: SAR 500K–2M | H15: '+35-60% | I15: 5–12% avg ER | J15: Internal Falcons data 2025; Newzoo MENA Report
A16: Nasr Esports | B16: KSA / MENA | C16: Tier 1 | D16: 100K–800K | E16: SAR 5,000–30,000 | F16: SAR 12,000–60,000 | G16: SAR 200K–800K | H16: '+30-50% | I16: 4–9% avg ER | J16: Shikenso MENA Esports Report 2025
A17: GE Wolves | B17: MENA | C17: Tier 2 | D17: 50K–400K | E17: SAR 3,000–15,000 | F17: SAR 8,000–35,000 | G17: SAR 100K–400K | H17: '+25-40% | I17: 5–10% avg ER | J17: Influencity MENA 2025
A18: Twisted Minds | B18: KSA | C18: Tier 2 | D18: 80K–500K | E18: SAR 4,000–20,000 | F18: SAR 10,000–45,000 | G18: SAR 150K–500K | H18: '+25-45% | I18: 6–11% avg ER | J18: Internal market intelligence 2025
A19: Galaxy Racer | B19: UAE / MENA | C19: Tier 2 | D19: 100K–1M | E19: SAR 4,500–22,000 | F19: SAR 11,000–50,000 | G19: SAR 180K–600K | H19: '+25-40% | I19: 4–9% avg ER | J19: Newzoo MENA 2025
A20: Team Vitality (MENA) | B20: MENA | C20: Tier 1 | D20: 200K–1.5M | E20: SAR 6,000–35,000 | F20: SAR 15,000–70,000 | G20: SAR 250K–900K | H20: '+30-50% | I20: 4–8% avg ER | J20: Shikenso Esports Report 2025
A22: SECTION 3 — PLATFORM RATE BENCHMARKS (Industry Standard CPM / CPE)
A23: Platform | B23: Content Type | C23: Nano (1K–10K) | D23: Micro (10K–100K) | E23: Mid (100K–1M) | F23: Macro (1M–5M) | G23: Mega (5M+) | H23: Min Engagement Req. | I23: Avg CPM (Gaming Niche) | J23: Notes / Source
A24: Instagram | B24: Reel (60s) | C24: $200–$1,000 | D24: $1,000–$5,000 | E24: $5,000–$15,000 | F24: $15,000–$50,000 | G24: $50,000+ | H24: Min 3% ER | I24: $8–$15 CPM | J24: Reels outperform static 3:1 for brand recall in gaming. Source: Influencity 2026
A25: Instagram | B25: Static Post | C25: $150–$800 | D25: $800–$4,000 | E25: $4,000–$12,000 | F25: $12,000–$40,000 | G25: $40,000+ | H25: Min 2% ER | I25: $5–$10 CPM | J25: Static posts declining vs Reels. Use for product shots. Source: Influencity 2026
A26: TikTok | B26: Branded Video | C26: $300–$1,500 | D26: $1,500–$6,000 | E26: $6,000–$20,000 | F26: $20,000–$60,000 | G26: $60,000+ | H26: Min 5% ER | I26: $10–$20 CPM | J26: TikTok commands 20–40% premium over IG in MENA. Source: Nielsen 2025
A27: YouTube | B27: Integration (30s) | C27: $500–$2,000 | D27: $2,000–$8,000 | E27: $8,000–$25,000 | F27: $25,000–$80,000 | G27: $80,000+ | H27: Min 1% ER | I27: $15–$30 CPM | J27: Highest brand recall (72% vs 45% social posts). Source: Nielsen Esports 2025
A28: YouTube | B28: Short (<60s) | C28: $200–$1,000 | D28: $1,000–$4,000 | E28: $4,000–$12,000 | F28: $12,000–$35,000 | G28: $35,000+ | H28: Min 3% ER | I28: $8–$18 CPM | J28: YouTube Shorts growing rapidly in MENA. Source: Newzoo 2025
A29: Twitch | B29: Stream Integration (2h) | C29: $1,000–$4,000 | D29: $4,000–$15,000 | E29: $15,000–$40,000 | F29: $40,000–$100,000 | G29: $100,000+ | H29: Min 500 avg viewers | I29: $5–$15 CPM | J29: Rates based on concurrent viewership not followers. Source: StreamElements 2025
A30: X (Twitter) | B30: Sponsored Post | C30: $100–$500 | D30: $500–$2,000 | E30: $2,000–$6,000 | F30: $6,000–$20,000 | G30: $20,000+ | H30: Min 1% ER | I30: $3–$8 CPM | J30: X declining in brand value post-rebrand. Use for real-time only. Source: Influencity 2026
A32: SECTION 4 — MULTIPLIER BENCHMARKS (Industry Standard vs Team Falcons)
A33: Multiplier Type | B33: Industry Low | C33: Industry Standard | D33: Industry High | E33: Team Falcons Rate | F33: Variance vs Industry | G33: Recommendation | H33: Source
A34: Exclusivity (30 days) | B34: 0.15 | C34: 0.25 | D34: 0.4 | E34: 0.25 | F34: At standard | G34: At standard | H34: Influencity 2026; Porter Wills Guide
A35: Exclusivity (90 days) | B35: 0.3 | C35: 0.5 | D35: 0.75 | E35: 0.4 | F35: Below standard — gap of 10% | G35: Below standard — gap of 10% | H35: Influencity 2026; Shikenso 2025
A36: Rush Fee (<72h) | B36: 0.15 | C36: 0.25 | D36: 0.35 | E36: 0.2 | F36: Below standard — gap of 5% | G36: Below standard — gap of 5% | H36: Internal benchmark; Influencity 2026
A37: Usage Rights (6 months) | B37: 0.2 | C37: 0.35 | D37: 0.5 | E37: 0.3 | F37: Below standard — gap of 5% | G37: Below standard — gap of 5% | H37: Porter Wills Esports Guide 2025
A38: Usage Rights (12 months) | B38: 0.4 | C38: 0.6 | D38: 0.8 | E38: 0.5 | F38: Below standard — gap of 10% | G38: Below standard — gap of 10% | H38: Porter Wills Esports Guide 2025
A39: Whitelist / Dark Post | B39: 0.15 | C39: 0.25 | D39: 0.4 | E39: 0.2 | F39: Below standard — gap of 5% | G39: Below standard — gap of 5% | H39: Influencity 2026
A40: Ramadan Premium (MENA) | B40: 0.25 | C40: 0.35 | D40: 0.5 | E40: 0.35 | F40: At standard | G40: At standard | H40: Newzoo MENA 2025; Internal data
A42: SECTION 5 — TEAM FALCONS COMPETITIVE POSITIONING
A43: Metric | B43: Team Falcons | C43: MENA Average | D43: Global Tier 1 | E43: Gap vs MENA | F43: Gap vs Global | G43: Action Required
A44: Roster Size | B44: 188 entries (131 players, 6 influencers, 51 staff) | C44: 80–120 players | D44: 150–200 players | E44: Above MENA avg (+78%) | F44: Above global avg | G44: Leverage scale — offer multi-player bundle packages
A45: Game Coverage | B45: 23 titles | C45: 10–15 titles | D45: 15–20 titles | E45: Above MENA avg | F45: Above global avg | G45: Position as one-stop-shop for brand esports activations
A46: Avg Base Fee (Tier 1) | B46: SAR 15,000 (~$4,000) | C46: SAR 8,000–12,000 | D46: $15,000–$50,000 | E46: Above MENA avg | F46: Below global Tier 1 | G46: Justified for MENA market. Increase for global brand pitches.
A47: Exclusivity Rates | B47: 35–40% uplift | C47: 25–35% uplift | D47: 40–75% uplift | E47: At/above MENA | F47: Below global standard | G47: Increase exclusivity floor to +40% across all tiers
A48: Rush Fee | B48: 20% uplift | C48: 15–20% uplift | D48: 25–35% uplift | E48: At MENA avg | F48: Below global standard | G48: Standardise rush fee at +30% minimum
A50: SECTION 6 — BASE FEE PRICING METHODOLOGY (World-Class Standard)
A51: How to set the base fee — the industry-standard 3-input model used by WME, CAA, and top esports agencies
A53: Input | B53: Formula Component
A54: 1. Audience Reach (CPM) | B54: Base = (Followers x Avg Reach Rate x CPM) / 1000
A55: 2. Engagement Value (CPE) | B55: Base = Total Engagements x CPE Rate
A56: 3. Market Comparables | B56: Base = Comparable talent rate +/- adjustment
A57: 4. Final Base Fee | B57: Base Fee = MAX(CPM model, CPE model, Comparable model) | C57: Take the highest of the 3 inputs as your floor. Never go below this floor. | D57: Never price below the floor — it devalues the talent | E57: This is the BASE before any multipliers. Multipliers are applied on top.
A58: 5. Sanity Check | B58: Final Price / Estimated Impressions = Effective CPM | C58: Effective CPM should be $10–$30 for gaming. If below $8, you are underpriced. | D58: Effective CPM $10–$30 for gaming niche | E58: Run this check on every deal before sending to client.
A60: KEY INSIGHTS & RECOMMENDATIONS FOR TEAM FALCONS
A61: 1. Bundle Pricing Advantage | B61: With 214 entries across 23 games, Falcons can offer multi-player, multi-game bundles that no MENA competitor can match. A 5-player bundle should command a 15–20% premium over individual rates summed.
A62: 2. Ramadan Window is Underpriced | B62: MENA content consumption peaks 3x during Ramadan. Current +35% seasonality multiplier is at the low end of the industry benchmark (+35–50%). Consider increasing to +45% for Tier 1 players.
A63: 3. Exclusivity is Undervalued | B63: Industry standard for 90-day exclusivity is +50%. Falcons currently charges +40%. Closing this gap on Tier 1 players alone could increase annual revenue by 15–20%.
A64: 4. TikTok Premium Opportunity | B64: TikTok commands a 20–40% premium over Instagram in MENA. Ensure TikTok rates reflect this — currently priced at near-parity with IG in some tiers.
A65: 5. Esports Influencers Category is High-Growth | B65: The Esports Influencers in the roster (Bijw, Abo Najd, FMG, etc.) are a premium category. MENA gaming influencers with 500K+ followers command $5,000–$15,000 per post. Ensure their rates reflect this.
A66: 6. Usage Rights are Systematically Underpriced | B66: Every usage rights tier is below industry standard by 5–10%. A systematic +5% increase across all usage rights tiers would add meaningful revenue with zero additional deliverables.
A68: DATA SOURCES & METHODOLOGY
A69: Source | B69: Type | C69: URL / Reference | D69: Data Used In
A70: Newzoo Global Esports & Live Streaming Market Report 2025 | B70: Industry Report | C70: newzoo.com/reports | D70: Sections 1, 2, 5 — org benchmarks, MENA market data
A71: Shikenso Esports Sponsorship ROI Guide 2025 | B71: Agency Report | C71: shikenso.com/resources | D71: Sections 1, 2, 4 — sponsorship values, multiplier benchmarks
A72: Nielsen Esports Audience Report 2025 | B72: Research Report | C72: nielsen.com/esports | D72: Sections 3, 4 — CPM benchmarks, brand recall data
A73: Influencity 2026 Rate Card Benchmarks | B73: Platform Data | C73: influencity.com/blog | D73: Sections 3, 4 — platform rates, multiplier standards
A74: Porter Wills Esports Marketing Guide 2025 | B74: Agency Guide | C74: porterwills.com | D74: Sections 1, 4, 6 — Tier 1 benchmarks, usage rights pricing
A75: StreamElements State of Streaming 2025 | B75: Platform Report | C75: streamelements.com/reports | D75: Section 3 — Twitch/streaming rate benchmarks
A76: WME / CAA / Wasserman Agency Practice | B76: Industry Standard | C76: Public deal disclosures & industry knowledge | D76: Section 6 — base fee pricing methodology
A77: Internal Team Falcons Commercial Data 2025 | B77: Internal | C77: Confidential | D77: Sections 2, 5 — Falcons-specific rates and positioning

Sheet 09_Guide_EN
B2: 05 — PRICING GUIDE & BEST PRACTICES (ENGLISH)
B3: How to use this Rate Card · Pricing Formula · Tier Definitions · Base Fee Methodology · Best Practices · Data Sources
B5: HOW TO USE THIS RATE CARD — 5 STEPS
B6: Step 1 — Find the Talent
B7: Go to 01_Player_Rate_Card. All 188 entries are listed. Use the filter on column D (Role) or I (Tier) or E (Game). Players: 131 | Influencers: 6 | Staff & Coaches: 51 | Across 23 games and 21 teams.
B9: Step 2 — Read the Base Fees
B10: The base fee is the starting price for each asset type based on talent tier. Tier 1 = premium price, Tier 2 = target price, Tier 3 = emerging price. Base fees are in SAR and include a USD equivalent at the current rate.
B12: Step 3 — Apply Adjustment Multipliers
B13: Go to 02_Adjustment_Matrix. Enter the base fee in cell C31. Select the appropriate multipliers for engagement quality (C32), audience quality (C33), and seasonality (C34). The matrix auto-calculates the adjusted price.
B15: Step 4 — Add Rights Packages
B16: Go to 03_Add_On_Rights. Select the required rights packages (exclusivity, usage rights, whitelist, rush fee, etc.). Sum the uplift percentages and enter the total in cell C35 of the Adjustment Matrix.
B18: Step 5 — Build the Full Deal
... B144: STEP-BY-STEP
B145: Step 1 | C145: Fill Campaign Details (rows 5-9): Campaign name, brand, period, prepared by
B146: Step 2
B147: Step 3 | C147: Add line items (rows 19-33): For each deliverable, select from dropdowns:
C148: • Player / Talent — select from full roster dropdown
C149: • Deliverable — IG Reel, TikTok Video, Twitch Stream, IRL Appearance, etc.
C150: • Qty — number of posts/appearances
C151: • Timing — Regular Season, Ramadan, EWC, etc. (auto-applies multiplier)
C152: • Audience — Core Gaming, Esports-focused, MENA/Saudi, etc. (auto-applies multiplier)
C153: • Add-on Package — None, Basic, Standard, Premium, Full, Exclusive (auto-applies uplift %)
B154: Step 4 | C154: Unit Price auto-calculates: Base Rate × Timing Multiplier × Audience Multiplier × (1 + Add-on %)
B155: Step 5 | C155: Summary auto-calculates: Subtotal → +10% Mgmt Fee → +15% VAT → Total SAR + USD
B156: Step 6 | C156: Click "GENERATE PDF QUOTE" button to export a formatted client document
B158: PRICING METHODOLOGY (Updated 2025)
B159: All player rates have been recalibrated using best-practice 2025 benchmarks:
B160: Source | C160: Porter Wills Esports Guide 2025, InfluenceFlow Benchmarks, Cloutboost Gaming Rates
B161: Tier 1 IG Reel Base | C161: 18,000 SAR (was 15,000) — aligned to macro esports creator rates ($4,800 USD)
B162: Tier 2 IG Reel Base | C162: 11,000 SAR (was 11,250) — refined for 100K-500K reach segment
B163: Tier 3 IG Reel Base | C163: 6,500 SAR (was 8,750) — corrected downward to match micro-creator benchmarks
B164: Platform Ratios | C164: TikTok = 78% of IG Reel | Twitch 2h = 145% | IRL = 220% | X Post = 20%
B165: Platform Count Bonus | C165: 0-1 platforms: -20% | 2-3: standard | 4-5: +15% | 6-7: +25% | 8+: +35%
B166: MENA Premium
B168: ADD-ON PACKAGES (simplified from 03_Add_On_Rights)
B169: None | C169: 0% uplift — base rate only
B170: Basic (+15%) | C170: Organic repost, 1 month — single platform
B171: Standard (+60%) | C171: Organic repost (3 months) + paid usage (limited)
B172: Premium (+115%) | C172: Organic repost (6 months) + paid usage (standard) + MENA territory
B173: Full (+170%) | C173: All organic + paid max + whitelisting (30 days)
B174: Exclusive (+320%) | C174: Full package + category exclusivity (12 months)
B176: TIMING MULTIPLIERS
B177: Regular Season | C177: 1.00x — baseline
B178: Off-season | C178: 0.80x — lower viewership
B179: Regional Major | C179: 1.25x — regional championship
B180: Global Major / Worlds | C180: 1.40x — peak esports interest
B181: Game Launch | C181: 1.30x — new title release
B182: Holiday Q4 | C182: 1.20x — year-end peak
B183: Ramadan (MENA) | C183: 1.35x — peak MENA consumption
B184: EWC / Mega Peak | C184: 1.50x — Esports World Cup (highest multiplier)
B186: AUDIENCE MULTIPLIERS
B187: Generic / Broad | C187: 0.85x
B188: Gaming-adjacent | C188: 1.00x
B189: Core Gaming | C189: 1.20x
B190: MENA / Saudi focus | C190: 1.30x
B191: Esports-focused | C191: 1.40x

Sheet 10_Guide_AR
B2: دليل التسعير وأفضل الممارسات — عربي
B3: كيفية الاستخدام · معادلة التسعير · منهجية الرسوم الأساسية · تعريفات الفئات · أفضل الممارسات · مصادر البيانات
B5: كيفية استخدام بطاقة الأسعار — 5 خطوات
B6: الخطوة 1 — ابحث عن المواهب
B7: اذهب إلى 01_Player_Rate_Card. جميع الـ 188 إدخالاً مدرجة. استخدم الفلتر على عمود D (الدور) أو I (الفئة) أو E (اللعبة). اللاعبون: 131 | المؤثرون: 6 | الطاقم والمدربون: 51 | عبر 23 لعبة و21 فريق.
B9: الخطوة 2 — اقرأ الرسوم الأساسية
B10: الرسوم الأساسية هي السعر المبدئي لكل نوع من الأصول بناءً على فئة الموهبة. الفئة 1 = سعر مرتفع، الفئة 2 = السعر المستهدف، الفئة 3 = سعر منخفض. الرسوم بالريال السعودي مع ما يعادلها بالدولار.
B12: الخطوة 3 — طبّق معاملات التعديل
B13: اذهب إلى 02_Adjustment_Matrix. أدخل الرسوم الأساسية في الخلية C31. اختر المضاعفات المناسبة لجودة التفاعل (C32) وجودة الجمهور (C33) والموسمية (C34). تحسب الورقة تلقائياً السعر المعدّل.
B15: الخطوة 4 — أضف حزم الحقوق
B16: اذهب إلى 03_Add_On_Rights. اختر حزم الحقوق المطلوبة (الحصرية، حقوق الاستخدام، القائمة البيضاء، رسوم الاستعجال، إلخ). اجمع نسب الزيادة وأدخل الإجمالي في الخلية C35 من مصفوفة التعديل.
B18: الخطوة 5 — ابنِ الصفقة الكاملة
... B143: خطوات الاستخدام
B144: الخطوة 1 | C144: تفاصيل الحملة (صفوف 5-9): اسم الحملة، العلامة التجارية، الفترة، المُعِد
B145: الخطوة 2
B146: الخطوة 3 | C146: أضف بنود التسليم (صفوف 19-33): لكل تسليم، اختر من القوائم:
C147: • اللاعب / الموهبة — اختر من القائمة الكاملة للرياضيين
C148: • نوع التسليم — ريلز إنستغرام، فيديو تيك توك، بث تويتش، حضور شخصي، إلخ
C149: • الكمية — عدد المنشورات أو الظهورات
C150: • التوقيت — الموسم العادي، رمضان، كأس العالم للرياضات الإلكترونية، إلخ
C151: • الجمهور — ألعاب أساسية، رياضات إلكترونية، منطقة الشرق الأوسط وشمال أفريقيا، إلخ
C152: • باقة الإضافات — لا شيء، أساسية، قياسية، مميزة، كاملة، حصرية
B153: الخطوة 4 | C153: يُحسب سعر الوحدة تلقائياً: السعر الأساسي × مضاعف التوقيت × مضاعف الجمهور × (1 + نسبة الإضافات)
B154: الخطوة 5 | C154: الملخص يُحسب تلقائياً: المجموع الفرعي + رسوم الإدارة 10% + ضريبة القيمة المضافة 15%
B155: الخطوة 6 | C155: انقر على "إنشاء عرض سعري PDF" لتصدير وثيقة منسقة للعميل
B157: منهجية التسعير (محدّثة 2025)
B158: تم إعادة معايرة جميع أسعار اللاعبين وفق أفضل الممارسات العالمية لعام 2025:
B159: الدرجة الأولى — ريلز إنستغرام | C159: 18,000 ريال (كانت 15,000) — متوافق مع معدلات منشئي المحتوى الكبار في الرياضات الإلكترونية
B160: الدرجة الثانية — ريلز إنستغرام | C160: 11,000 ريال (كانت 11,250) — محسّن لشريحة 100K-500K متابع
B161: الدرجة الثالثة — ريلز إنستغرام | C161: 6,500 ريال (كانت 8,750) — مصحّح للتوافق مع معايير منشئي المحتوى الصغار
B162: نسب المنصات | C162: تيك توك = 78% من ريلز إنستغرام | تويتش 2 ساعة = 145% | حضور شخصي = 220%
B163: مكافأة عدد المنصات | C163: 0-1 منصة: -20% | 2-3: معياري | 4-5: +15% | 6-7: +25% | 8+: +35%
B164: علاوة منطقة MENA
B166: باقات الإضافات (مبسّطة)
B167: لا شيء
B168: أساسية (+15%) | C168: إعادة نشر عضوي، شهر واحد — منصة واحدة
B169: قياسية (+60%) | C169: إعادة نشر عضوي (3 أشهر) + استخدام مدفوع (محدود)
B170: مميزة (+115%) | C170: إعادة نشر عضوي (6 أشهر) + استخدام مدفوع (قياسي) + حقوق منطقة MENA
B171: كاملة (+170%) | C171: جميع الحقوق العضوية + الاستخدام المدفوع الكامل + القائمة البيضاء (30 يوماً)
B172: حصرية (+320%) | C172: الباقة الكاملة + حصرية الفئة (12 شهراً)
B174: مضاعفات التوقيت
B175: الموسم العادي
B176: خارج الموسم | C176: 0.80x — مشاهدة منخفضة
B177: بطولة إقليمية كبرى | C177: 1.25x — بطولة إقليمية
B178: بطولة عالمية | C178: 1.40x — ذروة الاهتمام بالرياضات الإلكترونية
B179: إطلاق لعبة | C179: 1.30x — إصدار عنوان جديد
B180: نهاية العام (الربع الرابع) | C180: 1.20x — ذروة نهاية العام
B181: رمضان (منطقة MENA) | C181: 1.35x — ذروة الاستهلاك في منطقة MENA
B182: كأس العالم للرياضات الإلكترونية | C182: 1.50x — أعلى مضاعف في النظام

Sheet 11_Methodology
A1: TEAM FALCONS — COMMERCIAL PRICING METHODOLOGY & ROADMAP
A3: ① CURRENT PRICING MODEL (v2.0 — April 2026)
A4: Our current pricing engine uses a Base Rate + Multiplier model. This ensures baseline consistency across 189+ players while allowing dynamic adjustments for campaign specifics, audience quality, and content type.
A6: BASE RATES (The Foundation)
A7: Base rates are established per player, per platform, based on their Tier (1, 2, or 3) and Role (Player, Influencer, Coach, etc.).
A8: • Social Media: IG Reel, TikTok, YT Short, X Post, FB Post/Video
A9: • Live & Stream: Twitch 2h Stream, Twitch Integration
A10: • On-Ground & Events: IRL Appearance, Podcast Guesting (50% IRL), PR/CSR (100% IRL), Fan Meet (70% IRL), Photo Shoot (75% IRL) | B10: C | C10: D | D10: E | E10: F
B11: Audience Reach × CPM Rate | C11: Base Fee = (Followers × Avg Reach Rate × CPM) ÷ 1,000 Reach rates: IG 15–25%, TikTok 20–35%, YT 10–20% Gaming CPM: $8–$20 USD (MENA: $10–$15) | D11: WME, CAA, Wasserman standard FaZe: $15–25 CPM for gaming T1: $12–18 CPM for esports | E11: Applied as Floor 1 in our 3-input model. Sets the minimum viable rate based on expected impressions.
A12: THE MULTIPLIER CHAIN (The Adjustments) | B12: Engagement Quality Multiplier | C12: Multiplier applied on top of CPM floor: < 2%: 0.70x (below market) 2–4%: 0.90x (average) 4–6%: 1.00x (baseline) 6–8%: 1.20x (good) 8–10%: 1.40x (excellent) > 10%: 1.60x (premium micro) | D12: Industry standard: 4–6% is baseline for gaming Micro-influencers (< 100K) often 8–15% Macro (> 1M) typically 2–4% | E12: Applied as Engagement Multiplier in 02_Adjustment_Matrix. Reflects true audience quality beyond raw follower count.
A13: Final Price = Base Rate × Content Type × Engagement × Audience × Seasonality × Language × Authority Factor | B13: Targeting Value Multiplier | C13: Multiplier based on audience composition: Generic/Broad: 0.85x Gaming-adjacent: 1.00x Core Gaming: 1.20x MENA/Saudi focus: 1.30x Esports-focused: 1.40x Global Esports Elite: 1.50x | D13: Esports audiences command 30–50% premium over general gaming due to purchase intent. MENA premium: 20–35% above global baseline. | E13: Applied as Audience Quality Multiplier. Esports-focused Saudi audiences = highest value tier.
A14: • Content Type: Integrated (1.00x) vs. Dedicated/Brand-led (1.30x) | B14: Follower + Engagement Tier System | C14: Tier 1 (Premium): 1M+ followers, 8%+ engagement Tier 2 (Target): 100K–1M followers, 5–8% Tier 3 (Emerging): 10K–100K followers, high engagement Base rates set per tier per platform. | D14: T1 Esports: Faker = $50K+/post FaZe Clan Tier 1: $15K–$30K IG Reel NRG Tier 2: $5K–$12K IG Reel Micro-esports: $1K–$5K | E14: Tier 1 IG Reel: SAR 18,000 (~$4,800) Tier 2 IG Reel: SAR 11,000 (~$2,933) Tier 3 IG Reel: SAR 6,500 (~$1,733)
A15: • Engagement: Scales from 0.70x (<2%) to 1.60x (>10%) | B15: Cross-Platform Rate Calibration | C15: Relative value of each platform vs IG Reel (baseline): IG Reel = 100% (baseline) TikTok Video = 78% YouTube Short = 32% X Post = 20% Twitch Stream 2h = 145% Twitch Integration = 65% IRL Appearance = 220% | D15: Industry standard ratios from InfluenceFlow, Cloutboost, Porter Wills 2025. Twitch commands premium for live engagement. | E15: Applied in 01_Player_Rate_Card. All platform rates derived from IG Reel base × ratio.
A16: • Audience Quality: Gaming-adjacent (1.00x) vs. Esports Core (1.20x) | B16: Multi-Platform Presence Premium | C16: Bonus for talent with broad platform reach: 0–1 platforms: -20% 2–3 platforms: standard (0%) 4–5 platforms: +15% 6–7 platforms: +25% 8+ platforms: +35% | D16: Multi-platform creators command 15–35% premium due to broader campaign reach and cross-platform amplification. | E16: Applied at base fee level in rate card. Encourages talent to build multi-platform presence.
A17: • Seasonality: Regular (1.00x) vs. Ramadan/EWC Peak (1.25x) | B17: Demand-Based Timing Premium | C17: Off-season: 0.80x Regular season: 1.00x Regional Major: 1.25x Game Launch: 1.30x Holiday Q4: 1.20x Ramadan (MENA): 1.35x Global Major/Worlds: 1.40x EWC / Mega Peak: 1.50x | D17: Ramadan = highest MENA consumption period. EWC = highest esports event in MENA calendar. Peak demand = premium pricing justified. | E17: Applied in 02_Adjustment_Matrix. EWC multiplier (1.50x) is highest in the system.
A18: • Language: Arabic/Local (1.00x) vs. Global English (1.15x) | B18: IRL Appearance-Based Price Floor | C18: Ensures pro player pricing never falls below their appearance value: Floor = IRL_Fee × FloorShare × Seasonality × Language × AuthorityFactor Final = MAX(SocialPrice, AuthorityFloor) | D18: Used by WME, CAA for athlete-influencers. Pro status commands minimum floor regardless of social metrics. | E18: Applied in 02_Adjustment_Matrix. Protects Falcons pro player pricing integrity.
A19: • Authority Factor: Weighted blend of Awareness (0.3), Conversion (0.6), and Trust (0.9) based on player prestige | B19: Usage Rights & Exclusivity Uplift | C19: None: 0% Basic (+15%): Organic repost, 1 month Standard (+60%): Organic + paid (limited) Premium (+115%): Organic + paid + MENA territory Full (+170%): All organic + paid + whitelist Exclusive (+320%): Full + category exclusivity 12 months | D19: Industry standard: usage rights add 15–320% to base rate depending on scope. Exclusivity is the highest-value add-on. | E19: Applied in 03_Add_On_Rights. All rights packages documented with clear scope.
B20: Final Invoice Calculation | C20: Player Cost = Final Price ÷ (1 + Markup%) Falcons Revenue = Final Price - Player Cost Client Invoice = Final Price × 1.15 (15% KSA VAT) USD Equivalent = SAR ÷ 3.75 | D20: Standard agency model: 10–30% management fee. KSA VAT: 15% on all commercial transactions. Falcons markup: 20–75% depending on talent. | E20: Applied in 02_Adjustment_Matrix rows 64–70. All quotations include VAT in final client price.
A21: ADD-ONS & RIGHTS
A22: Applied as a percentage uplift on the final adjusted price:
A23: • Organic Repost: +15%
A24: • Paid Usage: Min (+15%), Std (+25%), Max (+40%)
A25: • Whitelisting: 30 Days (+15%), 90 Days (+25%), 1 Year (+40%)
A26: • Territory: MENA (Incl.), Global (+20%)
A27: • Exclusivity: Category 1mo (+20%), 3mo (+35%), 6mo (+50%)
A29: ② THE ROADMAP: EVOLVING TO WORLD-CLASS STANDARDS | B29: EVOLUTION COMPONENT | C29: DESCRIPTION | D29: FORMULA ADDITION | E29: PRIORITY
A30: To align with global Tier 1 esports organizations (T1, FaZe, 100 Thieves) and premium sports marketing agencies (CAA, WME), Team Falcons is transitioning from a static rate card to a dynamic, data-driven valuation model. | B30: Hourly Rate Integration | C30: Add a minimum hourly rate floor for all content creation. A 60-second IG Reel requires 4–8 hours of work (filming, editing, revisions). Current model ignores this. Minimum floor: SAR 500–800/hour for Tier 2–3 talent. | D30: HourlyFloor = HourlyRate × EstimatedHours Final = MAX(CurrentPrice, HourlyFloor) | E30: 🔴 HIGH — implement Q3 2026
B31: Production Cost Pass-Through | C31: When Falcons provides production support (camera crew, studio, editor, graphic designer), these costs should be itemized and passed through to the client at cost + 20% margin. Separates talent fee from production fee for cleaner P&L. | D31: Total = TalentFee + ProductionCost × 1.20 ProductionCost = Crew + Studio + Post-Production | E31: 🟡 MEDIUM — implement Q4 2026
A32: PHASE 1: Standardization (Current) | B32: Deliverable Complexity Scoring | C32: Not all IG Reels are equal. A 30-second product showcase ≠ a 3-minute cinematic brand story. Introduce a complexity score (1–5) that multiplies the base rate. Simple post: 1.0x. Complex branded content: 2.5–3.5x. | D32: ComplexityMultiplier = 1.0 to 3.5 AdjustedBase = BaseFee × ComplexityMultiplier | E32: 🟡 MEDIUM — implement Q1 2027
A33: • Unified rate card across all 189+ talents | B33: Performance-Based Bonus Tier | C33: Introduce a performance kicker: if content exceeds agreed KPIs (views, engagement, conversions), talent earns a bonus (10–25% of base). This aligns talent incentives with brand outcomes and is standard practice at T1 agencies for premium campaigns. | D33: BonusTrigger = IF(ActualKPI > TargetKPI × 1.2, BaseFee × 0.15, 0) FinalPayout = BaseFee + BonusTrigger | E33: 🟢 STRATEGIC — implement Q2 2027
A34: • Automated quote generation with transparent multiplier breakdowns | B34: Dynamic Market Rate Engine | C34: Replace static tier rates with a dynamic engine that pulls real-time market data: competitor pricing, platform CPM fluctuations, demand signals (event calendar), and talent performance history. Rates auto-adjust quarterly. This is how WME and CAA operate at scale. | D34: DynamicRate = f(MarketCPM, CompetitorRates, DemandIndex, TalentScore) Quarterly recalibration cycle | E34: 🔵 LONG-TERM — 2027+
A35: • Clear distinction between Integrated (Player-led) and Dedicated (Brand-led) content | B35: Full Cost-Plus Model for Branded Content | C35: For large-scale branded content series (3+ episodes, documentary-style, event coverage), move to a full cost-plus model: Total Cost = (Talent + Production + Distribution + Management) × (1 + Target Margin%) This is how Netflix, Amazon, and premium brand studios price content partnerships. | D35: TotalCost = Σ(AllCosts) × (1 + MarginTarget) MarginTarget = 25–40% for premium content | E35: 🔵 LONG-TERM — 2027+
A37: PHASE 2: CPM & Performance Integration (Q3 2026)
A38: • Shikenso Analytics Integration: Moving from static base rates to dynamic CPM-based pricing.
A39: • Formula: Price = (Average Views / 1000) × Target CPM
A40: • Target CPMs: IG Reels ($15-$25), TikTok ($10-$20), YouTube ($20-$35)
A41: • Why: Brands buy guaranteed impressions. CPM pricing justifies premium rates for high-performing talent and protects the brand on underperforming posts. | B41: HOURS ESTIMATE | C41: RATE/HOUR (SAR) | D41: FLOOR COST (SAR) | E41: NOTES
B42: 4–8 hours | C42: SAR 500–800 | D42: SAR 2,000–6,400 | E42: Filming + editing + revisions
A43: PHASE 3: Salary Benchmarking & Floor Pricing (Q4 2026) | B43: 3–6 hours | C43: SAR 400–700 | D43: SAR 1,200–4,200 | E43: Faster production cycle
A44: • Implementing a "Cost-Plus" floor to ensure commercial activities never operate at a loss relative to player salaries and operational overhead. | B44: 4–7 hours | C44: SAR 500–800 | D44: SAR 2,000–5,600 | E44: Higher production standard
A45: • Hourly Floor = (Player Annual Salary / 2000 hours) × Complexity Multiplier | B45: 3 hours prep + 2h live | C45: SAR 600–1,000 | D45: SAR 3,000–5,000 | E45: Prep + live + post-stream
A46: • Final Quote = MAX(Market CPM Valuation, Hourly Floor Cost) | B46: 6–8 hours total | C46: SAR 800–1,500 | D46: SAR 4,800–12,000 | E46: Travel + appearance + debrief
A47: • Why: Protects the organization's bottom line when deploying highly-paid Tier 1 talent for time-intensive branded content. | B47: 30–50 hours | C47: SAR 700–1,200 | D47: SAR 21,000–60,000 | E47: Full production cycle
B48: 60–120 hours | C48: SAR 1,000–2,000 | D48: SAR 60,000–240,000 | E48: Premium branded content
A49: PHASE 4: IP & Brand Equity Premium (2027) | B49: 8–10 hours | C49: SAR 3,000–8,000/day | D49: SAR 3,000–8,000 | E49: Camera, lighting, sound
A50: • Charging for the "Falcons Halo Effect" — not just the player's reach, but the association with the MENA region's premier esports brand. | B50: 8–16 hours/video | C50: SAR 400–800/hour | D50: SAR 3,200–12,800 | E50: Color grade + sound + motion
A51: • Implementation of a flat +20% IP usage fee on all campaigns that utilize Falcons branding, jerseys, or facilities. | B51: 4–8 hours/asset | C51: SAR 300–600/hour | D51: SAR 1,200–4,800 | E51: Thumbnails, overlays, branding
A53: ③ GLOBAL ESPORTS PRICING BENCHMARKS (2026)
A54: • T1 (Global): $15k-$50k+ per IG Reel (CPM + Authority floor, massive Faker premium) | B54: TIER 1 IG REEL | C54: TIER 2 IG REEL | D54: APPROACH | E54: KEY DIFFERENTIATOR
A55: • FaZe Clan (NA): $12k-$30k per IG Reel (Entertainment-first, lifestyle premium) | B55: $15,000–$50,000+ | C55: $3,000–$8,000 | D55: CPM + Authority floor | E55: Faker premium: 3–5x standard T1 rate
A56: • 100 Thieves (NA): $10k-$25k per IG Reel (Fashion/lifestyle hybrid premium) | B56: $12,000–$30,000 | C56: $2,500–$6,000 | D56: CPM + Brand equity premium | E56: Entertainment-first, gaming-adjacent audience
A57: • Team Falcons (Current): ~$3k-$5k per IG Reel (MENA premium + Event multipliers) | B57: $8,000–$20,000 | C57: $2,000–$5,000 | D57: CPM-based, platform ratios | E57: Strong esports-focused audience premium
A58: • Team Falcons (Target 2027): $6k-$10k+ per IG Reel (Full CPM + IP Equity model) | B58: $10,000–$25,000 | C58: $2,500–$6,000 | D58: Lifestyle + esports hybrid | E58: Fashion/lifestyle premium on top of gaming
A59: NRG (NA) | B59: $6,000–$15,000 | C59: $1,500–$4,000 | D59: Standard CPM model | E59: Competitive esports focus
A60: Karmine Corp (EU) | B60: €5,000–€15,000 | C60: €1,500–€4,000 | D60: CPM + MENA/EU premium | E60: Strong French-speaking audience premium
A61: Team Falcons (MENA) | B61: SAR 18,000 (~$4,800) | C61: SAR 11,000 (~$2,933) | D61: CPM + Authority + Seasonality | E61: MENA premium + Ramadan/EWC multipliers
A62: Team Falcons (Target) | B62: SAR 25,000+ (~$6,667) | C62: SAR 15,000+ (~$4,000) | D62: Full cost-based model | E62: Phase 3 evolution target (2027)
A64: 🦅 Team Falcons — Commercial Pricing Engine v2.0 · Confidential — Internal Use Only · April 2026
