Workbook

Sheet 00_Cover
B3: TEAM FALCONS
B4: Talent Commercial Rate Card · 2026
B5: Global Esports Pricing & Monetization Framework
B6: Updated: 14 April, 2026 · Currency: SAR · 1 USD = 3.75 SAR
B7: =IFERROR(__xludf.dummyfunction("""Total Talent: ""&COUNTA('01_Player_Rate_Card'!$C$5:$C$500)&"" entries across ""&COUNTUNIQUE(FILTER('01_Player_Rate_Card'!$E$5:$E$500,'01_Player_Rate_Card'!$E$5:$E$500<>""""))&"" games · ""&COUNTIF('01_Player_Rate_Card'!$D$5:$D$500,""Player"")&"" playe"&"rs · ""&COUNTUNIQUE(FILTER('01_Player_Rate_Card'!$F$5:$F$500,'01_Player_Rate_Card'!$F$5:$F$500<>""""))&"" teams · Confidential — Internal Use Only"""),"Total Talent: 189 entries across 23 games · 131 players · 21 teams · Confidential — Internal Use Only") -> Total Talent: 189 entries across 23 games · 131 players · 21 teams · Confidential — Internal Use Only
B10: =COUNTA('01_Player_Rate_Card'!$C$5:$C$500) -> 189 | D10: =COUNTIF('01_Player_Rate_Card'!$D$5:$D$500,"Player") -> 131 | F10: =COUNTIF('01_Player_Rate_Card'!$D$5:$D$500,"Influencer") -> 8 | H10: =COUNTA('01_Player_Rate_Card'!$C$5:$C$500)-COUNTIF('01_Player_Rate_Card'!$D$5:$D$500,"Player")-COUNTIF('01_Player_Rate_Card'!$D$5:$D$500,"Influencer") -> 50 | J10: =COUNTIF('01_Player_Rate_Card'!$I$5:$I$500,"Tier 1")&"/"&COUNTIF('01_Player_Rate_Card'!$I$5:$I$500,"Tier 2")&"/"&COUNTIF('01_Player_Rate_Card'!$I$5:$I$500,"Tier 3") -> 10/71/71
B11: Total Entries | D11: Players | F11: Esports Influencers | H11: Staff & Coaches | J11: T1 / T2 / T3
B13: SHEET NAVIGATION
B14: 01_Player_Rate_Card | D14: ="All "&COUNTA('01_Player_Rate_Card'!$C$5:$C$500)&" entries · rates per platform · filterable by role/game/team/tier" -> All 189 entries · rates per platform · filterable by role/game/team/tier
B15: 02_Adjustment_Matrix | D15: Engagement · Audience · Seasonality multipliers + Live Calculator
B16: 03_Add_On_Rights | D16: Rights packages with uplift % + bundle presets
B18: 05_Guide_EN | D18: Pricing methodology, formula, best practices (English)
B19: 06_Guide_AR | D19: دليل التسعير الكامل بالعربي
B20: COLOR LEGEND | D20: 1M+ followers · 8%+ engagement · World-class talent
B21: Tier 1 — Premium | D21: 100K–1M followers · 5–8% engagement · Established
B22: Tier 2 — Target | D22: 10K–100K followers · High engagement · Rising stars
B23: Tier 3 — Emerging | D23: Coaching staff — rates apply for appearances & content
B24: Coach / Head Coach | D24: Management staff — rates apply for appearances
B25: Manager | D25: Analyst staff — rates apply for appearances
B26: Analyst

Sheet QT_Template
B2: TEAM FALCONS | E2: Prepared by: | F2: —
E3: Approved by: | F3: —
E4: Date: | F4: {{DATE}}
E5: Quote #: | F5: {{QUOTE_ID}}
E6: Client: | F6: {{CLIENT}}
E7: Currency: | F7: SAR
B12: QUOTE LINE ITEMS
B13: Description | C13: Unit Cost (SAR) | D13: Qty | E13: Amount (SAR)
B14: — (line 1) — | C14: 0 | D14: 1 | E14: =C14*D14 -> 0
B15: — (line 2) — | C15: 0 | D15: 1 | E15: =C15*D15 -> 0
B16: — (line 3) — | C16: 0 | D16: 1 | E16: =C16*D16 -> 0
B17: — (line 4) — | C17: 0 | D17: 1 | E17: =C17*D17 -> 0
B18: — (line 5) — | C18: 0 | D18: 1 | E18: =C18*D18 -> 0
B19: — (line 6) — | C19: 0 | D19: 1 | E19: =C19*D19 -> 0
B20: — (line 7) — | C20: 0 | D20: 1 | E20: =C20*D20 -> 0
B21: Special notes and instructions: | D21: SUBTOTAL | E21: =SUM(E14:E20) -> 0
B22: {{CLIENT_NOTES}} | D22: (TAX RATE) | E22: 0.15
D23: TAX | E23: =E21*E22 -> 0
D25: TOTAL | E25: =E21+E23 -> 0
B28: PRICING MULTIPLIERS (9-AXIS MATRIX)
B29: Multiplier | C29: Selected Value | D29: Factor | E29: Impact
B30: ① Content Type | C30: {{CONTENT}} | D30: 1 | E30: — Baseline
B31: ② Engagement Rate | C31: {{ENGAGEMENT}} | D31: 1 | E31: — Baseline
B32: ③ Audience Quality | C32: {{AUDIENCE}} | D32: 1 | E32: — Baseline
B33: ④ Seasonality | C33: {{SEASONALITY}} | D33: 1 | E33: — Baseline
B34: ⑤ Language | C34: {{LANGUAGE}} | D34: 1 | E34: — Baseline
B35: ⑥ Authority Level | C35: {{AUTHORITY}} | D35: 1 | E35: — Baseline
B36: ⑦ Campaign Objective | C36: {{CAMPAIGN}} | D36: 1 | E36: — Baseline
B37: COMBINED PRICE MULTIPLIER | D37: =PRODUCT(D30:D36) -> 1 | E37: Applied to Base Fee
B40: Formula: Base Fee × Combined Multiplier + Add-Ons → Subtotal → TAX → TOTAL | Authority Floor = IRL × FloorShare × Seasonality × Language × AuthorityFactor
B42: King Abdulaziz Road, Riyadh 11564, Saudi Arabia · contact@teamfalcons.com
B43: [INTERNAL] FMG: 30% commission baseline. Authority Floor enforced per Methodology §3.

Sheet 07_Settings
A1: A (Key) | B1: B (Value)
A2: output_folder_id | B2: (Drive folder ID where PDFs go)
A3: legal_approver_email | B3: legal@…
A4: finance_approver_email | B4: finance@…
A5: client_email | B5: (optional default)
A6: approval_secret | B6: (any random word like falcons2026)
A8: TIER DEFAULTS TABLE
A9: Tier | B9: Label | C9: Follower Threshold | D9: Base Fee Min (SAR) | E9: Base Fee Max (SAR) | F9: Floor Share % | G9: Notes
A10: Tier S | B10: Superstar | C10: >1M on any platform | D10: 40000 | E10: 50000 | F10: 0.65 | G10: Global anchors — premium brand deals
A11: Tier 1 | B11: Star | C11: 250K–1M | D11: 22000 | E11: 30000 | F11: 0.55 | G11: Core pro athletes with notable reach
A12: Tier 2 | B12: Core Influencer | C12: 50K–250K | D12: 11000 | E12: 18000 | F12: 0.45 | G12: Active pros + mid-tier creators
A13: Tier 3 | B13: Rising | C13: 10K–50K | D13: 6500 | E13: 10000 | F13: 0.35 | G13: Emerging talent + niche specialists
A14: Tier 4 | B14: Entry / Staff | C14: <10K or staff | D14: 3000 | E14: 5500 | F14: 0.25 | G14: Support roles + developing roster
A17: MEASUREMENT CONFIDENCE LEVELS
A18: Level | B18: Trigger | C18: Premium Multipliers Allowed?
A19: exact | B19: Verified via Shikenso or direct platform API | C19: Yes — all multipliers available
A20: rounded | B20: Manual verification with clean round numbers | C20: Yes — all multipliers available
A21: estimated | B21: Partial data, public research, single-source | C21: Limited — engagement <1.2x, authority <1.3x
A22: pending | B22: No follower data yet | C22: No — default 1.0x multipliers only
A24: AUTHORITY FLOOR FORMULA
A25: Authority Floor = IRL Fee × Floor Share × Seasonality × Language × Authority Factor
A26: Final Price = MAX(Social Price, Authority Floor) × (1 + Add-on Rights %)

Sheet 01_Player_Rate_Card
B2: ="TALENT RATE CARD — ALL "&COUNTA($C$5:$C$500)&" ENTRIES" -> TALENT RATE CARD — ALL 189 ENTRIES | AO2: FOLLOWERS / SUBSCRIBERS ← enter real numbers here | AV2: CPM (SAR) ← auto-calculated | IG 20% reach · TikTok 30% · Twitter 10% · YouTube 25% · Twitch 100% | BA2: AUTHORITY FLOOR + CONFIDENCE LAYER ← new v8 engine
A3: ROLE LEGEND | B3: ● Player | C3: ● Head Coach | D3: ● Coach | E3: ● Manager | F3: ● Analyst | G3: ● Influencer | H3: ● Coach
B4: # | C4: Nickname | D4: Role | E4: Game | F4: Team | G4: Nationality | H4: Platforms | I4: Tier | J4: IG Reel (SAR) | K4: IG Static (SAR) | L4: IG Story (SAR) | M4: TikTok Video | N4: YT Short (SAR) | O4: X Post (SAR) | P4: FB Post/Video (SAR) | Q4: Twitch Stream 2h | R4: Twitch Integ. | S4: IRL / Appear. | T4: Rights Fee | U4: Exclusivity Fee | V4: Rush Fee | W4: WL Fee | X4: Notes | Y4: Falcons Commission % | Z4: Markup % (on Player Cost) | AA4: Full Name | AB4: X / Twitter | AC4: Instagram | AD4: Twitch | AE4: YouTube | AF4: TikTok | AG4: Kick | AH4: Facebook | AI4: Snapchat | AJ4: Link-in-Bio | AK4: Date of Birth | AL4: Game Role | AO4: Twitter Followers | AP4: Instagram Followers | AQ4: Twitch Followers | AR4: YouTube Subs | AS4: TikTok Followers | AT4: Kick Followers | AU4: Facebook Followers | AV4: IG CPM (SAR) | AW4: TikTok CPM (SAR) | AX4: Twitter CPM (SAR) | AY4: YouTube CPM (SAR) | AZ4: Twitch CPM (SAR) | BA4: Floor Share % | BB4: Authority Factor | BC4: Default Seasonality | BD4: Default Language | BE4: Authority Floor Baseline (SAR) | BF4: Measurement Confidence | BG4: Tier Review Flag
B5: =IF($C5="","",COUNTA($C$5:C5)) -> 1 | C5: Bijw | D5: Influencer | E5: Esports Influencers | F5: Esports Influencers | G5: Saudi Arabia | H5: 6 | I5: Tier 3 | J5: 11000 | K5: 4600 | L5: =IF($C5="","",ROUND($J5*0.17,0)) -> 1870 | M5: 8600 | N5: 3500 | O5: 2200 | P5: 2200 | Q5: 15950 | R5: 7150 | S5: =IF($C5="","",ROUND($J5*2.2,0)) -> 24200 | T5: 3850 | U5: 3300 | V5: 2000 | W5: 1650 | X5: 6 platforms | Y5: 0.3 | Z5: 1 | AA5: Hisham Nasser | AB5: https://x.com/_bijw | AC5: https://www.instagram.com/bijjw | AD5: https://www.twitch.tv/bijw | AE5: https://www.youtube.com/@Bijw | AF5: https://www.tiktok.com/@biijw | AG5: https://kick.com/bijw | AI5: https://www.snapchat.com/add/bijjw | AJ5: https://linktr.ee/bijw | AV5: =IF(AND(AP5>0,J5>0),J5*1000/(AP5*0.2),"") | AW5: =IF(AND(AS5>0,M5>0),M5*1000/(AS5*0.3),"") | AX5: =IF(AND(AO5>0,O5>0),O5*1000/(AO5*0.1),"") | AY5: =IF(AND(AR5>0,N5>0),N5*1000/(AR5*0.25),"") | AZ5: =IF(AND(AQ5>0,Q5>0),Q5*1000/(AQ5*1),"") | BA5: =IFERROR(VLOOKUP($I5,'07_Settings'!$A$10:$F$14,6,FALSE()),0.25) -> 0.35 | BB5: 1 | BC5: 1 | BD5: 1 | BE5: =IFERROR(ROUND($S5*BA5*BC5*BD5*BB5,0),0) -> 8470 | BF5: =IF(COUNT(AO5:AU5)>0,"estimated","pending") -> pending
B6: =IF($C6="","",COUNTA($C$5:C6)) -> 2 | C6: Abo Najd | D6: Influencer | E6: Esports Influencers | F6: Esports Influencers | G6: Saudi Arabia | H6: 4 | I6: Tier 3 | J6: 8100 | K6: 3200 | L6: =IF($C6="","",ROUND($J6*0.17,0)) -> 1377 | M6: 6350 | N6: 2600 | O6: 1600 | P6: 1600 | Q6: 11800 | R6: 5300 | S6: =IF($C6="","",ROUND($J6*2.2,0)) -> 17820 | T6: 2850 | U6: 2450 | V6: 1450 | W6: 1215 | X6: 4 platforms | Y6: 0.3 | Z6: 1 | AA6: Riyad Alfahmi | AB6: https://x.com/K22N8 | AC6: https://www.instagram.com/k2nn8?igsh=ajJsNHoybDlpMzFo | AD6: https://www.twitch.tv/k2nnn8 | AE6: https://www.youtube.com/@k2nn8 | AJ6: https://linktr.ee/K2nnn8 (alt: https://heylink.me/k2nn8) | AV6: =IF(AND(AP6>0,J6>0),J6*1000/(AP6*0.2),"") | AW6: =IF(AND(AS6>0,M6>0),M6*1000/(AS6*0.3),"") | AX6: =IF(AND(AO6>0,O6>0),O6*1000/(AO6*0.1),"") | AY6: =IF(AND(AR6>0,N6>0),N6*1000/(AR6*0.25),"") | AZ6: =IF(AND(AQ6>0,Q6>0),Q6*1000/(AQ6*1),"") | BA6: =IFERROR(VLOOKUP($I6,'07_Settings'!$A$10:$F$14,6,FALSE()),0.25) -> 0.35 | BB6: 1 | BC6: 1 | BD6: 1 | BE6: =IFERROR(ROUND($S6*BA6*BC6*BD6*BB6,0),0) -> 6237 | BF6: =IF(COUNT(AO6:AU6)>0,"estimated","pending") -> pending
B7: =IF($C7="","",COUNTA($C$5:C7)) -> 3 | C7: FMG | D7: Influencer | E7: Esports Influencers | F7: Esports Influencers | G7: Saudi Arabia | H7: 4 | I7: Tier 3 | J7: 7450 | K7: 3150 | L7: =IF($C7="","",ROUND($J7*0.17,0)) -> 1267 | M7: 5850 | N7: 2400 | O7: 1500 | P7: 1500 | Q7: 10850 | R7: 4850 | S7: =IF($C7="","",ROUND($J7*2.2,0)) -> 16390 | T7: 2600 | U7: 2250 | V7: 1350 | W7: 1118 | X7: 4 platforms | Y7: 0.3 | Z7: 1 | AA7: Nasser alotaibi | AB7: https://x.com/iFMG_ | AC7: https://www.instagram.com/fm.g/ | AD7: https://www.twitch.tv/fmg_ | AG7: https://kick.com/ifmg | AO7: 4792 | AP7: 4080 | AV7: =IF(AND(AP7>0,J7>0),J7*1000/(AP7*0.2),"") -> 9129.902 | AW7: =IF(AND(AS7>0,M7>0),M7*1000/(AS7*0.3),"") | AX7: =IF(AND(AO7>0,O7>0),O7*1000/(AO7*0.1),"") -> 3130.217 | AY7: =IF(AND(AR7>0,N7>0),N7*1000/(AR7*0.25),"") | AZ7: =IF(AND(AQ7>0,Q7>0),Q7*1000/(AQ7*1),"") | BA7: =IFERROR(VLOOKUP($I7,'07_Settings'!$A$10:$F$14,6,FALSE()),0.25) -> 0.35 | BB7: 1 | BC7: 1 | BD7: 1 | BE7: =IFERROR(ROUND($S7*BA7*BC7*BD7*BB7,0),0) -> 5737 | BF7: =IF(COUNT(AO7:AU7)>0,"estimated","pending") -> estimated
B8: =IF($C8="","",COUNTA($C$5:C8)) -> 4 | C8: Abo Ghazi | D8: Influencer | E8: Esports Influencers | F8: Esports Influencers | G8: Saudi Arabia | H8: 3 | I8: Tier 3 | J8: 5200 | K8: 2200 | L8: =IF($C8="","",ROUND($J8*0.17,0)) -> 884 | M8: 4050 | N8: 1650 | O8: 1050 | P8: 1050 | Q8: 7550 | R8: 3400 | S8: =IF($C8="","",ROUND($J8*2.2,0)) -> 11440 | T8: 1800 | U8: 1550 | V8: 950 | W8: 780 | X8: 3 platforms | Y8: 0.3 | Z8: 1 | AA8: Mohammed Albaqami | AB8: https://x.com/MohxamedZ | AD8: https://www.twitch.tv/ires | AG8: https://kick.com/iabughazi | AH8: https://www.facebook.com/AbuGhaziGaming93 | AI8: https://www.snapchat.com/add/faisalhajhasan | AJ8: https://linktr.ee/abughaazi | AV8: =IF(AND(AP8>0,J8>0),J8*1000/(AP8*0.2),"") | AW8: =IF(AND(AS8>0,M8>0),M8*1000/(AS8*0.3),"") | AX8: =IF(AND(AO8>0,O8>0),O8*1000/(AO8*0.1),"") | AY8: =IF(AND(AR8>0,N8>0),N8*1000/(AR8*0.25),"") | AZ8: =IF(AND(AQ8>0,Q8>0),Q8*1000/(AQ8*1),"") | BA8: =IFERROR(VLOOKUP($I8,'07_Settings'!$A$10:$F$14,6,FALSE()),0.25) -> 0.35 | BB8: 1 | BC8: 1 | BD8: 1 | BE8: =IFERROR(ROUND($S8*BA8*BC8*BD8*BB8,0),0) -> 4004 | BF8: =IF(COUNT(AO8:AU8)>0,"estimated","pending") -> pending
B9: =IF($C9="","",COUNTA($C$5:C9)) -> 5 | C9: Mary | D9: Influencer | E9: Esports Influencers | F9: Esports Influencers | G9: Bahraini | H9: 5 | I9: Tier 2 | J9: 8100 | K9: 3400 | L9: =IF($C9="","",ROUND($J9*0.17,0)) -> 1377 | M9: 6350 | N9: 2600 | O9: 1600 | P9: 1600 | Q9: 11800 | R9: 5300 | S9: =IF($C9="","",ROUND($J9*2.2,0)) -> 17820 | T9: 2850 | U9: 2450 | V9: 1450 | W9: 1215 | X9: 5 platforms | Y9: 0.3 | Z9: 1 | AA9: Maryam Maher | AB9: https://x.com/marypink | AC9: https://www.instagram.com/maryvalorantt/?hl=en | AD9: https://www.twitch.tv/mary | AE9: https://www.youtube.com/@maryvalorant/featured | AF9: https://www.tiktok.com/@maryvalorant | AJ9: https://linktr.ee/verymarygaming | AP9: 67000 | AV9: =IF(AND(AP9>0,J9>0),J9*1000/(AP9*0.2),"") -> 604.47761 | AW9: =IF(AND(AS9>0,M9>0),M9*1000/(AS9*0.3),"") | AX9: =IF(AND(AO9>0,O9>0),O9*1000/(AO9*0.1),"") | AY9: =IF(AND(AR9>0,N9>0),N9*1000/(AR9*0.25),"") | AZ9: =IF(AND(AQ9>0,Q9>0),Q9*1000/(AQ9*1),"") | BA9: =IFERROR(VLOOKUP($I9,'07_Settings'!$A$10:$F$14,6,FALSE()),0.25) -> 0.45 | BB9: 1 | BC9: 1 | BD9: 1 | BE9: =IFERROR(ROUND($S9*BA9*BC9*BD9*BB9,0),0) -> 8019 | BF9: =IF(COUNT(AO9:AU9)>0,"estimated","pending") -> estimated
B10: =IF($C10="","",COUNTA($C$5:C10)) -> 6 | C10: Ghala | D10: Influencer | E10: Esports Influencers | F10: Esports Influencers | G10: Saudi Arabia | H10: 5 | I10: Tier 3 | J10: 7450 | K10: 3150 | L10: =IF($C10="","",ROUND($J10*0.17,0)) -> 1267 | M10: 5850 | N10: 2400 | O10: 1500 | P10: 1500 | Q10: 10850 | R10: 4850 | S10: =IF($C10="","",ROUND($J10*2.2,0)) -> 16390 | T10: 2600 | U10: 2250 | V10: 1350 | W10: 1118 | X10: 5 platforms | Y10: 0.3 | Z10: 1 | AA10: Ghala Alqahtani | AB10: https://x.com/pg_ghala3?lang=en | AC10: https://www.instagram.com/pg_ghala3 | AE10: https://www.youtube.com/@pg_ghala3 | AF10: https://www.tiktok.com/@pg_ghala3 | AG10: https://kick.com/pg-ghala3 | AI10: https://snapchat.com/t/bLA2ZOsG | AJ10: https://linktr.ee/ga1lll | AV10: =IF(AND(AP10>0,J10>0),J10*1000/(AP10*0.2),"") | AW10: =IF(AND(AS10>0,M10>0),M10*1000/(AS10*0.3),"") | AX10: =IF(AND(AO10>0,O10>0),O10*1000/(AO10*0.1),"") | AY10: =IF(AND(AR10>0,N10>0),N10*1000/(AR10*0.25),"") | AZ10: =IF(AND(AQ10>0,Q10>0),Q10*1000/(AQ10*1),"") | BA10: =IFERROR(VLOOKUP($I10,'07_Settings'!$A$10:$F$14,6,FALSE()),0.25) -> 0.35 | BB10: 1 | BC10: 1 | BD10: 1 | BE10: =IFERROR(ROUND($S10*BA10*BC10*BD10*BB10,0),0) -> 5737 | BF10: =IF(COUNT(AO10:AU10)>0,"estimated","pending") -> pending
B11: =IF($C11="","",COUNTA($C$5:C11)) -> 7 | C11: Moaz | D11: Influencer | E11: Esports Influencers | F11: Esports Influencers | G11: Saudi Arabia | H11: 5 | I11: Tier 2 | J11: 6500 | K11: 5300 | L11: =IF($C11="","",ROUND($J11*0.17,0)) -> 1105 | M11: 3400 | N11: 4050 | O11: 2500 | P11: 2500 | Q11: 15950 | R11: 8200 | S11: =IF($C11="","",ROUND($J11*2.2,0)) -> 14300 | T11: 3800 | U11: 1900 | V11: 3150 | W11: 1250 | X11: 5 platforms | Y11: 0.3 | Z11: 1 | AA11: Moaz Asiri | AB11: https://x.com/mezostrong?s=21 | AC11: https://www.instagram.com/mezostrong | AE11: https://www.youtube.com/channel/UCZCgW8WW8K_vrHrO6sZ7oyg?app=desktop | AF11: https://www.tiktok.com/@mezostrong?_r=1&_t=zs-91bbrrsefwl | AG11: https://kick.com/MezoStrong | AV11: =IF(AND(AP11>0,J11>0),J11*1000/(AP11*0.2),"") | AW11: =IF(AND(AS11>0,M11>0),M11*1000/(AS11*0.3),"") | AX11: =IF(AND(AO11>0,O11>0),O11*1000/(AO11*0.1),"") | AY11: =IF(AND(AR11>0,N11>0),N11*1000/(AR11*0.25),"") | AZ11: =IF(AND(AQ11>0,Q11>0),Q11*1000/(AQ11*1),"") | BA11: =IFERROR(VLOOKUP($I11,'07_Settings'!$A$10:$F$14,6,FALSE()),0.25) -> 0.45 | BB11: 1 | BC11: 1 | BD11: 1 | BE11: =IFERROR(ROUND($S11*BA11*BC11*BD11*BB11,0),0) -> 6435 | BF11: =IF(COUNT(AO11:AU11)>0,"estimated","pending") -> pending
B12: =IF($C12="","",COUNTA($C$5:C12)) -> 8 | C12: vacwep | D12: Influencer | E12: Esports Influencers | F12: Esports Influencers | G12: Saudi Arabia | H12: 5 | I12: Tier 3 | J12: 7450 | K12: 3150 | L12: =IF($C12="","",ROUND($J12*0.17,0)) -> 1267 | M12: 5800 | N12: 2400 | O12: 1500 | P12: 1500 | Q12: 7500 | R12: 4850 | S12: =IF($C12="","",ROUND($J12*2.2,0)) -> 16390 | T12: 2250 | U12: 1100 | V12: 1850 | W12: 750 | X12: 5 platforms | Y12: 0.3 | Z12: 1 | AA12: Abdullah Mousa A Alsulaymi | AB12: https://x.com/vacwep?s=21&t=PiVx0_LPZgUm0TT5Ok_2Zw | AC12: https://www.instagram.com/vacwep_?igsh=Z28yMXRibTZ0OWlm&utm_source=qr | AF12: https://www.tiktok.com/@vacwep?_r=1&_t=ZS-94jrcxtNGEK | AG12: https://kick.com/vacwep | AH12: https://www.facebook.com/share/1BDLRfGMFS/?mibextid=wwXIfr | AK12: 12/07/1992 | AV12: =IF(AND(AP12>0,J12>0),J12*1000/(AP12*0.2),"") | AW12: =IF(AND(AS12>0,M12>0),M12*1000/(AS12*0.3),"") | AX12: =IF(AND(AO12>0,O12>0),O12*1000/(AO12*0.1),"") | AY12: =IF(AND(AR12>0,N12>0),N12*1000/(AR12*0.25),"") | AZ12: =IF(AND(AQ12>0,Q12>0),Q12*1000/(AQ12*1),"") | BA12: =IFERROR(VLOOKUP($I12,'07_Settings'!$A$10:$F$14,6,FALSE()),0.25) -> 0.35 | BB12: 1 | BC12: 1 | BD12: 1 | BE12: =IFERROR(ROUND($S12*BA12*BC12*BD12*BB12,0),0) -> 5737 | BF12: =IF(COUNT(AO12:AU12)>0,"estimated","pending") -> pending
B13: =IF($C13="","",COUNTA($C$5:C13)) -> 9 | C13: Cellium | D13: Player | E13: Call of Duty Black Ops 7 | F13: Riyadh Falcons | G13: American | H13: 3 | I13: Tier 1 | J13: 11250 | K13: 4500 | L13: =IF($C13="","",ROUND($J13*0.17,0)) -> 1913 | M13: 8000 | N13: 3500 | O13: 2000 | P13: 2000 | Q13: 13500 | R13: 6075 | S13: =IF($C13="","",ROUND($J13*2.2,0)) -> 24750 | T13: 4638 | U13: 4063 | V13: 2438 | W13: 2400 | X13: 3 platforms | Y13: 0.3 | Z13: 1 | AA13: McArthur Jovel | AB13: https://twitter.com/Cellium | AC13: https://www.instagram.com/cellium/ | AD13: https://www.twitch.tv/Cellium | AK13: 24/12/2000 | AL13: Assault Rifle / Main AR | AO13: 130000 | AP13: 38000 | AQ13: 105230 | AV13: =IF(AND(AP13>0,J13>0),J13*1000/(AP13*0.2),"") -> 1480.2632 | AW13: =IF(AND(AS13>0,M13>0),M13*1000/(AS13*0.3),"") | AX13: =IF(AND(AO13>0,O13>0),O13*1000/(AO13*0.1),"") -> 153.84615 | AY13: =IF(AND(AR13>0,N13>0),N13*1000/(AR13*0.25),"") | AZ13: =IF(AND(AQ13>0,Q13>0),Q13*1000/(AQ13*1),"") -> 128.29041 | BA13: =IFERROR(VLOOKUP($I13,'07_Settings'!$A$10:$F$14,6,FALSE()),0.25) -> 0.55 | BB13: 1 | BC13: 1 | BD13: 1 | BE13: =IFERROR(ROUND($S13*BA13*BC13*BD13*BB13,0),0) -> 13613 | BF13: =IF(COUNT(AO13:AU13)>0,"estimated","pending") -> estimated
B14: =IF($C14="","",COUNTA($C$5:C14)) -> 10 | C14: Exnid | D14: Player | E14: Call of Duty Black Ops 7 | F14: Riyadh Falcons | G14: Saudi Arabia | H14: 2 | I14: Tier 2 | J14: 11000 | K14: 4600 | L14: =IF($C14="","",ROUND($J14*0.17,0)) -> 1870 | M14: 8600 | N14: 3500 | O14: 2200 | P14: 2200 | Q14: 15950 | R14: 7150 | S14: =IF($C14="","",ROUND($J14*2.2,0)) -> 24200 | T14: 3850 | U14: 3300 | V14: 2000 | W14: 2400 | X14: 2 platforms | Y14: 0.3 | Z14: 1 | AA14: Saud Alati | AB14: https://x.com/Exnid_ | AD14: https://www.twitch.tv/exnid | AK14: 28/10/2002 | AL14: Sub-Machine Gun (SMG) | AO14: 36000 | AQ14: 63000 | AV14: =IF(AND(AP14>0,J14>0),J14*1000/(AP14*0.2),"") | AW14: =IF(AND(AS14>0,M14>0),M14*1000/(AS14*0.3),"") | AX14: =IF(AND(AO14>0,O14>0),O14*1000/(AO14*0.1),"") -> 611.11111 | AY14: =IF(AND(AR14>0,N14>0),N14*1000/(AR14*0.25),"") | AZ14: =IF(AND(AQ14>0,Q14>0),Q14*1000/(AQ14*1),"") -> 253.1746 | BA14: =IFERROR(VLOOKUP($I14,'07_Settings'!$A$10:$F$14,6,FALSE()),0.25) -> 0.45 | BB14: 1 | BC14: 1 | BD14: 1 | BE14: =IFERROR(ROUND($S14*BA14*BC14*BD14*BB14,0),0) -> 10890 | BF14: =IF(COUNT(AO14:AU14)>0,"estimated","pending") -> estimated
B15: =IF($C15="","",COUNTA($C$5:C15)) -> 11 | C15: KiSMET | D15: Player | E15: Call of Duty Black Ops 7 | F15: Riyadh Falcons | G15: American | H15: 3 | I15: Tier 3 | J15: 12100 | K15: 5100 | L15: =IF($C15="","",ROUND($J15*0.17,0)) -> 2057 | M15: 9450 | N15: 3850 | O15: 2400 | P15: 2400 | Q15: 17550 | R15: 7850 | S15: =IF($C15="","",ROUND($J15*2.2,0)) -> 26620 | T15: 4250 | U15: 3650 | V15: 2200 | W15: 2400 | X15: 3 platforms | Y15: 0.3 | Z15: 1 | AA15: Matthew Tinsley | AB15: https://twitter.com/KiSMET6_ | AC15: https://www.instagram.com/kismet6_ | AD15: https://www.twitch.tv/kismet6_ | AK15: 36475 | AL15: Assault Rifle / Flex | AO15: 48000 | AP15: 3677 | AQ15: 39000 | AV15: =IF(AND(AP15>0,J15>0),J15*1000/(AP15*0.2),"") -> 16453.631 | AW15: =IF(AND(AS15>0,M15>0),M15*1000/(AS15*0.3),"") | AX15: =IF(AND(AO15>0,O15>0),O15*1000/(AO15*0.1),"") -> 500 | AY15: =IF(AND(AR15>0,N15>0),N15*1000/(AR15*0.25),"") | AZ15: =IF(AND(AQ15>0,Q15>0),Q15*1000/(AQ15*1),"") -> 450 | BA15: =IFERROR(VLOOKUP($I15,'07_Settings'!$A$10:$F$14,6,FALSE()),0.25) -> 0.35 | BB15: 1 | BC15: 1 | BD15: 1 | BE15: =IFERROR(ROUND($S15*BA15*BC15*BD15*BB15,0),0) -> 9317 | BF15: =IF(COUNT(AO15:AU15)>0,"estimated","pending") -> estimated
B16: =IF($C16="","",COUNTA($C$5:C16)) -> 12 | C16: Pred | D16: Player | E16: Call of Duty Black Ops 7 | F16: Riyadh Falcons | G16: American | H16: 3 | I16: Tier 1 | J16: 11000 | K16: 4600 | L16: =IF($C16="","",ROUND($J16*0.17,0)) -> 1870 | M16: 8600 | N16: 3500 | O16: 2200 | P16: 2200 | Q16: 15950 | R16: 7150 | S16: =IF($C16="","",ROUND($J16*2.2,0)) -> 24200 | T16: 3850 | U16: 3300 | V16: 2000 | W16: 2400 | X16: 3 platforms | Y16: 0.3 | Z16: 1 | AA16: Amer Zulbeari | AB16: https://x.com/Pred | AC16: https://www.instagram.com/amerzulbeariii | AD16: https://www.twitch.tv/pred | AK16: 19/08/2001 | AL16: Sub-Machine Gun (SMG) | AO16: 138000 | AP16: 37000 | AQ16: 174000 | AV16: =IF(AND(AP16>0,J16>0),J16*1000/(AP16*0.2),"") -> 1486.4865 | AW16: =IF(AND(AS16>0,M16>0),M16*1000/(AS16*0.3),"") | AX16: =IF(AND(AO16>0,O16>0),O16*1000/(AO16*0.1),"") -> 159.42029 | AY16: =IF(AND(AR16>0,N16>0),N16*1000/(AR16*0.25),"") | AZ16: =IF(AND(AQ16>0,Q16>0),Q16*1000/(AQ16*1),"") -> 91.666667 | BA16: =IFERROR(VLOOKUP($I16,'07_Settings'!$A$10:$F$14,6,FALSE()),0.25) -> 0.55 | BB16: 1 | BC16: 1 | BD16: 1 | BE16: =IFERROR(ROUND($S16*BA16*BC16*BD16*BB16,0),0) -> 13310 | BF16: =IF(COUNT(AO16:AU16)>0,"estimated","pending") -> estimated
B17: =IF($C17="","",COUNTA($C$5:C17)) -> 13 | C17: KingAbody | D17: Player | E17: Call of Duty Black Ops 7 | F17: FaZe Falcons | G17: Saudi Arabia | H17: 1 | I17: Tier 3 | J17: 11000 | K17: 4600 | L17: =IF($C17="","",ROUND($J17*0.17,0)) -> 1870 | M17: 8600 | N17: 3500 | O17: 2200 | P17: 2200 | Q17: 15950 | R17: 7150 | S17: =IF($C17="","",ROUND($J17*2.2,0)) -> 24200 | T17: 3850 | U17: 3300 | V17: 2000 | W17: 2400 | X17: 1 platform | Y17: 0.3 | Z17: 1 | AA17: Abdulelah Alrajhi | AB17: https://x.com/KingAbody_ | AK17: 36679 | AL17: Sub-Machine Gun (SMG) | AO17: 6000 | AV17: =IF(AND(AP17>0,J17>0),J17*1000/(AP17*0.2),"") | AW17: =IF(AND(AS17>0,M17>0),M17*1000/(AS17*0.3),"") | AX17: =IF(AND(AO17>0,O17>0),O17*1000/(AO17*0.1),"") -> 3666.6667 | AY17: =IF(AND(AR17>0,N17>0),N17*1000/(AR17*0.25),"") | AZ17: =IF(AND(AQ17>0,Q17>0),Q17*1000/(AQ17*1),"") | BA17: =IFERROR(VLOOKUP($I17,'07_Settings'!$A$10:$F$14,6,FALSE()),0.25) -> 0.35 | BB17: 1 | BC17: 1 | BD17: 1 | BE17: =IFERROR(ROUND($S17*BA17*BC17*BD17*BB17,0),0) -> 8470 | BF17: =IF(COUNT(AO17:AU17)>0,"estimated","pending") -> estimated
B18: =IF($C18="","",COUNTA($C$5:C18)) -> 14 | C18: Arcitys | D18: Player | E18: Call of Duty Black Ops 7 | F18: Falcons Academy White | G18: American | H18: 3 | I18: Tier 1 | J18: 12100 | K18: 5100 | L18: =IF($C18="","",ROUND($J18*0.17,0)) -> 2057 | M18: 9450 | N18: 3850 | O18: 2400 | P18: 2400 | Q18: 17550 | R18: 7850 | S18: =IF($C18="","",ROUND($J18*2.2,0)) -> 26620 | T18: 4250 | U18: 3650 | V18: 2200 | W18: 2400 | X18: 3 platforms | Y18: 0.3 | Z18: 1 | AA18: Alec Sanderson | AB18: https://x.com/Arcitys | AC18: https://www.instagram.com/arcitys9 | AD18: https://www.twitch.tv/arcitys | AK18: 36045 | AL18: Assault Rifle / Main AR | AO18: 192000 | AP18: 25000 | AQ18: 140000 | AV18: =IF(AND(AP18>0,J18>0),J18*1000/(AP18*0.2),"") -> 2420 | AW18: =IF(AND(AS18>0,M18>0),M18*1000/(AS18*0.3),"") | AX18: =IF(AND(AO18>0,O18>0),O18*1000/(AO18*0.1),"") -> 125 | AY18: =IF(AND(AR18>0,N18>0),N18*1000/(AR18*0.25),"") | AZ18: =IF(AND(AQ18>0,Q18>0),Q18*1000/(AQ18*1),"") -> 125.35714 | BA18: =IFERROR(VLOOKUP($I18,'07_Settings'!$A$10:$F$14,6,FALSE()),0.25) -> 0.55 | BB18: 1 | BC18: 1 | BD18: 1 | BE18: =IFERROR(ROUND($S18*BA18*BC18*BD18*BB18,0),0) -> 14641 | BF18: =IF(COUNT(AO18:AU18)>0,"estimated","pending") -> estimated
B19: =IF($C19="","",COUNTA($C$5:C19)) -> 15 | C19: Paulehx | D19: Player | E19: Call of Duty Black Ops 7 | F19: Falcons Academy White | G19: American | H19: 2 | I19: Tier 3 | J19: 11000 | K19: 4600 | L19: =IF($C19="","",ROUND($J19*0.17,0)) -> 1870 | M19: 8600 | N19: 3500 | O19: 2200 | P19: 2200 | Q19: 15950 | R19: 7150 | S19: =IF($C19="","",ROUND($J19*2.2,0)) -> 24200 | T19: 3850 | U19: 3300 | V19: 2000 | W19: 2400 | X19: 2 platforms | Y19: 0.3 | Z19: 1 | AA19: Paul Avila | AB19: https://x.com/Paulehx_ | AD19: https://www.twitch.tv/paulehx | AK19: 21/01/2002 | AL19: Assault Rifle / Flex | AO19: 19000 | AV19: =IF(AND(AP19>0,J19>0),J19*1000/(AP19*0.2),"") | AW19: =IF(AND(AS19>0,M19>0),M19*1000/(AS19*0.3),"") | AX19: =IF(AND(AO19>0,O19>0),O19*1000/(AO19*0.1),"") -> 1157.8947 | AY19: =IF(AND(AR19>0,N19>0),N19*1000/(AR19*0.25),"") | AZ19: =IF(AND(AQ19>0,Q19>0),Q19*1000/(AQ19*1),"") | BA19: =IFERROR(VLOOKUP($I19,'07_Settings'!$A$10:$F$14,6,FALSE()),0.25) -> 0.35 | BB19: 1 | BC19: 1 | BD19: 1 | BE19: =IFERROR(ROUND($S19*BA19*BC19*BD19*BB19,0),0) -> 8470 | BF19: =IF(COUNT(AO19:AU19)>0,"estimated","pending") -> estimated
B20: =IF($C20="","",COUNTA($C$5:C20)) -> 16 | C20: hmoodx | D20: Player | E20: Call of Duty Warzone | F20: Team Falcons MENA | G20: Saudi Arabia | H20: 2 | I20: Tier 3 | J20: 11000 | K20: 4600 | L20: =IF($C20="","",ROUND($J20*0.17,0)) -> 1870 | M20: 8600 | N20: 3500 | O20: 2200 | P20: 2200 | Q20: 15950 | R20: 7150 | S20: =IF($C20="","",ROUND($J20*2.2,0)) -> 24200 | T20: 3850 | U20: 3300 | V20: 2000 | W20: 2400 | X20: 2 platforms | Y20: 0.3 | Z20: 1 | AA20: Mohammed Altowairqi | AB20: https://x.com/xihamoodx | AD20: https://www.twitch.tv/i_hmoodx | AQ20: 22000 | AV20: =IF(AND(AP20>0,J20>0),J20*1000/(AP20*0.2),"") | AW20: =IF(AND(AS20>0,M20>0),M20*1000/(AS20*0.3),"") | AX20: =IF(AND(AO20>0,O20>0),O20*1000/(AO20*0.1),"") | AY20: =IF(AND(AR20>0,N20>0),N20*1000/(AR20*0.25),"") | AZ20: =IF(AND(AQ20>0,Q20>0),Q20*1000/(AQ20*1),"") -> 725 | BA20: =IFERROR(VLOOKUP($I20,'07_Settings'!$A$10:$F$14,6,FALSE()),0.25) -> 0.35 | BB20: 1 | BC20: 1 | BD20: 1 | BE20: =IFERROR(ROUND($S20*BA20*BC20*BD20*BB20,0),0) -> 8470 | BF20: =IF(COUNT(AO20:AU20)>0,"estimated","pending") -> estimated
B21: =IF($C21="","",COUNTA($C$5:C21)) -> 17 | C21: xizx7 | D21: Player | E21: Call of Duty Warzone | F21: Team Falcons MENA | G21: Saudi Arabia | H21: 4 | I21: Tier 3 | J21: 12100 | K21: 5100 | L21: =IF($C21="","",ROUND($J21*0.17,0)) -> 2057 | M21: 9450 | N21: 3850 | O21: 2400 | P21: 2400 | Q21: 17550 | R21: 7850 | S21: =IF($C21="","",ROUND($J21*2.2,0)) -> 26620 | T21: 4250 | U21: 3650 | V21: 2200 | W21: 2400 | X21: 4 platforms | Y21: 0.3 | Z21: 1 | AA21: Jawad Al-Thawab | AB21: https://x.com/Jawxd7 | AC21: https://www.instagram.com/Jawxd7 | AD21: https://www.twitch.tv/jawad | AE21: https://www.youtube.com/channel/UCUWL8dR-JyA4FXZ08aSjjcg/videos | AQ21: 5000 | AV21: =IF(AND(AP21>0,J21>0),J21*1000/(AP21*0.2),"") | AW21: =IF(AND(AS21>0,M21>0),M21*1000/(AS21*0.3),"") | AX21: =IF(AND(AO21>0,O21>0),O21*1000/(AO21*0.1),"") | AY21: =IF(AND(AR21>0,N21>0),N21*1000/(AR21*0.25),"") | AZ21: =IF(AND(AQ21>0,Q21>0),Q21*1000/(AQ21*1),"") -> 3510 | BA21: =IFERROR(VLOOKUP($I21,'07_Settings'!$A$10:$F$14,6,FALSE()),0.25) -> 0.35 | BB21: 1 | BC21: 1 | BD21: 1 | BE21: =IFERROR(ROUND($S21*BA21*BC21*BD21*BB21,0),0) -> 9317 | BF21: =IF(COUNT(AO21:AU21)>0,"estimated","pending") -> estimated
B22: =IF($C22="","",COUNTA($C$5:C22)) -> 18 | C22: Alpine | D22: Manager | E22: Call of Duty Warzone | F22: Team Falcons | G22: American | H22: 1 | I22: Tier 4 | J22: 22750 | K22: 9550 | L22: =IF($C22="","",ROUND($J22*0.17,0)) -> 3868 | M22: 17750 | N22: 7300 | O22: 4550 | P22: 0 | Q22: 33000 | R22: 14800 | S22: =IF($C22="","",ROUND($J22*2.2,0)) -> 50050 | T22: 7950 | U22: 6850 | V22: 4100 | W22: 0 | X22: 1 platform | Y22: 0.3 | Z22: 1 | AA22: Alejandro Ayala | AB22: https://x.com/alpinedadog?lang=en | AK22: 24/02/1997 | AO22: 1170 | AV22: =IF(AND(AP22>0,J22>0),J22*1000/(AP22*0.2),"") | AW22: =IF(AND(AS22>0,M22>0),M22*1000/(AS22*0.3),"") | AX22: =IF(AND(AO22>0,O22>0),O22*1000/(AO22*0.1),"") -> 38888.889 | AY22: =IF(AND(AR22>0,N22>0),N22*1000/(AR22*0.25),"") | AZ22: =IF(AND(AQ22>0,Q22>0),Q22*1000/(AQ22*1),"") | BA22: =IFERROR(VLOOKUP($I22,'07_Settings'!$A$10:$F$14,6,FALSE()),0.25) -> 0.25 | BB22: 1 | BC22: 1 | BD22: 1 | BE22: =IFERROR(ROUND($S22*BA22*BC22*BD22*BB22,0),0) -> 12513 | BF22: =IF(COUNT(AO22:AU22)>0,"estimated","pending") -> estimated
B23: =IF($C23="","",COUNTA($C$5:C23)) -> 19 | C23: Newbz | D23: Player | E23: Call of Duty Warzone | F23: Team Falcons | G23: American | H23: 2 | I23: Tier 2 | J23: 20700 | K23: 8700 | L23: =IF($C23="","",ROUND($J23*0.17,0)) -> 3519 | M23: 16150 | N23: 6600 | O23: 4150 | P23: 4150 | Q23: 30000 | R23: 13450 | S23: =IF($C23="","",ROUND($J23*2.2,0)) -> 45540 | T23: 7250 | U23: 6200 | V23: 3750 | W23: 2400 | X23: 2 platforms | Y23: 0.2 | Z23: 1 | AA23: Edy Juan | AB23: https://x.com/TBE_Newbzz | AD23: https://www.twitch.tv/newbz | AK23: 36527 | AO23: 36000 | AQ23: 108000 | AV23: =IF(AND(AP23>0,J23>0),J23*1000/(AP23*0.2),"") | AW23: =IF(AND(AS23>0,M23>0),M23*1000/(AS23*0.3),"") | AX23: =IF(AND(AO23>0,O23>0),O23*1000/(AO23*0.1),"") -> 1152.7778 | AY23: =IF(AND(AR23>0,N23>0),N23*1000/(AR23*0.25),"") | AZ23: =IF(AND(AQ23>0,Q23>0),Q23*1000/(AQ23*1),"") -> 277.77778 | BA23: =IFERROR(VLOOKUP($I23,'07_Settings'!$A$10:$F$14,6,FALSE()),0.25) -> 0.45 | BB23: 1 | BC23: 1 | BD23: 1 | BE23: =IFERROR(ROUND($S23*BA23*BC23*BD23*BB23,0),0) -> 20493 | BF23: =IF(COUNT(AO23:AU23)>0,"estimated","pending") -> estimated
B24: =IF($C24="","",COUNTA($C$5:C24)) -> 20 | C24: Dongy | D24: Player | E24: Call of Duty Warzone | F24: Team Falcons | G24: American | H24: 2 | I24: Tier 2 | J24: 6500 | K24: 2750 | L24: =IF($C24="","",ROUND($J24*0.17,0)) -> 1105 | M24: 5050 | N24: 2100 | O24: 1300 | P24: 1300 | Q24: 9400 | R24: 4200 | S24: =IF($C24="","",ROUND($J24*2.2,0)) -> 14300 | T24: 2300 | U24: 1950 | V24: 1150 | W24: 2400 | X24: 2 platforms | Y24: 0.2 | Z24: 1 | AA24: Christopher Ledbetter | AB24: https://x.com/zDongyy | AD24: https://www.twitch.tv/Dongy | AK24: 23/03/2004 | AO24: 9000 | AQ24: 60000 | AV24: =IF(AND(AP24>0,J24>0),J24*1000/(AP24*0.2),"") | AW24: =IF(AND(AS24>0,M24>0),M24*1000/(AS24*0.3),"") | AX24: =IF(AND(AO24>0,O24>0),O24*1000/(AO24*0.1),"") -> 1444.4444 | AY24: =IF(AND(AR24>0,N24>0),N24*1000/(AR24*0.25),"") | AZ24: =IF(AND(AQ24>0,Q24>0),Q24*1000/(AQ24*1),"") -> 156.66667 | BA24: =IFERROR(VLOOKUP($I24,'07_Settings'!$A$10:$F$14,6,FALSE()),0.25) -> 0.45 | BB24: 1 | BC24: 1 | BD24: 1 | BE24: =IFERROR(ROUND($S24*BA24*BC24*BD24*BB24,0),0) -> 6435 | BF24: =IF(COUNT(AO24:AU24)>0,"estimated","pending") -> estimated
B25: =IF($C25="","",COUNTA($C$5:C25)) -> 21 | C25: Soka | D25: Player | E25: Call of Duty Warzone | F25: Team Falcons | G25: Tongan | H25: 5 | I25: Tier 2 | J25: 6500 | K25: 2750 | L25: =IF($C25="","",ROUND($J25*0.17,0)) -> 1105 | M25: 5050 | N25: 2100 | O25: 1300 | P25: 1300 | Q25: 9400 | R25: 4200 | S25: =IF($C25="","",ROUND($J25*2.2,0)) -> 14300 | T25: 2300 | U25: 1950 | V25: 1150 | W25: 2400 | X25: 5 platforms | Y25: 0.2 | Z25: 1 | AA25: Kasimili Tonga Tongamoa | AB25: https://twitter.com/HisokaT42 | AC25: https://www.instagram.com/hisokat42 | AD25: https://www.twitch.tv/HisokaT42 | AE25: https://www.youtube.com/channel/UCQDRE8aZRsrvF5OwMk_KmBg | AF25: https://tiktok.com/@missionarysoka | AK25: 28/01/2002 | AO25: 39000 | AP25: 32000 | AQ25: 191000 | AV25: =IF(AND(AP25>0,J25>0),J25*1000/(AP25*0.2),"") -> 1015.625 | AW25: =IF(AND(AS25>0,M25>0),M25*1000/(AS25*0.3),"") | AX25: =IF(AND(AO25>0,O25>0),O25*1000/(AO25*0.1),"") -> 333.33333 | AY25: =IF(AND(AR25>0,N25>0),N25*1000/(AR25*0.25),"") | AZ25: =IF(AND(AQ25>0,Q25>0),Q25*1000/(AQ25*1),"") -> 49.21466 | BA25: =IFERROR(VLOOKUP($I25,'07_Settings'!$A$10:$F$14,6,FALSE()),0.25) -> 0.45 | BB25: 1 | BC25: 1 | BD25: 1 | BE25: =IFERROR(ROUND($S25*BA25*BC25*BD25*BB25,0),0) -> 6435 | BF25: =IF(COUNT(AO25:AU25)>0,"estimated","pending") -> estimated
B26: =IF($C26="","",COUNTA($C$5:C26)) -> 22 | C26: Alireza Firouzja | D26: Player | E26: Chess | F26: Chess | G26: French/Iranian | H26: 5 | I26: Tier 2 | J26: 20700 | K26: 8700 | L26: =IF($C26="","",ROUND($J26*0.17,0)) -> 3519 | M26: 16150 | N26: 6600 | O26: 4150 | P26: 4150 | Q26: 30000 | R26: 13450 | S26: =IF($C26="","",ROUND($J26*2.2,0)) -> 45540 | T26: 7250 | U26: 6200 | V26: 3750 | W26: 2400 | X26: 5 platforms | Y26: 0.5 | Z26: 1 | AA26: Alireza Firouzja | AB26: https://twitter.com/AlirezaFirouzja | AC26: https://www.instagram.com/alirezafirouzja | AD26: https://www.twitch.tv/alirezafirouzja | AE26: https://www.youtube.com/@alirezafirouzja4080 | AH26: https://www.facebook.com/login/?next=https%3A%2F%2Fwww.facebook.com%2FAlireza.Firouzja.chess%2F | AK26: 18/06/2003 | AO26: 90000 | AP26: 149000 | AQ26: 97000 | AR26: 34500 | AU26: 1300 | AV26: =IF(AND(AP26>0,J26>0),J26*1000/(AP26*0.2),"") -> 694.63087 | AW26: =IF(AND(AS26>0,M26>0),M26*1000/(AS26*0.3),"") | AX26: =IF(AND(AO26>0,O26>0),O26*1000/(AO26*0.1),"") -> 461.11111 | AY26: =IF(AND(AR26>0,N26>0),N26*1000/(AR26*0.25),"") -> 765.21739 | AZ26: =IF(AND(AQ26>0,Q26>0),Q26*1000/(AQ26*1),"") -> 309.27835 | BA26: =IFERROR(VLOOKUP($I26,'07_Settings'!$A$10:$F$14,6,FALSE()),0.25) -> 0.45 | BB26: 1 | BC26: 1 | BD26: 1 | BE26: =IFERROR(ROUND($S26*BA26*BC26*BD26*BB26,0),0) -> 20493 | BF26: =IF(COUNT(AO26:AU26)>0,"estimated","pending") -> estimated
B27: =IF($C27="","",COUNTA($C$5:C27)) -> 23 | C27: Hikaru Nakamura | D27: Player | E27: Chess | F27: Chess | G27: American | H27: 6 | I27: Tier S | J27: 22500 | K27: 9450 | L27: =IF($C27="","",ROUND($J27*0.17,0)) -> 3825 | M27: 17550 | N27: 7200 | O27: 4500 | P27: 4500 | Q27: 32600 | R27: 14600 | S27: =IF($C27="","",ROUND($J27*2.2,0)) -> 49500 | T27: 7850 | U27: 6750 | V27: 4050 | W27: 2400 | X27: 6 platforms | Y27: 0.5 | Z27: 1 | AA27: Hikaru Nakamura | AB27: https://twitter.com/GMHikaru | AC27: https://www.instagram.com/gmhikaru | AD27: https://www.twitch.tv/gmhikaru | AE27: https://www.youtube.com/@gmhikaru | AG27: https://kick.com/gmhikaru | AH27: https://www.facebook.com/login/?next=https%3A%2F%2Fwww.facebook.com%2FGMHikaru%2F | AK27: 32120 | AO27: 629600 | AP27: 1000000 | AQ27: 2010000 | AR27: 3120000 | AS27: 730700 | AT27: 199200 | AU27: 323000 | AV27: =IF(AND(AP27>0,J27>0),J27*1000/(AP27*0.2),"") -> 112.5 | AW27: =IF(AND(AS27>0,M27>0),M27*1000/(AS27*0.3),"") -> 80.060216 | AX27: =IF(AND(AO27>0,O27>0),O27*1000/(AO27*0.1),"") -> 71.473952 | AY27: =IF(AND(AR27>0,N27>0),N27*1000/(AR27*0.25),"") -> 9.2307692 | AZ27: =IF(AND(AQ27>0,Q27>0),Q27*1000/(AQ27*1),"") -> 16.218905 | BA27: =IFERROR(VLOOKUP($I27,'07_Settings'!$A$10:$F$14,6,FALSE()),0.25) -> 0.65 | BB27: 1 | BC27: 1 | BD27: 1 | BE27: =IFERROR(ROUND($S27*BA27*BC27*BD27*BB27,0),0) -> 32175 | BF27: =IF(COUNT(AO27:AU27)>0,"estimated","pending") -> estimated
B28: =IF($C28="","",COUNTA($C$5:C28)) -> 24 | C28: Jon Ellis | D28: Manager | E28: Chess | F28: Chess | H28: 0 | I28: Tier 4 | J28: 22500 | K28: 9450 | L28: =IF($C28="","",ROUND($J28*0.17,0)) -> 3825 | M28: 17550 | N28: 7200 | O28: 4500 | P28: 0 | Q28: 32600 | R28: 14600 | S28: =IF($C28="","",ROUND($J28*2.2,0)) -> 49500 | T28: 7850 | U28: 6750 | V28: 4050 | W28: 0 | X28: 0 platforms | Y28: 0.3 | Z28: 1 | AA28: Jonathan Ellis | AV28: =IF(AND(AP28>0,J28>0),J28*1000/(AP28*0.2),"") | AW28: =IF(AND(AS28>0,M28>0),M28*1000/(AS28*0.3),"") | AX28: =IF(AND(AO28>0,O28>0),O28*1000/(AO28*0.1),"") | AY28: =IF(AND(AR28>0,N28>0),N28*1000/(AR28*0.25),"") | AZ28: =IF(AND(AQ28>0,Q28>0),Q28*1000/(AQ28*1),"") | BA28: =IFERROR(VLOOKUP($I28,'07_Settings'!$A$10:$F$14,6,FALSE()),0.25) -> 0.25 | BB28: 1 | BC28: 1 | BD28: 1 | BE28: =IFERROR(ROUND($S28*BA28*BC28*BD28*BB28,0),0) -> 12375 | BF28: =IF(COUNT(AO28:AU28)>0,"estimated","pending") -> pending
B29: =IF($C29="","",COUNTA($C$5:C29)) -> 25 | C29: kyousuke | D29: Player | E29: Counterstrike2 | F29: Team Falcons | G29: Russian | H29: 3 | I29: Tier 1 | J29: 15000 | K29: 6750 | L29: =IF($C29="","",ROUND($J29*0.17,0)) -> 2550 | M29: 11000 | N29: 5000 | O29: 3200 | P29: 3200 | Q29: 19500 | R29: 8775 | S29: =IF($C29="","",ROUND($J29*2.2,0)) -> 33000 | T29: 6800 | U29: 5950 | V29: 3570 | W29: 2400 | X29: 3 platforms | Y29: 0.75 | Z29: 1 | AA29: Maxim Lukin | AB29: https://twitter.com/FLCkyousuke | AC29: https://www.instagram.com/flckyousuke | AD29: https://www.twitch.tv/kyousuke999 | AK29: 30/01/2008 | AL29: Rifler | AO29: 39000 | AP29: 76000 | AQ29: 266000 | AV29: =IF(AND(AP29>0,J29>0),J29*1000/(AP29*0.2),"") -> 986.84211 | AW29: =IF(AND(AS29>0,M29>0),M29*1000/(AS29*0.3),"") | AX29: =IF(AND(AO29>0,O29>0),O29*1000/(AO29*0.1),"") -> 820.51282 | AY29: =IF(AND(AR29>0,N29>0),N29*1000/(AR29*0.25),"") | AZ29: =IF(AND(AQ29>0,Q29>0),Q29*1000/(AQ29*1),"") -> 73.308271 | BA29: =IFERROR(VLOOKUP($I29,'07_Settings'!$A$10:$F$14,6,FALSE()),0.25) -> 0.55 | BB29: 1 | BC29: 1 | BD29: 1 | BE29: =IFERROR(ROUND($S29*BA29*BC29*BD29*BB29,0),0) -> 18150 | BF29: =IF(COUNT(AO29:AU29)>0,"estimated","pending") -> estimated
B30: =IF($C30="","",COUNTA($C$5:C30)) -> 26 | C30: kyxsan | D30: Player | E30: Counterstrike2 | F30: Team Falcons | G30: North Macedonia | H30: 2 | I30: Tier 3 | J30: 22500 | K30: 9450 | L30: =IF($C30="","",ROUND($J30*0.17,0)) -> 3825 | M30: 17550 | N30: 7200 | O30: 4500 | P30: 4500 | Q30: 32600 | R30: 14600 | S30: =IF($C30="","",ROUND($J30*2.2,0)) -> 49500 | T30: 7850 | U30: 6750 | V30: 4050 | W30: 2400 | X30: 2 platforms | Y30: 0.75 | Z30: 1 | AA30: Damjan Stoilkovski | AB30: https://x.com/kyxsancs | AC30: https://www.instagram.com/kyxsancs/ | AK30: 26/05/2000 | AL30: IGL | AO30: 16000 | AP30: 11000 | AV30: =IF(AND(AP30>0,J30>0),J30*1000/(AP30*0.2),"") -> 10227.273 | AW30: =IF(AND(AS30>0,M30>0),M30*1000/(AS30*0.3),"") | AX30: =IF(AND(AO30>0,O30>0),O30*1000/(AO30*0.1),"") -> 2812.5 | AY30: =IF(AND(AR30>0,N30>0),N30*1000/(AR30*0.25),"") | AZ30: =IF(AND(AQ30>0,Q30>0),Q30*1000/(AQ30*1),"") | BA30: =IFERROR(VLOOKUP($I30,'07_Settings'!$A$10:$F$14,6,FALSE()),0.25) -> 0.35 | BB30: 1 | BC30: 1 | BD30: 1 | BE30: =IFERROR(ROUND($S30*BA30*BC30*BD30*BB30,0),0) -> 17325 | BF30: =IF(COUNT(AO30:AU30)>0,"estimated","pending") -> estimated
B31: =IF($C31="","",COUNTA($C$5:C31)) -> 27 | C31: m0NESY | D31: Player | E31: Counterstrike2 | F31: Team Falcons | G31: Russian | H31: 4 | I31: Tier S | J31: 22500 | K31: 9450 | L31: =IF($C31="","",ROUND($J31*0.17,0)) -> 3825 | M31: 17550 | N31: 7200 | O31: 4500 | P31: 4500 | Q31: 32600 | R31: 14600 | S31: =IF($C31="","",ROUND($J31*2.2,0)) -> 49500 | T31: 7850 | U31: 6750 | V31: 4050 | W31: 2400 | X31: 4 platforms | Y31: 0.2 | Z31: 1 | AA31: Ilya Osipov | AB31: https://x.com/FLCm0NESY | AC31: https://www.instagram.com/m0nesy13 | AD31: https://www.twitch.tv/m0nesyof | AE31: https://www.youtube.com/channel/UCJxjKA1Cl--4tCN1l_cHHvQ | AK31: 38357 | AL31: Awper | AO31: 323100 | AP31: 524000 | AQ31: 1179231 | AR31: 261000 | AV31: =IF(AND(AP31>0,J31>0),J31*1000/(AP31*0.2),"") -> 214.69466 | AW31: =IF(AND(AS31>0,M31>0),M31*1000/(AS31*0.3),"") | AX31: =IF(AND(AO31>0,O31>0),O31*1000/(AO31*0.1),"") -> 139.27577 | AY31: =IF(AND(AR31>0,N31>0),N31*1000/(AR31*0.25),"") -> 110.34483 | AZ31: =IF(AND(AQ31>0,Q31>0),Q31*1000/(AQ31*1),"") -> 27.645135 | BA31: =IFERROR(VLOOKUP($I31,'07_Settings'!$A$10:$F$14,6,FALSE()),0.25) -> 0.65 | BB31: 1 | BC31: 1 | BD31: 1 | BE31: =IFERROR(ROUND($S31*BA31*BC31*BD31*BB31,0),0) -> 32175 | BF31: =IF(COUNT(AO31:AU31)>0,"estimated","pending") -> estimated
B32: =IF($C32="","",COUNTA($C$5:C32)) -> 28 | C32: NiKo | D32: Player | E32: Counterstrike2 | F32: Team Falcons | G32: Bosnian | H32: 5 | I32: Tier 1 | J32: 22500 | K32: 9450 | L32: =IF($C32="","",ROUND($J32*0.17,0)) -> 3825 | M32: 17550 | N32: 7200 | O32: 4500 | P32: 4500 | Q32: 32600 | R32: 14600 | S32: =IF($C32="","",ROUND($J32*2.2,0)) -> 49500 | T32: 7850 | U32: 6750 | V32: 4050 | W32: 2400 | X32: 5 platforms | Y32: 0.3 | Z32: 1 | AA32: Nikola Kovač | AB32: https://x.com/NiKoCS_ | AC32: https://www.instagram.com/csgoniko/# | AD32: https://www.twitch.tv/NiKo | AE32: https://www.youtube.com/@NiKo_cs | AH32: https://www.facebook.com/csgoNiKo | AK32: 16/02/1997 | AL32: Rifler | AO32: 878100 | AP32: 639000 | AQ32: 727186 | AV32: =IF(AND(AP32>0,J32>0),J32*1000/(AP32*0.2),"") -> 176.05634 | AW32: =IF(AND(AS32>0,M32>0),M32*1000/(AS32*0.3),"") | AX32: =IF(AND(AO32>0,O32>0),O32*1000/(AO32*0.1),"") -> 51.247011 | AY32: =IF(AND(AR32>0,N32>0),N32*1000/(AR32*0.25),"") | AZ32: =IF(AND(AQ32>0,Q32>0),Q32*1000/(AQ32*1),"") -> 44.830346 | BA32: =IFERROR(VLOOKUP($I32,'07_Settings'!$A$10:$F$14,6,FALSE()),0.25) -> 0.55 | BB32: 1 | BC32: 1 | BD32: 1 | BE32: =IFERROR(ROUND($S32*BA32*BC32*BD32*BB32,0),0) -> 27225 | BF32: =IF(COUNT(AO32:AU32)>0,"estimated","pending") -> estimated
B33: =IF($C33="","",COUNTA($C$5:C33)) -> 29 | C33: OMYA | D33: Manager | E33: Counterstrike2 | F33: Team Falcons | G33: French | H33: 1 | I33: Tier 4 | J33: 22500 | K33: 9450 | L33: =IF($C33="","",ROUND($J33*0.17,0)) -> 3825 | M33: 17550 | N33: 7200 | O33: 4500 | P33: 0 | Q33: 32600 | R33: 14600 | S33: =IF($C33="","",ROUND($J33*2.2,0)) -> 49500 | T33: 7850 | U33: 6750 | V33: 4050 | W33: 0 | X33: 1 platform | Y33: 0.3 | Z33: 1 | AA33: Xavier Roussac | AB33: https://x.com/Xavier_Roussac | AK33: 20/05/1987 | AO33: 2565 | AV33: =IF(AND(AP33>0,J33>0),J33*1000/(AP33*0.2),"") | AW33: =IF(AND(AS33>0,M33>0),M33*1000/(AS33*0.3),"") | AX33: =IF(AND(AO33>0,O33>0),O33*1000/(AO33*0.1),"") -> 17543.86 | AY33: =IF(AND(AR33>0,N33>0),N33*1000/(AR33*0.25),"") | AZ33: =IF(AND(AQ33>0,Q33>0),Q33*1000/(AQ33*1),"") | BA33: =IFERROR(VLOOKUP($I33,'07_Settings'!$A$10:$F$14,6,FALSE()),0.25) -> 0.25 | BB33: 1 | BC33: 1 | BD33: 1 | BE33: =IFERROR(ROUND($S33*BA33*BC33*BD33*BB33,0),0) -> 12375 | BF33: =IF(COUNT(AO33:AU33)>0,"estimated","pending") -> estimated
B34: =IF($C34="","",COUNTA($C$5:C34)) -> 30 | C34: TeSeS | D34: Player | E34: Counterstrike2 | F34: Team Falcons | G34: Danish | H34: 2 | I34: Tier 3 | J34: 11250 | K34: 4500 | L34: =IF($C34="","",ROUND($J34*0.17,0)) -> 1913 | M34: 8000 | N34: 3500 | O34: 2000 | P34: 2000 | Q34: 13500 | R34: 6075 | S34: =IF($C34="","",ROUND($J34*2.2,0)) -> 24750 | T34: 4638 | U34: 4063 | V34: 2438 | W34: 2400 | X34: 2 platforms | Y34: 0.75 | Z34: 1 | AA34: René Madsen | AB34: https://x.com/tesescs | AC34: Instagram/TeseS | AD34: https://www.twitch.tv/tesesss | AK34: 36872 | AL34: Rifler | AO34: 45700 | AV34: =IF(AND(AP34>0,J34>0),J34*1000/(AP34*0.2),"") | AW34: =IF(AND(AS34>0,M34>0),M34*1000/(AS34*0.3),"") | AX34: =IF(AND(AO34>0,O34>0),O34*1000/(AO34*0.1),"") -> 437.63676 | AY34: =IF(AND(AR34>0,N34>0),N34*1000/(AR34*0.25),"") | AZ34: =IF(AND(AQ34>0,Q34>0),Q34*1000/(AQ34*1),"") | BA34: =IFERROR(VLOOKUP($I34,'07_Settings'!$A$10:$F$14,6,FALSE()),0.25) -> 0.35 | BB34: 1 | BC34: 1 | BD34: 1 | BE34: =IFERROR(ROUND($S34*BA34*BC34*BD34*BB34,0),0) -> 8663 | BF34: =IF(COUNT(AO34:AU34)>0,"estimated","pending") -> estimated
B35: =IF($C35="","",COUNTA($C$5:C35)) -> 31 | C35: Aymeinstein | D35: Assistant Coach | E35: Counterstrike2 | F35: Team Falcons | G35: French | H35: 2 | I35: Tier 4 | J35: 11000 | K35: 4600 | L35: =IF($C35="","",ROUND($J35*0.17,0)) -> 1870 | M35: 8600 | N35: 3500 | O35: 2200 | P35: 0 | Q35: 15950 | R35: 7150 | S35: =IF($C35="","",ROUND($J35*2.2,0)) -> 24200 | T35: 3850 | U35: 3300 | V35: 2000 | W35: 0 | X35: 2 platforms | Y35: 0.5 | Z35: 1 | AA35: Aymen Bencheikh | AB35: https://x.com/aymeinstein | AC35: https://www.instagram.com/aymeinsteintv | AK35: 22/04/1996 | AO35: 4833 | AP35: 4318 | AV35: =IF(AND(AP35>0,J35>0),J35*1000/(AP35*0.2),"") -> 12737.378 | AW35: =IF(AND(AS35>0,M35>0),M35*1000/(AS35*0.3),"") | AX35: =IF(AND(AO35>0,O35>0),O35*1000/(AO35*0.1),"") -> 4552.0381 | AY35: =IF(AND(AR35>0,N35>0),N35*1000/(AR35*0.25),"") | AZ35: =IF(AND(AQ35>0,Q35>0),Q35*1000/(AQ35*1),"") | BA35: =IFERROR(VLOOKUP($I35,'07_Settings'!$A$10:$F$14,6,FALSE()),0.25) -> 0.25 | BB35: 1 | BC35: 1 | BD35: 1 | BE35: =IFERROR(ROUND($S35*BA35*BC35*BD35*BB35,0),0) -> 6050 | BF35: =IF(COUNT(AO35:AU35)>0,"estimated","pending") -> estimated
B36: =IF($C36="","",COUNTA($C$5:C36)) -> 32 | C36: Zonic | D36: Head Coach | E36: Counterstrike2 | F36: Team Falcons | G36: Danish | H36: 2 | I36: Tier 2 | J36: 0 | K36: 0 | L36: =IF($C36="","",ROUND($J36*0.17,0)) -> 0 | M36: 0 | N36: 0 | O36: 0 | P36: 0 | Q36: 0 | R36: 0 | S36: =IF($C36="","",ROUND($J36*2.2,0)) -> 0 | T36: 0 | U36: 0 | V36: 2000 | W36: 0 | X36: 2 platforms | Y36: 0.5 | Z36: 1 | AA36: Danny Sørensen | AB36: https://x.com/zonic | AC36: Instagram/Zonic | AD36: https://www.twitch.tv/zonic | AH36: Facebook/Zonic | AK36: 30/07/1986 | AO36: 121400 | AP36: 80000 | AV36: =IF(AND(AP36>0,J36>0),J36*1000/(AP36*0.2),"") | AW36: =IF(AND(AS36>0,M36>0),M36*1000/(AS36*0.3),"") | AX36: =IF(AND(AO36>0,O36>0),O36*1000/(AO36*0.1),"") | AY36: =IF(AND(AR36>0,N36>0),N36*1000/(AR36*0.25),"") | AZ36: =IF(AND(AQ36>0,Q36>0),Q36*1000/(AQ36*1),"") | BA36: =IFERROR(VLOOKUP($I36,'07_Settings'!$A$10:$F$14,6,FALSE()),0.25) -> 0.45 | BB36: 1 | BC36: 1 | BD36: 1 | BE36: =IFERROR(ROUND($S36*BA36*BC36*BD36*BB36,0),0) -> 0 | BF36: =IF(COUNT(AO36:AU36)>0,"estimated","pending") -> estimated
B37: =IF($C37="","",COUNTA($C$5:C37)) -> 33 | C37: clockzi | D37: Player | E37: Counterstrike2 | F37: Falcons Force | G37: Danish | H37: 1 | I37: Tier 3 | J37: 11000 | K37: 4600 | L37: =IF($C37="","",ROUND($J37*0.17,0)) -> 1870 | M37: 8600 | N37: 3500 | O37: 2200 | P37: 2200 | Q37: 15950 | R37: 7150 | S37: =IF($C37="","",ROUND($J37*2.2,0)) -> 24200 | T37: 3850 | U37: 3300 | V37: 2000 | W37: 2400 | X37: 1 platform | Y37: 0.75 | Z37: 1 | AA37: Oskar Led Blæsbjerg | AB37: https://x.com/flcclockzi | AK37: 21/04/2011 | AL37: Rifler | AO37: 361 | AV37: =IF(AND(AP37>0,J37>0),J37*1000/(AP37*0.2),"") | AW37: =IF(AND(AS37>0,M37>0),M37*1000/(AS37*0.3),"") | AX37: =IF(AND(AO37>0,O37>0),O37*1000/(AO37*0.1),"") -> 60941.828 | AY37: =IF(AND(AR37>0,N37>0),N37*1000/(AR37*0.25),"") | AZ37: =IF(AND(AQ37>0,Q37>0),Q37*1000/(AQ37*1),"") | BA37: =IFERROR(VLOOKUP($I37,'07_Settings'!$A$10:$F$14,6,FALSE()),0.25) -> 0.35 | BB37: 1 | BC37: 1 | BD37: 1 | BE37: =IFERROR(ROUND($S37*BA37*BC37*BD37*BB37,0),0) -> 8470 | BF37: =IF(COUNT(AO37:AU37)>0,"estimated","pending") -> estimated
B38: =IF($C38="","",COUNTA($C$5:C38)) -> 34 | C38: grecu | D38: Player | E38: Counterstrike2 | F38: Falcons Force | G38: Romanian | H38: 2 | I38: Tier 2 | J38: 5200 | K38: 2200 | L38: =IF($C38="","",ROUND($J38*0.17,0)) -> 884 | M38: 4050 | N38: 1650 | O38: 1050 | P38: 1050 | Q38: 7550 | R38: 3400 | S38: =IF($C38="","",ROUND($J38*2.2,0)) -> 11440 | T38: 1800 | U38: 1550 | V38: 950 | W38: 2400 | X38: 2 platforms | Y38: 0.75 | Z38: 1 | AA38: Andrei Grecu | AB38: https://x.com/grecuflc | AD38: https://www.twitch.tv/gbcgrecu | AK38: 15/11/2007 | AL38: AWPer | AV38: =IF(AND(AP38>0,J38>0),J38*1000/(AP38*0.2),"") | AW38: =IF(AND(AS38>0,M38>0),M38*1000/(AS38*0.3),"") | AX38: =IF(AND(AO38>0,O38>0),O38*1000/(AO38*0.1),"") | AY38: =IF(AND(AR38>0,N38>0),N38*1000/(AR38*0.25),"") | AZ38: =IF(AND(AQ38>0,Q38>0),Q38*1000/(AQ38*1),"") | BA38: =IFERROR(VLOOKUP($I38,'07_Settings'!$A$10:$F$14,6,FALSE()),0.25) -> 0.45 | BB38: 1 | BC38: 1 | BD38: 1 | BE38: =IFERROR(ROUND($S38*BA38*BC38*BD38*BB38,0),0) -> 5148 | BF38: =IF(COUNT(AO38:AU38)>0,"estimated","pending") -> pending
B39: =IF($C39="","",COUNTA($C$5:C39)) -> 35 | C39: VENO | D39: Player | E39: Counterstrike2 | F39: Falcons Force | G39: Serbian | H39: 3 | I39: Tier 2 | J39: 12100 | K39: 5100 | L39: =IF($C39="","",ROUND($J39*0.17,0)) -> 2057 | M39: 9450 | N39: 3850 | O39: 2400 | P39: 2400 | Q39: 17550 | R39: 7850 | S39: =IF($C39="","",ROUND($J39*2.2,0)) -> 26620 | T39: 4250 | U39: 3650 | V39: 2200 | W39: 2400 | X39: 3 platforms | Y39: 0.75 | Z39: 1 | AA39: Vladimir Stanković | AB39: https://x.com/venocs2 | AD39: https://www.twitch.tv/venocs2 | AE39: https://www.youtube.com/@venocs2 | AK39: 30/04/2007 | AL39: Rifler | AO39: 489 | AV39: =IF(AND(AP39>0,J39>0),J39*1000/(AP39*0.2),"") | AW39: =IF(AND(AS39>0,M39>0),M39*1000/(AS39*0.3),"") | AX39: =IF(AND(AO39>0,O39>0),O39*1000/(AO39*0.1),"") -> 49079.755 | AY39: =IF(AND(AR39>0,N39>0),N39*1000/(AR39*0.25),"") | AZ39: =IF(AND(AQ39>0,Q39>0),Q39*1000/(AQ39*1),"") | BA39: =IFERROR(VLOOKUP($I39,'07_Settings'!$A$10:$F$14,6,FALSE()),0.25) -> 0.45 | BB39: 1 | BC39: 1 | BD39: 1 | BE39: =IFERROR(ROUND($S39*BA39*BC39*BD39*BB39,0),0) -> 11979 | BF39: =IF(COUNT(AO39:AU39)>0,"estimated","pending") -> estimated
B40: =IF($C40="","",COUNTA($C$5:C40)) -> 36 | C40: NaToSaphiX | D40: Head Coach | E40: Counterstrike2 | F40: Falcons Force | G40: Danish | H40: 5 | I40: Tier 2 | J40: 11000 | K40: 4600 | L40: =IF($C40="","",ROUND($J40*0.17,0)) -> 1870 | M40: 8600 | N40: 3500 | O40: 2200 | P40: 0 | Q40: 15950 | R40: 7150 | S40: =IF($C40="","",ROUND($J40*2.2,0)) -> 24200 | T40: 3850 | U40: 3300 | V40: 2000 | W40: 0 | X40: 5 platforms | Y40: 0.2 | Z40: 1 | AA40: Niels Christian Sillassen | AB40: https://x.com/NaToSaphiX | AC40: https://www.instagram.com/natosaphix | AD40: https://www.twitch.tv/natosaphix | AE40: https://www.youtube.com/NaToSaphiX | AK40: 17/08/1996 | AO40: 30500 | AQ40: 108539 | AR40: 138000 | AV40: =IF(AND(AP40>0,J40>0),J40*1000/(AP40*0.2),"") | AW40: =IF(AND(AS40>0,M40>0),M40*1000/(AS40*0.3),"") | AX40: =IF(AND(AO40>0,O40>0),O40*1000/(AO40*0.1),"") -> 721.31148 | AY40: =IF(AND(AR40>0,N40>0),N40*1000/(AR40*0.25),"") -> 101.44928 | AZ40: =IF(AND(AQ40>0,Q40>0),Q40*1000/(AQ40*1),"") -> 146.95179 | BA40: =IFERROR(VLOOKUP($I40,'07_Settings'!$A$10:$F$14,6,FALSE()),0.25) -> 0.45 | BB40: 1 | BC40: 1 | BD40: 1 | BE40: =IFERROR(ROUND($S40*BA40*BC40*BD40*BB40,0),0) -> 10890 | BF40: =IF(COUNT(AO40:AU40)>0,"estimated","pending") -> estimated
B41: =IF($C41="","",COUNTA($C$5:C41)) -> 37 | C41: Neoskai | D41: Manager | E41: Counterstrike2 | F41: Falcons Force | G41: French | H41: 2 | I41: Tier 4 | J41: 0 | K41: 0 | L41: =IF($C41="","",ROUND($J41*0.17,0)) -> 0 | M41: 0 | N41: 0 | O41: 0 | P41: 0 | Q41: 0 | R41: 0 | S41: =IF($C41="","",ROUND($J41*2.2,0)) -> 0 | T41: 0 | U41: 0 | V41: 1200 | W41: 0 | X41: 2 platforms | Y41: 0.2 | Z41: 1 | AA41: Loïc Potages | AB41: https://x.com/Neoskai | AC41: https://www.instagram.com/neoskai/ | AK41: 16/06/1994 | AV41: =IF(AND(AP41>0,J41>0),J41*1000/(AP41*0.2),"") | AW41: =IF(AND(AS41>0,M41>0),M41*1000/(AS41*0.3),"") | AX41: =IF(AND(AO41>0,O41>0),O41*1000/(AO41*0.1),"") | AY41: =IF(AND(AR41>0,N41>0),N41*1000/(AR41*0.25),"") | AZ41: =IF(AND(AQ41>0,Q41>0),Q41*1000/(AQ41*1),"") | BA41: =IFERROR(VLOOKUP($I41,'07_Settings'!$A$10:$F$14,6,FALSE()),0.25) -> 0.25 | BB41: 1 | BC41: 1 | BD41: 1 | BE41: =IFERROR(ROUND($S41*BA41*BC41*BD41*BB41,0),0) -> 0 | BF41: =IF(COUNT(AO41:AU41)>0,"estimated","pending") -> pending
B42: =IF($C42="","",COUNTA($C$5:C42)) -> 38 | C42: Nucleonz | D42: Player | E42: Counterstrike2 | F42: Falcons Force | G42: North Macedonian | H42: 1 | I42: Tier 3 | J42: 8750 | K42: 3000 | L42: =IF($C42="","",ROUND($J42*0.17,0)) -> 1488 | M42: 6000 | N42: 2500 | O42: 1200 | P42: 1200 | Q42: 9000 | R42: 4050 | S42: =IF($C42="","",ROUND($J42*2.2,0)) -> 19250 | T42: 2200 | U42: 1925 | V42: 1155 | W42: 2400 | X42: 1 platform | Y42: 0.75 | Z42: 1 | AA42: Matej Trajkoski | AB42: https://x.com/NucleonZz | AK42: 39722 | AL42: Rifler | AO42: 1342 | AV42: =IF(AND(AP42>0,J42>0),J42*1000/(AP42*0.2),"") | AW42: =IF(AND(AS42>0,M42>0),M42*1000/(AS42*0.3),"") | AX42: =IF(AND(AO42>0,O42>0),O42*1000/(AO42*0.1),"") -> 8941.8778 | AY42: =IF(AND(AR42>0,N42>0),N42*1000/(AR42*0.25),"") | AZ42: =IF(AND(AQ42>0,Q42>0),Q42*1000/(AQ42*1),"") | BA42: =IFERROR(VLOOKUP($I42,'07_Settings'!$A$10:$F$14,6,FALSE()),0.25) -> 0.35 | BB42: 1 | BC42: 1 | BD42: 1 | BE42: =IFERROR(ROUND($S42*BA42*BC42*BD42*BB42,0),0) -> 6738 | BF42: =IF(COUNT(AO42:AU42)>0,"estimated","pending") -> estimated
B43: =IF($C43="","",COUNTA($C$5:C43)) -> 39 | C43: Skiter | D43: Player | E43: Dota2 | F43: Dota2 | G43: Slovakia | H43: 2 | I43: Tier 3 | J43: 5200 | K43: 2200 | L43: =IF($C43="","",ROUND($J43*0.17,0)) -> 884 | M43: 4050 | N43: 1650 | O43: 1050 | P43: 1050 | Q43: 7550 | R43: 3400 | S43: =IF($C43="","",ROUND($J43*2.2,0)) -> 11440 | T43: 1800 | U43: 1550 | V43: 950 | W43: 2400 | X43: 2 platforms | Y43: 0.75 | Z43: 1 | AA43: Oliver Lepko | AB43: https://x.com/skiter | AC43: Instagram/Skiter | AH43: https://www.facebook.com/SkiterDota | AK43: 36138 | AO43: 18300 | AP43: 9703 | AV43: =IF(AND(AP43>0,J43>0),J43*1000/(AP43*0.2),"") -> 2679.5836 | AW43: =IF(AND(AS43>0,M43>0),M43*1000/(AS43*0.3),"") | AX43: =IF(AND(AO43>0,O43>0),O43*1000/(AO43*0.1),"") -> 573.77049 | AY43: =IF(AND(AR43>0,N43>0),N43*1000/(AR43*0.25),"") | AZ43: =IF(AND(AQ43>0,Q43>0),Q43*1000/(AQ43*1),"") | BA43: =IFERROR(VLOOKUP($I43,'07_Settings'!$A$10:$F$14,6,FALSE()),0.25) -> 0.35 | BB43: 1 | BC43: 1 | BD43: 1 | BE43: =IFERROR(ROUND($S43*BA43*BC43*BD43*BB43,0),0) -> 4004 | BF43: =IF(COUNT(AO43:AU43)>0,"estimated","pending") -> estimated
B44: =IF($C44="","",COUNTA($C$5:C44)) -> 40 | C44: Malr1ne | D44: Player | E44: Dota2 | F44: Dota2 | G44: Russian | H44: 2 | I44: Tier 2 | J44: 11000 | K44: 4600 | L44: =IF($C44="","",ROUND($J44*0.17,0)) -> 1870 | M44: 8600 | N44: 3500 | O44: 2200 | P44: 2200 | Q44: 15950 | R44: 7150 | S44: =IF($C44="","",ROUND($J44*2.2,0)) -> 24200 | T44: 3850 | U44: 3300 | V44: 2000 | W44: 2400 | X44: 2 platforms | Y44: 0.75 | Z44: 1 | AA44: Stanislav Potorak | AB44: https://x.com/Malr1ne_ | AC44: Instagram/Malr1ne | AD44: https://www.twitch.tv/malr1ne_dota | AK44: 17/09/2004 | AV44: =IF(AND(AP44>0,J44>0),J44*1000/(AP44*0.2),"") | AW44: =IF(AND(AS44>0,M44>0),M44*1000/(AS44*0.3),"") | AX44: =IF(AND(AO44>0,O44>0),O44*1000/(AO44*0.1),"") | AY44: =IF(AND(AR44>0,N44>0),N44*1000/(AR44*0.25),"") | AZ44: =IF(AND(AQ44>0,Q44>0),Q44*1000/(AQ44*1),"") | BA44: =IFERROR(VLOOKUP($I44,'07_Settings'!$A$10:$F$14,6,FALSE()),0.25) -> 0.45 | BB44: 1 | BC44: 1 | BD44: 1 | BE44: =IFERROR(ROUND($S44*BA44*BC44*BD44*BB44,0),0) -> 10890 | BF44: =IF(COUNT(AO44:AU44)>0,"estimated","pending") -> pending
B45: =IF($C45="","",COUNTA($C$5:C45)) -> 41 | C45: ATF | D45: Player | E45: Dota2 | F45: Dota2 | G45: Jordanian | H45: 2 | I45: Tier 2 | J45: 11000 | K45: 4600 | L45: =IF($C45="","",ROUND($J45*0.17,0)) -> 1870 | M45: 8600 | N45: 3500 | O45: 2200 | P45: 2200 | Q45: 15950 | R45: 7150 | S45: =IF($C45="","",ROUND($J45*2.2,0)) -> 24200 | T45: 3850 | U45: 3300 | V45: 2000 | W45: 2400 | X45: 2 platforms | Y45: 0.75 | Z45: 1 | AA45: Ammar Al-Assaf | AB45: https://x.com/AmmarAlassaf6 | AC45: Instagram/Ammar | AD45: https://www.twitch.tv/ammar_the_f | AK45: 38416 | AO45: 19700 | AP45: 17000 | AV45: =IF(AND(AP45>0,J45>0),J45*1000/(AP45*0.2),"") -> 3235.2941 | AW45: =IF(AND(AS45>0,M45>0),M45*1000/(AS45*0.3),"") | AX45: =IF(AND(AO45>0,O45>0),O45*1000/(AO45*0.1),"") -> 1116.7513 | AY45: =IF(AND(AR45>0,N45>0),N45*1000/(AR45*0.25),"") | AZ45: =IF(AND(AQ45>0,Q45>0),Q45*1000/(AQ45*1),"") | BA45: =IFERROR(VLOOKUP($I45,'07_Settings'!$A$10:$F$14,6,FALSE()),0.25) -> 0.45 | BB45: 1 | BC45: 1 | BD45: 1 | BE45: =IFERROR(ROUND($S45*BA45*BC45*BD45*BB45,0),0) -> 10890 | BF45: =IF(COUNT(AO45:AU45)>0,"estimated","pending") -> estimated
B46: =IF($C46="","",COUNTA($C$5:C46)) -> 42 | C46: Cr1t- | D46: Player | E46: Dota2 | F46: Dota2 | G46: Danish | H46: 3 | I46: Tier 2 | J46: 12100 | K46: 5100 | L46: =IF($C46="","",ROUND($J46*0.17,0)) -> 2057 | M46: 9450 | N46: 3850 | O46: 2400 | P46: 2400 | Q46: 17550 | R46: 7850 | S46: =IF($C46="","",ROUND($J46*2.2,0)) -> 26620 | T46: 4250 | U46: 3650 | V46: 2200 | W46: 2400 | X46: 3 platforms | Y46: 0.75 | Z46: 1 | AA46: Andreas Nielsen | AB46: https://x.com/Cr1tdota | AC46: Instagram/Cr1t | AD46: https://www.twitch.tv/cr1tdota | AE46: YT/Cr1t | AH46: https://www.facebook.com/Cr1tdota | AK46: 13/07/1996 | AO46: 149100 | AV46: =IF(AND(AP46>0,J46>0),J46*1000/(AP46*0.2),"") | AW46: =IF(AND(AS46>0,M46>0),M46*1000/(AS46*0.3),"") | AX46: =IF(AND(AO46>0,O46>0),O46*1000/(AO46*0.1),"") -> 160.96579 | AY46: =IF(AND(AR46>0,N46>0),N46*1000/(AR46*0.25),"") | AZ46: =IF(AND(AQ46>0,Q46>0),Q46*1000/(AQ46*1),"") | BA46: =IFERROR(VLOOKUP($I46,'07_Settings'!$A$10:$F$14,6,FALSE()),0.25) -> 0.45 | BB46: 1 | BC46: 1 | BD46: 1 | BE46: =IFERROR(ROUND($S46*BA46*BC46*BD46*BB46,0),0) -> 11979 | BF46: =IF(COUNT(AO46:AU46)>0,"estimated","pending") -> estimated
B47: =IF($C47="","",COUNTA($C$5:C47)) -> 43 | C47: Sneyking | D47: Player | E47: Dota2 | F47: Dota2 | G47: American / Chinese | H47: 2 | I47: Tier 3 | J47: 20700 | K47: 8700 | L47: =IF($C47="","",ROUND($J47*0.17,0)) -> 3519 | M47: 16150 | N47: 6600 | O47: 4150 | P47: 4150 | Q47: 30000 | R47: 13450 | S47: =IF($C47="","",ROUND($J47*2.2,0)) -> 45540 | T47: 7250 | U47: 6200 | V47: 3750 | W47: 2400 | X47: 2 platforms | Y47: 0.75 | Z47: 1 | AA47: Jingjun Wu | AB47: https://x.com/SneykingGaming | AD47: https://www.twitch.tv/sneykingdota | AK47: 34763 | AO47: 18900 | AV47: =IF(AND(AP47>0,J47>0),J47*1000/(AP47*0.2),"") | AW47: =IF(AND(AS47>0,M47>0),M47*1000/(AS47*0.3),"") | AX47: =IF(AND(AO47>0,O47>0),O47*1000/(AO47*0.1),"") -> 2195.7672 | AY47: =IF(AND(AR47>0,N47>0),N47*1000/(AR47*0.25),"") | AZ47: =IF(AND(AQ47>0,Q47>0),Q47*1000/(AQ47*1),"") | BA47: =IFERROR(VLOOKUP($I47,'07_Settings'!$A$10:$F$14,6,FALSE()),0.25) -> 0.35 | BB47: 1 | BC47: 1 | BD47: 1 | BE47: =IFERROR(ROUND($S47*BA47*BC47*BD47*BB47,0),0) -> 15939 | BF47: =IF(COUNT(AO47:AU47)>0,"estimated","pending") -> estimated
B48: =IF($C48="","",COUNTA($C$5:C48)) -> 44 | C48: Aui_2000 | D48: Head Coach | E48: Dota2 | F48: Dota2 | G48: Canada | H48: 2 | I48: Tier 2 | J48: 11000 | K48: 4600 | L48: =IF($C48="","",ROUND($J48*0.17,0)) -> 1870 | M48: 8600 | N48: 3500 | O48: 2200 | P48: 0 | Q48: 15950 | R48: 7150 | S48: =IF($C48="","",ROUND($J48*2.2,0)) -> 24200 | T48: 3850 | U48: 3300 | V48: 2000 | W48: 0 | X48: 2 platforms | Y48: 0.75 | Z48: 1 | AA48: Kurtis Ling | AB48: https://x.com/Aui_2000 | AD48: https://www.twitch.tv/aui_2000 | AE48: YT/Aui_2000 | AK48: 33644 | AO48: 133283 | AV48: =IF(AND(AP48>0,J48>0),J48*1000/(AP48*0.2),"") | AW48: =IF(AND(AS48>0,M48>0),M48*1000/(AS48*0.3),"") | AX48: =IF(AND(AO48>0,O48>0),O48*1000/(AO48*0.1),"") -> 165.06231 | AY48: =IF(AND(AR48>0,N48>0),N48*1000/(AR48*0.25),"") | AZ48: =IF(AND(AQ48>0,Q48>0),Q48*1000/(AQ48*1),"") | BA48: =IFERROR(VLOOKUP($I48,'07_Settings'!$A$10:$F$14,6,FALSE()),0.25) -> 0.45 | BB48: 1 | BC48: 1 | BD48: 1 | BE48: =IFERROR(ROUND($S48*BA48*BC48*BD48*BB48,0),0) -> 10890 | BF48: =IF(COUNT(AO48:AU48)>0,"estimated","pending") -> estimated
B49: =IF($C49="","",COUNTA($C$5:C49)) -> 45 | C49: AfromOush | D49: Manager | E49: Dota2 | F49: Dota2 | G49: Jordanian | H49: 3 | I49: Tier 4 | J49: 0 | K49: 0 | L49: =IF($C49="","",ROUND($J49*0.17,0)) -> 0 | M49: 0 | N49: 0 | O49: 0 | P49: 0 | Q49: 0 | R49: 0 | S49: =IF($C49="","",ROUND($J49*2.2,0)) -> 0 | T49: 0 | U49: 0 | V49: 1200 | W49: 0 | X49: 3 platforms | Y49: 0.5 | Z49: 1 | AA49: Mohammad Abu Al Eis | AB49: https://x.com/AfrOmoush | AD49: https://www.twitch.tv/afromoush | AH49: https://www.facebook.com/RealAfrOmoush | AK49: 35228 | AO49: 861 | AV49: =IF(AND(AP49>0,J49>0),J49*1000/(AP49*0.2),"") | AW49: =IF(AND(AS49>0,M49>0),M49*1000/(AS49*0.3),"") | AX49: =IF(AND(AO49>0,O49>0),O49*1000/(AO49*0.1),"") | AY49: =IF(AND(AR49>0,N49>0),N49*1000/(AR49*0.25),"") | AZ49: =IF(AND(AQ49>0,Q49>0),Q49*1000/(AQ49*1),"") | BA49: =IFERROR(VLOOKUP($I49,'07_Settings'!$A$10:$F$14,6,FALSE()),0.25) -> 0.25 | BB49: 1 | BC49: 1 | BD49: 1 | BE49: =IFERROR(ROUND($S49*BA49*BC49*BD49*BB49,0),0) -> 0 | BF49: =IF(COUNT(AO49:AU49)>0,"estimated","pending") -> estimated
B50: =IF($C50="","",COUNTA($C$5:C50)) -> 46 | C50: Bonkers | D50: Analyst | E50: Dota2 | F50: Dota2 | G50: British | H50: 1 | I50: Tier 4 | J50: 0 | K50: 0 | L50: =IF($C50="","",ROUND($J50*0.17,0)) -> 0 | M50: 0 | N50: 0 | O50: 0 | P50: 0 | Q50: 0 | R50: 0 | S50: =IF($C50="","",ROUND($J50*2.2,0)) -> 0 | T50: 0 | U50: 0 | V50: 600 | W50: 0 | X50: 1 platform | Y50: 0.5 | Z50: 1 | AA50: Allen Cook | AB50: https://x.com/thisisallencook | AK50: 15/02/1980 | AO50: 1596 | AV50: =IF(AND(AP50>0,J50>0),J50*1000/(AP50*0.2),"") | AW50: =IF(AND(AS50>0,M50>0),M50*1000/(AS50*0.3),"") | AX50: =IF(AND(AO50>0,O50>0),O50*1000/(AO50*0.1),"") | AY50: =IF(AND(AR50>0,N50>0),N50*1000/(AR50*0.25),"") | AZ50: =IF(AND(AQ50>0,Q50>0),Q50*1000/(AQ50*1),"") | BA50: =IFERROR(VLOOKUP($I50,'07_Settings'!$A$10:$F$14,6,FALSE()),0.25) -> 0.25 | BB50: 1 | BC50: 1 | BD50: 1 | BE50: =IFERROR(ROUND($S50*BA50*BC50*BD50*BB50,0),0) -> 0 | BF50: =IF(COUNT(AO50:AU50)>0,"estimated","pending") -> estimated
B51: =IF($C51="","",COUNTA($C$5:C51)) -> 47 | C51: GoatMoh | D51: Player | E51: EAFC25 | F51: EA Sport FC | G51: Saudi Arabia | H51: 2 | I51: Tier 2 | J51: 11250 | K51: 4500 | L51: =IF($C51="","",ROUND($J51*0.17,0)) -> 1913 | M51: 8000 | N51: 3500 | O51: 2000 | P51: 2000 | Q51: 13500 | R51: 6075 | S51: =IF($C51="","",ROUND($J51*2.2,0)) -> 24750 | T51: 4638 | U51: 4063 | V51: 2438 | W51: 2400 | X51: 2 platforms | Y51: 0.3 | Z51: 1 | AA51: Mohammed Alarfaj | AB51: https://x.com/GoatMoh_ | AD51: https://www.twitch.tv/goatmoh | AK51: 15/02/2000 | AV51: =IF(AND(AP51>0,J51>0),J51*1000/(AP51*0.2),"") | AW51: =IF(AND(AS51>0,M51>0),M51*1000/(AS51*0.3),"") | AX51: =IF(AND(AO51>0,O51>0),O51*1000/(AO51*0.1),"") | AY51: =IF(AND(AR51>0,N51>0),N51*1000/(AR51*0.25),"") | AZ51: =IF(AND(AQ51>0,Q51>0),Q51*1000/(AQ51*1),"") | BA51: =IFERROR(VLOOKUP($I51,'07_Settings'!$A$10:$F$14,6,FALSE()),0.25) -> 0.45 | BB51: 1 | BC51: 1 | BD51: 1 | BE51: =IFERROR(ROUND($S51*BA51*BC51*BD51*BB51,0),0) -> 11138 | BF51: =IF(COUNT(AO51:AU51)>0,"estimated","pending") -> pending
B52: =IF($C52="","",COUNTA($C$5:C52)) -> 48 | C52: Hafez | D52: Coach | E52: EAFC25 | F52: EA Sport FC | G52: Saudi Arabia | H52: 1 | I52: Tier 4 | J52: 12100 | K52: 5100 | L52: =IF($C52="","",ROUND($J52*0.17,0)) -> 2057 | M52: 9450 | N52: 3850 | O52: 2400 | P52: 0 | Q52: 17550 | R52: 7850 | S52: =IF($C52="","",ROUND($J52*2.2,0)) -> 26620 | T52: 4250 | U52: 3650 | V52: 2200 | W52: 0 | X52: 1 platform | Y52: 0.3 | Z52: 1 | AA52: Mohammad Hafiz | AB52: https://x.com/_Hafez10 | AK52: 29/12/1997 | AV52: =IF(AND(AP52>0,J52>0),J52*1000/(AP52*0.2),"") | AW52: =IF(AND(AS52>0,M52>0),M52*1000/(AS52*0.3),"") | AX52: =IF(AND(AO52>0,O52>0),O52*1000/(AO52*0.1),"") | AY52: =IF(AND(AR52>0,N52>0),N52*1000/(AR52*0.25),"") | AZ52: =IF(AND(AQ52>0,Q52>0),Q52*1000/(AQ52*1),"") | BA52: =IFERROR(VLOOKUP($I52,'07_Settings'!$A$10:$F$14,6,FALSE()),0.25) -> 0.25 | BB52: 1 | BC52: 1 | BD52: 1 | BE52: =IFERROR(ROUND($S52*BA52*BC52*BD52*BB52,0),0) -> 6655 | BF52: =IF(COUNT(AO52:AU52)>0,"estimated","pending") -> pending
B53: =IF($C53="","",COUNTA($C$5:C53)) -> 49 | C53: Javivillar7 | D53: Coach | E53: EAFC25 | F53: EA Sport FC | G53: Spanish | H53: 4 | I53: Tier 4 | J53: 0 | K53: 0 | L53: =IF($C53="","",ROUND($J53*0.17,0)) -> 0 | M53: 0 | N53: 0 | O53: 0 | P53: 0 | Q53: 0 | R53: 0 | S53: =IF($C53="","",ROUND($J53*2.2,0)) -> 0 | T53: 0 | U53: 0 | V53: 2000 | W53: 0 | X53: 4 platforms | Y53: 0.3 | Z53: 1 | AA53: Javier Villar Gómez | AB53: https://x.com/Javivillar7 | AC53: Instagram/Javivillar7 | AD53: https://www.twitch.tv/javivillar7/ | AE53: https://www.youtube.com/@javivillar7 | AF53: https://www.tiktok.com/@javivillar7?lang=en | AK53: 31/12/2002 | AV53: =IF(AND(AP53>0,J53>0),J53*1000/(AP53*0.2),"") | AW53: =IF(AND(AS53>0,M53>0),M53*1000/(AS53*0.3),"") | AX53: =IF(AND(AO53>0,O53>0),O53*1000/(AO53*0.1),"") | AY53: =IF(AND(AR53>0,N53>0),N53*1000/(AR53*0.25),"") | AZ53: =IF(AND(AQ53>0,Q53>0),Q53*1000/(AQ53*1),"") | BA53: =IFERROR(VLOOKUP($I53,'07_Settings'!$A$10:$F$14,6,FALSE()),0.25) -> 0.25 | BB53: 1 | BC53: 1 | BD53: 1 | BE53: =IFERROR(ROUND($S53*BA53*BC53*BD53*BB53,0),0) -> 0 | BF53: =IF(COUNT(AO53:AU53)>0,"estimated","pending") -> pending
B54: =IF($C54="","",COUNTA($C$5:C54)) -> 50 | C54: Msdossary | D54: Player | E54: EAFC25 | F54: EA Sport FC | G54: Saudi Arabia | H54: 1 | I54: Tier 1 | J54: 11250 | K54: 4500 | L54: =IF($C54="","",ROUND($J54*0.17,0)) -> 1913 | M54: 8000 | N54: 3500 | O54: 2000 | P54: 2000 | Q54: 13500 | R54: 6075 | S54: =IF($C54="","",ROUND($J54*2.2,0)) -> 24750 | T54: 4638 | U54: 4063 | V54: 2438 | W54: 2400 | X54: 1 platform | Y54: 0.3 | Z54: 1 | AA54: Mossad Aldossary | AB54: https://x.com/msdossary7 | AC54: Instagram/Msdossary | AE54: YT/Msdossary7 | AK54: 20/03/2000 | AP54: 483000 | AQ54: 224000 | AR54: 558000 | AV54: =IF(AND(AP54>0,J54>0),J54*1000/(AP54*0.2),"") -> 116.45963 | AW54: =IF(AND(AS54>0,M54>0),M54*1000/(AS54*0.3),"") | AX54: =IF(AND(AO54>0,O54>0),O54*1000/(AO54*0.1),"") | AY54: =IF(AND(AR54>0,N54>0),N54*1000/(AR54*0.25),"") -> 25.089606 | AZ54: =IF(AND(AQ54>0,Q54>0),Q54*1000/(AQ54*1),"") -> 60.267857 | BA54: =IFERROR(VLOOKUP($I54,'07_Settings'!$A$10:$F$14,6,FALSE()),0.25) -> 0.55 | BB54: 1 | BC54: 1 | BD54: 1 | BE54: =IFERROR(ROUND($S54*BA54*BC54*BD54*BB54,0),0) -> 13613 | BF54: =IF(COUNT(AO54:AU54)>0,"estimated","pending") -> estimated
B55: =IF($C55="","",COUNTA($C$5:C55)) -> 51 | C55: Vejrgang | D55: Player | E55: EAFC25 | F55: EA Sport FC | G55: Danish | H55: 4 | I55: Tier 1 | J55: 12100 | K55: 5100 | L55: =IF($C55="","",ROUND($J55*0.17,0)) -> 2057 | M55: 9450 | N55: 3850 | O55: 2400 | P55: 2400 | Q55: 17550 | R55: 7850 | S55: =IF($C55="","",ROUND($J55*2.2,0)) -> 26620 | T55: 4250 | U55: 3650 | V55: 2200 | W55: 2400 | X55: 4 platforms | Y55: 0.3 | Z55: 1 | AA55: Anders Vejrgang | AB55: https://twitter.com/FLC_Vejrgang | AC55: https://www.instagram.com/rblz_vejrgang | AD55: https://www.twitch.tv/anders_vejrgang | AE55: https://www.youtube.com/AndersVejrgangofficial | AK55: 25/01/2006 | AO55: 81400 | AP55: 232000 | AV55: =IF(AND(AP55>0,J55>0),J55*1000/(AP55*0.2),"") -> 260.77586 | AW55: =IF(AND(AS55>0,M55>0),M55*1000/(AS55*0.3),"") | AX55: =IF(AND(AO55>0,O55>0),O55*1000/(AO55*0.1),"") -> 294.84029 | AY55: =IF(AND(AR55>0,N55>0),N55*1000/(AR55*0.25),"") | AZ55: =IF(AND(AQ55>0,Q55>0),Q55*1000/(AQ55*1),"") | BA55: =IFERROR(VLOOKUP($I55,'07_Settings'!$A$10:$F$14,6,FALSE()),0.25) -> 0.55 | BB55: 1 | BC55: 1 | BD55: 1 | BE55: =IFERROR(ROUND($S55*BA55*BC55*BD55*BB55,0),0) -> 14641 | BF55: =IF(COUNT(AO55:AU55)>0,"estimated","pending") -> estimated
B56: =IF($C56="","",COUNTA($C$5:C56)) -> 52 | C56: A9 | D56: Manager | E56: EAFC25 | F56: EA Sport FC | G56: Saudi Arabia | H56: 0 | I56: Tier 4 | J56: 20700 | K56: 8700 | L56: =IF($C56="","",ROUND($J56*0.17,0)) -> 3519 | M56: 16150 | N56: 6600 | O56: 4150 | P56: 0 | Q56: 30000 | R56: 13450 | S56: =IF($C56="","",ROUND($J56*2.2,0)) -> 45540 | T56: 7250 | U56: 6200 | V56: 3750 | W56: 0 | X56: 0 platforms | Y56: 0.3 | Z56: 1 | AA56: Aseel Aldokheel | AK56: 35343 | AV56: =IF(AND(AP56>0,J56>0),J56*1000/(AP56*0.2),"") | AW56: =IF(AND(AS56>0,M56>0),M56*1000/(AS56*0.3),"") | AX56: =IF(AND(AO56>0,O56>0),O56*1000/(AO56*0.1),"") | AY56: =IF(AND(AR56>0,N56>0),N56*1000/(AR56*0.25),"") | AZ56: =IF(AND(AQ56>0,Q56>0),Q56*1000/(AQ56*1),"") | BA56: =IFERROR(VLOOKUP($I56,'07_Settings'!$A$10:$F$14,6,FALSE()),0.25) -> 0.25 | BB56: 1 | BC56: 1 | BD56: 1 | BE56: =IFERROR(ROUND($S56*BA56*BC56*BD56*BB56,0),0) -> 11385 | BF56: =IF(COUNT(AO56:AU56)>0,"estimated","pending") -> pending
B57: =IF($C57="","",COUNTA($C$5:C57)) -> 53 | C57: Kiimo7 | D57: Player | E57: EAFC25 | F57: EA Sport FC | G57: Saudi Arabia | H57: 2 | I57: Tier 2 | J57: 11250 | K57: 4500 | L57: =IF($C57="","",ROUND($J57*0.17,0)) -> 1913 | M57: 8000 | N57: 3500 | O57: 2000 | P57: 2000 | Q57: 13500 | R57: 6075 | S57: =IF($C57="","",ROUND($J57*2.2,0)) -> 24750 | T57: 4638 | U57: 4063 | V57: 2438 | W57: 2400 | X57: 2 platforms | Y57: 0.3 | Z57: 1 | AA57: Abdulkareem Bamogaddam | AB57: https://x.com/kiimo__1 | AC57: https://www.instagram.com/kreemvv/ | AK57: 39757 | AV57: =IF(AND(AP57>0,J57>0),J57*1000/(AP57*0.2),"") | AW57: =IF(AND(AS57>0,M57>0),M57*1000/(AS57*0.3),"") | AX57: =IF(AND(AO57>0,O57>0),O57*1000/(AO57*0.1),"") | AY57: =IF(AND(AR57>0,N57>0),N57*1000/(AR57*0.25),"") | AZ57: =IF(AND(AQ57>0,Q57>0),Q57*1000/(AQ57*1),"") | BA57: =IFERROR(VLOOKUP($I57,'07_Settings'!$A$10:$F$14,6,FALSE()),0.25) -> 0.45 | BB57: 1 | BC57: 1 | BD57: 1 | BE57: =IFERROR(ROUND($S57*BA57*BC57*BD57*BB57,0),0) -> 11138 | BF57: =IF(COUNT(AO57:AU57)>0,"estimated","pending") -> pending
B58: =IF($C58="","",COUNTA($C$5:C58)) -> 54 | C58: Rashed | D58: Manager | E58: Fortnite | F58: Fortnite | G58: Saudi | H58: 0 | I58: Tier 4 | J58: 12100 | K58: 5100 | L58: =IF($C58="","",ROUND($J58*0.17,0)) -> 2057 | M58: 9450 | N58: 3850 | O58: 2400 | P58: 0 | Q58: 17550 | R58: 7850 | S58: =IF($C58="","",ROUND($J58*2.2,0)) -> 26620 | T58: 4250 | U58: 3650 | V58: 2200 | W58: 0 | X58: 0 platforms | Y58: 0.3 | Z58: 1 | AA58: Rashed Aldmaikhi | AV58: =IF(AND(AP58>0,J58>0),J58*1000/(AP58*0.2),"") | AW58: =IF(AND(AS58>0,M58>0),M58*1000/(AS58*0.3),"") | AX58: =IF(AND(AO58>0,O58>0),O58*1000/(AO58*0.1),"") | AY58: =IF(AND(AR58>0,N58>0),N58*1000/(AR58*0.25),"") | AZ58: =IF(AND(AQ58>0,Q58>0),Q58*1000/(AQ58*1),"") | BA58: =IFERROR(VLOOKUP($I58,'07_Settings'!$A$10:$F$14,6,FALSE()),0.25) -> 0.25 | BB58: 1 | BC58: 1 | BD58: 1 | BE58: =IFERROR(ROUND($S58*BA58*BC58*BD58*BB58,0),0) -> 6655 | BF58: =IF(COUNT(AO58:AU58)>0,"estimated","pending") -> pending
B59: =IF($C59="","",COUNTA($C$5:C59)) -> 55 | C59: Abu Omar | D59: Player | E59: Fatal Fury | F59: Fatal Fury | G59: Saudi | H59: 1 | I59: Tier 3 | J59: 8750 | K59: 3000 | L59: =IF($C59="","",ROUND($J59*0.17,0)) -> 1488 | M59: 6000 | N59: 2500 | O59: 1200 | P59: 1200 | Q59: 9000 | R59: 4050 | S59: =IF($C59="","",ROUND($J59*2.2,0)) -> 19250 | T59: 2200 | U59: 1925 | V59: 1155 | W59: 2400 | X59: 1 platform | Y59: 0.3 | Z59: 1 | AA59: Wesam Alghamdi | AB59: https://x.com/wess21111?lang=en | AK59: 30/05/1987 | AV59: =IF(AND(AP59>0,J59>0),J59*1000/(AP59*0.2),"") | AW59: =IF(AND(AS59>0,M59>0),M59*1000/(AS59*0.3),"") | AX59: =IF(AND(AO59>0,O59>0),O59*1000/(AO59*0.1),"") | AY59: =IF(AND(AR59>0,N59>0),N59*1000/(AR59*0.25),"") | AZ59: =IF(AND(AQ59>0,Q59>0),Q59*1000/(AQ59*1),"") | BA59: =IFERROR(VLOOKUP($I59,'07_Settings'!$A$10:$F$14,6,FALSE()),0.25) -> 0.35 | BB59: 1 | BC59: 1 | BD59: 1 | BE59: =IFERROR(ROUND($S59*BA59*BC59*BD59*BB59,0),0) -> 6738 | BF59: =IF(COUNT(AO59:AU59)>0,"estimated","pending") -> pending
B60: =IF($C60="","",COUNTA($C$5:C60)) -> 56 | C60: E.T. | D60: Player | E60: Fatal Fury | F60: Fatal Fury | G60: Taiwan | H60: 3 | I60: Tier 3 | J60: 5700 | K60: 2400 | L60: =IF($C60="","",ROUND($J60*0.17,0)) -> 969 | M60: 4450 | N60: 1850 | O60: 1150 | P60: 1150 | Q60: 8300 | R60: 3700 | S60: =IF($C60="","",ROUND($J60*2.2,0)) -> 12540 | T60: 2000 | U60: 1700 | V60: 1050 | W60: 2400 | X60: 3 platforms | Y60: 0.1 | Z60: 1 | AA60: Lin Chia-hung | AB60: https://x.com/et1120 | AC60: https://www.instagram.com/dbj_et/# | AH60: https://www.facebook.com/Taiwan.1.ET | AK60: 20/11/1984 | AV60: =IF(AND(AP60>0,J60>0),J60*1000/(AP60*0.2),"") | AW60: =IF(AND(AS60>0,M60>0),M60*1000/(AS60*0.3),"") | AX60: =IF(AND(AO60>0,O60>0),O60*1000/(AO60*0.1),"") | AY60: =IF(AND(AR60>0,N60>0),N60*1000/(AR60*0.25),"") | AZ60: =IF(AND(AQ60>0,Q60>0),Q60*1000/(AQ60*1),"") | BA60: =IFERROR(VLOOKUP($I60,'07_Settings'!$A$10:$F$14,6,FALSE()),0.25) -> 0.35 | BB60: 1 | BC60: 1 | BD60: 1 | BE60: =IFERROR(ROUND($S60*BA60*BC60*BD60*BB60,0),0) -> 4389 | BF60: =IF(COUNT(AO60:AU60)>0,"estimated","pending") -> pending
B61: =IF($C61="","",COUNTA($C$5:C61)) -> 57 | C61: Ghirlanda | D61: Manager | E61: Tekken | F61: Tekken | G61: Italian | H61: 1 | I61: Tier 3 | J61: 11000 | K61: 4600 | L61: =IF($C61="","",ROUND($J61*0.17,0)) -> 1870 | M61: 8600 | N61: 3500 | O61: 2200 | P61: 0 | Q61: 15950 | R61: 7150 | S61: =IF($C61="","",ROUND($J61*2.2,0)) -> 24200 | T61: 3850 | U61: 3300 | V61: 2000 | W61: 0 | X61: 1 platform | Y61: 0.5 | Z61: 1 | AA61: Joshua Bianchi | AB61: https://x.com/ghirlandatekken | AK61: 26/02/1992 | AO61: 6213 | AV61: =IF(AND(AP61>0,J61>0),J61*1000/(AP61*0.2),"") | AW61: =IF(AND(AS61>0,M61>0),M61*1000/(AS61*0.3),"") | AX61: =IF(AND(AO61>0,O61>0),O61*1000/(AO61*0.1),"") -> 3540.9625 | AY61: =IF(AND(AR61>0,N61>0),N61*1000/(AR61*0.25),"") | AZ61: =IF(AND(AQ61>0,Q61>0),Q61*1000/(AQ61*1),"") | BA61: =IFERROR(VLOOKUP($I61,'07_Settings'!$A$10:$F$14,6,FALSE()),0.25) -> 0.35 | BB61: 1 | BC61: 1 | BD61: 1 | BE61: =IFERROR(ROUND($S61*BA61*BC61*BD61*BB61,0),0) -> 8470 | BF61: =IF(COUNT(AO61:AU61)>0,"estimated","pending") -> estimated
B62: =IF($C62="","",COUNTA($C$5:C62)) -> 58 | C62: Kindevu | D62: Player | E62: Fatal Fury | F62: Fatal Fury | G62: Japanese | H62: 3 | I62: Tier 3 | J62: 11250 | K62: 4500 | L62: =IF($C62="","",ROUND($J62*0.17,0)) -> 1913 | M62: 8000 | N62: 3500 | O62: 2000 | P62: 2000 | Q62: 13500 | R62: 6075 | S62: =IF($C62="","",ROUND($J62*2.2,0)) -> 24750 | T62: 4638 | U62: 4063 | V62: 2438 | W62: 2400 | X62: 3 platforms | Y62: 0.75 | Z62: 1 | AA62: Yosuke Ito | AB62: https://x.com/kindevu | AD62: https://www.twitch.tv/kindevu0827 | AE62: https://www.youtube.com/channel/UCQevn7lvmrpl3ElLd58YsNQ | AK62: 27/08/1984 | AO62: 18000 | AV62: =IF(AND(AP62>0,J62>0),J62*1000/(AP62*0.2),"") | AW62: =IF(AND(AS62>0,M62>0),M62*1000/(AS62*0.3),"") | AX62: =IF(AND(AO62>0,O62>0),O62*1000/(AO62*0.1),"") -> 1111.1111 | AY62: =IF(AND(AR62>0,N62>0),N62*1000/(AR62*0.25),"") | AZ62: =IF(AND(AQ62>0,Q62>0),Q62*1000/(AQ62*1),"") | BA62: =IFERROR(VLOOKUP($I62,'07_Settings'!$A$10:$F$14,6,FALSE()),0.25) -> 0.35 | BB62: 1 | BC62: 1 | BD62: 1 | BE62: =IFERROR(ROUND($S62*BA62*BC62*BD62*BB62,0),0) -> 8663 | BF62: =IF(COUNT(AO62:AU62)>0,"estimated","pending") -> estimated
B63: =IF($C63="","",COUNTA($C$5:C63)) -> 59 | C63: mok | D63: Player | E63: Fatal Fury | F63: Fatal Fury | G63: Japan | H63: 2 | I63: Tier 2 | J63: 11000 | K63: 4600 | L63: =IF($C63="","",ROUND($J63*0.17,0)) -> 1870 | M63: 8600 | N63: 3500 | O63: 2200 | P63: 2200 | Q63: 15950 | R63: 7150 | S63: =IF($C63="","",ROUND($J63*2.2,0)) -> 24200 | T63: 3850 | U63: 3300 | V63: 2000 | W63: 2400 | X63: 2 platforms | Y63: 0.75 | Z63: 1 | AA63: Hiroaki Hashizume | AB63: https://twitter.com/andytheworld320 | AE63: https://www.youtube.com/channel/UC-Ksra-atsz4eW5i9ZDAa8A | AK63: 20/03/1985 | AO63: 3274 | AV63: =IF(AND(AP63>0,J63>0),J63*1000/(AP63*0.2),"") | AW63: =IF(AND(AS63>0,M63>0),M63*1000/(AS63*0.3),"") | AX63: =IF(AND(AO63>0,O63>0),O63*1000/(AO63*0.1),"") -> 6719.609 | AY63: =IF(AND(AR63>0,N63>0),N63*1000/(AR63*0.25),"") | AZ63: =IF(AND(AQ63>0,Q63>0),Q63*1000/(AQ63*1),"") | BA63: =IFERROR(VLOOKUP($I63,'07_Settings'!$A$10:$F$14,6,FALSE()),0.25) -> 0.45 | BB63: 1 | BC63: 1 | BD63: 1 | BE63: =IFERROR(ROUND($S63*BA63*BC63*BD63*BB63,0),0) -> 10890 | BF63: =IF(COUNT(AO63:AU63)>0,"estimated","pending") -> estimated
B64: =IF($C64="","",COUNTA($C$5:C64)) -> 60 | C64: Sai | D64: Player | E64: Fatal Fury | F64: Fatal Fury | G64: Saudi | H64: 1 | I64: Tier 3 | J64: 11000 | K64: 4600 | L64: =IF($C64="","",ROUND($J64*0.17,0)) -> 1870 | M64: 8600 | N64: 3500 | O64: 2200 | P64: 2200 | Q64: 15950 | R64: 7150 | S64: =IF($C64="","",ROUND($J64*2.2,0)) -> 24200 | T64: 3850 | U64: 3300 | V64: 2000 | W64: 2400 | X64: 1 platform | Y64: 0.3 | Z64: 1 | AA64: Ali Abdullah Alduhaysh | AB64: https://x.com/Zenga83 | AK64: 26/11/1983 | AV64: =IF(AND(AP64>0,J64>0),J64*1000/(AP64*0.2),"") | AW64: =IF(AND(AS64>0,M64>0),M64*1000/(AS64*0.3),"") | AX64: =IF(AND(AO64>0,O64>0),O64*1000/(AO64*0.1),"") | AY64: =IF(AND(AR64>0,N64>0),N64*1000/(AR64*0.25),"") | AZ64: =IF(AND(AQ64>0,Q64>0),Q64*1000/(AQ64*1),"") | BA64: =IFERROR(VLOOKUP($I64,'07_Settings'!$A$10:$F$14,6,FALSE()),0.25) -> 0.35 | BB64: 1 | BC64: 1 | BD64: 1 | BE64: =IFERROR(ROUND($S64*BA64*BC64*BD64*BB64,0),0) -> 8470 | BF64: =IF(COUNT(AO64:AU64)>0,"estimated","pending") -> pending
B65: =IF($C65="","",COUNTA($C$5:C65)) -> 61 | C65: Shadow X | D65: Player | E65: Fatal Fury | F65: Fatal Fury | G65: Mexican | H65: 2 | I65: Tier 2 | J65: 5700 | K65: 2400 | L65: =IF($C65="","",ROUND($J65*0.17,0)) -> 969 | M65: 4450 | N65: 1850 | O65: 1150 | P65: 1150 | Q65: 8300 | R65: 3700 | S65: =IF($C65="","",ROUND($J65*2.2,0)) -> 12540 | T65: 2000 | U65: 1700 | V65: 1050 | W65: 2400 | X65: 2 platforms | Y65: 0.75 | Z65: 1 | AA65: Abraham Sanchez | AB65: https://x.com/ShadowX_FGC | AD65: https://www.twitch.tv/ChonFx | AK65: 14/03/1982 | AV65: =IF(AND(AP65>0,J65>0),J65*1000/(AP65*0.2),"") | AW65: =IF(AND(AS65>0,M65>0),M65*1000/(AS65*0.3),"") | AX65: =IF(AND(AO65>0,O65>0),O65*1000/(AO65*0.1),"") | AY65: =IF(AND(AR65>0,N65>0),N65*1000/(AR65*0.25),"") | AZ65: =IF(AND(AQ65>0,Q65>0),Q65*1000/(AQ65*1),"") | BA65: =IFERROR(VLOOKUP($I65,'07_Settings'!$A$10:$F$14,6,FALSE()),0.25) -> 0.45 | BB65: 1 | BC65: 1 | BD65: 1 | BE65: =IFERROR(ROUND($S65*BA65*BC65*BD65*BB65,0),0) -> 5643 | BF65: =IF(COUNT(AO65:AU65)>0,"estimated","pending") -> pending
B66: =IF($C66="","",COUNTA($C$5:C66)) -> 62 | C66: Tamago | D66: Player | E66: Fatal Fury | F66: Fatal Fury | G66: Mexican | H66: 1 | I66: Tier 3 | J66: 11000 | K66: 4600 | L66: =IF($C66="","",ROUND($J66*0.17,0)) -> 1870 | M66: 8600 | N66: 3500 | O66: 2200 | P66: 2200 | Q66: 15950 | R66: 7150 | S66: =IF($C66="","",ROUND($J66*2.2,0)) -> 24200 | T66: 3850 | U66: 3300 | V66: 2000 | W66: 2400 | X66: 1 platform | Y66: 0.75 | Z66: 1 | AA66: Ángel Chong | AB66: https://x.com/ChonFx | AK66: 31480 | AO66: 652 | AV66: =IF(AND(AP66>0,J66>0),J66*1000/(AP66*0.2),"") | AW66: =IF(AND(AS66>0,M66>0),M66*1000/(AS66*0.3),"") | AX66: =IF(AND(AO66>0,O66>0),O66*1000/(AO66*0.1),"") -> 33742.331 | AY66: =IF(AND(AR66>0,N66>0),N66*1000/(AR66*0.25),"") | AZ66: =IF(AND(AQ66>0,Q66>0),Q66*1000/(AQ66*1),"") | BA66: =IFERROR(VLOOKUP($I66,'07_Settings'!$A$10:$F$14,6,FALSE()),0.25) -> 0.35 | BB66: 1 | BC66: 1 | BD66: 1 | BE66: =IFERROR(ROUND($S66*BA66*BC66*BD66*BB66,0),0) -> 8470 | BF66: =IF(COUNT(AO66:AU66)>0,"estimated","pending") -> estimated
B67: =IF($C67="","",COUNTA($C$5:C67)) -> 63 | C67: Xyzzy | D67: Player | E67: Fatal Fury | F67: Fatal Fury | G67: South Korean | H67: 2 | I67: Tier 2 | J67: 5200 | K67: 2200 | L67: =IF($C67="","",ROUND($J67*0.17,0)) -> 884 | M67: 4050 | N67: 1650 | O67: 1050 | P67: 1050 | Q67: 7550 | R67: 3400 | S67: =IF($C67="","",ROUND($J67*2.2,0)) -> 11440 | T67: 1800 | U67: 1550 | V67: 950 | W67: 2400 | X67: 2 platforms | Y67: 0.75 | Z67: 1 | AA67: Lee Hanbyul | AB67: https://x.com/xyzzylshift | AD67: https://www.twitch.tv/xyzzyshift | AK67: 32517 | AO67: 1217 | AV67: =IF(AND(AP67>0,J67>0),J67*1000/(AP67*0.2),"") | AW67: =IF(AND(AS67>0,M67>0),M67*1000/(AS67*0.3),"") | AX67: =IF(AND(AO67>0,O67>0),O67*1000/(AO67*0.1),"") -> 8627.7732 | AY67: =IF(AND(AR67>0,N67>0),N67*1000/(AR67*0.25),"") | AZ67: =IF(AND(AQ67>0,Q67>0),Q67*1000/(AQ67*1),"") | BA67: =IFERROR(VLOOKUP($I67,'07_Settings'!$A$10:$F$14,6,FALSE()),0.25) -> 0.45 | BB67: 1 | BC67: 1 | BD67: 1 | BE67: =IFERROR(ROUND($S67*BA67*BC67*BD67*BB67,0),0) -> 5148 | BF67: =IF(COUNT(AO67:AU67)>0,"estimated","pending") -> estimated
B68: =IF($C68="","",COUNTA($C$5:C68)) -> 64 | C68: Xiaohai | D68: Player | E68: Street Fighter | F68: Street Fighter | G68: China | H68: 1 | I68: Tier 3 | J68: 11000 | K68: 4600 | L68: =IF($C68="","",ROUND($J68*0.17,0)) -> 1870 | M68: 8600 | N68: 3500 | O68: 2200 | P68: 2200 | Q68: 15950 | R68: 7150 | S68: =IF($C68="","",ROUND($J68*2.2,0)) -> 24200 | T68: 3850 | U68: 3300 | V68: 2000 | W68: 2400 | X68: 1 platform | Y68: 0.1 | Z68: 1 | AA68: Zeng Zhuojun | AB68: https://x.com/Xiaohai_ | AK68: 26/04/1989 | AO68: 30800 | AP68: 268 | AV68: =IF(AND(AP68>0,J68>0),J68*1000/(AP68*0.2),"") -> 205223.88 | AW68: =IF(AND(AS68>0,M68>0),M68*1000/(AS68*0.3),"") | AX68: =IF(AND(AO68>0,O68>0),O68*1000/(AO68*0.1),"") -> 714.28571 | AY68: =IF(AND(AR68>0,N68>0),N68*1000/(AR68*0.25),"") | AZ68: =IF(AND(AQ68>0,Q68>0),Q68*1000/(AQ68*1),"") | BA68: =IFERROR(VLOOKUP($I68,'07_Settings'!$A$10:$F$14,6,FALSE()),0.25) -> 0.35 | BB68: 1 | BC68: 1 | BD68: 1 | BE68: =IFERROR(ROUND($S68*BA68*BC68*BD68*BB68,0),0) -> 8470 | BF68: =IF(COUNT(AO68:AU68)>0,"estimated","pending") -> estimated
B69: =IF($C69="","",COUNTA($C$5:C69)) -> 65 | C69: Peterbot | D69: Player | E69: Fortnite | F69: Fortnite | G69: American/Hungarian | H69: 3 | I69: Tier S | J69: 11000 | K69: 4600 | L69: =IF($C69="","",ROUND($J69*0.17,0)) -> 1870 | M69: 8600 | N69: 3500 | O69: 2200 | P69: 2200 | Q69: 15950 | R69: 7150 | S69: =IF($C69="","",ROUND($J69*2.2,0)) -> 24200 | T69: 3850 | U69: 3300 | V69: 2000 | W69: 2400 | X69: 3 platforms | Y69: 0.5 | Z69: 1 | AA69: Peter Kata | AB69: https://x.com/PeterbotFN | AD69: https://www.twitch.tv/peterbot | AE69: https://www.youtube.com/channel/UC_RGYvZpoesD8yX-o677-xw | AK69: 20/06/2007 | AO69: 458600 | AP69: 213000 | AQ69: 1150157 | AR69: 325000 | AS69: 701100 | AV69: =IF(AND(AP69>0,J69>0),J69*1000/(AP69*0.2),"") -> 258.21596 | AW69: =IF(AND(AS69>0,M69>0),M69*1000/(AS69*0.3),"") -> 40.888128 | AX69: =IF(AND(AO69>0,O69>0),O69*1000/(AO69*0.1),"") -> 47.972089 | AY69: =IF(AND(AR69>0,N69>0),N69*1000/(AR69*0.25),"") -> 43.076923 | AZ69: =IF(AND(AQ69>0,Q69>0),Q69*1000/(AQ69*1),"") -> 13.867672 | BA69: =IFERROR(VLOOKUP($I69,'07_Settings'!$A$10:$F$14,6,FALSE()),0.25) -> 0.65 | BB69: 1 | BC69: 1 | BD69: 1 | BE69: =IFERROR(ROUND($S69*BA69*BC69*BD69*BB69,0),0) -> 15730 | BF69: =IF(COUNT(AO69:AU69)>0,"estimated","pending") -> estimated
B70: =IF($C70="","",COUNTA($C$5:C70)) -> 66 | C70: FHD | D70: Player | E70: Fortnite | F70: Fortnite | G70: Saudi | H70: 3 | I70: Tier 3 | J70: 11000 | K70: 4600 | L70: =IF($C70="","",ROUND($J70*0.17,0)) -> 1870 | M70: 8600 | N70: 3500 | O70: 2200 | P70: 2200 | Q70: 15950 | R70: 7150 | S70: =IF($C70="","",ROUND($J70*2.2,0)) -> 24200 | T70: 3850 | U70: 3300 | V70: 2000 | W70: 2400 | X70: 3 platforms | Y70: 0.3 | Z70: 1 | AA70: Fahad Almutairi | AB70: https://x.com/Fahadclipz | AC70: https://www.instagram.com/fahadclipz/?hl=en | AD70: https://www.twitch.tv/fahadfn | AK70: 31/03/2004 | AO70: 28900 | AV70: =IF(AND(AP70>0,J70>0),J70*1000/(AP70*0.2),"") | AW70: =IF(AND(AS70>0,M70>0),M70*1000/(AS70*0.3),"") | AX70: =IF(AND(AO70>0,O70>0),O70*1000/(AO70*0.1),"") -> 761.24567 | AY70: =IF(AND(AR70>0,N70>0),N70*1000/(AR70*0.25),"") | AZ70: =IF(AND(AQ70>0,Q70>0),Q70*1000/(AQ70*1),"") | BA70: =IFERROR(VLOOKUP($I70,'07_Settings'!$A$10:$F$14,6,FALSE()),0.25) -> 0.35 | BB70: 1 | BC70: 1 | BD70: 1 | BE70: =IFERROR(ROUND($S70*BA70*BC70*BD70*BB70,0),0) -> 8470 | BF70: =IF(COUNT(AO70:AU70)>0,"estimated","pending") -> estimated
B71: =IF($C71="","",COUNTA($C$5:C71)) -> 67 | C71: Gntl | D71: Player | E71: Call of Duty Black Ops 7 | F71: FaZe Falcons | G71: Saudi | H71: 4 | I71: Tier 2 | J71: 12100 | K71: 5100 | L71: =IF($C71="","",ROUND($J71*0.17,0)) -> 2057 | M71: 9450 | N71: 3850 | O71: 2400 | P71: 2400 | Q71: 17550 | R71: 7850 | S71: =IF($C71="","",ROUND($J71*2.2,0)) -> 26620 | T71: 4250 | U71: 3650 | V71: 2200 | W71: 2400 | X71: 4 platforms | Y71: 0.3 | Z71: 1 | AA71: Abdullah Albaqami | AB71: https://x.com/g1ntl | AC71: https://www.instagram.com/accounts/login/?next=%2Fg1ntl&source=omni_redirect | AD71: https://www.twitch.tv/GntL | AE71: https://www.youtube.com/c/g1ntl | AK71: 24/09/2002 | AO71: 107300 | AP71: 95000 | AV71: =IF(AND(AP71>0,J71>0),J71*1000/(AP71*0.2),"") -> 636.84211 | AW71: =IF(AND(AS71>0,M71>0),M71*1000/(AS71*0.3),"") | AX71: =IF(AND(AO71>0,O71>0),O71*1000/(AO71*0.1),"") -> 223.67195 | AY71: =IF(AND(AR71>0,N71>0),N71*1000/(AR71*0.25),"") | AZ71: =IF(AND(AQ71>0,Q71>0),Q71*1000/(AQ71*1),"") | BA71: =IFERROR(VLOOKUP($I71,'07_Settings'!$A$10:$F$14,6,FALSE()),0.25) -> 0.45 | BB71: 1 | BC71: 1 | BD71: 1 | BE71: =IFERROR(ROUND($S71*BA71*BC71*BD71*BB71,0),0) -> 11979 | BF71: =IF(COUNT(AO71:AU71)>0,"estimated","pending") -> estimated
B72: =IF($C72="","",COUNTA($C$5:C72)) -> 68 | C72: NM7 | D72: Player | E72: Fortnite | F72: Fortnite | G72: Saudi | H72: 4 | I72: Tier 3 | J72: 5700 | K72: 2400 | L72: =IF($C72="","",ROUND($J72*0.17,0)) -> 969 | M72: 4450 | N72: 1850 | O72: 1150 | P72: 1150 | Q72: 8300 | R72: 3700 | S72: =IF($C72="","",ROUND($J72*2.2,0)) -> 12540 | T72: 2000 | U72: 1700 | V72: 1050 | W72: 2400 | X72: 4 platforms | Y72: 0.3 | Z72: 1 | AA72: Nawaf Alharthi | AB72: https://x.com/iNm7x | AC72: https://www.instagram.com/accounts/login/?next=%2Finm7x&source=omni_redirect | AD72: https://www.twitch.tv/iiNm7x | AE72: https://www.youtube.com/c/iNm7x | AK72: 37502 | AO72: 34500 | AV72: =IF(AND(AP72>0,J72>0),J72*1000/(AP72*0.2),"") | AW72: =IF(AND(AS72>0,M72>0),M72*1000/(AS72*0.3),"") | AX72: =IF(AND(AO72>0,O72>0),O72*1000/(AO72*0.1),"") -> 333.33333 | AY72: =IF(AND(AR72>0,N72>0),N72*1000/(AR72*0.25),"") | AZ72: =IF(AND(AQ72>0,Q72>0),Q72*1000/(AQ72*1),"") | BA72: =IFERROR(VLOOKUP($I72,'07_Settings'!$A$10:$F$14,6,FALSE()),0.25) -> 0.35 | BB72: 1 | BC72: 1 | BD72: 1 | BE72: =IFERROR(ROUND($S72*BA72*BC72*BD72*BB72,0),0) -> 4389 | BF72: =IF(COUNT(AO72:AU72)>0,"estimated","pending") -> estimated
B73: =IF($C73="","",COUNTA($C$5:C73)) -> 69 | C73: Spy | D73: Player | E73: Fortnite | F73: Fortnite | G73: Saudi | H73: 4 | I73: Tier 2 | J73: 5700 | K73: 2400 | L73: =IF($C73="","",ROUND($J73*0.17,0)) -> 969 | M73: 4450 | N73: 1850 | O73: 1150 | P73: 1150 | Q73: 8300 | R73: 3700 | S73: =IF($C73="","",ROUND($J73*2.2,0)) -> 12540 | T73: 2000 | U73: 1700 | V73: 1050 | W73: 2400 | X73: 4 platforms | Y73: 0.3 | Z73: 1 | AA73: Osama Almasad | AB73: https://x.com/spyerfrog | AC73: https://www.instagram.com/accounts/login/?next=%2Fspyerfrog&source=omni_redirect | AD73: https://www.twitch.tv/spyerfrog | AE73: https://www.youtube.com/channel/UCl9pp6XYMcjyVESzYD8myQg | AK73: 26/02/2002 | AO73: 83800 | AP73: 76000 | AQ73: 182930 | AV73: =IF(AND(AP73>0,J73>0),J73*1000/(AP73*0.2),"") -> 375 | AW73: =IF(AND(AS73>0,M73>0),M73*1000/(AS73*0.3),"") | AX73: =IF(AND(AO73>0,O73>0),O73*1000/(AO73*0.1),"") -> 137.2315 | AY73: =IF(AND(AR73>0,N73>0),N73*1000/(AR73*0.25),"") | AZ73: =IF(AND(AQ73>0,Q73>0),Q73*1000/(AQ73*1),"") -> 45.372547 | BA73: =IFERROR(VLOOKUP($I73,'07_Settings'!$A$10:$F$14,6,FALSE()),0.25) -> 0.45 | BB73: 1 | BC73: 1 | BD73: 1 | BE73: =IFERROR(ROUND($S73*BA73*BC73*BD73*BB73,0),0) -> 5643 | BF73: =IF(COUNT(AO73:AU73)>0,"estimated","pending") -> estimated
B74: =IF($C74="","",COUNTA($C$5:C74)) -> 70 | C74: Yonx | D74: Player | E74: Fortnite | F74: Fortnite | G74: Saudi | H74: 3 | I74: Tier 3 | J74: 5700 | K74: 2400 | L74: =IF($C74="","",ROUND($J74*0.17,0)) -> 969 | M74: 4450 | N74: 1850 | O74: 1150 | P74: 1150 | Q74: 8300 | R74: 3700 | S74: =IF($C74="","",ROUND($J74*2.2,0)) -> 12540 | T74: 2000 | U74: 1700 | V74: 1050 | W74: 2400 | X74: 3 platforms | Y74: 0.3 | Z74: 1 | AA74: Faisal Almusharraf | AB74: https://x.com/YonxFN | AD74: https://www.twitch.tv/YonxFN | AE74: https://www.youtube.com/channel/UCSKgsqUfo7vA4BuBvtf6vwg | AK74: 38295 | AO74: 11199 | AP74: 7622 | AV74: =IF(AND(AP74>0,J74>0),J74*1000/(AP74*0.2),"") -> 3739.1761 | AW74: =IF(AND(AS74>0,M74>0),M74*1000/(AS74*0.3),"") | AX74: =IF(AND(AO74>0,O74>0),O74*1000/(AO74*0.1),"") -> 1026.8774 | AY74: =IF(AND(AR74>0,N74>0),N74*1000/(AR74*0.25),"") | AZ74: =IF(AND(AQ74>0,Q74>0),Q74*1000/(AQ74*1),"") | BA74: =IFERROR(VLOOKUP($I74,'07_Settings'!$A$10:$F$14,6,FALSE()),0.25) -> 0.35 | BB74: 1 | BC74: 1 | BD74: 1 | BE74: =IFERROR(ROUND($S74*BA74*BC74*BD74*BB74,0),0) -> 4389 | BF74: =IF(COUNT(AO74:AU74)>0,"estimated","pending") -> estimated
B75: =IF($C75="","",COUNTA($C$5:C75)) -> 71 | C75: Matteo | D75: Manager | E75: Fortnite | F75: Fortnite | G75: French | H75: 0 | I75: Tier 3 | J75: 0 | K75: 0 | L75: =IF($C75="","",ROUND($J75*0.17,0)) -> 0 | M75: 0 | N75: 0 | O75: 0 | P75: 0 | Q75: 0 | R75: 0 | S75: =IF($C75="","",ROUND($J75*2.2,0)) -> 0 | T75: 0 | U75: 0 | V75: 600 | W75: 0 | X75: 0 platforms | Y75: 0.3 | Z75: 1 | AA75: Matteo Paganin | AO75: 6367 | AV75: =IF(AND(AP75>0,J75>0),J75*1000/(AP75*0.2),"") | AW75: =IF(AND(AS75>0,M75>0),M75*1000/(AS75*0.3),"") | AX75: =IF(AND(AO75>0,O75>0),O75*1000/(AO75*0.1),"") | AY75: =IF(AND(AR75>0,N75>0),N75*1000/(AR75*0.25),"") | AZ75: =IF(AND(AQ75>0,Q75>0),Q75*1000/(AQ75*1),"") | BA75: =IFERROR(VLOOKUP($I75,'07_Settings'!$A$10:$F$14,6,FALSE()),0.25) -> 0.35 | BB75: 1 | BC75: 1 | BD75: 1 | BE75: =IFERROR(ROUND($S75*BA75*BC75*BD75*BB75,0),0) -> 0 | BF75: =IF(COUNT(AO75:AU75)>0,"estimated","pending") -> estimated
B76: =IF($C76="","",COUNTA($C$5:C76)) -> 72 | C76: Conan | D76: Head Coach | E76: Free Fire | F76: Team Falcons | G76: Thailand | H76: 2 | I76: Tier 4 | J76: 0 | K76: 0 | L76: =IF($C76="","",ROUND($J76*0.17,0)) -> 0 | M76: 0 | N76: 0 | O76: 0 | P76: 0 | Q76: 0 | R76: 0 | S76: =IF($C76="","",ROUND($J76*2.2,0)) -> 0 | T76: 0 | U76: 0 | V76: 1200 | W76: 0 | X76: 2 platforms | Y76: 0.3 | Z76: 1 | AA76: Tana Kamruang | AC76: https://www.instagram.com/thana_kamruang/ | AH76: https://facebook.com/profile.php?id=100006004232176 | AK76: 34003 | AV76: =IF(AND(AP76>0,J76>0),J76*1000/(AP76*0.2),"") | AW76: =IF(AND(AS76>0,M76>0),M76*1000/(AS76*0.3),"") | AX76: =IF(AND(AO76>0,O76>0),O76*1000/(AO76*0.1),"") | AY76: =IF(AND(AR76>0,N76>0),N76*1000/(AR76*0.25),"") | AZ76: =IF(AND(AQ76>0,Q76>0),Q76*1000/(AQ76*1),"") | BA76: =IFERROR(VLOOKUP($I76,'07_Settings'!$A$10:$F$14,6,FALSE()),0.25) -> 0.25 | BB76: 1 | BC76: 1 | BD76: 1 | BE76: =IFERROR(ROUND($S76*BA76*BC76*BD76*BB76,0),0) -> 0 | BF76: =IF(COUNT(AO76:AU76)>0,"estimated","pending") -> pending
B77: =IF($C77="","",COUNTA($C$5:C77)) -> 73 | C77: KERORO | D77: Player | E77: Free Fire | F77: Team Falcons | G77: Thailand | H77: 2 | I77: Tier 2 | J77: 11250 | K77: 4500 | L77: =IF($C77="","",ROUND($J77*0.17,0)) -> 1913 | M77: 8000 | N77: 3500 | O77: 2000 | P77: 2000 | Q77: 13500 | R77: 6075 | S77: =IF($C77="","",ROUND($J77*2.2,0)) -> 24750 | T77: 4638 | U77: 4063 | V77: 2438 | W77: 2400 | X77: 2 platforms | Y77: 0.3 | Z77: 1 | AA77: Natthaphong Phuangpriang | AC77: https://www.instagram.com/keroro_god | AH77: https://facebook.com/profile.php?id=100014997245027 | AK77: 13/01/2006 | AV77: =IF(AND(AP77>0,J77>0),J77*1000/(AP77*0.2),"") | AW77: =IF(AND(AS77>0,M77>0),M77*1000/(AS77*0.3),"") | AX77: =IF(AND(AO77>0,O77>0),O77*1000/(AO77*0.1),"") | AY77: =IF(AND(AR77>0,N77>0),N77*1000/(AR77*0.25),"") | AZ77: =IF(AND(AQ77>0,Q77>0),Q77*1000/(AQ77*1),"") | BA77: =IFERROR(VLOOKUP($I77,'07_Settings'!$A$10:$F$14,6,FALSE()),0.25) -> 0.45 | BB77: 1 | BC77: 1 | BD77: 1 | BE77: =IFERROR(ROUND($S77*BA77*BC77*BD77*BB77,0),0) -> 11138 | BF77: =IF(COUNT(AO77:AU77)>0,"estimated","pending") -> pending
B78: =IF($C78="","",COUNTA($C$5:C78)) -> 74 | C78: LIMIT | D78: Player | E78: Free Fire | F78: Team Falcons | G78: Thailand | H78: 3 | I78: Tier 2 | J78: 11000 | K78: 4600 | L78: =IF($C78="","",ROUND($J78*0.17,0)) -> 1870 | M78: 8600 | N78: 3500 | O78: 2200 | P78: 2200 | Q78: 15950 | R78: 7150 | S78: =IF($C78="","",ROUND($J78*2.2,0)) -> 24200 | T78: 3850 | U78: 3300 | V78: 2000 | W78: 2400 | X78: 3 platforms | Y78: 0.3 | Z78: 1 | AA78: Rachata Wanaphurksasilp | AC78: https://www.instagram.com/limit_juy | AF78: https://tiktok.com/@limitxstep8 | AH78: https://facebook.com/profile.php?id=100015743748929 | AK78: 20/02/2006 | AP78: 4771 | AV78: =IF(AND(AP78>0,J78>0),J78*1000/(AP78*0.2),"") -> 11527.982 | AW78: =IF(AND(AS78>0,M78>0),M78*1000/(AS78*0.3),"") | AX78: =IF(AND(AO78>0,O78>0),O78*1000/(AO78*0.1),"") | AY78: =IF(AND(AR78>0,N78>0),N78*1000/(AR78*0.25),"") | AZ78: =IF(AND(AQ78>0,Q78>0),Q78*1000/(AQ78*1),"") | BA78: =IFERROR(VLOOKUP($I78,'07_Settings'!$A$10:$F$14,6,FALSE()),0.25) -> 0.45 | BB78: 1 | BC78: 1 | BD78: 1 | BE78: =IFERROR(ROUND($S78*BA78*BC78*BD78*BB78,0),0) -> 10890 | BF78: =IF(COUNT(AO78:AU78)>0,"estimated","pending") -> estimated
B79: =IF($C79="","",COUNTA($C$5:C79)) -> 75 | C79: ONEMORE | D79: Player | E79: Free Fire | F79: Team Falcons | G79: Thailand | H79: 3 | I79: Tier 2 | J79: 11000 | K79: 4600 | L79: =IF($C79="","",ROUND($J79*0.17,0)) -> 1870 | M79: 8600 | N79: 3500 | O79: 2200 | P79: 2200 | Q79: 15950 | R79: 7150 | S79: =IF($C79="","",ROUND($J79*2.2,0)) -> 24200 | T79: 3850 | U79: 3300 | V79: 2000 | W79: 2400 | X79: 3 platforms | Y79: 0.3 | Z79: 1 | AA79: Rattapoom Sunthalunai | AC79: https://www.instagram.com/poomgohome_ | AF79: https://tiktok.com/@pm.rt | AH79: https://facebook.com/ratta.poom.790 | AK79: 38600 | AP79: 5917 | AV79: =IF(AND(AP79>0,J79>0),J79*1000/(AP79*0.2),"") -> 9295.251 | AW79: =IF(AND(AS79>0,M79>0),M79*1000/(AS79*0.3),"") | AX79: =IF(AND(AO79>0,O79>0),O79*1000/(AO79*0.1),"") | AY79: =IF(AND(AR79>0,N79>0),N79*1000/(AR79*0.25),"") | AZ79: =IF(AND(AQ79>0,Q79>0),Q79*1000/(AQ79*1),"") | BA79: =IFERROR(VLOOKUP($I79,'07_Settings'!$A$10:$F$14,6,FALSE()),0.25) -> 0.45 | BB79: 1 | BC79: 1 | BD79: 1 | BE79: =IFERROR(ROUND($S79*BA79*BC79*BD79*BB79,0),0) -> 10890 | BF79: =IF(COUNT(AO79:AU79)>0,"estimated","pending") -> estimated
B80: =IF($C80="","",COUNTA($C$5:C80)) -> 76 | C80: ONFIRE | D80: Player | E80: Free Fire | F80: Team Falcons | G80: Thailand | H80: 3 | I80: Tier 2 | J80: 11000 | K80: 4600 | L80: =IF($C80="","",ROUND($J80*0.17,0)) -> 1870 | M80: 8600 | N80: 3500 | O80: 2200 | P80: 2200 | Q80: 15950 | R80: 7150 | S80: =IF($C80="","",ROUND($J80*2.2,0)) -> 24200 | T80: 3850 | U80: 3300 | V80: 2000 | W80: 2400 | X80: 3 platforms | Y80: 0.3 | Z80: 1 | AA80: Phulipat Yosit | AC80: https://www.instagram.com/onfirebaby__ | AF80: https://tiktok.com/@onfireeieii | AH80: https://facebook.com/profile.php?id=100072006039523 | AK80: 27/09/2005 | AP80: 23000 | AV80: =IF(AND(AP80>0,J80>0),J80*1000/(AP80*0.2),"") -> 2391.3043 | AW80: =IF(AND(AS80>0,M80>0),M80*1000/(AS80*0.3),"") | AX80: =IF(AND(AO80>0,O80>0),O80*1000/(AO80*0.1),"") | AY80: =IF(AND(AR80>0,N80>0),N80*1000/(AR80*0.25),"") | AZ80: =IF(AND(AQ80>0,Q80>0),Q80*1000/(AQ80*1),"") | BA80: =IFERROR(VLOOKUP($I80,'07_Settings'!$A$10:$F$14,6,FALSE()),0.25) -> 0.45 | BB80: 1 | BC80: 1 | BD80: 1 | BE80: =IFERROR(ROUND($S80*BA80*BC80*BD80*BB80,0),0) -> 10890 | BF80: =IF(COUNT(AO80:AU80)>0,"estimated","pending") -> estimated
B81: =IF($C81="","",COUNTA($C$5:C81)) -> 77 | C81: Penna | D81: Player | E81: Free Fire | F81: Team Falcons | G81: Thailand | H81: 2 | I81: Tier 2 | J81: 11000 | K81: 4600 | L81: =IF($C81="","",ROUND($J81*0.17,0)) -> 1870 | M81: 8600 | N81: 3500 | O81: 2200 | P81: 2200 | Q81: 15950 | R81: 7150 | S81: =IF($C81="","",ROUND($J81*2.2,0)) -> 24200 | T81: 3850 | U81: 3300 | V81: 2000 | W81: 2400 | X81: 2 platforms | Y81: 0.3 | Z81: 1 | AA81: Natthawut Srinaknil | AC81: https://www.instagram.com/pee_2006._?igsh=enRyOTlwbnV2bjg5 | AF81: https://www.tiktok.com/@peena._?_r=1&_t=ZS-93QJymJbPfx | AK81: 13/09/2006 | AV81: =IF(AND(AP81>0,J81>0),J81*1000/(AP81*0.2),"") | AW81: =IF(AND(AS81>0,M81>0),M81*1000/(AS81*0.3),"") | AX81: =IF(AND(AO81>0,O81>0),O81*1000/(AO81*0.1),"") | AY81: =IF(AND(AR81>0,N81>0),N81*1000/(AR81*0.25),"") | AZ81: =IF(AND(AQ81>0,Q81>0),Q81*1000/(AQ81*1),"") | BA81: =IFERROR(VLOOKUP($I81,'07_Settings'!$A$10:$F$14,6,FALSE()),0.25) -> 0.45 | BB81: 1 | BC81: 1 | BD81: 1 | BE81: =IFERROR(ROUND($S81*BA81*BC81*BD81*BB81,0),0) -> 10890 | BF81: =IF(COUNT(AO81:AU81)>0,"estimated","pending") -> pending
B82: =IF($C82="","",COUNTA($C$5:C82)) -> 78 | C82: PROTETO | D82: Player | E82: Free Fire | F82: Team Falcons | G82: Thailand | H82: 2 | I82: Tier 2 | J82: 11000 | K82: 4600 | L82: =IF($C82="","",ROUND($J82*0.17,0)) -> 1870 | M82: 8600 | N82: 3500 | O82: 2200 | P82: 2200 | Q82: 15950 | R82: 7150 | S82: =IF($C82="","",ROUND($J82*2.2,0)) -> 24200 | T82: 3850 | U82: 3300 | V82: 2000 | W82: 2400 | X82: 2 platforms | Y82: 0.3 | Z82: 1 | AA82: Ratchata Soonklang | AC82: https://www.instagram.com/protetae | AH82: https://facebook.com/pongsatorn.pongsatorn.754 | AK82: 39905 | AV82: =IF(AND(AP82>0,J82>0),J82*1000/(AP82*0.2),"") | AW82: =IF(AND(AS82>0,M82>0),M82*1000/(AS82*0.3),"") | AX82: =IF(AND(AO82>0,O82>0),O82*1000/(AO82*0.1),"") | AY82: =IF(AND(AR82>0,N82>0),N82*1000/(AR82*0.25),"") | AZ82: =IF(AND(AQ82>0,Q82>0),Q82*1000/(AQ82*1),"") | BA82: =IFERROR(VLOOKUP($I82,'07_Settings'!$A$10:$F$14,6,FALSE()),0.25) -> 0.45 | BB82: 1 | BC82: 1 | BD82: 1 | BE82: =IFERROR(ROUND($S82*BA82*BC82*BD82*BB82,0),0) -> 10890 | BF82: =IF(COUNT(AO82:AU82)>0,"estimated","pending") -> pending
B83: =IF($C83="","",COUNTA($C$5:C83)) -> 79 | C83: SAINOI | D83: Manager | E83: Free Fire | F83: Team Falcons | G83: Thailand | H83: 0 | I83: Tier 4 | J83: 11000 | K83: 4600 | L83: =IF($C83="","",ROUND($J83*0.17,0)) -> 1870 | M83: 8600 | N83: 3500 | O83: 2200 | P83: 0 | Q83: 15950 | R83: 7150 | S83: =IF($C83="","",ROUND($J83*2.2,0)) -> 24200 | T83: 3850 | U83: 3300 | V83: 2000 | W83: 0 | X83: 0 platforms | Y83: 0.3 | Z83: 1 | AA83: Worrawan Kasikarn | AU83: 28000 | AV83: =IF(AND(AP83>0,J83>0),J83*1000/(AP83*0.2),"") | AW83: =IF(AND(AS83>0,M83>0),M83*1000/(AS83*0.3),"") | AX83: =IF(AND(AO83>0,O83>0),O83*1000/(AO83*0.1),"") | AY83: =IF(AND(AR83>0,N83>0),N83*1000/(AR83*0.25),"") | AZ83: =IF(AND(AQ83>0,Q83>0),Q83*1000/(AQ83*1),"") | BA83: =IFERROR(VLOOKUP($I83,'07_Settings'!$A$10:$F$14,6,FALSE()),0.25) -> 0.25 | BB83: 1 | BC83: 1 | BD83: 1 | BE83: =IFERROR(ROUND($S83*BA83*BC83*BD83*BB83,0),0) -> 6050 | BF83: =IF(COUNT(AO83:AU83)>0,"estimated","pending") -> estimated
B84: =IF($C84="","",COUNTA($C$5:C84)) -> 80 | C84: Jose Serrano | D84: Player | E84: Gran Turismo | F84: Gran Turismo | G84: Spanish | H84: 3 | I84: Tier 2 | J84: 11250 | K84: 4500 | L84: =IF($C84="","",ROUND($J84*0.17,0)) -> 1913 | M84: 8000 | N84: 3500 | O84: 2000 | P84: 2000 | Q84: 13500 | R84: 6075 | S84: =IF($C84="","",ROUND($J84*2.2,0)) -> 24750 | T84: 4638 | U84: 4063 | V84: 2438 | W84: 2400 | X84: 3 platforms | Y84: 0.75 | Z84: 1 | AA84: Jose Serrano | AB84: https://x.com/JoseSerrano_16 | AC84: https://www.instagram.com/joseserranoo_/ | AD84: https://www.twitch.tv/JoseSerrano_16 | AK84: 25/09/2002 | AL84: Driver | AO84: 6313 | AP84: 4161 | AV84: =IF(AND(AP84>0,J84>0),J84*1000/(AP84*0.2),"") -> 13518.385 | AW84: =IF(AND(AS84>0,M84>0),M84*1000/(AS84*0.3),"") | AX84: =IF(AND(AO84>0,O84>0),O84*1000/(AO84*0.1),"") -> 3168.0659 | AY84: =IF(AND(AR84>0,N84>0),N84*1000/(AR84*0.25),"") | AZ84: =IF(AND(AQ84>0,Q84>0),Q84*1000/(AQ84*1),"") | BA84: =IFERROR(VLOOKUP($I84,'07_Settings'!$A$10:$F$14,6,FALSE()),0.25) -> 0.45 | BB84: 1 | BC84: 1 | BD84: 1 | BE84: =IFERROR(ROUND($S84*BA84*BC84*BD84*BB84,0),0) -> 11138 | BF84: =IF(COUNT(AO84:AU84)>0,"estimated","pending") -> estimated
B85: =IF($C85="","",COUNTA($C$5:C85)) -> 81 | C85: Naif Alfaleh | D85: Player | E85: Gran Turismo | F85: Gran Turismo | G85: Saudi | H85: 2 | I85: Tier 2 | J85: 11000 | K85: 4600 | L85: =IF($C85="","",ROUND($J85*0.17,0)) -> 1870 | M85: 8600 | N85: 3500 | O85: 2200 | P85: 2200 | Q85: 15950 | R85: 7150 | S85: =IF($C85="","",ROUND($J85*2.2,0)) -> 24200 | T85: 3850 | U85: 3300 | V85: 2000 | W85: 2400 | X85: 2 platforms | Y85: 0.3 | Z85: 1 | AA85: Naif Alfaleh | AB85: https://x.com/Falcon_Naifx | AC85: https://www.instagram.com/falcon_naifx/ | AK85: 30/06/2003 | AL85: Driver | AO85: 461 | AP85: 418 | AV85: =IF(AND(AP85>0,J85>0),J85*1000/(AP85*0.2),"") -> 131578.95 | AW85: =IF(AND(AS85>0,M85>0),M85*1000/(AS85*0.3),"") | AX85: =IF(AND(AO85>0,O85>0),O85*1000/(AO85*0.1),"") -> 47722.343 | AY85: =IF(AND(AR85>0,N85>0),N85*1000/(AR85*0.25),"") | AZ85: =IF(AND(AQ85>0,Q85>0),Q85*1000/(AQ85*1),"") | BA85: =IFERROR(VLOOKUP($I85,'07_Settings'!$A$10:$F$14,6,FALSE()),0.25) -> 0.45 | BB85: 1 | BC85: 1 | BD85: 1 | BE85: =IFERROR(ROUND($S85*BA85*BC85*BD85*BB85,0),0) -> 10890 | BF85: =IF(COUNT(AO85:AU85)>0,"estimated","pending") -> estimated
B86: =IF($C86="","",COUNTA($C$5:C86)) -> 82 | C86: Pol Urra | D86: Player | E86: Gran Turismo | F86: Gran Turismo | G86: Spanish | H86: 2 | I86: Tier 2 | J86: 12100 | K86: 5100 | L86: =IF($C86="","",ROUND($J86*0.17,0)) -> 2057 | M86: 9450 | N86: 3850 | O86: 2400 | P86: 2400 | Q86: 17550 | R86: 7850 | S86: =IF($C86="","",ROUND($J86*2.2,0)) -> 26620 | T86: 4250 | U86: 3650 | V86: 2200 | W86: 2400 | X86: 2 platforms | Y86: 0.75 | Z86: 1 | AA86: Pol Urra | AB86: https://x.com/polurra | AC86: https://www.instagram.com/pol_urra/ | AK86: 21/02/2005 | AL86: Driver | AP86: 995 | AV86: =IF(AND(AP86>0,J86>0),J86*1000/(AP86*0.2),"") -> 60804.02 | AW86: =IF(AND(AS86>0,M86>0),M86*1000/(AS86*0.3),"") | AX86: =IF(AND(AO86>0,O86>0),O86*1000/(AO86*0.1),"") | AY86: =IF(AND(AR86>0,N86>0),N86*1000/(AR86*0.25),"") | AZ86: =IF(AND(AQ86>0,Q86>0),Q86*1000/(AQ86*1),"") | BA86: =IFERROR(VLOOKUP($I86,'07_Settings'!$A$10:$F$14,6,FALSE()),0.25) -> 0.45 | BB86: 1 | BC86: 1 | BD86: 1 | BE86: =IFERROR(ROUND($S86*BA86*BC86*BD86*BB86,0),0) -> 11979 | BF86: =IF(COUNT(AO86:AU86)>0,"estimated","pending") -> estimated
B87: =IF($C87="","",COUNTA($C$5:C87)) -> 83 | C87: Wesam Khalil | D87: Player | E87: Gran Turismo | F87: Gran Turismo | G87: Saudi | H87: 2 | I87: Tier 2 | J87: 11000 | K87: 4600 | L87: =IF($C87="","",ROUND($J87*0.17,0)) -> 1870 | M87: 8600 | N87: 3500 | O87: 2200 | P87: 2200 | Q87: 15950 | R87: 7150 | S87: =IF($C87="","",ROUND($J87*2.2,0)) -> 24200 | T87: 3850 | U87: 3300 | V87: 2000 | W87: 2400 | X87: 2 platforms | Y87: 0.3 | Z87: 1 | AA87: Wesam Khalil | AB87: https://x.com/Falcon_Wesam | AC87: https://www.instagram.com/falcon_wesam/ | AK87: 17/06/1999 | AL87: Driver | AV87: =IF(AND(AP87>0,J87>0),J87*1000/(AP87*0.2),"") | AW87: =IF(AND(AS87>0,M87>0),M87*1000/(AS87*0.3),"") | AX87: =IF(AND(AO87>0,O87>0),O87*1000/(AO87*0.1),"") | AY87: =IF(AND(AR87>0,N87>0),N87*1000/(AR87*0.25),"") | AZ87: =IF(AND(AQ87>0,Q87>0),Q87*1000/(AQ87*1),"") | BA87: =IFERROR(VLOOKUP($I87,'07_Settings'!$A$10:$F$14,6,FALSE()),0.25) -> 0.45 | BB87: 1 | BC87: 1 | BD87: 1 | BE87: =IFERROR(ROUND($S87*BA87*BC87*BD87*BB87,0),0) -> 10890 | BF87: =IF(COUNT(AO87:AU87)>0,"estimated","pending") -> pending
B88: =IF($C88="","",COUNTA($C$5:C88)) -> 84 | C88: Skwal | D88: Manager | E88: Gran Turismo | F88: Gran Turismo | G88: French | H88: 2 | I88: Tier 4 | J88: 12100 | K88: 5100 | L88: =IF($C88="","",ROUND($J88*0.17,0)) -> 2057 | M88: 9450 | N88: 3850 | O88: 2400 | P88: 0 | Q88: 17550 | R88: 7850 | S88: =IF($C88="","",ROUND($J88*2.2,0)) -> 26620 | T88: 4250 | U88: 3650 | V88: 2200 | W88: 0 | X88: 2 platforms | Y88: 0.3 | Z88: 1 | AA88: Nicolas Sautron | AB88: https://x.com/SkwalGG | AC88: https://www.instagram.com/skwalgg/ | AK88: 28/03/1992 | AV88: =IF(AND(AP88>0,J88>0),J88*1000/(AP88*0.2),"") | AW88: =IF(AND(AS88>0,M88>0),M88*1000/(AS88*0.3),"") | AX88: =IF(AND(AO88>0,O88>0),O88*1000/(AO88*0.1),"") | AY88: =IF(AND(AR88>0,N88>0),N88*1000/(AR88*0.25),"") | AZ88: =IF(AND(AQ88>0,Q88>0),Q88*1000/(AQ88*1),"") | BA88: =IFERROR(VLOOKUP($I88,'07_Settings'!$A$10:$F$14,6,FALSE()),0.25) -> 0.25 | BB88: 1 | BC88: 1 | BD88: 1 | BE88: =IFERROR(ROUND($S88*BA88*BC88*BD88*BB88,0),0) -> 6655 | BF88: =IF(COUNT(AO88:AU88)>0,"estimated","pending") -> pending
B89: =IF($C89="","",COUNTA($C$5:C89)) -> 85 | C89: Boyet | D89: Player | E89: Mobile Legends Bang Bang | F89: Team Falcons MENA | G89: Philippines | H89: 1 | I89: Tier 3 | J89: 8750 | K89: 3000 | L89: =IF($C89="","",ROUND($J89*0.17,0)) -> 1488 | M89: 6000 | N89: 2500 | O89: 1200 | P89: 1200 | Q89: 9000 | R89: 4050 | S89: =IF($C89="","",ROUND($J89*2.2,0)) -> 19250 | T89: 2200 | U89: 1925 | V89: 1155 | W89: 2400 | X89: 1 platform | Y89: 0.3 | Z89: 1 | AA89: Bien Salvador C Chumacera | AC89: https://www.instagram.com/boyetdr_ | AK89: 29/01/2003 | AL89: Jungler | AP89: 2574 | AV89: =IF(AND(AP89>0,J89>0),J89*1000/(AP89*0.2),"") -> 16996.892 | AW89: =IF(AND(AS89>0,M89>0),M89*1000/(AS89*0.3),"") | AX89: =IF(AND(AO89>0,O89>0),O89*1000/(AO89*0.1),"") | AY89: =IF(AND(AR89>0,N89>0),N89*1000/(AR89*0.25),"") | AZ89: =IF(AND(AQ89>0,Q89>0),Q89*1000/(AQ89*1),"") | BA89: =IFERROR(VLOOKUP($I89,'07_Settings'!$A$10:$F$14,6,FALSE()),0.25) -> 0.35 | BB89: 1 | BC89: 1 | BD89: 1 | BE89: =IFERROR(ROUND($S89*BA89*BC89*BD89*BB89,0),0) -> 6738 | BF89: =IF(COUNT(AO89:AU89)>0,"estimated","pending") -> estimated
B90: =IF($C90="","",COUNTA($C$5:C90)) -> 86 | C90: Cuffin | D90: Player | E90: Mobile Legends Bang Bang | F90: Team Falcons MENA | G90: Saudi Arabia | H90: 1 | I90: Tier 3 | J90: 5200 | K90: 2200 | L90: =IF($C90="","",ROUND($J90*0.17,0)) -> 884 | M90: 4050 | N90: 1650 | O90: 1050 | P90: 1050 | Q90: 7550 | R90: 3400 | S90: =IF($C90="","",ROUND($J90*2.2,0)) -> 11440 | T90: 1800 | U90: 1550 | V90: 950 | W90: 2400 | X90: 1 platform | Y90: 0.3 | Z90: 1 | AA90: Muath saad alquraini | AC90: https://www.instagram.com/accounts/login/?next=%2Fcuffin_ml&source=omni_redirect | AK90: 19/10/2002 | AL90: Middle | AV90: =IF(AND(AP90>0,J90>0),J90*1000/(AP90*0.2),"") | AW90: =IF(AND(AS90>0,M90>0),M90*1000/(AS90*0.3),"") | AX90: =IF(AND(AO90>0,O90>0),O90*1000/(AO90*0.1),"") | AY90: =IF(AND(AR90>0,N90>0),N90*1000/(AR90*0.25),"") | AZ90: =IF(AND(AQ90>0,Q90>0),Q90*1000/(AQ90*1),"") | BA90: =IFERROR(VLOOKUP($I90,'07_Settings'!$A$10:$F$14,6,FALSE()),0.25) -> 0.35 | BB90: 1 | BC90: 1 | BD90: 1 | BE90: =IFERROR(ROUND($S90*BA90*BC90*BD90*BB90,0),0) -> 4004 | BF90: =IF(COUNT(AO90:AU90)>0,"estimated","pending") -> pending
B91: =IF($C91="","",COUNTA($C$5:C91)) -> 87 | C91: Kakashi | D91: Manager | E91: Mobile Legends Bang Bang | F91: Falcons Vega MENA | G91: Egypt | H91: 1 | I91: Tier 4 | J91: 5700 | K91: 2400 | L91: =IF($C91="","",ROUND($J91*0.17,0)) -> 969 | M91: 4450 | N91: 1850 | O91: 1150 | P91: 0 | Q91: 8300 | R91: 3700 | S91: =IF($C91="","",ROUND($J91*2.2,0)) -> 12540 | T91: 2000 | U91: 1700 | V91: 1050 | W91: 0 | X91: 1 platform | Y91: 0.3 | Z91: 1 | AA91: AMR WAFED YASSIN | AC91: https://www.instagram.com/cuffin_ml | AK91: 37050 | AV91: =IF(AND(AP91>0,J91>0),J91*1000/(AP91*0.2),"") | AW91: =IF(AND(AS91>0,M91>0),M91*1000/(AS91*0.3),"") | AX91: =IF(AND(AO91>0,O91>0),O91*1000/(AO91*0.1),"") | AY91: =IF(AND(AR91>0,N91>0),N91*1000/(AR91*0.25),"") | AZ91: =IF(AND(AQ91>0,Q91>0),Q91*1000/(AQ91*1),"") | BA91: =IFERROR(VLOOKUP($I91,'07_Settings'!$A$10:$F$14,6,FALSE()),0.25) -> 0.25 | BB91: 1 | BC91: 1 | BD91: 1 | BE91: =IFERROR(ROUND($S91*BA91*BC91*BD91*BB91,0),0) -> 3135 | BF91: =IF(COUNT(AO91:AU91)>0,"estimated","pending") -> pending
B92: =IF($C92="","",COUNTA($C$5:C92)) -> 88 | C92: Kakashi | D92: Manager | E92: Mobile Legends Bang Bang | F92: Falcons Vega MENA | G92: Egypt | H92: 1 | I92: Tier 4 | J92: 0 | K92: 0 | L92: =IF($C92="","",ROUND($J92*0.17,0)) -> 0 | M92: 0 | N92: 0 | O92: 0 | P92: 0 | Q92: 0 | R92: 0 | S92: =IF($C92="","",ROUND($J92*2.2,0)) -> 0 | T92: 0 | U92: 0 | V92: 600 | W92: 0 | X92: 1 platform | Y92: 0.3 | Z92: 1 | AA92: AMR WAFED YASSIN | AC92: https://www.instagram.com/cuffin_ml | AK92: 37050 | AV92: =IF(AND(AP92>0,J92>0),J92*1000/(AP92*0.2),"") | AW92: =IF(AND(AS92>0,M92>0),M92*1000/(AS92*0.3),"") | AX92: =IF(AND(AO92>0,O92>0),O92*1000/(AO92*0.1),"") | AY92: =IF(AND(AR92>0,N92>0),N92*1000/(AR92*0.25),"") | AZ92: =IF(AND(AQ92>0,Q92>0),Q92*1000/(AQ92*1),"") | BA92: =IFERROR(VLOOKUP($I92,'07_Settings'!$A$10:$F$14,6,FALSE()),0.25) -> 0.25 | BB92: 1 | BC92: 1 | BD92: 1 | BE92: =IFERROR(ROUND($S92*BA92*BC92*BD92*BB92,0),0) -> 0 | BF92: =IF(COUNT(AO92:AU92)>0,"estimated","pending") -> pending
B93: =IF($C93="","",COUNTA($C$5:C93)) -> 89 | C93: Saano | D93: Player | E93: Mobile Legends Bang Bang | F93: Team Falcons MENA | G93: Saudi Arabia | H93: 0 | I93: Tier 3 | J93: 8750 | K93: 3000 | L93: =IF($C93="","",ROUND($J93*0.17,0)) -> 1488 | M93: 6000 | N93: 2500 | O93: 1200 | P93: 1200 | Q93: 9000 | R93: 4050 | S93: =IF($C93="","",ROUND($J93*2.2,0)) -> 19250 | T93: 2200 | U93: 1925 | V93: 1155 | W93: 2400 | X93: 0 platforms | Y93: 0.3 | Z93: 1 | AA93: SULAIMAN MUSALLAM ALRASHDI | AK93: 30/06/2004 | AL93: Gold Lane | AV93: =IF(AND(AP93>0,J93>0),J93*1000/(AP93*0.2),"") | AW93: =IF(AND(AS93>0,M93>0),M93*1000/(AS93*0.3),"") | AX93: =IF(AND(AO93>0,O93>0),O93*1000/(AO93*0.1),"") | AY93: =IF(AND(AR93>0,N93>0),N93*1000/(AR93*0.25),"") | AZ93: =IF(AND(AQ93>0,Q93>0),Q93*1000/(AQ93*1),"") | BA93: =IFERROR(VLOOKUP($I93,'07_Settings'!$A$10:$F$14,6,FALSE()),0.25) -> 0.35 | BB93: 1 | BC93: 1 | BD93: 1 | BE93: =IFERROR(ROUND($S93*BA93*BC93*BD93*BB93,0),0) -> 6738 | BF93: =IF(COUNT(AO93:AU93)>0,"estimated","pending") -> pending
B94: =IF($C94="","",COUNTA($C$5:C94)) -> 90 | C94: Sanji | D94: Player | E94: Mobile Legends Bang Bang | F94: Team Falcons MENA | G94: Saudi Arabia | H94: 1 | I94: Tier 3 | J94: 5700 | K94: 2400 | L94: =IF($C94="","",ROUND($J94*0.17,0)) -> 969 | M94: 4450 | N94: 1850 | O94: 1150 | P94: 1150 | Q94: 8300 | R94: 3700 | S94: =IF($C94="","",ROUND($J94*2.2,0)) -> 12540 | T94: 2000 | U94: 1700 | V94: 1050 | W94: 2400 | X94: 1 platform | Y94: 0.3 | Z94: 1 | AA94: Ayman Othman Alqarni | AC94: https://www.instagram.com/trolll_ml | AK94: 37682 | AL94: EXP Lane | AV94: =IF(AND(AP94>0,J94>0),J94*1000/(AP94*0.2),"") | AW94: =IF(AND(AS94>0,M94>0),M94*1000/(AS94*0.3),"") | AX94: =IF(AND(AO94>0,O94>0),O94*1000/(AO94*0.1),"") | AY94: =IF(AND(AR94>0,N94>0),N94*1000/(AR94*0.25),"") | AZ94: =IF(AND(AQ94>0,Q94>0),Q94*1000/(AQ94*1),"") | BA94: =IFERROR(VLOOKUP($I94,'07_Settings'!$A$10:$F$14,6,FALSE()),0.25) -> 0.35 | BB94: 1 | BC94: 1 | BD94: 1 | BE94: =IFERROR(ROUND($S94*BA94*BC94*BD94*BB94,0),0) -> 4389 | BF94: =IF(COUNT(AO94:AU94)>0,"estimated","pending") -> pending
B95: =IF($C95="","",COUNTA($C$5:C95)) -> 91 | C95: Tarzaan | D95: Player | E95: Mobile Legends Bang Bang | F95: Team Falcons MENA | G95: Saudi Arabia | H95: 0 | I95: Tier 3 | J95: 5700 | K95: 2400 | L95: =IF($C95="","",ROUND($J95*0.17,0)) -> 969 | M95: 4450 | N95: 1850 | O95: 1150 | P95: 1150 | Q95: 8300 | R95: 3700 | S95: =IF($C95="","",ROUND($J95*2.2,0)) -> 12540 | T95: 2000 | U95: 1700 | V95: 1050 | W95: 2400 | X95: 0 platforms | Y95: 0.3 | Z95: 1 | AA95: Mohammed Ayman Kharabah | AK95: 14/05/2000 | AL95: Jungler | AV95: =IF(AND(AP95>0,J95>0),J95*1000/(AP95*0.2),"") | AW95: =IF(AND(AS95>0,M95>0),M95*1000/(AS95*0.3),"") | AX95: =IF(AND(AO95>0,O95>0),O95*1000/(AO95*0.1),"") | AY95: =IF(AND(AR95>0,N95>0),N95*1000/(AR95*0.25),"") | AZ95: =IF(AND(AQ95>0,Q95>0),Q95*1000/(AQ95*1),"") | BA95: =IFERROR(VLOOKUP($I95,'07_Settings'!$A$10:$F$14,6,FALSE()),0.25) -> 0.35 | BB95: 1 | BC95: 1 | BD95: 1 | BE95: =IFERROR(ROUND($S95*BA95*BC95*BD95*BB95,0),0) -> 4389 | BF95: =IF(COUNT(AO95:AU95)>0,"estimated","pending") -> pending
B96: =IF($C96="","",COUNTA($C$5:C96)) -> 92 | C96: Troll | D96: Player | E96: Mobile Legends Bang Bang | F96: Team Falcons MENA | G96: Saudi Arabia | H96: 0 | I96: Tier 3 | J96: 5700 | K96: 2400 | L96: =IF($C96="","",ROUND($J96*0.17,0)) -> 969 | M96: 4450 | N96: 1850 | O96: 1150 | P96: 1150 | Q96: 8300 | R96: 3700 | S96: =IF($C96="","",ROUND($J96*2.2,0)) -> 12540 | T96: 2000 | U96: 1700 | V96: 1050 | W96: 2400 | X96: 0 platforms | Y96: 0.3 | Z96: 1 | AA96: Moayed ayman kharaba | AK96: 31/01/2007 | AL96: Roamer | AV96: =IF(AND(AP96>0,J96>0),J96*1000/(AP96*0.2),"") | AW96: =IF(AND(AS96>0,M96>0),M96*1000/(AS96*0.3),"") | AX96: =IF(AND(AO96>0,O96>0),O96*1000/(AO96*0.1),"") | AY96: =IF(AND(AR96>0,N96>0),N96*1000/(AR96*0.25),"") | AZ96: =IF(AND(AQ96>0,Q96>0),Q96*1000/(AQ96*1),"") | BA96: =IFERROR(VLOOKUP($I96,'07_Settings'!$A$10:$F$14,6,FALSE()),0.25) -> 0.35 | BB96: 1 | BC96: 1 | BD96: 1 | BE96: =IFERROR(ROUND($S96*BA96*BC96*BD96*BB96,0),0) -> 4389 | BF96: =IF(COUNT(AO96:AU96)>0,"estimated","pending") -> pending
B97: =IF($C97="","",COUNTA($C$5:C97)) -> 93 | C97: Owgwen | D97: Player | E97: Mobile Legends Bang Bang | F97: Team Falcons PH | G97: Philippines | H97: 4 | I97: Tier 3 | J97: 11000 | K97: 4600 | L97: =IF($C97="","",ROUND($J97*0.17,0)) -> 1870 | M97: 8600 | N97: 3500 | O97: 2200 | P97: 2200 | Q97: 15950 | R97: 7150 | S97: =IF($C97="","",ROUND($J97*2.2,0)) -> 24200 | T97: 3850 | U97: 3300 | V97: 2000 | W97: 2400 | X97: 4 platforms | Y97: 0.3 | Z97: 1 | AA97: Rowgien Stimpson Unigo | AB97: https://twitter.com/Ogiiiieeen | AC97: https://www.instagram.com/flcn.owgwen | AF97: https://www.tiktok.com/@ogiiiieeen | AH97: https://facebook.com/Ogiiiieeen | AK97: 25/04/2001 | AL97: Roamer | AP97: 14000 | AS97: 65500 | AU97: 54000 | AV97: =IF(AND(AP97>0,J97>0),J97*1000/(AP97*0.2),"") -> 3928.5714 | AW97: =IF(AND(AS97>0,M97>0),M97*1000/(AS97*0.3),"") -> 437.65903 | AX97: =IF(AND(AO97>0,O97>0),O97*1000/(AO97*0.1),"") | AY97: =IF(AND(AR97>0,N97>0),N97*1000/(AR97*0.25),"") | AZ97: =IF(AND(AQ97>0,Q97>0),Q97*1000/(AQ97*1),"") | BA97: =IFERROR(VLOOKUP($I97,'07_Settings'!$A$10:$F$14,6,FALSE()),0.25) -> 0.35 | BB97: 1 | BC97: 1 | BD97: 1 | BE97: =IFERROR(ROUND($S97*BA97*BC97*BD97*BB97,0),0) -> 8470 | BF97: =IF(COUNT(AO97:AU97)>0,"estimated","pending") -> estimated
B98: =IF($C98="","",COUNTA($C$5:C98)) -> 94 | C98: Super Marco | D98: Player | E98: Mobile Legends Bang Bang | F98: Team Falcons PH | G98: Philippines | H98: 3 | I98: Tier 2 | J98: 18000 | K98: 7550 | L98: =IF($C98="","",ROUND($J98*0.17,0)) -> 3060 | M98: 14050 | N98: 5750 | O98: 3600 | P98: 3600 | Q98: 26100 | R98: 11700 | S98: =IF($C98="","",ROUND($J98*2.2,0)) -> 39600 | T98: 6300 | U98: 5400 | V98: 3250 | W98: 2400 | X98: 3 platforms | Y98: 0.3 | Z98: 1 | AA98: Marco Stephen Requitiano | AC98: https://www.tiktok.com/@flcnsupermarco | AF98: https://www.tiktok.com/@flcnsupermarco | AH98: https://www.facebook.com/FLCNSupermarco | AK98: 36687 | AL98: Gold Lane | AV98: =IF(AND(AP98>0,J98>0),J98*1000/(AP98*0.2),"") | AW98: =IF(AND(AS98>0,M98>0),M98*1000/(AS98*0.3),"") | AX98: =IF(AND(AO98>0,O98>0),O98*1000/(AO98*0.1),"") | AY98: =IF(AND(AR98>0,N98>0),N98*1000/(AR98*0.25),"") | AZ98: =IF(AND(AQ98>0,Q98>0),Q98*1000/(AQ98*1),"") | BA98: =IFERROR(VLOOKUP($I98,'07_Settings'!$A$10:$F$14,6,FALSE()),0.25) -> 0.45 | BB98: 1 | BC98: 1 | BD98: 1 | BE98: =IFERROR(ROUND($S98*BA98*BC98*BD98*BB98,0),0) -> 17820 | BF98: =IF(COUNT(AO98:AU98)>0,"estimated","pending") -> pending
B99: =IF($C99="","",COUNTA($C$5:C99)) -> 95 | C99: Hadji | D99: Player | E99: Mobile Legends Bang Bang | F99: Team Falcons PH | G99: Philippines | H99: 3 | I99: Tier 2 | J99: 11000 | K99: 4600 | L99: =IF($C99="","",ROUND($J99*0.17,0)) -> 1870 | M99: 8600 | N99: 3500 | O99: 2200 | P99: 2200 | Q99: 15950 | R99: 7150 | S99: =IF($C99="","",ROUND($J99*2.2,0)) -> 24200 | T99: 3850 | U99: 3300 | V99: 2000 | W99: 2400 | X99: 3 platforms | Y99: 0.3 | Z99: 1 | AA99: Salic Imam | AC99: https://www.instagram.com/hadjizy | AF99: https://www.tiktok.com/@hadjizy_ | AH99: https://facebook.com/Hadjizyyyyy | AK99: 23/04/2003 | AL99: Middle | AP99: 85000 | AS99: 193300 | AU99: 658375 | AV99: =IF(AND(AP99>0,J99>0),J99*1000/(AP99*0.2),"") -> 647.05882 | AW99: =IF(AND(AS99>0,M99>0),M99*1000/(AS99*0.3),"") -> 148.30143 | AX99: =IF(AND(AO99>0,O99>0),O99*1000/(AO99*0.1),"") | AY99: =IF(AND(AR99>0,N99>0),N99*1000/(AR99*0.25),"") | AZ99: =IF(AND(AQ99>0,Q99>0),Q99*1000/(AQ99*1),"") | BA99: =IFERROR(VLOOKUP($I99,'07_Settings'!$A$10:$F$14,6,FALSE()),0.25) -> 0.45 | BB99: 1 | BC99: 1 | BD99: 1 | BE99: =IFERROR(ROUND($S99*BA99*BC99*BD99*BB99,0),0) -> 10890 | BF99: =IF(COUNT(AO99:AU99)>0,"estimated","pending") -> estimated
B100: =IF($C100="","",COUNTA($C$5:C100)) -> 96 | C100: Moody | D100: Assistant Coach | E100: Mobile Legends Bang Bang | F100: Team Falcons PH | G100: Philippines | H100: 3 | I100: Tier 4 | J100: 0 | K100: 0 | L100: =IF($C100="","",ROUND($J100*0.17,0)) -> 0 | M100: 0 | N100: 0 | O100: 0 | P100: 0 | Q100: 0 | R100: 0 | S100: =IF($C100="","",ROUND($J100*2.2,0)) -> 0 | T100: 0 | U100: 0 | V100: 1200 | W100: 0 | X100: 3 platforms | Y100: 0.3 | Z100: 1 | AA100: Mohammad Samal | AC100: https://www.instagram.com/moodysamal | AF100: https://www.tiktok.com/@flcn.moody | AH100: https://www.facebook.com/liquidcoachmoody/ | AK100: 26/08/1996 | AV100: =IF(AND(AP100>0,J100>0),J100*1000/(AP100*0.2),"") | AW100: =IF(AND(AS100>0,M100>0),M100*1000/(AS100*0.3),"") | AX100: =IF(AND(AO100>0,O100>0),O100*1000/(AO100*0.1),"") | AY100: =IF(AND(AR100>0,N100>0),N100*1000/(AR100*0.25),"") | AZ100: =IF(AND(AQ100>0,Q100>0),Q100*1000/(AQ100*1),"") | BA100: =IFERROR(VLOOKUP($I100,'07_Settings'!$A$10:$F$14,6,FALSE()),0.25) -> 0.25 | BB100: 1 | BC100: 1 | BD100: 1 | BE100: =IFERROR(ROUND($S100*BA100*BC100*BD100*BB100,0),0) -> 0 | BF100: =IF(COUNT(AO100:AU100)>0,"estimated","pending") -> pending
B101: =IF($C101="","",COUNTA($C$5:C101)) -> 97 | C101: VR3N | D101: Analyst | E101: Mobile Legends Bang Bang | F101: Team Falcons PH | G101: Philippines | H101: 3 | I101: Tier 4 | J101: 0 | K101: 0 | L101: =IF($C101="","",ROUND($J101*0.17,0)) -> 0 | M101: 0 | N101: 0 | O101: 0 | P101: 0 | Q101: 0 | R101: 0 | S101: =IF($C101="","",ROUND($J101*2.2,0)) -> 0 | T101: 0 | U101: 0 | V101: 1200 | W101: 0 | X101: 3 platforms | Y101: 0.3 | Z101: 1 | AA101: Vrendon Pesebre | AC101: https://www.instagram.com/vrendonlin | AF101: https://www.tiktok.com/@vrendonlin | AH101: https://www.facebook.com/kutspogi | AK101: 22/04/1991 | AU101: 7811 | AV101: =IF(AND(AP101>0,J101>0),J101*1000/(AP101*0.2),"") | AW101: =IF(AND(AS101>0,M101>0),M101*1000/(AS101*0.3),"") | AX101: =IF(AND(AO101>0,O101>0),O101*1000/(AO101*0.1),"") | AY101: =IF(AND(AR101>0,N101>0),N101*1000/(AR101*0.25),"") | AZ101: =IF(AND(AQ101>0,Q101>0),Q101*1000/(AQ101*1),"") | BA101: =IFERROR(VLOOKUP($I101,'07_Settings'!$A$10:$F$14,6,FALSE()),0.25) -> 0.25 | BB101: 1 | BC101: 1 | BD101: 1 | BE101: =IFERROR(ROUND($S101*BA101*BC101*BD101*BB101,0),0) -> 0 | BF101: =IF(COUNT(AO101:AU101)>0,"estimated","pending") -> estimated
...

Sheet 02_Creator_Rate_Card
B2: CREATOR RATE CARD
B3: Top-tier content creators · Scoring: Reach 40% · Engagement 30% · Audience Quality 20% · Authority 10%
B4: # | C4: Creator | D4: Score | E4: Tier | F4: X Post / Quote | G4: X Repost | H4: IG Post | I4: IG Story | J4: IG Reels | K4: YT Full Video | L4: YT 1–2min Pre-roll | M4: YT Shorts | N4: Snapchat | O4: TikTok Our-side | P4: TikTok Client Vids | Q4: Event + Snap | R4: Twitch / Kick Live | S4: Kick IRL | T4: Telegram | U4: Notes | V4: Link
B5: =IF($C5="","",COUNTA($C$5:C5)) -> 1 | C5: BanderitaX | D5: 98 | E5: Tier S | F5: 56250 | G5: 22500 | H5: 28125 | I5: 16875 | J5: 28125 | K5: 67500 | L5: 50625 | M5: 39375 | N5: 31500 | O5: 14063 | P5: 28125 | Q5: 11250 | R5: 39375
B6: =IF($C6="","",COUNTA($C$5:C6)) -> 2 | C6: oPiiLz | D6: 72 | E6: Tier 1 | F6: 22500 | G6: 9000 | H6: 11250 | I6: 6750 | J6: 11250 | K6: 27000 | L6: 20250 | M6: 15750 | N6: 12600 | O6: 5625 | P6: 11250 | Q6: 4500 | R6: 15750
B7: =IF($C7="","",COUNTA($C$5:C7)) -> 3 | C7: Msdossary7 | D7: 72 | E7: Tier 1 | F7: 22500 | G7: 9000 | H7: 11250 | I7: 6750 | J7: 11250 | K7: 27000 | L7: 20250 | M7: 15750 | N7: 12600 | O7: 5625 | P7: 11250 | Q7: 4500 | R7: 15750
B8: =IF($C8="","",COUNTA($C$5:C8)) -> 4 | C8: Aziz | D8: 68 | E8: Tier 1 | F8: 18000 | G8: 7200 | H8: 9000 | I8: 5400 | J8: 9000 | K8: 21600 | L8: 16200 | M8: 12600 | N8: 10080 | O8: 4500 | P8: 9000 | Q8: 3600 | R8: 12600
B9: =IF($C9="","",COUNTA($C$5:C9)) -> 5 | C9: Bo3omar22 | D9: 68 | E9: Tier 1 | F9: 18000 | G9: 7200 | H9: 9000 | I9: 5400 | J9: 9000 | K9: 21600 | L9: 16200 | M9: 12600 | N9: 10080 | O9: 4500 | P9: 9000 | Q9: 3600 | R9: 12600
B10: =IF($C10="","",COUNTA($C$5:C10)) -> 6 | C10: Abu abeer | D10: 60 | E10: Tier 2 | F10: 11250 | G10: 4500 | H10: 5625 | I10: 3375 | J10: 5625 | K10: 13500 | L10: 10125 | M10: 7875 | N10: 6300 | O10: 2813 | P10: 5625 | Q10: 2250 | R10: 7875
B11: =IF($C11="","",COUNTA($C$5:C11)) -> 7 | C11: LLE | D11: 58 | E11: Tier 2 | F11: 10125 | G11: 4050 | H11: 5063 | I11: 3038 | J11: 5063 | K11: 12150 | L11: 9113 | M11: 7088 | N11: 5670 | O11: 2531 | P11: 5063 | Q11: 2025 | R11: 7088
B12: =IF($C12="","",COUNTA($C$5:C12)) -> 8 | C12: Oden | D12: 55 | E12: Tier 2 | F12: 9000 | G12: 3600 | H12: 4500 | I12: 2700 | J12: 4500 | K12: 10800 | L12: 8100 | M12: 6300 | N12: 5040 | O12: 2250 | P12: 4500 | Q12: 1800 | R12: 6300
B13: =IF($C13="","",COUNTA($C$5:C13)) -> 9 | C13: xSMA333 | D13: 52 | E13: Tier 2 | F13: 7875 | G13: 3150 | H13: 3938 | I13: 2363 | J13: 3938 | K13: 9450 | L13: 7088 | M13: 5513 | N13: 4410 | O13: 1969 | P13: 3938 | Q13: 1575 | R13: 5513
B14: =IF($C14="","",COUNTA($C$5:C14)) -> 10 | C14: 3ADEL | D14: 50 | E14: Tier 2 | F14: 6750 | G14: 2700 | H14: 3375 | I14: 2025 | J14: 3375 | K14: 8100 | L14: 6075 | M14: 4725 | N14: 3780 | O14: 1688 | P14: 3375 | Q14: 1350 | R14: 4725
B15: =IF($C15="","",COUNTA($C$5:C15)) -> 11 | C15: RAED | D15: 48 | E15: Tier 2 | F15: 6188 | G15: 2475 | H15: 3094 | I15: 1856 | J15: 3094 | K15: 7425 | L15: 5569 | M15: 4331 | N15: 3465 | O15: 1547 | P15: 3094 | Q15: 1238 | R15: 4331
B16: =IF($C16="","",COUNTA($C$5:C16)) -> 12 | C16: Falcons | D16: 45 | E16: Tier 2 | F16: 5625 | G16: 2250 | H16: 2813 | I16: 1688 | J16: 2813 | K16: 6750 | L16: 5063 | M16: 3938 | N16: 3150 | O16: 1406 | P16: 2813 | Q16: 1125 | R16: 3938
... B21: =IF($C21="","",COUNTA($C$5:C21)) -> 17 | C21: 9leeh | D21: 32 | E21: Tier 3 | F21: 2250 | G21: 900 | H21: 1125 | I21: 675 | J21: 1125 | K21: 2700 | L21: 2025 | M21: 1575 | N21: 1260 | O21: 563 | P21: 1125 | Q21: 450 | R21: 1575
B22: =IF($C22="","",COUNTA($C$5:C22))
B23: =IF($C23="","",COUNTA($C$5:C23))
B24: =IF($C24="","",COUNTA($C$5:C24))
B25: =IF($C25="","",COUNTA($C$5:C25))
B26: =IF($C26="","",COUNTA($C$5:C26))
B27: =IF($C27="","",COUNTA($C$5:C27))
B28: =IF($C28="","",COUNTA($C$5:C28))
B29: =IF($C29="","",COUNTA($C$5:C29))
B30: =IF($C30="","",COUNTA($C$5:C30))
B31: =IF($C31="","",COUNTA($C$5:C31))
B32: =IF($C32="","",COUNTA($C$5:C32))
B33: =IF($C33="","",COUNTA($C$5:C33))
... B36: =IF($C36="","",COUNTA($C$5:C36))

Sheet 02_Adjustment_Matrix
B2: DYNAMIC PRICING ADJUSTMENT MATRIX
B3: Select a player → choose an asset → adjust multipliers → get the final price
B5: 🔍 Search Player | D5: moaz | F5: =IFERROR(__xludf.dummyfunction("IF(TRIM(D5)="""","""",IFERROR(INDEX(FILTER('01_Player_Rate_Card'!C$5:C1016,REGEXMATCH(LOWER('01_Player_Rate_Card'!C$5:C1016),LOWER(TRIM(D5)))) ,1),""No match — check spelling""))"),"Moaz") -> Moaz | H5: Type a full or partial name in D5 → best matching player appears in F5 → selection syncs automatically below
B7: ① PLAYER SELECTOR
B8: Select Player | C8: Game | D8: Team | E8: Role | F8: Tier | G8: Nationality | H8: Platforms
B9: =IF(OR($F$5="",$F$5="No match — check spelling"),"",$F$5) -> Moaz | C9: =IFERROR(VLOOKUP(B9,'01_Player_Rate_Card'!$C$5:$AL$500,3,0),"") -> Esports Influencers | D9: =IFERROR(VLOOKUP(B9,'01_Player_Rate_Card'!$C$5:$AL$500,4,0),"") -> Esports Influencers | E9: =IFERROR(VLOOKUP(B9,'01_Player_Rate_Card'!$C$5:$AL$500,2,0),"") -> Influencer | F9: =IFERROR(VLOOKUP(B9,'01_Player_Rate_Card'!$C$5:$AL$500,7,0),"") -> Tier 2 | G9: =IFERROR(VLOOKUP(B9,'01_Player_Rate_Card'!$C$5:$AL$500,5,0),"") -> Saudi Arabia | H9: =IFERROR(VLOOKUP(B9,'01_Player_Rate_Card'!$C$5:$AL$500,6,0),"") -> 5
B10: ② PLAYER RATE CARD (all values in SAR)
B11: IG Reel | C11: IG Static | D11: IG Story | E11: TikTok Video | F11: YT Short | G11: X Post | H11: FB Post/Video | I11: Twitch 2h | J11: Twitch Integ. | K11: IRL / Appear. | L11: Rights Fee | M11: Exclusivity | N11: Rush Fee | O11: WL Fee | P11: Repost
B12: =IFERROR(VLOOKUP(B9,'01_Player_Rate_Card'!$C$5:$AL$500,8,0),"N/A") -> 6500 | C12: =IFERROR(VLOOKUP(B9,'01_Player_Rate_Card'!$C$5:$AL$500,9,0),"N/A") -> 5300 | D12: =IFERROR(VLOOKUP(B9,'01_Player_Rate_Card'!$C$5:$AL$500,10,0),"N/A") -> 1105 | E12: =IFERROR(VLOOKUP(B9,'01_Player_Rate_Card'!$C$5:$AL$500,11,0),"N/A") -> 3400 | F12: =IFERROR(VLOOKUP(B9,'01_Player_Rate_Card'!$C$5:$AL$500,12,0),"N/A") -> 4050 | G12: =IFERROR(VLOOKUP(B9,'01_Player_Rate_Card'!$C$5:$AL$500,13,0),"N/A") -> 2500 | H12: =IFERROR(VLOOKUP(B9,'01_Player_Rate_Card'!$C$5:$AL$500,14,0),"N/A") -> 2500 | I12: =IFERROR(VLOOKUP(B9,'01_Player_Rate_Card'!$C$5:$AL$500,15,0),"N/A") -> 15950 | J12: =IFERROR(VLOOKUP(B9,'01_Player_Rate_Card'!$C$5:$AL$500,16,0),"N/A") -> 8200 | K12: =IFERROR(VLOOKUP(B9,'01_Player_Rate_Card'!$C$5:$AL$500,17,0),"N/A") -> 14300 | L12: =IFERROR(VLOOKUP(B9,'01_Player_Rate_Card'!$C$5:$AL$500,18,0),"N/A") -> 3800 | M12: =IFERROR(VLOOKUP(B9,'01_Player_Rate_Card'!$C$5:$AL$500,19,0),"N/A") -> 1900 | N12: =IFERROR(VLOOKUP(B9,'01_Player_Rate_Card'!$C$5:$AL$500,20,0),"N/A") -> 3150 | O12: =IFERROR(VLOOKUP(B9,'01_Player_Rate_Card'!$C$5:$AL$500,21,0),"N/A") -> 1250 | P12: =IFERROR(ROUND(IFERROR(VLOOKUP(B9,'01_Player_Rate_Card'!$C$5:$AL$500,8,0),0)*0.15,0),"N/A") -> 975
B14: ③ ASSET SELECTOR — Choose the deliverable type
B15: Asset Type | D15: Base Fee (SAR) | F15: Notes / Basis
B16: Podcast Guesting | D16: {=IFERROR(xlookup(B16,$B$17:$B$34,$D$17:$D$34,0),0)} -> 0
B17: IG Reel | D17: =IFERROR(VLOOKUP($B$9,'01_Player_Rate_Card'!$C$5:$AL$500,8,FALSE()),0) -> 6500 | F17: Player IG Reel rate from Rate Card
B18: IG Static Post | D18: =IFERROR(VLOOKUP($B$9,'01_Player_Rate_Card'!$C$5:$AL$500,9,FALSE()),0) -> 5300 | F18: Player IG Static rate
B19: IG Story | D19: =IFERROR(VLOOKUP($B$9,'01_Player_Rate_Card'!$C$5:$AL$500,10,FALSE()),0) -> 1105 | F19: Player IG Story rate
B20: TikTok Video | D20: =IFERROR(VLOOKUP($B$9,'01_Player_Rate_Card'!$C$5:$AL$500,11,FALSE()),0) -> 3400 | F20: Player TikTok rate
B21: YT Short | D21: =IFERROR(VLOOKUP($B$9,'01_Player_Rate_Card'!$C$5:$AL$500,12,FALSE()),0) -> 4050 | F21: Player YT Short rate
B22: X Post | D22: =IFERROR(VLOOKUP($B$9,'01_Player_Rate_Card'!$C$5:$AL$500,13,FALSE()),0) -> 2500 | F22: Player X Post rate
B23: FB Post / Video | D23: =IFERROR(VLOOKUP($B$9,'01_Player_Rate_Card'!$C$5:$AL$500,14,FALSE()),0) -> 2500 | F23: Player FB rate
B24: Content Repost | D24: =IFERROR(VLOOKUP($B$9,'01_Player_Rate_Card'!$C$5:$AL$500,8,FALSE())*0.15,0) -> 975 | F24: 15% of IG Reel rate
B25: — LIVE & STREAM —
B26: Twitch Stream 2h | D26: =IFERROR(VLOOKUP($B$9,'01_Player_Rate_Card'!$C$5:$AL$500,15,FALSE()),0) -> 15950 | F26: Player Twitch 2h rate
B27: Twitch Integration | D27: =IFERROR(VLOOKUP($B$9,'01_Player_Rate_Card'!$C$5:$AL$500,16,FALSE()),0) -> 8200 | F27: Player Twitch Integ. rate
B28: — ON-GROUND & EVENTS —
B29: IRL Appearance | D29: =IFERROR(VLOOKUP($B$9,'01_Player_Rate_Card'!$C$5:$AL$500,17,FALSE()),0) -> 14300 | F29: Player IRL rate
B30: Podcast Guesting | D30: =IFERROR(VLOOKUP($B$9,'01_Player_Rate_Card'!$C$5:$AL$500,17,FALSE())*0.5,0) -> 7150 | F30: 50% of IRL — 1-2h time commitment
B31: PR Appearance / CSR | D31: =IFERROR(VLOOKUP($B$9,'01_Player_Rate_Card'!$C$5:$AL$500,17,FALSE()),0) -> 14300 | F31: Full IRL rate — brand presence + media
B32: Fan Meet & Greet | D32: =IFERROR(VLOOKUP($B$9,'01_Player_Rate_Card'!$C$5:$AL$500,17,FALSE())*0.7,0) -> 10010 | F32: 70% of IRL — structured 2-4h fan interaction
B33: — OTHER —
B34: Photo Shoot (Brand) | D34: =IFERROR(VLOOKUP($B$9,'01_Player_Rate_Card'!$C$5:$AL$500,17,FALSE())*0.75,0) -> 10725 | F34: 75% of IRL — half-day shoot, brand usage rights incl. | H34: Weight | I34: Description
B35: < 2% | D35: 0.70x | E35: Below average — audience not engaged | F35: Awareness | H35: 0.2 | I35: Brand visibility — social reach matters most
B36: 2% – 4% | D36: 0.90x | E36: Average — slight discount from baseline | F36: Conversion | H36: 0.4 | I36: Direct response — engagement + credibility
B37: 4% – 6% | D37: 1.00x | E37: Baseline — standard market rate | F37: Trust (Pro Authority) | H37: 0.7 | I37: Credibility campaigns — pro status is the product
B38: 6% – 8% | D38: 1.20x | E38: Good — 20% premium
B39: 8% – 10% | D39: 1.40x | E39: Excellent — strong audience connection | F39: AUTHORITY MULTIPLIER PRESETS | H39: Value | I39: Profile
B40: > 10% | D40: 1.60x | E40: Premium micro-influencer effect | F40: Normal | H40: 1 | I40: Content creator / standard player
F41: Proven / Established | H41: 1.15 | I41: Regional champion, 2+ years pro
B42: AUDIENCE QUALITY | D42: Multiplier | E42: Notes | F42: Elite Contender | H42: 1.3 | I42: Top-10 world ranking, major finalist
B43: Generic / Broad | D43: 0.85x | E43: Mixed interests, low targeting | F43: Global Star / Major Winner | H43: 1.5 | I43: World champion, iconic pro name
B44: Gaming-adjacent | D44: 1.00x | E44: Baseline — general gaming
B45: Core Gaming | D45: 1.20x | E45: Dedicated gamers, high purchase intent | F45: LANGUAGE MULTIPLIER | H45: Value | I45: Context
B46: Esports-focused | D46: 1.40x | E46: Competitive gaming — premium targeting | F46: English | H46: 1 | I46: Global / English-language content
B47: MENA / Saudi focus | D47: 1.30x | E47: Regional premium — cultural relevance | F47: Arabic | H47: 1.05 | I47: MENA-specific Arabic content (+5% regional premium)
B48: Global Esports Elite | D48: 1.50x | E48: Maximum premium — top-tier audience | F48: Bilingual | H48: 1.15 | I48: Dual-language content — maximum MENA reach
B50: SEASONALITY & TIMING | D50: Multiplier | E50: Context | F50: AUTHORITY FLOOR (FloorShare) | H50: Range | I50: Use When
B51: Off-season | D51: 0.80x | E51: Low viewership period | F51: Not used | H51: 0 | I51: Standard content campaigns
B52: Regular season | D52: 1.00x | E52: Baseline — standard competition | F52: Partial floor | H52: 0.30–0.50 | I52: Hardware / peripherals ("pro choice" campaigns)
B53: Regional Major | D53: 1.25x | E53: Regional championship | F53: Strong floor | H53: 0.60–0.80 | I53: Credibility campaigns, tournament windows
B54: Global Major / Worlds | D54: 1.40x | E54: Peak esports interest
B55: Game launch | D55: 1.30x | E55: New title release | F55: AuthorityFactor formula: | H55: AuthorityFactor = 1 + ObjWeight x (AuthMult - 1)
B56: Holiday season (Q4) | D56: 1.20x | E56: Year-end peak
B57: Ramadan (MENA) | D57: 1.35x | E57: Peak MENA consumption — highest regional multiplier
B58: Ewc/Mega Peak | D58: 1.50x | E58: esports world cup highest multiplier
B59: ⑥ LIVE PRICE CALCULATOR — Authority Patch v1 — Enter values in blue cells
B60: Input | D60: Value | E60: [parsed]
B61: Base Fee (SAR) | D61: =IF(ISNUMBER(D16),D16,0) -> 0 | E61: Auto-pulled from player + asset selection above
B62: Engagement Multiplier | D62: 0.70 — Below average (< 2%) | E62: =IFERROR(IF(ISNUMBER(D62),D62,VALUE(TRIM(LEFT(TRIM(D62),FIND(" ",TRIM(D62)&" ")-1)))),1) -> 0.7
B63: Audience Quality Multiplier | D63: 0.85 — Generic / Broad | E63: =IFERROR(IF(ISNUMBER(D63),D63,VALUE(TRIM(LEFT(TRIM(D63),FIND(" ",TRIM(D63)&" ")-1)))),1) -> 0.85
B64: Seasonality Multiplier | D64: 0.80 — Off-season | E64: =IFERROR(IF(ISNUMBER(D64),D64,VALUE(TRIM(LEFT(TRIM(D64),FIND(" ",TRIM(D64)&" ")-1)))),1) -> 0.8
B65: Content Type Multiplier | D65: 1.00 — Integrated (Player-led) | E65: =IFERROR(IF(ISNUMBER(D65),D65,VALUE(TRIM(LEFT(TRIM(D65),FIND(" ",TRIM(D65)&" ")-1)))),1) -> 1
B66: Add-on Uplift (total %) | D66: 0 | E66: Sum of selected add-ons from 03_Add_On_Rights
B67: Campaign Objective | D67: Conversion | E67: Drives ObjectiveWeight — see Authority table →
B68: Authority Multiplier | D68: 1.10 — Proven / Established | E68: =IFERROR(IF(ISNUMBER(D68),D68,VALUE(TRIM(LEFT(TRIM(D68),FIND(" ",TRIM(D68)&" ")-1)))),1) -> 1.1
B69: Language Multiplier | D69: 1.00 — English | E69: =IFERROR(IF(ISNUMBER(D69),D69,VALUE(TRIM(LEFT(TRIM(D69),FIND(" ",TRIM(D69)&" ")-1)))),1) -> 1
B70: Authority Floor Share | D70: 0.50 — Standard floor | E70: =IFERROR(IF(ISNUMBER(D70),D70,VALUE(TRIM(LEFT(TRIM(D70),FIND(" ",TRIM(D70)&" ")-1)))),0) -> 0.5
B71: IRL Appearance Fee (SAR) | D71: =IFERROR(VLOOKUP($B$9,'01_Player_Rate_Card'!$C$5:$AL$500,17,FALSE()),0) -> 14300 | E71: Auto-pulled from selected player's IRL / Appear. column
B73: AuthorityFactor | D73: =IFERROR(1+IF(TRIM(D67)="Awareness",0.3,IF(TRIM(D67)="Conversion",0.6,IF(TRIM(D67)="Trust (Pro Authority)",0.9,0.6)))*(IFERROR(IF(ISNUMBER(D68),D68,VALUE(TRIM(LEFT(TRIM(D68),FIND(" ",TRIM(D68)&" ")-1)))),1)-1),1) -> 1.06 | E73: Objective-weighted authority premium
B74: SocialPrice (pre-floor, pre-add-on) | D74: =IFERROR(D61*IFERROR(IF(ISNUMBER(D62),D62,VALUE(TRIM(LEFT(TRIM(D62),FIND(" ",TRIM(D62)&" ")-1)))),1)*IFERROR(IF(ISNUMBER(D63),D63,VALUE(TRIM(LEFT(TRIM(D63),FIND(" ",TRIM(D63)&" ")-1)))),1)*IFERROR(IF(ISNUMBER(D64),D64,VALUE(TRIM(LEFT(TRIM(D64),FIND(" ",TRIM(D64)&" ")-1)))),1)*E65*IFERROR(IF(ISNUMBER(D69),D69,VALUE(TRIM(LEFT(TRIM(D69),FIND(" ",TRIM(D69)&" ")-1)))),1)*D73,0) -> 0 | E74: BaseFee x Eng x Aud x Season x ContentType x Language x AuthorityFactor
B75: AuthorityFloor | D75: =IFERROR(D71*IFERROR(IF(ISNUMBER(D70),D70,VALUE(TRIM(LEFT(TRIM(D70),FIND(" ",TRIM(D70)&" ")-1)))),0)*IFERROR(IF(ISNUMBER(D64),D64,VALUE(TRIM(LEFT(TRIM(D64),FIND(" ",TRIM(D64)&" ")-1)))),1)*IFERROR(IF(ISNUMBER(D69),D69,VALUE(TRIM(LEFT(TRIM(D69),FIND(" ",TRIM(D69)&" ")-1)))),1)*D73,0) -> 6063.2 | E75: IRL Fee x FloorShare x Seasonality x Language x AuthorityFactor
B76: PreAddOnPrice = MAX(Social, Floor) | D76: =IFERROR(MAX(D74,D75),0) -> 6063.2 | E76: Higher of SocialPrice or AuthorityFloor — floor protects pro pricing
B78: FINAL ADJUSTED PRICE (SAR) | D78: =IFERROR(ROUND(D76*(1+IF(ISNUMBER(D66),D66,IFERROR(VALUE(TRIM(SUBSTITUTE(TEXT(D66,"0.00%"),"%","")))/100,0))),0),0) -> 6063 | E78: =IFERROR("~= USD","~= USD") -> ~= USD | F78: =IFERROR("$"&TEXT(ROUND(D78/3.75,0),"#,##0"),"—") -> $1,617
B80: Falcons Commission % | D80: =IFERROR(VLOOKUP($B$9,'01_Player_Rate_Card'!$C$5:$AL$500,23,FALSE()),0) -> 0.3 | E80: Auto-pulled from player's Commission % · edit to override
B81: Markup % (on Player Cost) | D81: =IFERROR(VLOOKUP($B$9,'01_Player_Rate_Card'!$C$5:$AL$500,24,FALSE()),0) -> 1 | E81: Auto-pulled from player's Markup % · edit to override
B83: Player Cost (SAR) | D83: =IFERROR(IF(ISNUMBER(D81),D78/(1+D81),D78/1.75),0) -> 3031.5 | E83: What Falcons pays the player
B84: Falcons Revenue (SAR) | D84: =IFERROR(D78-D83,0) -> 3031.5 | E84: Falcons earnings on this deal
B85: Client Price incl. VAT (SAR) | D85: =IFERROR(D78*1.15,0) -> 6972.45 | E85: Final invoice to client (15% VAT)
B86: Client Price incl. VAT (USD) | D86: =IFERROR(D85/3.75,0) -> 1859.32 | E86: ~= USD equivalent
C87: 1
B90: ⑦ PLAYER PRICE PREVIEW — all assets for selected player at default multipliers (engagement/audience/seasonality = 1.00x)
B91: Asset | C91: Rate Card Base Fee (SAR) | D91: Social Price (default mult) | E91: Authority Floor (IRL × Floor%) | F91: Final = MAX (Social, Floor) | G91: Final ~USD | H91: Confidence Gate | I91: Notes
B92: IG Reel | C92: =IFERROR(VLOOKUP($B$9,'01_Player_Rate_Card'!$C$5:$BG$250,8,FALSE()),0) -> 6500 | D92: =C92 -> 6500 | E92: =IFERROR(VLOOKUP($B$9,'01_Player_Rate_Card'!$C$5:$BG$250,17,FALSE())*VLOOKUP($B$9,'01_Player_Rate_Card'!$C$5:$BG$250,53,FALSE()),0) -> 14300 | F92: =MAX(D92,E92) -> 14300 | G92: =IFERROR(ROUND(F92/3.75,0),0) -> 3813 | H92: =IFERROR(VLOOKUP($B$9,'01_Player_Rate_Card'!$C$5:$BG$250,58,FALSE()),"pending") -> pending | I92: Baseline for social benchmarking
B93: IG Static | C93: =IFERROR(VLOOKUP($B$9,'01_Player_Rate_Card'!$C$5:$BG$250,9,FALSE()),0) -> 5300 | D93: =C93 -> 5300 | E93: =IFERROR(VLOOKUP($B$9,'01_Player_Rate_Card'!$C$5:$BG$250,17,FALSE())*VLOOKUP($B$9,'01_Player_Rate_Card'!$C$5:$BG$250,53,FALSE()),0) -> 14300 | F93: =MAX(D93,E93) -> 14300 | G93: =IFERROR(ROUND(F93/3.75,0),0) -> 3813 | H93: =IFERROR(VLOOKUP($B$9,'01_Player_Rate_Card'!$C$5:$BG$250,58,FALSE()),"pending") -> pending
B94: IG Story | C94: =IFERROR(VLOOKUP($B$9,'01_Player_Rate_Card'!$C$5:$BG$250,10,FALSE()),0) -> 1105 | D94: =C94 -> 1105 | E94: =IFERROR(VLOOKUP($B$9,'01_Player_Rate_Card'!$C$5:$BG$250,17,FALSE())*VLOOKUP($B$9,'01_Player_Rate_Card'!$C$5:$BG$250,53,FALSE()),0) -> 14300 | F94: =MAX(D94,E94) -> 14300 | G94: =IFERROR(ROUND(F94/3.75,0),0) -> 3813 | H94: =IFERROR(VLOOKUP($B$9,'01_Player_Rate_Card'!$C$5:$BG$250,58,FALSE()),"pending") -> pending
B95: TikTok Video | C95: =IFERROR(VLOOKUP($B$9,'01_Player_Rate_Card'!$C$5:$BG$250,11,FALSE()),0) -> 3400 | D95: =C95 -> 3400 | E95: =IFERROR(VLOOKUP($B$9,'01_Player_Rate_Card'!$C$5:$BG$250,17,FALSE())*VLOOKUP($B$9,'01_Player_Rate_Card'!$C$5:$BG$250,53,FALSE()),0) -> 14300 | F95: =MAX(D95,E95) -> 14300 | G95: =IFERROR(ROUND(F95/3.75,0),0) -> 3813 | H95: =IFERROR(VLOOKUP($B$9,'01_Player_Rate_Card'!$C$5:$BG$250,58,FALSE()),"pending") -> pending
B96: YT Short | C96: =IFERROR(VLOOKUP($B$9,'01_Player_Rate_Card'!$C$5:$BG$250,12,FALSE()),0) -> 4050 | D96: =C96 -> 4050 | E96: =IFERROR(VLOOKUP($B$9,'01_Player_Rate_Card'!$C$5:$BG$250,17,FALSE())*VLOOKUP($B$9,'01_Player_Rate_Card'!$C$5:$BG$250,53,FALSE()),0) -> 14300 | F96: =MAX(D96,E96) -> 14300 | G96: =IFERROR(ROUND(F96/3.75,0),0) -> 3813 | H96: =IFERROR(VLOOKUP($B$9,'01_Player_Rate_Card'!$C$5:$BG$250,58,FALSE()),"pending") -> pending
B97: X Post | C97: =IFERROR(VLOOKUP($B$9,'01_Player_Rate_Card'!$C$5:$BG$250,13,FALSE()),0) -> 2500 | D97: =C97 -> 2500 | E97: =IFERROR(VLOOKUP($B$9,'01_Player_Rate_Card'!$C$5:$BG$250,17,FALSE())*VLOOKUP($B$9,'01_Player_Rate_Card'!$C$5:$BG$250,53,FALSE()),0) -> 14300 | F97: =MAX(D97,E97) -> 14300 | G97: =IFERROR(ROUND(F97/3.75,0),0) -> 3813 | H97: =IFERROR(VLOOKUP($B$9,'01_Player_Rate_Card'!$C$5:$BG$250,58,FALSE()),"pending") -> pending
B98: FB Post/Video | C98: =IFERROR(VLOOKUP($B$9,'01_Player_Rate_Card'!$C$5:$BG$250,14,FALSE()),0) -> 2500 | D98: =C98 -> 2500 | E98: =IFERROR(VLOOKUP($B$9,'01_Player_Rate_Card'!$C$5:$BG$250,17,FALSE())*VLOOKUP($B$9,'01_Player_Rate_Card'!$C$5:$BG$250,53,FALSE()),0) -> 14300 | F98: =MAX(D98,E98) -> 14300 | G98: =IFERROR(ROUND(F98/3.75,0),0) -> 3813 | H98: =IFERROR(VLOOKUP($B$9,'01_Player_Rate_Card'!$C$5:$BG$250,58,FALSE()),"pending") -> pending
B99: Twitch Stream 2h | C99: =IFERROR(VLOOKUP($B$9,'01_Player_Rate_Card'!$C$5:$BG$250,15,FALSE()),0) -> 15950 | D99: =C99 -> 15950 | E99: =IFERROR(VLOOKUP($B$9,'01_Player_Rate_Card'!$C$5:$BG$250,17,FALSE())*VLOOKUP($B$9,'01_Player_Rate_Card'!$C$5:$BG$250,53,FALSE()),0) -> 14300 | F99: =MAX(D99,E99) -> 15950 | G99: =IFERROR(ROUND(F99/3.75,0),0) -> 4253 | H99: =IFERROR(VLOOKUP($B$9,'01_Player_Rate_Card'!$C$5:$BG$250,58,FALSE()),"pending") -> pending
B100: Twitch Integration | C100: =IFERROR(VLOOKUP($B$9,'01_Player_Rate_Card'!$C$5:$BG$250,16,FALSE()),0) -> 8200 | D100: =C100 -> 8200 | E100: =IFERROR(VLOOKUP($B$9,'01_Player_Rate_Card'!$C$5:$BG$250,17,FALSE())*VLOOKUP($B$9,'01_Player_Rate_Card'!$C$5:$BG$250,53,FALSE()),0) -> 14300 | F100: =MAX(D100,E100) -> 14300 | G100: =IFERROR(ROUND(F100/3.75,0),0) -> 3813 | H100: =IFERROR(VLOOKUP($B$9,'01_Player_Rate_Card'!$C$5:$BG$250,58,FALSE()),"pending") -> pending | I100: Check min 500 concurrent viewers
B101: IRL / Appearance | C101: =IFERROR(VLOOKUP($B$9,'01_Player_Rate_Card'!$C$5:$BG$250,17,FALSE()),0) -> 14300 | D101: =C101 -> 14300 | E101: =IFERROR(VLOOKUP($B$9,'01_Player_Rate_Card'!$C$5:$BG$250,17,FALSE())*VLOOKUP($B$9,'01_Player_Rate_Card'!$C$5:$BG$250,53,FALSE()),0) -> 14300 | F101: =MAX(D101,E101) -> 14300 | G101: =IFERROR(ROUND(F101/3.75,0),0) -> 3813 | H101: =IFERROR(VLOOKUP($B$9,'01_Player_Rate_Card'!$C$5:$BG$250,58,FALSE()),"pending") -> pending | I101: Drives Authority Floor for all assets
B103: TOTAL (all organic assets) | C103: =SUM(C92:C100) -> 49505 | D103: =SUM(D92:D100) -> 49505 | E103: n/a | F103: =SUM(F92:F100) -> 130350 | G103: =ROUND(F103/3.75,0) -> 34760
B105: HOW TO USE THIS PANEL:
B106: 1. Type player name in D5 above. Rates auto-populate here.
B107: 2. Green = Final price per asset (MAX of Social vs Authority Floor).
B108: 3. If Confidence = "pending" or "estimated", avoid premium multipliers (>1.2x) — see Settings tab.
B109: 4. Use this to validate the quote before entering multipliers in Section ⑥.
B111: 📌 HOW TO USE
B112: ⚡ KEY PRINCIPLES
B113: 1. Never negotiate below the Base Fee
B114: 2. Engagement beats follower count
...

Sheet 04_Tier_Progression
B2: TIER PROGRESSION LADDER
B3: Promotion & demotion criteria · Industry-reasonable defaults — calibrate quarterly once Shikenso data lands
B5: Tier | C5: Label | D5: Follower Threshold | E5: Avg Engagement Rate | F5: Audience Quality Score | G5: Authority Signal | H5: Base Fee Range (SAR) | I5: Promotion Trigger
B6: Tier S | C6: Superstar | D6: >1M on any platform | E6: ≥7% | F6: ≥85 (verified) | G6: Global anchor · Mainstream cross-over | H6: 40,000 – 50,000 | I6: Brand partnership waitlist; negotiate upward
B7: Tier 1 | C7: Star | D7: 250K – 1M | E7: 5% – 7% | F7: 70 – 85 | G7: Regional top 10 in their game/vertical | H7: 22,000 – 30,000 | I7: Sustained ≥1M reach for 2 consecutive quarters
B8: Tier 2 | C8: Core Influencer | D8: 50K – 250K | E8: 4% – 6% | F8: 55 – 70 | G8: Active pro or mid-tier creator | H8: 11,000 – 18,000 | I8: Hit 250K+ followers AND 5%+ ER for 2 quarters
B9: Tier 3 | C9: Rising | D9: 10K – 50K | E9: 3% – 5% | F9: 45 – 55 | G9: Emerging talent · Niche specialist | H9: 6,500 – 10,000 | I9: Cross 50K followers OR secure major tournament
B10: Tier 4 | C10: Entry / Staff | D10: <10K or staff | E10: <3% | F10: <45 | G10: Support roles · Developing roster | H10: 3,000 – 5,500 | I10: Cross 10K followers + 3% ER for 2 quarters
B13: DEMOTION & REVIEW TRIGGERS
B14: • Two consecutive quarters below the tier's follower threshold → demote one level
B15: • Engagement rate drops below the tier minimum for 3 months → flag for pricing review
B16: • Authority signal decay (lost major sponsor, dropped from top-tier roster) → manual committee review
B17: • Extended inactivity (>90 days no content) → freeze tier pending return

Sheet 08_Creator_Axes
B2: CREATOR-SPECIFIC PRICING AXES
B3: Axis overrides that apply to creators (not players). See Methodology §4 for full rationale.
B5: # | C5: Axis | D5: Player Default | E5: Creator Override | F5: Multiplier / Rule | G5: Rationale
B6: 1 | C6: ① IRL Floor | D6: Authority Floor = IRL × FloorShare × Seasonality × Language × AuthorityFactor | E6: N/A — creators do not carry IRL fees | F6: 0 (skip) | G6: Creators monetise content, not appearances. Apply social-only pricing.
B7: 2 | C7: ② Platform-Mix Premium | D7: Single-platform baseline | E7: Multi-platform bundle discount OR premium | F7: +10% for 3-platform simulcast · -5% for single-platform repurpose | G7: Creators deliver across their stack. Reward bundling, discount scraps.
B8: 3 | C8: ③ Burst-Demand Seasonality | D8: Regular (1.0×) · Playoffs (1.2×) · Finals (1.35×) | E8: Viral-window override | F8: Up to 1.5× during trending audio/format windows (≤72h expiry) | G8: Creator reach spikes on trend timing — price the spike, not the baseline.
B9: 4 | C9: ④ Player-Overlap De-Dupe | D9: N/A | E9: If creator also rostered as player → pick ONE card per quote | F9: Applied at Quote Builder level | G9: Prevents double-billing when an asset can be sourced either way.
B10: 5 | C10: ⑤ Script-Approval Factor | D10: Client script allowed (1.0×) | E10: Creator-led freedom is core deliverable | F10: 1.0× for creative freedom · 1.15× for heavy client script | G10: Restricting creator voice hurts performance; price the friction.
B11: 6 | C11: ⑥ Exclusivity Window | D11: 30-day exclusivity (1.1×) | E11: Category exclusivity over time | F11: +0.05× per category locked · +0.08× for 90-day exclusive | G11: Creators say no to competitors — compensate opportunity cost.

Sheet 03_Add_On_Rights
B2: ADD-ON RIGHTS PACKAGES
B3: Select applicable add-ons and sum the uplift percentages · Enter total in cell C35 of the Live Calculator (02_Adjustment_Matrix)
B5: RIGHTS PACKAGES — PRICE UPLIFT TABLE
B6: Add-on Type | C6: Uplift % | D6: Description
B7: Organic Repost — Min | C7: 0.15 | D7: Single repost, 1 month
B8: Organic Repost — Std | C8: 0.35 | D8: 3-5 reposts, 3 months
B9: Organic Repost — Max | C9: 0.6 | D9: Unlimited + takeover, 6 months
B10: Paid Usage — Min | C10: 0.25 | D10: Limited, SAR 25K cap
B11: Paid Usage — Std | C11: 0.5 | D11: Standard, SAR 75K cap
B12: Paid Usage — Max | C12: 1 | D12: Unlimited paid media
B13: Whitelisting — Std | C13: 0.4 | D13: 30 days, single platform
B14: Whitelisting — Extended | C14: 0.75 | D14: 90 days, multi-platform
B15: Whitelisting — Premium | C15: 1.2 | D15: 180 days, dark posts included
B16: Territory — MENA | C16: 0.2 | D16: MENA rights, 3 months
B17: Territory — Global | C17: 0.75 | D17: Worldwide, 6 months
B18: Exclusivity — Category | C18: 1.5 | D18: Exclusive category, 12 months
B19: Exclusivity — Full | C19: 2 | D19: Full exclusivity, 12 months
B22: BUNDLE PRESETS — READY TO PITCH
B23: Bundle Tier | C23: Included Add-ons | D23: Total Uplift
B24: Basic | C24: Organic Repost Min | D24: 15%
B25: Standard | C25: Organic Repost Std + Paid Usage Min | D25: 60%
B26: Premium | C26: Organic Repost Max + Paid Usage Std + MENA Territory | D26: 115%
B27: Full | C27: Organic Max + Paid Max + Whitelisting Std + MENA Territory | D27: 170%
B28: Exclusive | C28: All above + Category Exclusivity (12 months) | D28: 320%

Sheet 05_Guide_EN
A1: TEAM FALCONS PRICING ENGINE — USER GUIDE (v8)
A3: 1. WHAT THIS ENGINE DOES
A4: Generates commercial quotes for Falcons talent across social, streaming, and IRL activations. Uses a 5-tier classification with dual-floor logic (Social Price + Authority Floor) and a Confidence layer to prevent premium pricing on unverified data.
A6: 2. THE 5 TABS YOU USE MOST
A7: • 01_Player_Rate_Card — master roster (189 players), tier, rates, follower data, confidence • 02_Adjustment_Matrix — where you build quotes: player search + price preview + live calculator • 03_Add_On_Rights — rights bundles (Organic/Paid/Whitelisting/Exclusivity/Territory) • 07_Settings — tier defaults, floor shares, confidence definitions • QT-... — the client-facing quote output
A9: 3. HOW TO BUILD A QUOTE — STEP BY STEP
A10: Step 1: Open 02_Adjustment_Matrix. Step 2: Type player name in cell D5. The engine auto-matches the closest player. Step 3: Review Section ⑦ PLAYER PRICE PREVIEW — see all asset rates, Authority Floor, and Final Price at default multipliers. This is your sanity check BEFORE entering multipliers. Step 4: Check Confidence tag. If "pending" or "estimated", stay within the allowed multiplier range (see Settings). Step 5: In Section ⑥ LIVE PRICE CALCULATOR, pick your asset, enter engagement/audience/seasonality/authority/language values. Step 6: Add Rights package from 03_Add_On_Rights (as % uplift). Step 7: Confirm FINAL ADJUSTED PRICE. Transfer to QT quote template. Step 8: Legal + Finance approval → send to client.
A12: 4. WHEN AUTHORITY FLOOR OVERRIDES SOCIAL PRICE
A13: If a pro player has modest social (e.g., 30K IG) but high IRL fee (e.g., 25,000 SAR), their Authority Floor = 25,000 × 0.55 = 13,750 SAR. If their Social Price for IG Reel comes out to only 8,000 SAR (low followers × CPM), the engine uses the 13,750 floor. This protects pro player earnings on pure-social briefs.
A15: 5. CONFIDENCE GOVERNANCE RULES
A16: • exact / rounded → all multipliers available (up to the table max) • estimated → engagement capped at 1.2x, authority capped at 1.3x • pending → all multipliers locked at 1.0x until follower data is verified Commercial lead can override, but override must be logged in the quote notes.
A18: 6. WHAT'S NEXT
A19: v9 (Q3 2026): Shikenso integration will auto-fill follower data and upgrade confidence tags across the roster. v10 (Q4 2026): Engagement multipliers will be scored from 30d/90d data instead of manual dropdowns. v11+ (2027): Authority × Objective weighting, dynamic seasonality from inquiry log history.
B82: Source 5: Porter Wills Esports Marketing Guide 2025
B83: Used for: Tier 1 org benchmarks, usage rights pricing standards. URL: porterwills.com
B85: Source 6: StreamElements State of Streaming 2025
B86: Used for: Twitch/streaming rate benchmarks, subscription income data. URL: streamelements.com/reports
B88: Source 7: WME / CAA / Wasserman Agency Practice
B89: Used for: base fee pricing methodology (CPM + CPE + comparables model). Source: public deal disclosures and industry standard practice.
B91: Source 8: Internal Team Falcons Commercial Data 2025
B92: Used for: Falcons-specific base fees, roster data, MENA market rates. Source: Confidential internal data.
B94: Source 9: Case Studies (Tab 10_Case_Studies)
B95: Used for: 0-to-hero monetisation journeys, revenue breakdown benchmarks. Sources: Forbes, Bloomberg, public creator disclosures, Streamlabs, Newzoo MENA.
B97: TABS OVERVIEW
B98: 00_Cover — Overview and navigation guide
... B144: STEP-BY-STEP
B145: Step 1 | C145: Fill Campaign Details (rows 5-9): Campaign name, brand, period, prepared by
B146: Step 2
B147: Step 3 | C147: Add line items (rows 19-33): For each deliverable, select from dropdowns:
C148: • Player / Talent — select from full roster dropdown
C149: • Deliverable — IG Reel, TikTok Video, Twitch Stream, IRL Appearance, etc.
C150: • Qty — number of posts/appearances
C151: • Timing — Regular Season, Ramadan, EWC, etc. (auto-applies multiplier)
C152: • Audience — Core Gaming, Esports-focused, MENA/Saudi, etc. (auto-applies multiplier)
C153: • Add-on Package — None, Basic, Standard, Premium, Full, Exclusive (auto-applies uplift %)
B154: Step 4 | C154: Unit Price auto-calculates: Base Rate × Timing Multiplier × Audience Multiplier × (1 + Add-on %)
B155: Step 5 | C155: Summary auto-calculates: Subtotal → +10% Mgmt Fee → +15% VAT → Total SAR + USD
B156: Step 6 | C156: Click "GENERATE PDF QUOTE" button to export a formatted client document
B158: PRICING METHODOLOGY (Updated 2025)
B159: All player rates have been recalibrated using best-practice 2025 benchmarks:
B160: Source | C160: Porter Wills Esports Guide 2025, InfluenceFlow Benchmarks, Cloutboost Gaming Rates
B161: Tier 1 IG Reel Base | C161: 18,000 SAR (was 15,000) — aligned to macro esports creator rates ($4,800 USD)
B162: Tier 2 IG Reel Base | C162: 11,000 SAR (was 11,250) — refined for 100K-500K reach segment
B163: Tier 3 IG Reel Base | C163: 6,500 SAR (was 8,750) — corrected downward to match micro-creator benchmarks
B164: Platform Ratios | C164: TikTok = 78% of IG Reel | Twitch 2h = 145% | IRL = 220% | X Post = 20%
B165: Platform Count Bonus | C165: 0-1 platforms: -20% | 2-3: standard | 4-5: +15% | 6-7: +25% | 8+: +35%
B166: MENA Premium
B168: ADD-ON PACKAGES (simplified from 03_Add_On_Rights)
B169: None | C169: 0% uplift — base rate only
B170: Basic (+15%) | C170: Organic repost, 1 month — single platform
B171: Standard (+60%) | C171: Organic repost (3 months) + paid usage (limited)
B172: Premium (+115%) | C172: Organic repost (6 months) + paid usage (standard) + MENA territory
B173: Full (+170%) | C173: All organic + paid max + whitelisting (30 days)
B174: Exclusive (+320%) | C174: Full package + category exclusivity (12 months)
B176: TIMING MULTIPLIERS
B177: Regular Season | C177: 1.00x — baseline
B178: Off-season | C178: 0.80x — lower viewership
B179: Regional Major | C179: 1.25x — regional championship
B180: Global Major / Worlds | C180: 1.40x — peak esports interest
B181: Game Launch | C181: 1.30x — new title release
B182: Holiday Q4 | C182: 1.20x — year-end peak
B183: Ramadan (MENA) | C183: 1.35x — peak MENA consumption
B184: EWC / Mega Peak | C184: 1.50x — Esports World Cup (highest multiplier)
B186: AUDIENCE MULTIPLIERS
B187: Generic / Broad | C187: 0.85x
B188: Gaming-adjacent | C188: 1.00x
B189: Core Gaming | C189: 1.20x
B190: MENA / Saudi focus | C190: 1.30x
B191: Esports-focused | C191: 1.40x

Sheet 06_Guide_AR
A1: محرّك التسعير لفريق Falcons — دليل الاستخدام (الإصدار 8)
A3: 1. ما الذي يفعله هذا المحرّك
A4: يُنتج عروض أسعار تجارية لمواهب Falcons عبر منصات التواصل الاجتماعي والبث والحضور الفعلي. يستخدم تصنيفًا من 5 طبقات مع منطق ذي حدّين أدنى (سعر اجتماعي + حدّ أدنى للسلطة) وطبقة ثقة تمنع التسعير المرتفع على بيانات غير موثّقة.
A6: 2. التبويبات الأكثر استخدامًا
A7: • 01_Player_Rate_Card — اللائحة الرئيسية (189 لاعبًا)، الطبقة، الأسعار، بيانات المتابعين، الثقة • 02_Adjustment_Matrix — حيث تبني العروض: بحث اللاعب + معاينة السعر + حاسبة السعر المباشر • 03_Add_On_Rights — حزم الحقوق (عضوي/مدفوع/قوائم بيضاء/حصرية/إقليمية) • 07_Settings — افتراضات الطبقات، نسب الحدّ الأدنى، تعريفات الثقة • QT-... — عرض السعر النهائي المقدّم للعميل
A9: 3. كيف تبني عرض سعر — خطوة بخطوة
A10: الخطوة 1: افتح 02_Adjustment_Matrix. الخطوة 2: اكتب اسم اللاعب في الخلية D5. يطابق المحرّك أقرب لاعب تلقائيًا. الخطوة 3: راجع القسم ⑦ معاينة سعر اللاعب — اطّلع على جميع أسعار الأصول والحدّ الأدنى للسلطة والسعر النهائي بالمضاعفات الافتراضية. الخطوة 4: تحقّق من وسم الثقة. إن كان "قيد الانتظار" أو "مقدّر"، التزم بنطاق المضاعفات المسموح. الخطوة 5: في القسم ⑥ حاسبة السعر المباشر، اختر الأصل، أدخل قيم التفاعل/الجمهور/الموسمية/السلطة/اللغة. الخطوة 6: أضف حزمة الحقوق من 03_Add_On_Rights. الخطوة 7: أكّد السعر النهائي المعدّل. انقله إلى قالب عرض السعر QT. الخطوة 8: موافقة قانونية ومالية → إرسال العرض للعميل.
A12: 4. متى يتجاوز الحدّ الأدنى للسلطة السعرَ الاجتماعي
A13: إذا كان اللاعب محترفًا بجمهور اجتماعي متواضع (مثال: 30 ألف انستغرام) ولكن أجر حضوره الفعلي مرتفع (25,000 ريال)، فإن الحدّ الأدنى للسلطة = 25,000 × 0.55 = 13,750 ريال. يحمي ذلك دخل اللاعب المحترف على الحملات الاجتماعية الصافية.
A15: 5. قواعد حوكمة الثقة
A16: • exact / rounded → جميع المضاعفات متاحة • estimated → التفاعل محدود بـ 1.2x، السلطة محدودة بـ 1.3x • pending → جميع المضاعفات مثبّتة على 1.0x حتى التحقق من بيانات المتابعين يمكن للمدير التجاري التجاوز، لكن يجب تسجيل ذلك في ملاحظات العرض.
A18: 6. ما التالي
A19: الإصدار 9 (الربع الثالث 2026): تكامل Shikenso لتعبئة بيانات المتابعين وترقية وسوم الثقة عبر اللائحة. الإصدار 10 (الربع الرابع 2026): مضاعفات التفاعل ستُحسب من بيانات 30/90 يومًا بدلاً من القوائم اليدوية. الإصدار 11+ (2027): ترجيح السلطة × الهدف، موسمية ديناميكية من سجل الاستفسارات.
B82: المصدر 5: دليل Porter Wills للتسويق في الرياضات الإلكترونية 2025
B83: يُستخدم لـ: معايير المنظمات من الفئة الأولى، معايير تسعير حقوق الاستخدام. الرابط: porterwills.com
B85: المصدر 6: تقرير StreamElements لحالة البث 2025
B86: يُستخدم لـ: معايير أسعار Twitch/البث، بيانات دخل الاشتراكات. الرابط: streamelements.com/reports
B88: المصدر 7: ممارسة وكالات WME / CAA / Wasserman
B89: يُستخدم لـ: منهجية تسعير الرسوم الأساسية (نموذج CPM + CPE + المقارنات). المصدر: الإفصاحات العلنية عن الصفقات والممارسة المعيارية في الصناعة.
B91: المصدر 8: بيانات فالكونز التجارية الداخلية 2025
B92: يُستخدم لـ: الرسوم الأساسية الخاصة بفالكونز، بيانات القائمة، أسعار سوق MENA. المصدر: بيانات داخلية سرية.
B94: المصدر 9: دراسات الحالة (علامة التبويب 10_Case_Studies)
B95: يُستخدم لـ: رحلات تحقيق الدخل من الصفر إلى القمة، معايير توزيع الإيرادات. المصادر: Forbes وBloomberg والإفصاحات العلنية للمبدعين وStreamlabs وNewzoo MENA.
B97: نظرة عامة على علامات التبويب
B98: 00_Cover — نظرة عامة ودليل التنقل
... B143: خطوات الاستخدام
B144: الخطوة 1 | C144: تفاصيل الحملة (صفوف 5-9): اسم الحملة، العلامة التجارية، الفترة، المُعِد
B145: الخطوة 2
B146: الخطوة 3 | C146: أضف بنود التسليم (صفوف 19-33): لكل تسليم، اختر من القوائم:
C147: • اللاعب / الموهبة — اختر من القائمة الكاملة للرياضيين
C148: • نوع التسليم — ريلز إنستغرام، فيديو تيك توك، بث تويتش، حضور شخصي، إلخ
C149: • الكمية — عدد المنشورات أو الظهورات
C150: • التوقيت — الموسم العادي، رمضان، كأس العالم للرياضات الإلكترونية، إلخ
C151: • الجمهور — ألعاب أساسية، رياضات إلكترونية، منطقة الشرق الأوسط وشمال أفريقيا، إلخ
C152: • باقة الإضافات — لا شيء، أساسية، قياسية، مميزة، كاملة، حصرية
B153: الخطوة 4 | C153: يُحسب سعر الوحدة تلقائياً: السعر الأساسي × مضاعف التوقيت × مضاعف الجمهور × (1 + نسبة الإضافات)
B154: الخطوة 5 | C154: الملخص يُحسب تلقائياً: المجموع الفرعي + رسوم الإدارة 10% + ضريبة القيمة المضافة 15%
B155: الخطوة 6 | C155: انقر على "إنشاء عرض سعري PDF" لتصدير وثيقة منسقة للعميل
B157: منهجية التسعير (محدّثة 2025)
B158: تم إعادة معايرة جميع أسعار اللاعبين وفق أفضل الممارسات العالمية لعام 2025:
B159: الدرجة الأولى — ريلز إنستغرام | C159: 18,000 ريال (كانت 15,000) — متوافق مع معدلات منشئي المحتوى الكبار في الرياضات الإلكترونية
B160: الدرجة الثانية — ريلز إنستغرام | C160: 11,000 ريال (كانت 11,250) — محسّن لشريحة 100K-500K متابع
B161: الدرجة الثالثة — ريلز إنستغرام | C161: 6,500 ريال (كانت 8,750) — مصحّح للتوافق مع معايير منشئي المحتوى الصغار
B162: نسب المنصات | C162: تيك توك = 78% من ريلز إنستغرام | تويتش 2 ساعة = 145% | حضور شخصي = 220%
B163: مكافأة عدد المنصات | C163: 0-1 منصة: -20% | 2-3: معياري | 4-5: +15% | 6-7: +25% | 8+: +35%
B164: علاوة منطقة MENA
B166: باقات الإضافات (مبسّطة)
B167: لا شيء
B168: أساسية (+15%) | C168: إعادة نشر عضوي، شهر واحد — منصة واحدة
B169: قياسية (+60%) | C169: إعادة نشر عضوي (3 أشهر) + استخدام مدفوع (محدود)
B170: مميزة (+115%) | C170: إعادة نشر عضوي (6 أشهر) + استخدام مدفوع (قياسي) + حقوق منطقة MENA
B171: كاملة (+170%) | C171: جميع الحقوق العضوية + الاستخدام المدفوع الكامل + القائمة البيضاء (30 يوماً)
B172: حصرية (+320%) | C172: الباقة الكاملة + حصرية الفئة (12 شهراً)
B174: مضاعفات التوقيت
B175: الموسم العادي
B176: خارج الموسم | C176: 0.80x — مشاهدة منخفضة
B177: بطولة إقليمية كبرى | C177: 1.25x — بطولة إقليمية
B178: بطولة عالمية | C178: 1.40x — ذروة الاهتمام بالرياضات الإلكترونية
B179: إطلاق لعبة | C179: 1.30x — إصدار عنوان جديد
B180: نهاية العام (الربع الرابع) | C180: 1.20x — ذروة نهاية العام
B181: رمضان (منطقة MENA) | C181: 1.35x — ذروة الاستهلاك في منطقة MENA
B182: كأس العالم للرياضات الإلكترونية | C182: 1.50x — أعلى مضاعف في النظام

Sheet 09_Benchmarks
A1: 09 — MARKET BENCHMARKS & COMPETITIVE INTELLIGENCE 2025/2026
A2: Industry rate benchmarks, multiplier standards, and competitive positioning for Team Falcons talent monetisation
A4: SECTION 1 — GLOBAL TIER 1 ESPORTS ORG BENCHMARKS
A5: Organisation | B5: Region | C5: Tier | D5: Avg Followers (Key Talent) | E5: Avg Base Fee / Post (USD) | F5: Avg Stream Deal (USD) | G5: Avg Annual Sponsorship (USD) | H5: Exclusivity Premium | I5: Engagement Benchmark | J5: Source / Notes
A6: T1 Esports | B6: Global | C6: Tier 1 | D6: 2M–8M | E6: $8,000–$25,000 | F6: $20,000–$80,000 | G6: $500K–$2M | H6: '+50-100% | I6: 4–7% avg ER | J6: Newzoo 2025; public deal disclosures
A7: FaZe Clan | B7: Global | C7: Tier 1 | D7: 3M–15M | E7: $10,000–$40,000 | F7: $30,000–$120,000 | G7: $1M–$5M | H7: '+40-75% | I7: 3–6% avg ER | J7: Newzoo 2025; SEC filing data
A8: Natus Vincere (NaVi) | B8: EMEA | C8: Tier 1 | D8: 1M–5M | E8: $5,000–$20,000 | F8: $15,000–$60,000 | G8: $300K–$1.5M | H8: '+35-60% | I8: 4–8% avg ER | J8: Shikenso Esports Sponsorship Report 2025
A9: Fnatic | B9: EMEA | C9: Tier 1 | D9: 500K–3M | E9: $4,000–$15,000 | F9: $10,000–$45,000 | G9: $200K–$800K | H9: '+30-50% | I9: 5–9% avg ER | J9: Influencity 2026 Rate Benchmarks
A10: Cloud9 | B10: NA | C10: Tier 1 | D10: 1M–6M | E10: $6,000–$22,000 | F10: $18,000–$70,000 | G10: $400K–$1.8M | H10: '+30-50% | I10: 3–6% avg ER | J10: Nielsen Esports Audience Report 2025
A11: 100 Thieves | B11: NA | C11: Tier 1 | D11: 500K–4M | E11: $5,000–$18,000 | F11: $15,000–$55,000 | G11: $350K–$1.2M | H11: '+40-70% | I11: 5–10% avg ER | J11: Porter Wills Esports Marketing Guide 2025
A13: SECTION 2 — MENA ESPORTS ORG BENCHMARKS
A14: Organisation | B14: Region | C14: Tier | D14: Avg Followers (Key Talent) | E14: Avg Base Fee / Post (SAR) | F14: Avg Stream Deal (SAR) | G14: Avg Annual Sponsorship (SAR) | H14: Exclusivity Premium | I14: Engagement Benchmark | J14: Source / Notes
A15: Team Falcons | B15: KSA / MENA | C15: Tier 1 | D15: 200K–2M | E15: SAR 8,000–60,000 | F15: SAR 20,000–120,000 | G15: SAR 500K–2M | H15: '+35-60% | I15: 5–12% avg ER | J15: Internal Falcons data 2025; Newzoo MENA Report
A16: Nasr Esports | B16: KSA / MENA | C16: Tier 1 | D16: 100K–800K | E16: SAR 5,000–30,000 | F16: SAR 12,000–60,000 | G16: SAR 200K–800K | H16: '+30-50% | I16: 4–9% avg ER | J16: Shikenso MENA Esports Report 2025
A17: GE Wolves | B17: MENA | C17: Tier 2 | D17: 50K–400K | E17: SAR 3,000–15,000 | F17: SAR 8,000–35,000 | G17: SAR 100K–400K | H17: '+25-40% | I17: 5–10% avg ER | J17: Influencity MENA 2025
A18: Twisted Minds | B18: KSA | C18: Tier 2 | D18: 80K–500K | E18: SAR 4,000–20,000 | F18: SAR 10,000–45,000 | G18: SAR 150K–500K | H18: '+25-45% | I18: 6–11% avg ER | J18: Internal market intelligence 2025
A19: Galaxy Racer | B19: UAE / MENA | C19: Tier 2 | D19: 100K–1M | E19: SAR 4,500–22,000 | F19: SAR 11,000–50,000 | G19: SAR 180K–600K | H19: '+25-40% | I19: 4–9% avg ER | J19: Newzoo MENA 2025
A20: Team Vitality (MENA) | B20: MENA | C20: Tier 1 | D20: 200K–1.5M | E20: SAR 6,000–35,000 | F20: SAR 15,000–70,000 | G20: SAR 250K–900K | H20: '+30-50% | I20: 4–8% avg ER | J20: Shikenso Esports Report 2025
A22: SECTION 3 — PLATFORM RATE BENCHMARKS (Industry Standard CPM / CPE)
A23: Platform | B23: Content Type | C23: Nano (1K–10K) | D23: Micro (10K–100K) | E23: Mid (100K–1M) | F23: Macro (1M–5M) | G23: Mega (5M+) | H23: Min Engagement Req. | I23: Avg CPM (Gaming Niche) | J23: Notes / Source
A24: Instagram | B24: Reel (60s) | C24: $200–$1,000 | D24: $1,000–$5,000 | E24: $5,000–$15,000 | F24: $15,000–$50,000 | G24: $50,000+ | H24: Min 3% ER | I24: $8–$15 CPM | J24: Reels outperform static 3:1 for brand recall in gaming. Source: Influencity 2026
A25: Instagram | B25: Static Post | C25: $150–$800 | D25: $800–$4,000 | E25: $4,000–$12,000 | F25: $12,000–$40,000 | G25: $40,000+ | H25: Min 2% ER | I25: $5–$10 CPM | J25: Static posts declining vs Reels. Use for product shots. Source: Influencity 2026
A26: TikTok | B26: Branded Video | C26: $300–$1,500 | D26: $1,500–$6,000 | E26: $6,000–$20,000 | F26: $20,000–$60,000 | G26: $60,000+ | H26: Min 5% ER | I26: $10–$20 CPM | J26: TikTok commands 20–40% premium over IG in MENA. Source: Nielsen 2025
A27: YouTube | B27: Integration (30s) | C27: $500–$2,000 | D27: $2,000–$8,000 | E27: $8,000–$25,000 | F27: $25,000–$80,000 | G27: $80,000+ | H27: Min 1% ER | I27: $15–$30 CPM | J27: Highest brand recall (72% vs 45% social posts). Source: Nielsen Esports 2025
A28: YouTube | B28: Short (<60s) | C28: $200–$1,000 | D28: $1,000–$4,000 | E28: $4,000–$12,000 | F28: $12,000–$35,000 | G28: $35,000+ | H28: Min 3% ER | I28: $8–$18 CPM | J28: YouTube Shorts growing rapidly in MENA. Source: Newzoo 2025
A29: Twitch | B29: Stream Integration (2h) | C29: $1,000–$4,000 | D29: $4,000–$15,000 | E29: $15,000–$40,000 | F29: $40,000–$100,000 | G29: $100,000+ | H29: Min 500 avg viewers | I29: $5–$15 CPM | J29: Rates based on concurrent viewership not followers. Source: StreamElements 2025
A30: X (Twitter) | B30: Sponsored Post | C30: $100–$500 | D30: $500–$2,000 | E30: $2,000–$6,000 | F30: $6,000–$20,000 | G30: $20,000+ | H30: Min 1% ER | I30: $3–$8 CPM | J30: X declining in brand value post-rebrand. Use for real-time only. Source: Influencity 2026
A32: SECTION 4 — MULTIPLIER BENCHMARKS (Industry Standard vs Team Falcons)
A33: Multiplier Type | B33: Industry Low | C33: Industry Standard | D33: Industry High | E33: Team Falcons Rate | F33: Variance vs Industry | G33: Recommendation | H33: Source
A34: Exclusivity (30 days) | B34: 0.15 | C34: 0.25 | D34: 0.4 | E34: 0.25 | F34: At standard | G34: At standard | H34: Influencity 2026; Porter Wills Guide
A35: Exclusivity (90 days) | B35: 0.3 | C35: 0.5 | D35: 0.75 | E35: 0.4 | F35: Below standard — gap of 10% | G35: Below standard — gap of 10% | H35: Influencity 2026; Shikenso 2025
A36: Rush Fee (<72h) | B36: 0.15 | C36: 0.25 | D36: 0.35 | E36: 0.2 | F36: Below standard — gap of 5% | G36: Below standard — gap of 5% | H36: Internal benchmark; Influencity 2026
A37: Usage Rights (6 months) | B37: 0.2 | C37: 0.35 | D37: 0.5 | E37: 0.3 | F37: Below standard — gap of 5% | G37: Below standard — gap of 5% | H37: Porter Wills Esports Guide 2025
A38: Usage Rights (12 months) | B38: 0.4 | C38: 0.6 | D38: 0.8 | E38: 0.5 | F38: Below standard — gap of 10% | G38: Below standard — gap of 10% | H38: Porter Wills Esports Guide 2025
A39: Whitelist / Dark Post | B39: 0.15 | C39: 0.25 | D39: 0.4 | E39: 0.2 | F39: Below standard — gap of 5% | G39: Below standard — gap of 5% | H39: Influencity 2026
A40: Ramadan Premium (MENA) | B40: 0.25 | C40: 0.35 | D40: 0.5 | E40: 0.35 | F40: At standard | G40: At standard | H40: Newzoo MENA 2025; Internal data
A42: SECTION 5 — TEAM FALCONS COMPETITIVE POSITIONING
A43: Metric | B43: Team Falcons | C43: MENA Average | D43: Global Tier 1 | E43: Gap vs MENA | F43: Gap vs Global | G43: Action Required
A44: Roster Size | B44: 188 entries (131 players, 6 influencers, 51 staff) | C44: 80–120 players | D44: 150–200 players | E44: Above MENA avg (+78%) | F44: Above global avg | G44: Leverage scale — offer multi-player bundle packages
A45: Game Coverage | B45: 23 titles | C45: 10–15 titles | D45: 15–20 titles | E45: Above MENA avg | F45: Above global avg | G45: Position as one-stop-shop for brand esports activations
A46: Avg Base Fee (Tier 1) | B46: SAR 15,000 (~$4,000) | C46: SAR 8,000–12,000 | D46: $15,000–$50,000 | E46: Above MENA avg | F46: Below global Tier 1 | G46: Justified for MENA market. Increase for global brand pitches.
A47: Exclusivity Rates | B47: 35–40% uplift | C47: 25–35% uplift | D47: 40–75% uplift | E47: At/above MENA | F47: Below global standard | G47: Increase exclusivity floor to +40% across all tiers
A48: Rush Fee | B48: 20% uplift | C48: 15–20% uplift | D48: 25–35% uplift | E48: At MENA avg | F48: Below global standard | G48: Standardise rush fee at +30% minimum
A52: SECTION 5 — FALCONS 5-TIER MAPPING vs INDUSTRY (new in v8)
A54: Falcons Tier | B54: Follower Threshold | C54: Base Fee (SAR) | D54: Base Fee (USD) | E54: Industry Equivalent | F54: Global Org Peer | G54: MENA Peer | H54: Floor Share % | I54: Confidence Default | J54: Notes
A55: Tier S | B55: >1M | C55: 40,000 – 50,000 | D55: $10,700 – $13,300 | E55: Mega / Tier 1 Global | F55: T1 Esports, FaZe, Cloud9 elite | G55: Regional anchor rare | H55: 65% | I55: exact required | J55: Global anchors — world champions, iconic IG/Twitch names
A56: Tier 1 | B56: 250K – 1M | C56: 22,000 – 30,000 | D56: $5,900 – $8,000 | E56: Macro / Tier 1 | F56: FaZe mid-tier, Fnatic pros | G56: Nasr top roster, Galaxy Racer stars | H56: 55% | I56: rounded+ | J56: Regional majors, 2+ years pro
A57: Tier 2 | B57: 50K – 250K | C57: 11,000 – 18,000 | D57: $2,900 – $4,800 | E57: Mid / Tier 2 | F57: 100T rising, Cloud9 depth | G57: GE Wolves, Twisted Minds core | H57: 45% | I57: estimated+ | J57: Active competitive pros + mid-tier creators
A58: Tier 3 | B58: 10K – 50K | C58: 6,500 – 10,000 | D58: $1,700 – $2,700 | E58: Micro / Tier 2 | F58: Academy rosters | G58: MENA Tier 2 academies | H58: 35% | I58: estimated | J58: Rising talent, niche specialists
A59: Tier 4 | B59: <10K / staff | C59: 3,000 – 5,500 | D59: $800 – $1,500 | E59: Nano / Support | F59: Coaches, analysts, staff | G59: Coaches, analysts, staff | H59: 25% | I59: pending allowed | J59: Non-competing roles + developing roster
A63: CONFIDENCE LAYER COMMENTARY
A65: • Why Falcons added a Confidence layer: as of v8, 65/189 players have no verified follower data. Pricing premiums on this data would be dishonest to clients and risk margin erosion when clients verify independently.
A66: • Industry practice: NeoReach and Modash both flag data confidence before applying authority multipliers. Goat Agency refuses to guarantee CPE on "estimated" data.
A67: • Falcons commercial rule: "exact" and "rounded" talent get full multiplier range. "estimated" talent cap at +20% engagement and +30% authority. "pending" talent hold at 1.0x across the board until Shikenso sync.
A68: • Target state (v9+): >95% of 189 players at "exact" or "rounded" confidence via Shikenso integration.

Sheet 10_Case_Studies
A1: 10 — CASE STUDIES: FROM 0 TO HERO — CONTENT-ENABLED MONETISATION JOURNEYS
A2: Real-world examples of unknown / low-profile players who built $10K–$500K+ annual income through strategic content, ads, and brand partnerships
A4: SECTION A — GLOBAL CASE STUDIES (Non-Famous to Monetised Creator)
A5: # | B5: Creator / Player | C5: Game | D5: Starting Point | E5: Platform Strategy | F5: Year 1 Revenue | G5: Year 2 Revenue | H5: Year 3 Revenue | I5: Key Monetisation Levers | J5: Peak Monthly Income | K5: Lesson for Falcons Talent
A6: CS-01 | B6: Symfuhny (Mason Lanier) | C6: Fortnite / Warzone | D6: 0 followers, unknown player, streaming to 0 viewers (2018) | E6: Twitch daily streams 8h+, highlight clips to Twitter, YouTube VODs | F6: $12,000 (Twitch subs + bits) | G6: $85,000 (first brand deal: Scuf Gaming) | H6: $400,000+ (NRG signing + multiple brand deals) | I6: Twitch subscriptions, ad revenue, Scuf Gaming, G Fuel, NRG salary | J6: $45,000/month at peak | K6: Consistency + clip virality is the engine. First brand deal came at 200K followers.
A7: CS-02 | B7: Nickmercs (Nick Kolcheff) | C7: Fortnite / Warzone | D7: Streamed for 6 years with minimal growth. Pivoted to Fortnite 2018. | E7: Twitch-first, YouTube highlights, Twitter engagement, tournament appearances | F7: $30,000 (Twitch affiliate income) | G7: $250,000 (FaZe Clan signing + brand deals) | H7: $1.2M+ (FaZe equity + Scuf, G Fuel, Turtle Beach) | I7: Twitch subs, FaZe salary, G Fuel, Scuf Gaming, own merch line (MFAM) | J7: $120,000/month at peak | K7: Org signing is a multiplier — not a starting point. Build the audience first.
A8: CS-03 | B8: Valkyrae (Rachell Hofstetter) | C8: Among Us / Valorant | D8: Retail worker. Started streaming on Twitch in 2014 with no gaming background. | E8: Twitch to YouTube Gaming (exclusive deal 2020), TikTok clips | F8: $8,000 (Twitch subs) | G8: $150,000 (YouTube Gaming exclusivity deal) | H8: $1.5M+ (100T co-ownership + brand deals + RFLCT skincare line) | I8: YouTube Gaming exclusive deal, 100 Thieves co-ownership, brand deals, own product line | J8: $200,000/month at peak (2021) | K8: Platform exclusivity deals are a step-change income event. Negotiate early.
A9: CS-04 | B9: TimTheTatman (Timothy Betar) | C9: Fortnite / CoD | D9: Casual streamer with a day job. Started streaming in 2012. | E9: Twitch-first for 9 years, YouTube Gaming exclusive 2021 | F9: $50,000/year (Twitch income) | G9: $300,000 (brand deals: Bud Light, Gillette) | H9: $2M+ (YouTube Gaming exclusive deal + NerdStreet, SteelSeries, Bud Light) | I9: YouTube Gaming exclusivity ($multi-million), brand deals, own merch | J9: $180,000/month at peak | K9: Exclusivity deals from platforms (YouTube, Twitch) are the biggest single income events.
A10: CS-05 | B10: Clix (Cody Conrod) | C10: Fortnite | D10: Unknown 13-year-old. Started competing in Fortnite tournaments 2019. | E10: Twitch streaming + tournament clips to Twitter/YouTube | F10: $40,000 (tournament winnings + Twitch) | G10: $200,000 (NRG signing + brand deals) | H10: $600,000+ (NRG salary + G Fuel, Scuf, Logitech) | I10: Tournament prize money, NRG org salary, G Fuel, Scuf Gaming, Logitech G | J10: $55,000/month | K10: Competitive results + content = dual income stream. Tournaments build credibility for brands.
A11: CS-06 | B11: Jynxzi (Nicholas Stewart) | C11: Rainbow Six Siege | D11: Unknown R6S player. Started streaming in 2021. | E11: TikTok-first strategy (short clips), then Twitch, then YouTube | F11: $5,000 (TikTok creator fund + Twitch) | G11: $120,000 (Twitch growth + first brand deals) | H11: $800,000+ (Twitch Partner, NRG signing, brand deals, own merch) | I11: Twitch subscriptions, NRG salary, brand deals (Logitech, G Fuel), merch | J11: $80,000/month | K11: TikTok as discovery engine for Twitch is the most efficient 0-to-hero path in 2024–2025.
A12: CS-07 | B12: Lacy (Lacey Jones) | C12: Fortnite | D12: Unknown female player. Zero following. Started content in 2020. | E12: TikTok clips + Twitch streams + YouTube tutorials | F12: $3,000 (TikTok creator fund) | G12: $45,000 (Twitch growth + first brand deal) | H12: $180,000 (NRG signing + brand deals + Twitch) | I12: Twitch subs, NRG salary, G Fuel, SteelSeries, own merch | J12: $20,000/month | K12: Female gaming creators have 40% higher brand CPM in gaming niche — underpriced opportunity.
A13: CS-08 | B13: Kai Cenat | C13: GTA V / variety | D13: Unknown streamer from the Bronx. Started on YouTube 2020. | E13: YouTube Shorts viral clips, then Twitch, then cross-platform | F13: $15,000 (YouTube ad revenue) | G13: $300,000 (Twitch growth + brand deals) | H13: $5M+ (Twitch record-breaking sub count, AMP, brand deals, Amazon deal) | I13: Twitch subscriptions (record 306K subs), Amazon deal, AMP label, brand deals | J13: $500,000+/month at peak (2023) | K13: Sub-a-thon events are the single highest-revenue activation for Twitch streamers.
A15: SECTION B — MENA / ARABIC GAMING CREATOR CASE STUDIES
A16: # | B16: Creator / Player | C16: Game | D16: Starting Point | E16: Platform Strategy | F16: Year 1 Revenue (SAR) | G16: Year 2 Revenue (SAR) | H16: Year 3 Revenue (SAR) | I16: Key Monetisation Levers | J16: Peak Monthly Income (SAR) | K16: Lesson for Falcons Talent
A17: MENA-01 | B17: Mendo (Mohammed Al-Otaibi) | C17: FIFA / FC | D17: Unknown FIFA player in KSA. Started YouTube in 2017. | E17: YouTube Arabic FIFA content, TikTok clips, Instagram highlights | F17: SAR 30,000 (YouTube ads) | G17: SAR 180,000 (EA Sports deal + YouTube growth) | H17: SAR 800,000+ (EA Sports, STC, multiple brand deals) | I17: YouTube ad revenue, EA Sports partnership, STC sponsorship, brand deals | J17: SAR 90,000/month | K17: Arabic FIFA content has the highest CPM in MENA gaming — $15–$25 CPM. EA Sports is the anchor brand.
A18: MENA-02 | B18: Ninja Saudi (Faisal Al-Harbi) | C18: Fortnite / PUBG | D18: Unknown PUBG player. Started streaming on YouTube 2019. | E18: YouTube Arabic gaming content, TikTok highlights, Twitch streams | F18: SAR 20,000 (YouTube ads + Twitch) | G18: SAR 120,000 (first brand deals: STC, Lenovo) | H18: SAR 500,000+ (Lenovo, STC, Falcons-adjacent deal, own merch) | I18: YouTube ads, STC sponsorship, Lenovo Arabia, tournament appearances | J18: SAR 55,000/month | K18: STC and Lenovo Arabia are the two anchor brands for MENA gaming creators. Target these first.
A19: MENA-03 | B19: Abo Najd (Falcons Roster) | C19: FC / FIFA | D19: Started as unknown FIFA player. Joined Falcons ecosystem. | E19: YouTube Arabic content, TikTok viral clips, Instagram | F19: SAR 15,000 (organic content) | G19: SAR 200,000 (Falcons org support + brand deals) | H19: SAR 600,000+ (Falcons + EA Sports + multiple brand deals) | I19: Falcons org salary, EA Sports, brand deals enabled by Falcons commercial team | J19: SAR 65,000/month | K19: Org backing multiplies earning potential 5–10x vs independent. Falcons commercial infrastructure is the differentiator.
A20: MENA-04 | B20: Bijw (Falcons Roster) | C20: Valorant / variety | D20: Competitive player with small following. Joined Falcons. | E20: TikTok-first clips, YouTube highlights, Twitch streams | F20: SAR 25,000 (competitive salary + small content income) | G20: SAR 180,000 (Falcons + brand deals unlocked by org) | H20: SAR 550,000+ (Falcons + Riot Games, STC, multiple deals) | I20: Falcons org salary, Riot Games partnership, STC, brand deals | J20: SAR 60,000/month | K20: Riot Games (Valorant) is an anchor brand partner for Valorant creators — Falcons Valorant talent should always be pitched to Riot.
A21: MENA-05 | B21: Saud Al-Harbi (independent) | C21: PUBG Mobile | D21: Unknown PUBG Mobile player. Started TikTok in 2021. | E21: TikTok Arabic PUBG clips (viral), YouTube tutorials, Instagram | F21: SAR 8,000 (TikTok creator fund) | G21: SAR 80,000 (PUBG Mobile brand deal + TikTok growth) | H21: SAR 320,000 (PUBG Mobile, Pepsi Gaming, STC) | I21: TikTok creator fund, PUBG Mobile official partnership, Pepsi Gaming, STC | J21: SAR 38,000/month | K21: PUBG Mobile has an official creator program — apply at 50K followers. Pepsi Gaming is the highest-paying FMCG brand in MENA gaming.
A22: MENA-06 | B22: Hamood (independent) | C22: Minecraft / variety | D22: Unknown Minecraft Arabic creator. Started YouTube 2020. | E22: YouTube Arabic Minecraft content, TikTok clips, Instagram | F22: SAR 12,000 (YouTube ads) | G22: SAR 95,000 (YouTube growth + first brand deals) | H22: SAR 380,000 (multiple brand deals, YouTube, own merch) | I22: YouTube ad revenue, brand deals (Noon, Jarir, STC), own merch line | J22: SAR 42,000/month | K22: Arabic Minecraft content has the youngest audience in MENA gaming — highest CPM for toy/FMCG brands ($18–$28 CPM).
A23: MENA-07 | B23: FMG (Falcons Roster) | C23: Esports Influencer | D23: Esports influencer with moderate following. Joined Falcons. | E23: Multi-platform: YouTube, TikTok, Instagram, Twitter | F23: SAR 40,000 (independent content income) | G23: SAR 250,000 (Falcons + brand deals) | H23: SAR 700,000+ (Falcons + STC, EA, Pepsi, multiple deals) | I23: Falcons org salary, STC, EA Sports, Pepsi Gaming, event appearances | J23: SAR 75,000/month | K23: Esports influencers (non-competitive) command the highest brand CPM in MENA — $20–$35 CPM for lifestyle/gaming crossover content.
A24: MENA-08 | B24: Unknown Warzone Creator (composite) | C24: Warzone / CoD | D24: 0 followers. Started posting Arabic Warzone clips on TikTok (2022). | E24: TikTok Arabic clips daily, Twitch streams, YouTube highlights | F24: SAR 5,000 (TikTok creator fund + Twitch bits) | G24: SAR 60,000 (Twitch growth + first brand deal: Logitech Arabia) | H24: SAR 220,000 (Logitech, STC, Activision Arabia deal) | I24: TikTok creator fund, Twitch subs, Logitech Arabia, STC, Activision | J24: SAR 28,000/month | K24: Logitech Arabia and STC are the two most accessible entry-level brand deals for MENA gaming creators at 50K–200K followers.
A26: SECTION C — MONETISATION REVENUE BREAKDOWN BY SOURCE (Industry Averages)
A27: How top gaming creators split their income — benchmark for Falcons talent revenue diversification
A28: Revenue Source | B28: Nano Creator (1K–10K) | C28: Micro Creator (10K–100K) | D28: Mid Creator (100K–1M) | E28: Macro Creator (1M–5M) | F28: Mega Creator (5M+) | G28: Notes
A29: Platform Ad Revenue (YouTube/Twitch) | B29: 60–80% of income | C29: 40–60% of income | D29: 20–35% of income | E29: 10–20% of income | F29: 5–15% of income | G29: Decreases as % as brand deals grow. CPM: $3–$8 for gaming.
A30: Brand Sponsorships / Deals | B30: 5–15% of income | C30: 20–35% of income | D30: 35–50% of income | E30: 40–55% of income | F30: 30–50% of income | G30: Becomes dominant income source at 100K+ followers.
A31: Org Salary (if signed) | B31: 0% (rarely signed) | C31: 0–10% of income | D31: 10–25% of income | E31: 15–30% of income | F31: 10–20% of income | G31: Org salary is a floor, not a ceiling. Brand deals are the upside.
A32: Merchandise / Own Products | B32: 0–5% of income | C32: 2–8% of income | D32: 5–15% of income | E32: 10–20% of income | F32: 15–30% of income | G32: Merch becomes significant at 500K+ followers with strong community.
A33: Tournament Prize Money | B33: 0–30% (if competitive) | C33: 0–20% (if competitive) | D33: 0–15% (if competitive) | E33: 0–10% (if competitive) | F33: 0–5% (if competitive) | G33: Competitive income is volatile. Content income is more stable.
A34: Platform Exclusivity Deals | B34: 0 | C34: 0 | D34: 0–5% (rare) | E34: 5–15% (Twitch/YT deals) | F34: 10–25% (major deals) | G34: Platform exclusivity deals (Twitch, YouTube Gaming) are step-change events.
A35: Subscriptions (Twitch/YouTube) | B35: 10–20% of income | C35: 10–20% of income | D35: 10–20% of income | E35: 10–15% of income | F35: 5–10% of income | G35: Stable recurring income. Twitch subs = $2.50–$5.00 per sub/month.
A36: Events / IRL Appearances | B36: 0–5% of income | C36: 2–8% of income | D36: 5–10% of income | E36: 5–10% of income | F36: 5–15% of income | G36: IRL events command $500–$50,000 per appearance depending on tier.
A38: SECTION D — THE 0-TO-HERO PLAYBOOK (Step-by-Step Framework)
A39: The proven 4-phase framework used by every successful gaming creator — applicable to all Falcons talent starting content
A41: Phase | B41: Timeline | C41: Goal | D41: Platform Focus | E41: Content Strategy | F41: Monetisation Target | G41: KPI to Hit Before Moving On
A42: Phase 1 — Discovery | B42: Months 1–3 | C42: Build algorithmic momentum. Get discovered. | D42: TikTok primary, Instagram secondary | E42: Daily short clips (30–60s). Highlight plays. Reaction content. No long-form yet. | F42: None — focus 100% on growth | G42: 10,000 TikTok followers + 1 viral clip (500K+ views)
A43: Phase 2 — Community | B43: Months 4–8 | C43: Convert viewers to loyal community. Build Twitch/YouTube base. | D43: Twitch + YouTube (long-form), TikTok (clips) | E43: Twitch streams 4–5x/week. YouTube VODs. TikTok clips from streams. Twitter engagement. | F43: Twitch affiliate income (SAR 2,000–8,000/month) | G43: 50,000 total followers across platforms + Twitch Affiliate status
A44: Phase 3 — Monetisation | B44: Months 9–18 | C44: Land first brand deals. Activate all revenue streams. | D44: All platforms active. YouTube + Twitch primary. | E44: Consistent schedule. Tournaments if applicable. Collaborations with other creators. | F44: First brand deal (SAR 5,000–20,000). Twitch Partner. YouTube monetisation. | G44: 100,000 followers + 1 brand deal signed + Twitch Partner status
A45: Phase 4 — Scale | B45: Month 18+ | C45: Diversify income. Build brand equity. Org-level deals. | D45: All platforms. Consider platform exclusivity negotiation. | E45: Premium content. Event appearances. Own merch. Multiple brand partnerships. | F45: SAR 50,000–200,000+/month from multiple streams | G45: SAR 500,000+ annual income + org deal or platform exclusivity
A47: SECTION E — WHAT FALCONS CAN DO DIFFERENTLY (Commercial Edge)
A49: 1. Org Infrastructure as Accelerator | B49: Independent creators take 18–36 months to reach Phase 3. Falcons talent with org support (commercial team, brand relationships, production) can reach Phase 3 in 6–12 months. This is the core value proposition of the Falcons commercial infrastructure.
A50: 2. Bundle Deals Unlock Higher CPM | B50: A brand deal for a single creator might be SAR 10,000. A bundle deal for 5 Falcons creators across 3 games can command SAR 80,000–150,000 — a 60–200% premium over individual rates summed. No independent creator can offer this.
A51: 3. MENA-First Positioning is Unique | B51: Global brands (Nike, Pepsi, Samsung) pay a 20–35% premium for MENA-specific content. Falcons talent creates authentic Arabic content for the Saudi/MENA market — a positioning no global org can replicate at scale.
A52: 4. Ramadan is a Structural Advantage | B52: Ramadan drives 3x content consumption in MENA. Falcons can offer brands a "Ramadan Package" — pre-planned content calendar, guaranteed delivery, and guaranteed reach during the highest-value window in the MENA marketing calendar.
A53: 5. Esports Credibility = Brand Safety | B53: Brands in MENA are risk-averse. Falcons talent carries the org credibility as brand safety assurance. Independent creators cannot offer this. This is worth a 15–25% premium in every negotiation.
A54: 6. Data-Driven Pitching | B54: Most MENA esports orgs pitch on follower count alone. Falcons should pitch on CPM, CPE, and ROI benchmarks (from this tab). Brands that see data-driven proposals convert at 3x the rate of follower-count-only pitches.
A56: SOURCES FOR CASE STUDIES
A57: Source | B57: Reference
A58: Streamlabs / StreamElements State of Streaming 2025 | B58: Twitch income benchmarks, sub counts, platform data
A59: Newzoo MENA Esports Report 2025 | B59: MENA creator income data, CPM benchmarks
A60: Influencity 2026 Rate Card Benchmarks | B60: Platform CPM/CPE data, brand deal benchmarks
A61: Nielsen Esports Audience Report 2025 | B61: Brand recall, audience quality data
A62: Public creator income disclosures (Forbes, Bloomberg, YouTube) | B62: Symfuhny, Nickmercs, Valkyrae, TimTheTatman, Kai Cenat income data
A63: Shikenso Esports Sponsorship ROI Guide 2025 | B63: Bundle deal premiums, org value multipliers
A64: Internal Team Falcons commercial data 2025 | B64: Falcons roster-specific data (Abo Najd, Bijw, FMG)

Sheet 11_Methodology
A1: TEAM FALCONS — COMMERCIAL PRICING METHODOLOGY & ROADMAP (v8, April 2026)
A3: ① CURRENT PRICING MODEL (v8.0 — April 2026)
A4: Falcons uses a 5-tier talent classification with a dual-floor pricing engine: every quote respects both a Social Price (base × multipliers) AND an Authority Floor (IRL fee × floor share × multipliers). Final Price = MAX of the two, × (1 + Add-on Rights %). A Measurement Confidence layer governs when premium multipliers are allowed, preventing inflated pricing on unverified data.
A6: BASE RATES (The Foundation)
A7: Base rates are established per player, per platform, based on their Tier (1, 2, or 3) and Role (Player, Influencer, Coach, etc.).
A8: • Social Media: IG Reel, TikTok, YT Short, X Post, FB Post/Video
A9: • Live & Stream: Twitch 2h Stream, Twitch Integration
A10: • On-Ground & Events: IRL Appearance, Podcast Guesting (50% IRL), PR/CSR (100% IRL), Fan Meet (70% IRL), Photo Shoot (75% IRL) | B10: C | C10: D | D10: E | E10: F
B11: Audience Reach × CPM Rate | C11: Base Fee = (Followers × Avg Reach Rate × CPM) ÷ 1,000 Reach rates: IG 15–25%, TikTok 20–35%, YT 10–20% Gaming CPM: $8–$20 USD (MENA: $10–$15) | D11: WME, CAA, Wasserman standard FaZe: $15–25 CPM for gaming T1: $12–18 CPM for esports | E11: Applied as Floor 1 in our 3-input model. Sets the minimum viable rate based on expected impressions.
A12: THE MULTIPLIER CHAIN (The Adjustments) | B12: Engagement Quality Multiplier | C12: Multiplier applied on top of CPM floor: < 2%: 0.70x (below market) 2–4%: 0.90x (average) 4–6%: 1.00x (baseline) 6–8%: 1.20x (good) 8–10%: 1.40x (excellent) > 10%: 1.60x (premium micro) | D12: Industry standard: 4–6% is baseline for gaming Micro-influencers (< 100K) often 8–15% Macro (> 1M) typically 2–4% | E12: Applied as Engagement Multiplier in 02_Adjustment_Matrix. Reflects true audience quality beyond raw follower count.
A13: Final Price = Base Rate × Content Type × Engagement × Audience × Seasonality × Language × Authority Factor | B13: Targeting Value Multiplier | C13: Multiplier based on audience composition: Generic/Broad: 0.85x Gaming-adjacent: 1.00x Core Gaming: 1.20x MENA/Saudi focus: 1.30x Esports-focused: 1.40x Global Esports Elite: 1.50x | D13: Esports audiences command 30–50% premium over general gaming due to purchase intent. MENA premium: 20–35% above global baseline. | E13: Applied as Audience Quality Multiplier. Esports-focused Saudi audiences = highest value tier.
A14: • Content Type: Integrated (1.00x) vs. Dedicated/Brand-led (1.30x) | B14: Follower + Engagement Tier System | C14: Tier 1 (Premium): 1M+ followers, 8%+ engagement Tier 2 (Target): 100K–1M followers, 5–8% Tier 3 (Emerging): 10K–100K followers, high engagement Base rates set per tier per platform. | D14: T1 Esports: Faker = $50K+/post FaZe Clan Tier 1: $15K–$30K IG Reel NRG Tier 2: $5K–$12K IG Reel Micro-esports: $1K–$5K | E14: Tier 1 IG Reel: SAR 18,000 (~$4,800) Tier 2 IG Reel: SAR 11,000 (~$2,933) Tier 3 IG Reel: SAR 6,500 (~$1,733)
A15: • Engagement: Scales from 0.70x (<2%) to 1.60x (>10%) | B15: Cross-Platform Rate Calibration | C15: Relative value of each platform vs IG Reel (baseline): IG Reel = 100% (baseline) TikTok Video = 78% YouTube Short = 32% X Post = 20% Twitch Stream 2h = 145% Twitch Integration = 65% IRL Appearance = 220% | D15: Industry standard ratios from InfluenceFlow, Cloutboost, Porter Wills 2025. Twitch commands premium for live engagement. | E15: Applied in 01_Player_Rate_Card. All platform rates derived from IG Reel base × ratio.
A16: • Audience Quality: Gaming-adjacent (1.00x) vs. Esports Core (1.20x) | B16: Multi-Platform Presence Premium | C16: Bonus for talent with broad platform reach: 0–1 platforms: -20% 2–3 platforms: standard (0%) 4–5 platforms: +15% 6–7 platforms: +25% 8+ platforms: +35% | D16: Multi-platform creators command 15–35% premium due to broader campaign reach and cross-platform amplification. | E16: Applied at base fee level in rate card. Encourages talent to build multi-platform presence.
A17: • Seasonality: Regular (1.00x) vs. Ramadan/EWC Peak (1.25x) | B17: Demand-Based Timing Premium | C17: Off-season: 0.80x Regular season: 1.00x Regional Major: 1.25x Game Launch: 1.30x Holiday Q4: 1.20x Ramadan (MENA): 1.35x Global Major/Worlds: 1.40x EWC / Mega Peak: 1.50x | D17: Ramadan = highest MENA consumption period. EWC = highest esports event in MENA calendar. Peak demand = premium pricing justified. | E17: Applied in 02_Adjustment_Matrix. EWC multiplier (1.50x) is highest in the system.
A18: • Language: Arabic/Local (1.00x) vs. Global English (1.15x) | B18: IRL Appearance-Based Price Floor | C18: Ensures pro player pricing never falls below their appearance value: Floor = IRL_Fee × FloorShare × Seasonality × Language × AuthorityFactor Final = MAX(SocialPrice, AuthorityFloor) | D18: Used by WME, CAA for athlete-influencers. Pro status commands minimum floor regardless of social metrics. | E18: Applied in 02_Adjustment_Matrix. Protects Falcons pro player pricing integrity.
A19: • Authority Factor: Weighted blend of Awareness (0.3), Conversion (0.6), and Trust (0.9) based on player prestige | B19: Usage Rights & Exclusivity Uplift | C19: None: 0% Basic (+15%): Organic repost, 1 month Standard (+60%): Organic + paid (limited) Premium (+115%): Organic + paid + MENA territory Full (+170%): All organic + paid + whitelist Exclusive (+320%): Full + category exclusivity 12 months | D19: Industry standard: usage rights add 15–320% to base rate depending on scope. Exclusivity is the highest-value add-on. | E19: Applied in 03_Add_On_Rights. All rights packages documented with clear scope.
B20: Final Invoice Calculation | C20: Player Cost = Final Price ÷ (1 + Markup%) Falcons Revenue = Final Price - Player Cost Client Invoice = Final Price × 1.15 (15% KSA VAT) USD Equivalent = SAR ÷ 3.75 | D20: Standard agency model: 10–30% management fee. KSA VAT: 15% on all commercial transactions. Falcons markup: 20–75% depending on talent. | E20: Applied in 02_Adjustment_Matrix rows 64–70. All quotations include VAT in final client price.
A21: ADD-ONS & RIGHTS
A22: Applied as a percentage uplift on the final adjusted price:
A23: • Organic Repost: +15%
A24: • Paid Usage: Min (+15%), Std (+25%), Max (+40%)
A25: • Whitelisting: 30 Days (+15%), 90 Days (+25%), 1 Year (+40%)
A26: • Territory: MENA (Incl.), Global (+20%)
A27: • Exclusivity: Category 1mo (+20%), 3mo (+35%), 6mo (+50%)
A29: ② THE ROADMAP: EVOLVING TO WORLD-CLASS STANDARDS | B29: EVOLUTION COMPONENT | C29: DESCRIPTION | D29: FORMULA ADDITION | E29: PRIORITY
A30: To align with global Tier 1 esports organizations (T1, FaZe, 100 Thieves) and premium sports marketing agencies (CAA, WME), Team Falcons is transitioning from a static rate card to a dynamic, data-driven valuation model. | B30: Hourly Rate Integration | C30: Add a minimum hourly rate floor for all content creation. A 60-second IG Reel requires 4–8 hours of work (filming, editing, revisions). Current model ignores this. Minimum floor: SAR 500–800/hour for Tier 2–3 talent. | D30: HourlyFloor = HourlyRate × EstimatedHours Final = MAX(CurrentPrice, HourlyFloor) | E30: 🔴 HIGH — implement Q3 2026
B31: Production Cost Pass-Through | C31: When Falcons provides production support (camera crew, studio, editor, graphic designer), these costs should be itemized and passed through to the client at cost + 20% margin. Separates talent fee from production fee for cleaner P&L. | D31: Total = TalentFee + ProductionCost × 1.20 ProductionCost = Crew + Studio + Post-Production | E31: 🟡 MEDIUM — implement Q4 2026
A32: PHASE 1: Standardization (Current) | B32: Deliverable Complexity Scoring | C32: Not all IG Reels are equal. A 30-second product showcase ≠ a 3-minute cinematic brand story. Introduce a complexity score (1–5) that multiplies the base rate. Simple post: 1.0x. Complex branded content: 2.5–3.5x. | D32: ComplexityMultiplier = 1.0 to 3.5 AdjustedBase = BaseFee × ComplexityMultiplier | E32: 🟡 MEDIUM — implement Q1 2027
A33: • Unified rate card across all 189+ talents | B33: Performance-Based Bonus Tier | C33: Introduce a performance kicker: if content exceeds agreed KPIs (views, engagement, conversions), talent earns a bonus (10–25% of base). This aligns talent incentives with brand outcomes and is standard practice at T1 agencies for premium campaigns. | D33: BonusTrigger = IF(ActualKPI > TargetKPI × 1.2, BaseFee × 0.15, 0) FinalPayout = BaseFee + BonusTrigger | E33: 🟢 STRATEGIC — implement Q2 2027
A34: • Automated quote generation with transparent multiplier breakdowns | B34: Dynamic Market Rate Engine | C34: Replace static tier rates with a dynamic engine that pulls real-time market data: competitor pricing, platform CPM fluctuations, demand signals (event calendar), and talent performance history. Rates auto-adjust quarterly. This is how WME and CAA operate at scale. | D34: DynamicRate = f(MarketCPM, CompetitorRates, DemandIndex, TalentScore) Quarterly recalibration cycle | E34: 🔵 LONG-TERM — 2027+
A35: • Clear distinction between Integrated (Player-led) and Dedicated (Brand-led) content | B35: Full Cost-Plus Model for Branded Content | C35: For large-scale branded content series (3+ episodes, documentary-style, event coverage), move to a full cost-plus model: Total Cost = (Talent + Production + Distribution + Management) × (1 + Target Margin%) This is how Netflix, Amazon, and premium brand studios price content partnerships. | D35: TotalCost = Σ(AllCosts) × (1 + MarginTarget) MarginTarget = 25–40% for premium content | E35: 🔵 LONG-TERM — 2027+
A37: PHASE 2: CPM & Performance Integration (Q3 2026)
A38: • Shikenso Analytics Integration: Moving from static base rates to dynamic CPM-based pricing.
A39: • Formula: Price = (Average Views / 1000) × Target CPM
A40: • Target CPMs: IG Reels ($15-$25), TikTok ($10-$20), YouTube ($20-$35)
A41: • Why: Brands buy guaranteed impressions. CPM pricing justifies premium rates for high-performing talent and protects the brand on underperforming posts. | B41: HOURS ESTIMATE | C41: RATE/HOUR (SAR) | D41: FLOOR COST (SAR) | E41: NOTES
A42: 5-TIER TALENT CLASSIFICATION (new in v8)
A43: Tier | B43: Label | C43: Follower Threshold | D43: Base Fee Range (SAR) | E43: Floor Share % | F43: Typical Profile
A44: Tier S | B44: Superstar | C44: >1M on any platform | D44: 40,000 – 50,000 | E44: 65% | F44: Global anchors — Nakamura, ImperialHal, m0NESY, Peterbot
A45: Tier 1 | B45: Star | C45: 250K – 1M | D45: 22,000 – 30,000 | E45: 55% | F45: Major pros — NiKo, Clayster, Msdossary, TGLTN tier
A46: Tier 2 | B46: Core Influencer | C46: 50K – 250K | D46: 11,000 – 18,000 | E46: 45% | F46: Active competitive pros + mid-tier creators
A47: Tier 3 | B47: Rising | C47: 10K – 50K | D47: 6,500 – 10,000 | E47: 35% | F47: Emerging talent, niche specialists
A48: Tier 4 | B48: Entry / Staff | C48: <10K or staff role | D48: 3,000 – 5,500 | E48: 25% | F48: Support roles, developing roster, analysts, coaches
A51: AUTHORITY FLOOR LOGIC (new in v8)
A52: Problem solved: previously, pro players with modest social reach were underpriced on social briefs because rates were derived purely from follower count × CPM. Authority Floor ensures a pro player competing in top-tier tournaments never falls below the IRL-appearance-anchored baseline — even for a "pure social" campaign.
A54: Formulas:
A55: • Social Price = Base Fee × Content Type × Engagement × Audience × Seasonality × Language × Authority Factor
A56: • Authority Floor = IRL Fee × Floor Share × Seasonality × Language × Authority Factor
A57: • Final Price = MAX(Social Price, Authority Floor) × (1 + Add-on Rights %)
A60: MEASUREMENT CONFIDENCE LAYER (new in v8)
A61: Every player row carries a Confidence tag. Premium multipliers (>1.2x engagement, >1.3x authority) are soft-blocked for players at "estimated" or "pending" confidence. This disciplines the commercial team: no premium pricing on hearsay data.
A63: Level | B63: Trigger | C63: Premium Multipliers
A64: exact | B64: Verified via Shikenso or direct platform API | C64: All allowed
A65: rounded | B65: Manual verification, clean round numbers | C65: All allowed
A66: estimated | B66: Partial data, public research, single source | C66: Capped: eng <1.2x, auth <1.3x
A67: pending | B67: No follower data yet | C67: Disabled — 1.0x only
A70: QUOTE WORKFLOW (v8 standardized flow)
A71: 1. Open 02_Adjustment_Matrix → type player name in D5 → confirm player identity.
A72: 2. Scroll to Section ⑦ Player Price Preview — review all asset rates, Authority Floor, and Final Price at default multipliers.
A73: 3. Check Confidence tag — if "pending" or "estimated", restrict premium multipliers.
A74: 4. Select assets needed → enter multipliers in Section ⑥ Live Price Calculator (one asset at a time).
A75: 5. Choose Add-on Rights package from 03_Add_On_Rights.
A76: 6. Confirm Final Price in calculator → transfer to quote template (QT tab).
A77: 7. Approval gate: Legal + Finance sign-off before sending to client.
A80: ② EVOLUTION ROADMAP (v8 → v12)
A81: Phase | B81: Timeline | C81: Goal | D81: Status
A82: v8 — Foundation | B82: April 2026 (NOW) | C82: 5-tier system, Authority Floor, Confidence layer, Player Price Preview | D82: ✅ Complete
A83: v9 — Data Pipeline | B83: Q3 2026 | C83: Shikenso integration, automated follower sync, engagement rate layer | D83: 🟡 Next
A84: v10 — Engagement Intelligence | B84: Q4 2026 | C84: Engagement scored from 30d/90d ER + recency weighting + volatility penalty | D84: 🟡 Planned
A85: v11 — Authority × Objective | B85: Q1 2027 | C85: Authority multiplier scales with brief type (awareness vs trust vs conversion) | D85: 🟡 Planned
A86: v12 — Dynamic Seasonality | B86: Q2 2027+ | C86: Demand-based multipliers from inquiry log history, ML-suggested pricing | D86: 🔵 Strategic

Sheet 12_Quote_Log
B2: QUOTE LOG
B3: Archive of issued quotes · Populated by Apps Script on quote generation
B4: Quote # | C4: Date | D4: Client | E4: Prepared By | F4: Approved By | G4: Subtotal (SAR) | H4: Tax | I4: Total (SAR) | J4: Currency | K4: Axes Summary | L4: Confidence | M4: Line Count | N4: Status | O4: PDF Link

Sheet 99_Assumptions_Log
B2: ASSUMPTIONS & INDUSTRY DEFAULTS LOG
B3: Every value flagged as industry-reasonable pending calibration against live data (Shikenso, Q3 2026)
B5: # | C5: Area | D5: Assumption | E5: Source / Rationale | F5: Confidence | G5: Revisit Trigger
B6: 1 | C6: Tier S threshold | D6: >1M followers on any one platform | E6: Industry benchmark: Creator Economy Report 2024 (Influencer Marketing Hub) | F6: Medium | G6: Shikenso audience data Phase 2 (Q3 2026)
B7: 2 | C7: Tier 1 threshold | D7: 250K – 1M | E7: Peer survey of MENA esports orgs (NAVI, G2, FURIA comparable ranges) | F7: Medium | G7: Quarterly market scan
B8: 3 | C8: Floor Share % (0.65 → 0.25 by tier) | D8: Defines IRL floor as fraction of IRL appearance fee | E8: Conservative internal estimate — higher tiers lock more of their IRL value into social | F8: Low-Medium | G8: First 5 Shikenso-measured campaigns
B9: 4 | C9: Base Fee Range S: SAR 40K-50K | D9: Anchored to regional superstar deal comps | E9: Cross-ref: 2024 KSA tournament sponsorship tier pricing | F9: Medium | G9: Any new Tier S signing
B10: 5 | C10: Base Fee Range T4: SAR 3K-5.5K | D10: Entry-level staff rate | E10: Team Falcons payroll equivalency + reference brand comps | F10: High | G10: Annual review
B11: 6 | C11: Engagement Rate tiers (<3% → ≥7%) | D11: ER brackets for 9-axis matrix | E11: Industry norm: gaming vertical median ER 4-5% (Hootsuite Social Trends 2024) | F11: High | G11: Shikenso monthly reports
B12: 7 | C12: IG Story multiplier = 0.17 × IG Reel | D12: Hardcoded in Player RC col L formula | E12: Internal measurement (v1.0 → v1.5 campaigns, n=22) | F12: Medium | G12: Every 10 campaigns
B13: 8 | C13: IRL = 2.2 × IG Reel | D13: Hardcoded in Player RC col S formula | E13: Internal — IRL carries 2× exposure × premium for physical presence | F13: Low-Medium | G13: Revisit after next 3 IRL activations
B14: 9 | C14: Confidence cap ladder (pending=0.75× → exact=1.0×) | D14: Pricing haircut when measurement is incomplete | E14: Protects Falcons from over-promising; standard agency practice | F14: High | G14: Post-Shikenso integration
B15: 10 | C15: Commission % = 30% default | D15: FMG commission baseline | E15: Team Falcons × FMG contract (already set — DO NOT modify without finance sign-off) | F15: Locked | G15: Contract renewal only
B16: 11 | C16: Authority Factor default = 1.0 | D16: Applied when no objective-weighted authority override is set | E16: Neutral baseline; escalates for Tier S on brand-anchor campaigns | F16: High | G16: Per-campaign review
B17: 12 | C17: Seasonality: Regular 1.0 / Playoffs 1.2 / Finals 1.35 | D17: Baseline competition seasons only | E17: Conservative vs. Twitch viewership lifts (up to 1.6× during Majors) | F17: Medium | G17: Major-tournament specific
... B20: 15 | C20: Audience Quality: Gaming-adjacent 1.0 / Gaming-core 1.15 / Elite 1.25 | D20: Premium for on-target gaming audiences | E20: Brand-fit proxy pending Shikenso audience breakdown | F20: Medium | G20: Shikenso audience enrichment live
